Workbook
Name \0: #REF!
Name \A: #REF!
Name \B: #REF!
Name \C: #REF!
Name \E: #REF!
Name \F: #REF!
Name \G: #REF!
Name \J: #REF!
Name \K: #REF!
Name \L: #REF!
Name \P: #REF!
Name \R: #REF!
Name \RL: #REF!
Name \S: #REF!
Name \U: #REF!
Name \v: #REF!
Name \X: #REF!
Name \Y: #REF!
Name _: #REF!
Name __: #REF!
Name ___: #REF!
Name ____: #REF!
Name _____: #REF!
Name _____gas87: #REF!
Name _____gas91: #REF!
Name _____gas93: #REF!
Name _____gas95: #REF!
Name ____gas87: #REF!
Name ____gas91: #REF!
Name ____gas93: #REF!
Name ____gas95: #REF!
Name ___gas87: #REF!
Name ___gas91: #REF!
Name ___gas93: #REF!
Name ___gas95: #REF!
Name __gas87: #REF!
Name __gas91: #REF!
Name __gas93: #REF!
Name __gas95: #REF!
Name _1: #REF!
Name _1_: #REF!
Name _10: #REF!
Name _10t__WT: #REF!
Name _11: #REF!
Name _12: #REF!
Name _12WSOL: #REF!
Name _13: #REF!
Name _14: #REF!
Name _14W__WS: #REF!
Name _15: #REF!
Name _16: #REF!
Name _17: #REF!
Name _18: #REF!
Name _19: #REF!
Name _2: #REF!
Name _2_: #REF!
Name _20: #REF!
Name _21: #REF!
Name _2G: #REF!
Name _3: #REF!

Sheet Golden Rulebook-CDErule level
A1: DED Phase 2 | Golden DQ Rulebook – Single Source of Truth
A2: SCOPE / CDE BASELINE | H2: SUBMISSION FORMAT | AE2: REVIEW & SIGN-OFF
A3: Sprint | B3: Table Name | C3: Table ID | D3: Attribute Name | E3: Attribute ID | F3: Silver Technical ID | G3: Bronze Technical ID | H3: DQ_Rule_Key | I3: Rule ID | J3: Rule_Name_Title | K3: Business Rule Description | L3: DQ Dimension | M3: Scope_Granularity | N3: Data_Domain | O3: Business_Owner | P3: Technical_Owner | Q3: Data_Source_System | R3: Data_Table_ID | S3: Attribute_ID | T3: Rule_Type | U3: Rule_Expression_Logic | V3: Expected_Outcome_Threshold | W3: Frequency_Execution_Schedule | X3: Data_Quality_Metric_KPI | Y3: Priority_Criticality | Z3: Exceptions_Exclusions | AA3: Status | AB3: Updated_Date | AC3: Remediation_ID | AD3: Business/ Tech Rule | AE3: Business Review Required? | AF3: Business Review Status | AG3: 1st Business Review: Date & Comments | AH3: 2nd Business Review: Date & Comments | AI3: 3rd Business Review: Date & Comments | AJ3: IT Review Required? | AK3: IT Review Status | AL3: Technical Owner | AM3: 1st Technical Review: Date & Comments | AN3: 2nd Technical Review: Date & Comments | AO3: DED Data Sign-off | AP3: DED Data Comments | AQ3: C.4.4 Failed Record Log Ref | AR3: Issue Description | AS3: Remediation Action
A4: Sprint 3 | B4: basic_information | C4: DED_Data_Table_181 | D4: identification_number | E4: DED_Attribute_2717 | F4: 2f3bea9d-2853-41ed-bcbb-d2257f0248e5 | G4: 4313a3f7-b41d-4eee-9947-9d6f548d3d17 | H4: DQP-4005 | I4: DQO-4005 | J4: Val_Chk-basic_information-identification_number | K4: Check that non-null identification numbers are positive whole-number identifiers containing digits only, with no decimals, zero, negatives or non-numeric characters. | L4: Validity | M4: Attribute | N4: Business Registration & Licensing | تسجيل الأعمال والتراخيص | O4: rfmdaas@adra.gov.ae, bmalkindi@adra.gov.ae, aiaalsheebani@ded.abudhabi.ae | P4: asalmehiry@adra.gov.ae, rfmdaas@adra.gov.ae, sraalbadi@ded.abudhabi.ae | Q4: Accela | R4: DED_Data_Table_181 | S4: DED_Attribute_2717 | T4: CustomSQL | U4: identification_number RLIKE '^[1-9][0-9]*$' | V4: 1 | W4: Weekly | X4: DQI | Y4: High | Z4: basic_information | AA4: Active | AB4: 46310 | AD4: Technical | AE4: No | AF4: In Review | AJ4: Yes | AK4: Approved | AL4: Samer | AM4: 02/10/2026 - Yes - Yes means conditional technical feasibility, subject to the conditions below; it is not business approval. Apply only to basic_information.identification_number records linked to the approved Group / Type / Subtype / Category combinations in columns J:M; validate actual four-level service combinations, not a Cartesian product of the listed values. Evaluate populated identification_number only; null/blank values belong to a separately approved completeness rule. Use an explicit null/blank policy so SQL UNKNOWN is not silently counted as pass or fail. Character-format check only; it does not establish accuracy or lookup membership. Confirm the execution engine and test the regex on actual Arabic/English source samples. Pattern rejects zero and leading zeros; business must confirm this is valid for this identifier/value. Preserve identifiers as text. Translate platform-specific syntax if execution is on Oracle; otherwise validate on the nominated DQ engine. Technical assessment only, based on supplied metadata; source mapping and execution are unverified. Business owner MUST document approval of applicability, four-level service mapping, mandatory/optional status, allowed values and exceptions before implementation. Implementation team must verify final logic/filters and failed-record extracts against Accela before DED validation. | AO4: Signed Off
A5: Sprint 3 | B5: amendment_type | C5: DED_Data_Table_179 | D5: trade_name_amendment | E5: DED_Attribute_2616 | F5: d49d9cae-da9a-4eea-a69f-ef64efae366b | G5: 8f74a657-bc00-41df-b0c5-0eeb5c09d408 | H5: DQP-2926 | I5: DQO-2926 | J5: Compl_Check-amendment_type-trade_name_amendment | K5: Validate that the critical data element amendment_type.trade_name_amendment is populated and not blank for in-scope records.Profiling results were used to identify current null/blank exposure where available. | L5: Completeness | M5: Attribute | N5: Business Registration & Licensing | تسجيل الأعمال والتراخيص | O5: rfmdaas@adra.gov.ae, bmalkindi@adra.gov.ae | P5: asalmehiry@adra.gov.ae, rfmdaas@adra.gov.ae | Q5: Accela | R5: DED_Data_Table_179 | S5: DED_Attribute_2616 | T5: Custom | U5: !isNull({trade_name_amendment}) | V5: 0.95 | W5: Weekly | X5: DQI | Y5: High | Z5: {rec_status} == 'A' | AA5: Active | AB5: 46310 | AD5: Technical | AE5: No | AF5: In Review | AJ5: Yes | AK5: Approved | AL5: Samer | AM5: 30/09/2026 - Yes Service: Industrial / License / License / NA. REC_STATUS = 'A'; evaluate only where trade_name_amendment is mandatory for the service/stage; Confirm applicable amendment options; do not require every flag to be selected; an explicit No counts as populated; Non-applicable records excluded from denominator. Business confirmation required. | AO5: Signed Off
A6: Sprint 3 | B6: amendment_type | C6: DED_Data_Table_179 | D6: company_address_amendment | E6: DED_Attribute_2617 | F6: 30d50e4d-ee01-4de4-8d7a-bab188a6b7c0 | G6: 65c9373e-be12-48a8-9f08-0e854aefc158 | H6: DQP-2927 | I6: DQO-2927 | J6: Compl_Chk-amend_type-company_address_amendment | K6: Validate that the critical data element amendment_type.company_address_amendment is populated and not blank for in-scope records.Profiling results were used to identify current null/blank exposure where available. | L6: Completeness | M6: Attribute | N6: Business Registration & Licensing | تسجيل الأعمال والتراخيص | O6: rfmdaas@adra.gov.ae, bmalkindi@adra.gov.ae | P6: asalmehiry@adra.gov.ae, rfmdaas@adra.gov.ae | Q6: Accela | R6: DED_Data_Table_179 | S6: DED_Attribute_2617 | T6: Custom | U6: !isNull({company_address_amendment}) | V6: 0.95 | W6: Weekly | X6: DQI | Y6: High | Z6: {rec_status} == 'A' | AA6: Active | AB6: 46310 | AD6: Technical | AE6: No | AF6: In Review | AJ6: Yes | AK6: Approved | AL6: Samer | AM6: 30/09/2026 - Yes Approved exact four-level service paths from O:R; do not cross-combine listed subtypes/categories. REC_STATUS = 'A'; evaluate only where company_address_amendment is mandatory for the service/stage; Confirm applicable amendment options; do not require every flag to be selected; an explicit No counts as populated; Non-applicable records excluded from denominator. Business confirmation required. | AO6: Signed Off
A7: Sprint 3 | B7: amendment_type | C7: DED_Data_Table_179 | D7: partners_amendment | E7: DED_Attribute_2618 | F7: 2d6ea40f-bf95-473c-8bf9-3b6923dddf91 | G7: e9f66a7a-07da-46d4-b981-2af1f88966a2 | H7: DQP-2928 | I7: DQO-2928 | J7: Compl_Check-amendment_type-partners_amendment | K7: Validate that the critical data element amendment_type.partners_amendment is populated and not blank for in-scope records.Profiling results were used to identify current null/blank exposure where available. | L7: Completeness | M7: Attribute | N7: Business Registration & Licensing | تسجيل الأعمال والتراخيص | O7: rfmdaas@adra.gov.ae, bmalkindi@adra.gov.ae | P7: asalmehiry@adra.gov.ae, rfmdaas@adra.gov.ae | Q7: Accela | R7: DED_Data_Table_179 | S7: DED_Attribute_2618 | T7: Custom | U7: !isNull({partners_amendment}) | V7: 0.95 | W7: Weekly | X7: DQI | Y7: High | Z7: {rec_status} == 'A' | AA7: Active | AB7: 46310 | AD7: Technical | AE7: No | AF7: In Review | AJ7: Yes | AK7: Approved | AL7: Samer | AM7: 30/09/2026 - Yes Service: Industrial / License / License / NA. REC_STATUS = 'A'; evaluate only where partners_amendment is mandatory for the service/stage; Confirm applicable amendment options; do not require every flag to be selected; an explicit No counts as populated; Non-applicable records excluded from denominator. Business confirmation required. | AO7: Signed Off
A8: Sprint 3 | B8: amendment_type | C8: DED_Data_Table_179 | D8: raw_material_amendment | E8: DED_Attribute_2619 | F8: 81494825-2a7d-49bf-9c02-49c15a23eea0 | G8: d6b366e8-b292-442b-8781-15282aa657ec | H8: DQP-2929 | I8: DQO-2929 | J8: Compl_Chk-amendment_type-raw_material_amendment | K8: Validate that the critical data element amendment_type.raw_material_amendment is populated and not blank for in-scope records.Profiling results were used to identify current null/blank exposure where available. | L8: Completeness | M8: Attribute | N8: Business Registration & Licensing | تسجيل الأعمال والتراخيص | O8: rfmdaas@adra.gov.ae, bmalkindi@adra.gov.ae | P8: asalmehiry@adra.gov.ae, rfmdaas@adra.gov.ae | Q8: Accela | R8: DED_Data_Table_179 | S8: DED_Attribute_2619 | T8: Custom | U8: !isNull({raw_material_amendment}) | V8: 0.95 | W8: Weekly | X8: DQI | Y8: High | Z8: {rec_status} == 'A' | AA8: Active | AB8: 46310 | AD8: Technical | AE8: No | AF8: In Review | AJ8: Yes | AK8: Approved | AL8: Samer | AM8: 30/09/2026 - Yes Approved exact four-level service paths from O:R; do not cross-combine listed subtypes/categories. REC_STATUS = 'A'; evaluate only where raw_material_amendment is mandatory for the service/stage; Confirm applicable amendment options; do not require every flag to be selected; an explicit No counts as populated; Non-applicable records excluded from denominator. Business confirmation required. | AO8: Signed Off
A9: Sprint 3 | B9: amendment_type | C9: DED_Data_Table_179 | D9: activity_amendment | E9: DED_Attribute_2620 | F9: 73b50fcf-a942-475c-b122-0af54333b82b | G9: fe79f012-4600-4093-b0fa-75513d370326 | H9: DQP-2930 | I9: DQO-2930 | J9: Compl_Check-amendment_type-activity_amendment | K9: Validate that the critical data element amendment_type.activity_amendment is populated and not blank for in-scope records.Profiling results were used to identify current null/blank exposure where available. | L9: Completeness | M9: Attribute | N9: Business Registration & Licensing | تسجيل الأعمال والتراخيص | O9: rfmdaas@adra.gov.ae, bmalkindi@adra.gov.ae | P9: asalmehiry@adra.gov.ae, rfmdaas@adra.gov.ae | Q9: Accela | R9: DED_Data_Table_179 | S9: DED_Attribute_2620 | T9: Custom | U9: !isNull({activity_amendment}) | V9: 0.95 | W9: Weekly | X9: DQI | Y9: High | Z9: {rec_status} == 'A' | AA9: Active | AB9: 46310 | AD9: Technical | AE9: No | AF9: In Review | AJ9: Yes | AK9: Approved | AL9: Samer | AM9: 30/09/2026 - Yes Approved exact four-level service paths from O:R; do not cross-combine listed subtypes/categories. REC_STATUS = 'A'; evaluate only where activity_amendment is mandatory for the service/stage; Confirm applicable amendment options; do not require every flag to be selected; an explicit No counts as populated; Non-applicable records excluded from denominator. Business confirmation required. | AO9: Signed Off
A10: Sprint 3 | B10: amendment_type | C10: DED_Data_Table_179 | D10: service_amendment | E10: DED_Attribute_2621 | F10: 66e72d2f-f7ab-4331-99ed-53728eb1f65e | G10: 95623e78-5286-46dd-9059-0f66531b9d4c | H10: DQP-2931 | I10: DQO-2931 | J10: Compl_Check-amendment_type-service_amendment | K10: Validate that the critical data element amendment_type.service_amendment is populated and not blank for in-scope records.Profiling results were used to identify current null/blank exposure where available. | L10: Completeness | M10: Attribute | N10: Business Registration & Licensing | تسجيل الأعمال والتراخيص | O10: rfmdaas@adra.gov.ae, bmalkindi@adra.gov.ae | P10: asalmehiry@adra.gov.ae, rfmdaas@adra.gov.ae | Q10: Accela | R10: DED_Data_Table_179 | S10: DED_Attribute_2621 | T10: Custom | U10: !isNull({service_amendment}) | V10: 0.95 | W10: Weekly | X10: DQI | Y10: High | Z10: {rec_status} == 'A' | AA10: Active | AB10: 46310 | AD10: Technical | AE10: No | AF10: In Review | AJ10: Yes | AK10: Approved | AL10: Samer | AM10: 30/09/2026 - Yes Approved exact four-level service paths from O:R; do not cross-combine listed subtypes/categories. REC_STATUS = 'A'; evaluate only where service_amendment is mandatory for the service/stage; Confirm applicable amendment options; do not require every flag to be selected; an explicit No counts as populated; Non-applicable records excluded from denominator. Business confirmation required. | AO10: Signed Off
A11: Sprint 3 | B11: amendment_type | C11: DED_Data_Table_179 | D11: investment_amendment | E11: DED_Attribute_2622 | F11: f0caffc5-be9d-4de5-aa9f-9ccb5d8e7244 | G11: 1a51593e-19fa-43f4-b5fa-5a32f35b73a7 | H11: DQP-2932 | I11: DQO-2932 | J11: Compl_Check-amendment_type-investment_amendment | K11: Validate that the critical data element amendment_type.investment_amendment is populated and not blank for in-scope records.Profiling results were used to identify current null/blank exposure where available. | L11: Completeness | M11: Attribute | N11: Business Registration & Licensing | تسجيل الأعمال والتراخيص | O11: rfmdaas@adra.gov.ae, bmalkindi@adra.gov.ae | P11: asalmehiry@adra.gov.ae, rfmdaas@adra.gov.ae | Q11: Accela | R11: DED_Data_Table_179 | S11: DED_Attribute_2622 | T11: Custom | U11: !isNull({investment_amendment}) | V11: 0.95 | W11: Weekly | X11: DQI | Y11: High | Z11: {rec_status} == 'A' | AA11: Active | AB11: 46310 | AD11: Technical | AE11: No | AF11: In Review | AJ11: Yes | AK11: Approved | AL11: Samer | AM11: 30/09/2026 - Yes Approved exact four-level service paths from O:R; do not cross-combine listed subtypes/categories. REC_STATUS = 'A'; evaluate only where investment_amendment is mandatory for the service/stage; Confirm applicable amendment options; do not require every flag to be selected; an explicit No counts as populated; Only where an investment contract/project is applicable; Non-applicable records excluded from denominator. Business confirmation required. | AO11: Signed Off
A12: Sprint 3 | B12: amendment_type | C12: DED_Data_Table_179 | D12: normal_license_to_foreign_investor_amendment | E12: DED_Attribute_2623 | F12: 41d3ce98-9d1f-486d-a45a-633217ceacde | G12: 8787cdd2-ce79-4093-b8fa-e977746a4096 | H12: DQP-2933 | I12: DQO-2933 | J12: Comp_Chk-amen_typ-normal_lice_to_fore_inve_amen | K12: Validate that the critical data element amendment_type.normal_license_to_foreign_investor_amendment is populated and not blank for in-scope records.Profiling results were used to identify current null/blank exposure where available. | L12: Completeness | M12: Attribute | N12: Business Registration & Licensing | تسجيل الأعمال والتراخيص | O12: rfmdaas@adra.gov.ae, bmalkindi@adra.gov.ae | P12: asalmehiry@adra.gov.ae, rfmdaas@adra.gov.ae | Q12: Accela | R12: DED_Data_Table_179 | S12: DED_Attribute_2623 | T12: Custom | U12: !isNull({normal_license_to_foreign_investor_amendment}) | V12: 0.95 | W12: Weekly | X12: DQI | Y12: High | Z12: {rec_status} == 'A' | AA12: Active | AB12: 46310 | AD12: Technical | AE12: No | AF12: In Review | AJ12: Yes | AK12: Approved | AL12: Samer | AM12: 30/09/2026 - Yes Approved exact four-level service paths from O:R; do not cross-combine listed subtypes/categories. REC_STATUS = 'A'; evaluate only where normal_license_to_foreign_investor_amendment is mandatory for the service/stage; Confirm applicable amendment options; do not require every flag to be selected; an explicit No counts as populated; Non-applicable records excluded from denominator. Business confirmation required. | AO12: Signed Off
A13: Sprint 3 | B13: amendment_type | C13: DED_Data_Table_179 | D13: legal_type_amendment | E13: DED_Attribute_2624 | F13: 5daab735-2fce-45dc-9dea-a922c398a4d6 | G13: c2d627ef-5821-4d79-99d6-d55576d37f2c | H13: DQP-2934 | I13: DQO-2934 | J13: Compl_Check-amendment_type-legal_type_amendment | K13: Validate that the critical data element amendment_type.legal_type_amendment is populated and not blank for in-scope records.Profiling results were used to identify current null/blank exposure where available. | L13: Completeness | M13: Attribute | N13: Business Registration & Licensing | تسجيل الأعمال والتراخيص | O13: rfmdaas@adra.gov.ae, bmalkindi@adra.gov.ae | P13: asalmehiry@adra.gov.ae, rfmdaas@adra.gov.ae | Q13: Accela | R13: DED_Data_Table_179 | S13: DED_Attribute_2624 | T13: Custom | U13: !isNull({legal_type_amendment}) | V13: 0.95 | W13: Weekly | X13: DQI | Y13: High | Z13: {rec_status} == 'A' | AA13: Active | AB13: 46310 | AD13: Technical | AE13: No | AF13: In Review | AJ13: Yes | AK13: Approved | AL13: Samer | AM13: 30/09/2026 - Yes Approved exact four-level service paths from O:R; do not cross-combine listed subtypes/categories. REC_STATUS = 'A'; evaluate only where legal_type_amendment is mandatory for the service/stage; Confirm applicable amendment options; do not require every flag to be selected; an explicit No counts as populated; Non-applicable records excluded from denominator. Business confirmation required. | AO13: Signed Off
A14: Sprint 3 | B14: amendment_type | C14: DED_Data_Table_179 | D14: hse_details_amendment | E14: DED_Attribute_2625 | F14: 23514162-2ce4-4e70-adb9-0a05a4995dbd | G14: 08a928ea-96af-4d8a-a078-62a9b4ed58a9 | H14: DQP-2935 | I14: DQO-2935 | J14: Compl_Chk-amendment_type-hse_details_amendment | K14: Validate that the critical data element amendment_type.hse_details_amendment is populated and not blank for in-scope records.Profiling results were used to identify current null/blank exposure where available. | L14: Completeness | M14: Attribute | N14: Business Registration & Licensing | تسجيل الأعمال والتراخيص | O14: rfmdaas@adra.gov.ae, bmalkindi@adra.gov.ae | P14: asalmehiry@adra.gov.ae, rfmdaas@adra.gov.ae | Q14: Accela | R14: DED_Data_Table_179 | S14: DED_Attribute_2625 | T14: Custom | U14: !isNull({hse_details_amendment}) | V14: 0.95 | W14: Weekly | X14: DQI | Y14: High | Z14: {rec_status} == 'A' | AA14: Active | AB14: 46310 | AD14: Technical | AE14: No | AF14: In Review | AJ14: Yes | AK14: Approved | AL14: Samer | AM14: 30/09/2026 - Yes Approved exact four-level service paths from O:R; do not cross-combine listed subtypes/categories. REC_STATUS = 'A'; evaluate only where hse_details_amendment is mandatory for the service/stage; Confirm applicable amendment options; do not require every flag to be selected; an explicit No counts as populated; Non-applicable records excluded from denominator. Business confirmation required. | AO14: Signed Off
A15: Sprint 3 | B15: amendment_type | C15: DED_Data_Table_179 | D15: partners_shares_amendment | E15: DED_Attribute_2626 | F15: 6624d091-ad95-4178-8568-450d51de9bda | G15: a669c62b-30b1-47be-93a5-692b547f1a97 | H15: DQP-2936 | I15: DQO-2936 | J15: Compl_Chk-amendm_type-partners_shares_amendment | K15: Validate that the critical data element amendment_type.partners_shares_amendment is populated and not blank for in-scope records.Profiling results were used to identify current null/blank exposure where available. | L15: Completeness | M15: Attribute | N15: Business Registration & Licensing | تسجيل الأعمال والتراخيص | O15: rfmdaas@adra.gov.ae, bmalkindi@adra.gov.ae | P15: asalmehiry@adra.gov.ae, rfmdaas@adra.gov.ae | Q15: Accela | R15: DED_Data_Table_179 | S15: DED_Attribute_2626 | T15: Custom | U15: !isNull({partners_shares_amendment}) | V15: 0.95 | W15: Weekly | X15: DQI | Y15: High | Z15: {rec_status} == 'A' | AA15: Active | AB15: 46310 | AD15: Technical | AE15: No | AF15: In Review | AJ15: Yes | AK15: Approved | AL15: Samer | AM15: 30/09/2026 - Yes Service: Industrial / License / License / NA. REC_STATUS = 'A'; evaluate only where partners_shares_amendment is mandatory for the service/stage; Confirm applicable amendment options; do not require every flag to be selected; an explicit No counts as populated; Non-applicable records excluded from denominator. Business confirmation required. | AO15: Signed Off
... A32: Sprint 3 | B32: amendment_type | C32: DED_Data_Table_179 | D32: signboard_amendment | E32: DED_Attribute_2644 | F32: 5bd0197f-c8d1-4e61-bc4c-76fd0b7f3746 | G32: 8fd8f4a3-b576-4821-ae55-438fc9d9d905 | H32: DQP-2953 | I32: DQO-2953 | J32: Compl_Chk-amendment_type-signboard_amendment | K32: Validate that the critical data element amendment_type.signboard_amendment is populated and not blank for in-scope records.Profiling results were used to identify current null/blank exposure where available. | L32: Completeness | M32: Attribute | N32: Business Registration & Licensing | تسجيل الأعمال والتراخيص | O32: rfmdaas@adra.gov.ae, bmalkindi@adra.gov.ae | P32: asalmehiry@adra.gov.ae, rfmdaas@adra.gov.ae | Q32: Accela | R32: DED_Data_Table_179 | S32: DED_Attribute_2644 | T32: Custom | U32: !isNull({signboard_amendment}) | V32: 0.95 | W32: Weekly | X32: DQI | Y32: High | Z32: {rec_status} == 'A' | AA32: Active | AB32: 46310 | AD32: Technical | AE32: No | AF32: In Review | AJ32: Yes | AK32: Rejected | AL32: Samer | AM32: 30/09/2026 - No | AO32: Signed Off
A33: Sprint 3 | B33: amendment_type | C33: DED_Data_Table_179 | D33: amend_beneficiaries | E33: DED_Attribute_2645 | F33: 7a671bfb-ea51-460f-8c51-1c22f01bcd2c | G33: de6c39a2-442a-4a77-9502-078f90e9ad45 | H33: DQP-2739 | I33: DQO-2739 | J33: Compl_Chk-amendment_type-amend_beneficiaries | K33: Validate that the critical data element amendment_type.amend_beneficiaries is populated and not blank for in-scope records.Profiling results were used to identify current null/blank exposure where available. | L33: Completeness | M33: Attribute | N33: Business Registration & Licensing | تسجيل الأعمال والتراخيص | O33: rfmdaas@adra.gov.ae, bmalkindi@adra.gov.ae | P33: asalmehiry@adra.gov.ae, rfmdaas@adra.gov.ae | Q33: Accela | R33: DED_Data_Table_179 | S33: DED_Attribute_2645 | T33: Custom | U33: !isNull({amend_beneficiaries}) | V33: 0.95 | W33: Weekly | X33: DQI | Y33: High | Z33: {rec_status} == 'A' | AA33: Active | AB33: 46310 | AD33: Business | AE33: Yes | AF33: Approved | AG33: 9/17 approve | AJ33: No | AO33: Signed Off
A34: Sprint 3 | B34: amendment_type | C34: DED_Data_Table_179 | D34: country_amendment_foreign_company | E34: DED_Attribute_2647 | F34: 90852861-3bfd-4662-b279-9c7a61842096 | G34: 169b3533-9b00-459a-8bf8-76de841e40a8 | H34: DQP-2954 | I34: DQO-2954 | J34: Comp_Chk-amen_type-country_amen_foreign_company | K34: Validate that the critical data element amendment_type.country_amendment_foreign_company is populated and not blank for in-scope records.Profiling results were used to identify current null/blank exposure where available. | L34: Completeness | M34: Attribute | N34: Business Registration & Licensing | تسجيل الأعمال والتراخيص | O34: rfmdaas@adra.gov.ae, bmalkindi@adra.gov.ae | P34: asalmehiry@adra.gov.ae, rfmdaas@adra.gov.ae | Q34: Accela | R34: DED_Data_Table_179 | S34: DED_Attribute_2647 | T34: Custom | U34: !isNull({country_amendment_foreign_company}) | V34: 0.95 | W34: Weekly | X34: DQI | Y34: High | Z34: {rec_status} == 'A' | AA34: Active | AB34: 46310 | AD34: Technical | AE34: No | AF34: In Review | AJ34: Yes | AK34: Rejected | AL34: Samer | AM34: 30/09/2026 - No | AO34: Signed Off
A35: Sprint 3 | B35: amendment_type | C35: DED_Data_Table_179 | D35: heirs_amendment | E35: DED_Attribute_2648 | F35: c03da223-44f8-40a0-8f7f-21b3b16be7d1 | G35: 83f0d5b2-d6d5-4152-8786-35306ca1866f | H35: DQP-2955 | I35: DQO-2955 | J35: Compl_Chk-amendment_type-heirs_amendment | K35: Validate that the critical data element amendment_type.heirs_amendment is populated and not blank for in-scope records.Profiling results were used to identify current null/blank exposure where available. | L35: Completeness | M35: Attribute | N35: Business Registration & Licensing | تسجيل الأعمال والتراخيص | O35: rfmdaas@adra.gov.ae, bmalkindi@adra.gov.ae | P35: asalmehiry@adra.gov.ae, rfmdaas@adra.gov.ae | Q35: Accela | R35: DED_Data_Table_179 | S35: DED_Attribute_2648 | T35: Custom | U35: !isNull({heirs_amendment}) | V35: 0.95 | W35: Weekly | X35: DQI | Y35: High | Z35: {rec_status} == 'A' | AA35: Active | AB35: 46310 | AD35: Technical | AE35: No | AF35: In Review | AJ35: Yes | AK35: Rejected | AL35: Samer | AM35: 30/09/2026 - No | AO35: Signed Off
A36: Sprint 3 | B36: amendment_type | C36: DED_Data_Table_179 | D36: capital_amendment | E36: DED_Attribute_2649 | F36: f3500d1a-7aa0-4ef8-91b6-50cfe7e28bf9 | G36: 7fa53995-7a4e-468f-87b7-e930e6bd067e | H36: DQP-2956 | I36: DQO-2956 | J36: Compl_Chk-amendment_type-capital_amendment | K36: Validate that the critical data element amendment_type.capital_amendment is populated and not blank for in-scope records.Profiling results were used to identify current null/blank exposure where available. | L36: Completeness | M36: Attribute | N36: Business Registration & Licensing | تسجيل الأعمال والتراخيص | O36: rfmdaas@adra.gov.ae, bmalkindi@adra.gov.ae | P36: asalmehiry@adra.gov.ae, rfmdaas@adra.gov.ae | Q36: Accela | R36: DED_Data_Table_179 | S36: DED_Attribute_2649 | T36: Custom | U36: !isNull({capital_amendment}) | V36: 0.95 | W36: Weekly | X36: DQI | Y36: High | Z36: {rec_status} == 'A' | AA36: Active | AB36: 46310 | AD36: Technical | AE36: No | AF36: In Review | AJ36: Yes | AK36: Rejected | AL36: Samer | AM36: 30/09/2026 - No | AO36: Signed Off
A37: Sprint 3 | B37: amendment_type | C37: DED_Data_Table_179 | D37: sponsor_amendment | E37: DED_Attribute_2650 | F37: dc60ac28-c966-4b54-9c0a-660a50fde9d3 | G37: d2e9d448-1b77-4632-8a96-f909f3f3b2e5 | H37: DQP-2957 | I37: DQO-2957 | J37: Compl_Chk-amendment_type-sponsor_amendment | K37: Validate that the critical data element amendment_type.sponsor_amendment is populated and not blank for in-scope records.Profiling results were used to identify current null/blank exposure where available. | L37: Completeness | M37: Attribute | N37: Business Registration & Licensing | تسجيل الأعمال والتراخيص | O37: rfmdaas@adra.gov.ae, bmalkindi@adra.gov.ae | P37: asalmehiry@adra.gov.ae, rfmdaas@adra.gov.ae | Q37: Accela | R37: DED_Data_Table_179 | S37: DED_Attribute_2650 | T37: Custom | U37: !isNull({sponsor_amendment}) | V37: 0.95 | W37: Weekly | X37: DQI | Y37: High | Z37: {rec_status} == 'A' | AA37: Active | AB37: 46310 | AD37: Technical | AE37: No | AF37: In Review | AJ37: Yes | AK37: Rejected | AL37: Samer | AM37: 30/09/2026 - No | AO37: Signed Off
A38: Sprint 3 | B38: amendment_type | C38: DED_Data_Table_179 | D38: location_amendment_c | E38: DED_Attribute_2651 | F38: 3c26e1fe-b44d-4645-9fb9-efcc657b3fab | G38: e5acb72f-84a4-42d9-b925-f79fc7803807 | H38: DQP-2958 | I38: DQO-2958 | J38: Compl_Chk-amendment_type-location_amendment_c | K38: Validate that the critical data element amendment_type.location_amendment_c is populated and not blank for in-scope records.Profiling results were used to identify current null/blank exposure where available. | L38: Completeness | M38: Attribute | N38: Business Registration & Licensing | تسجيل الأعمال والتراخيص | O38: rfmdaas@adra.gov.ae, bmalkindi@adra.gov.ae | P38: asalmehiry@adra.gov.ae, rfmdaas@adra.gov.ae | Q38: Accela | R38: DED_Data_Table_179 | S38: DED_Attribute_2651 | T38: Custom | U38: !isNull({location_amendment_c}) | V38: 0.95 | W38: Weekly | X38: DQI | Y38: High | Z38: {rec_status} == 'A' | AA38: Active | AB38: 46310 | AD38: Technical | AE38: No | AF38: In Review | AJ38: Yes | AK38: Rejected | AL38: Samer | AM38: 30/09/2026 - No | AO38: Signed Off
A39: Sprint 3 | B39: amendment_type | C39: DED_Data_Table_179 | D39: activity_replacement | E39: DED_Attribute_2652 | F39: c9ba16d4-85d5-4927-83d4-ae2d674a737a | G39: 4f063b30-c5ba-4c72-95ba-5324713bc93f | H39: DQP-2959 | I39: DQO-2959 | J39: Compl_Chk-amendment_type-activity_replacement | K39: Validate that the critical data element amendment_type.activity_replacement is populated and not blank for in-scope records.Profiling results were used to identify current null/blank exposure where available. | L39: Completeness | M39: Attribute | N39: Business Registration & Licensing | تسجيل الأعمال والتراخيص | O39: rfmdaas@adra.gov.ae, bmalkindi@adra.gov.ae | P39: asalmehiry@adra.gov.ae, rfmdaas@adra.gov.ae | Q39: Accela | R39: DED_Data_Table_179 | S39: DED_Attribute_2652 | T39: Custom | U39: !isNull({activity_replacement}) | V39: 0.95 | W39: Weekly | X39: DQI | Y39: High | Z39: {rec_status} == 'A' | AA39: Active | AB39: 46310 | AD39: Technical | AE39: No | AF39: In Review | AJ39: Yes | AK39: Rejected | AL39: Samer | AM39: 30/09/2026 - No | AO39: Signed Off
A40: Sprint 3 | B40: amendment_type | C40: DED_Data_Table_179 | D40: location_amendment | E40: DED_Attribute_2653 | F40: 0f99dd01-5475-4701-b0e3-b797d1741874 | G40: e972c837-d37f-4710-bef3-a547d551fffe | H40: DQP-2960 | I40: DQO-2960 | J40: Compl_Chk-amendment_type-location_amendment | K40: Validate that the critical data element amendment_type.location_amendment is populated and not blank for in-scope records.Profiling results were used to identify current null/blank exposure where available. | L40: Completeness | M40: Attribute | N40: Business Registration & Licensing | تسجيل الأعمال والتراخيص | O40: rfmdaas@adra.gov.ae, bmalkindi@adra.gov.ae | P40: asalmehiry@adra.gov.ae, rfmdaas@adra.gov.ae | Q40: Accela | R40: DED_Data_Table_179 | S40: DED_Attribute_2653 | T40: Custom | U40: !isNull({location_amendment}) | V40: 0.95 | W40: Weekly | X40: DQI | Y40: High | Z40: {rec_status} == 'A' | AA40: Active | AB40: 46310 | AD40: Technical | AE40: No | AF40: In Review | AJ40: Yes | AK40: Rejected | AL40: Samer | AM40: 30/09/2026 - No | AO40: Signed Off
A41: Sprint 3 | B41: amendment_type | C41: DED_Data_Table_179 | D41: notarisation_contracts_amendment | E41: DED_Attribute_2654 | F41: c2c1128d-734c-4c6c-a2b2-2530baae1697 | G41: 27fea252-37c9-4559-aead-32b548ef3336 | H41: DQP-2961 | I41: DQO-2961 | J41: Compl_Chk-amen_type-notarisation_cont_amendment | K41: Validate that the critical data element amendment_type.notarisation_contracts_amendment is populated and not blank for in-scope records.Profiling results were used to identify current null/blank exposure where available. | L41: Completeness | M41: Attribute | N41: Business Registration & Licensing | تسجيل الأعمال والتراخيص | O41: rfmdaas@adra.gov.ae, bmalkindi@adra.gov.ae | P41: asalmehiry@adra.gov.ae, rfmdaas@adra.gov.ae | Q41: Accela | R41: DED_Data_Table_179 | S41: DED_Attribute_2654 | T41: Custom | U41: !isNull({notarisation_contracts_amendment}) | V41: 0.95 | W41: Weekly | X41: DQI | Y41: High | Z41: {rec_status} == 'A' | AA41: Active | AB41: 46310 | AD41: Technical | AE41: No | AF41: In Review | AJ41: Yes | AK41: Approved | AL41: Samer | AM41: 30/09/2026 - Yes Approved exact four-level service paths from O:R; do not cross-combine listed subtypes/categories. REC_STATUS = 'A'; evaluate only where notarisation_contracts_amendment is mandatory for the service/stage; Confirm applicable amendment options; do not require every flag to be selected; an explicit No counts as populated; Confirm legal-form and contract applicability; Non-applicable records excluded from denominator. Business confirmation required. | AO41: Signed Off
A42: Sprint 3 | B42: amendment_type | C42: DED_Data_Table_179 | D42: amend_board_of_directors | E42: DED_Attribute_2655 | F42: 4733d60d-0cf2-44bf-b7de-396ad790a24e | G42: 23c4c4cd-70d5-4650-930e-3f1b7061d853 | H42: DQP-2740 | I42: DQO-2740 | J42: Compl_Chk-amen_type-amend_board_of_directors | K42: Validate that the critical data element amendment_type.amend_board_of_directors is populated and not blank for in-scope records.Profiling results were used to identify current null/blank exposure where available. | L42: Completeness | M42: Attribute | N42: Business Registration & Licensing | تسجيل الأعمال والتراخيص | O42: rfmdaas@adra.gov.ae, bmalkindi@adra.gov.ae | P42: asalmehiry@adra.gov.ae, rfmdaas@adra.gov.ae | Q42: Accela | R42: DED_Data_Table_179 | S42: DED_Attribute_2655 | T42: Custom | U42: !isNull({amend_board_of_directors}) | V42: 0.95 | W42: Weekly | X42: DQI | Y42: High | Z42: {rec_status} == 'A' | AA42: Active | AB42: 46310 | AD42: Business | AE42: Yes | AF42: Approved | AG42: 9/17 approve | AJ42: No | AO42: Signed Off
A43: Sprint 3 | B43: amendment_type | C43: DED_Data_Table_179 | D43: license_type_amendment | E43: DED_Attribute_2657 | F43: 239e3083-9d3b-4cca-99d7-221887cb9299 | G43: abd833d5-0e92-479e-82de-1bb6001ae414 | H43: DQP-2962 | I43: DQO-2962 | J43: Compl_Chk-amendment_type-license_type_amendment | K43: Validate that the critical data element amendment_type.license_type_amendment is populated and not blank for in-scope records.Profiling results were used to identify current null/blank exposure where available. | L43: Completeness | M43: Attribute | N43: Business Registration & Licensing | تسجيل الأعمال والتراخيص | O43: rfmdaas@adra.gov.ae, bmalkindi@adra.gov.ae | P43: asalmehiry@adra.gov.ae, rfmdaas@adra.gov.ae | Q43: Accela | R43: DED_Data_Table_179 | S43: DED_Attribute_2657 | T43: Custom | U43: !isNull({license_type_amendment}) | V43: 0.95 | W43: Weekly | X43: DQI | Y43: High | Z43: {rec_status} == 'A' | AA43: Active | AB43: 46310 | AD43: Technical | AE43: No | AF43: In Review | AJ43: Yes | AK43: Rejected | AL43: Samer | AM43: 30/09/2026 - No | AO43: Signed Off
A44: Sprint 3 | B44: amendment_type | C44: DED_Data_Table_179 | D44: legal_form_amendment | E44: DED_Attribute_2658 | F44: 897f1a1e-69d7-4e0e-9a43-0db73e1bd9a2 | G44: b69501b8-7a43-4f9d-b8f7-4b7db6927c10 | H44: DQP-2963 | I44: DQO-2963 | J44: Compl_Chk-amendment_type-legal_form_amendment | K44: Validate that the critical data element amendment_type.legal_form_amendment is populated and not blank for in-scope records.Profiling results were used to identify current null/blank exposure where available. | L44: Completeness | M44: Attribute | N44: Business Registration & Licensing | تسجيل الأعمال والتراخيص | O44: rfmdaas@adra.gov.ae, bmalkindi@adra.gov.ae | P44: asalmehiry@adra.gov.ae, rfmdaas@adra.gov.ae | Q44: Accela | R44: DED_Data_Table_179 | S44: DED_Attribute_2658 | T44: Custom | U44: !isNull({legal_form_amendment}) | V44: 0.95 | W44: Weekly | X44: DQI | Y44: High | Z44: {rec_status} == 'A' | AA44: Active | AB44: 46310 | AD44: Technical | AE44: No | AF44: In Review | AJ44: Yes | AK44: Rejected | AL44: Samer | AM44: 30/09/2026 - No | AO44: Signed Off
A45: Sprint 3 | B45: amendment_type | C45: DED_Data_Table_179 | D45: partners_shares_amendment_c | E45: DED_Attribute_2659 | F45: 2dfa443b-68d1-4205-a99f-9670e3029ec2 | G45: 7007e825-0fd2-45f0-b412-3299523f55ee | H45: DQP-2964 | I45: DQO-2964 | J45: Compl_Chk-amen_type-partners_shares_amendment_c | K45: Validate that the critical data element amendment_type.partners_shares_amendment_c is populated and not blank for in-scope records.Profiling results were used to identify current null/blank exposure where available. | L45: Completeness | M45: Attribute | N45: Business Registration & Licensing | تسجيل الأعمال والتراخيص | O45: rfmdaas@adra.gov.ae, bmalkindi@adra.gov.ae | P45: asalmehiry@adra.gov.ae, rfmdaas@adra.gov.ae | Q45: Accela | R45: DED_Data_Table_179 | S45: DED_Attribute_2659 | T45: Custom | U45: !isNull({partners_shares_amendment_c}) | V45: 0.95 | W45: Weekly | X45: DQI | Y45: High | Z45: {rec_status} == 'A' | AA45: Active | AB45: 46310 | AD45: Technical | AE45: No | AF45: In Review | AJ45: Yes | AK45: Rejected | AL45: Samer | AM45: 30/09/2026 - No | AO45: Signed Off
A46: Sprint 3 | B46: amendment_type | C46: DED_Data_Table_179 | D46: country_amendment_foreign_company_c | E46: DED_Attribute_2660 | F46: bdd142d6-4233-444a-a659-2b7e9c95fe2c | G46: e648b9b6-34cc-418c-b82e-2408440b04c4 | H46: DQP-2965 | I46: DQO-2965 | J46: Compl_Chk-amen_typ-count_amen_foreign_company_c | K46: Validate that the critical data element amendment_type.country_amendment_foreign_company_c is populated and not blank for in-scope records.Profiling results were used to identify current null/blank exposure where available. | L46: Completeness | M46: Attribute | N46: Business Registration & Licensing | تسجيل الأعمال والتراخيص | O46: rfmdaas@adra.gov.ae, bmalkindi@adra.gov.ae | P46: asalmehiry@adra.gov.ae, rfmdaas@adra.gov.ae | Q46: Accela | R46: DED_Data_Table_179 | S46: DED_Attribute_2660 | T46: Custom | U46: !isNull({country_amendment_foreign_company_c}) | V46: 0.95 | W46: Weekly | X46: DQI | Y46: High | Z46: {rec_status} == 'A' | AA46: Active | AB46: 46310 | AD46: Technical | AE46: No | AF46: In Review | AJ46: Yes | AK46: Rejected | AL46: Samer | AM46: 30/09/2026 - No | AO46: Signed Off
A47: Sprint 3 | B47: amendment_type | C47: DED_Data_Table_179 | D47: capital_amendment_c | E47: DED_Attribute_2661 | F47: 3af6af11-445b-456a-b753-9cb69a7f0cbf | G47: 1357d163-95ff-453d-b7d4-8962392363ed | H47: DQP-2966 | I47: DQO-2966 | J47: Compl_Chk-amendment_type-capital_amendment_c | K47: Validate that the critical data element amendment_type.capital_amendment_c is populated and not blank for in-scope records.Profiling results were used to identify current null/blank exposure where available. | L47: Completeness | M47: Attribute | N47: Business Registration & Licensing | تسجيل الأعمال والتراخيص | O47: rfmdaas@adra.gov.ae, bmalkindi@adra.gov.ae | P47: asalmehiry@adra.gov.ae, rfmdaas@adra.gov.ae | Q47: Accela | R47: DED_Data_Table_179 | S47: DED_Attribute_2661 | T47: Custom | U47: !isNull({capital_amendment_c}) | V47: 0.95 | W47: Weekly | X47: DQI | Y47: High | Z47: {rec_status} == 'A' | AA47: Active | AB47: 46310 | AD47: Technical | AE47: No | AF47: In Review | AJ47: Yes | AK47: Rejected | AL47: Samer | AM47: 30/09/2026 - No | AO47: Signed Off
A48: Sprint 3 | B48: amendment_type | C48: DED_Data_Table_179 | D48: activity_replacement_c | E48: DED_Attribute_2662 | F48: b5b16ce7-2527-4d6b-883d-ed4fb60e9eb2 | G48: ff3c7a87-41e4-4145-bd43-1a133ec46f8b | H48: DQP-2967 | I48: DQO-2967 | J48: Compl_Chk-amendment_type-activity_replacement_c | K48: Validate that the critical data element amendment_type.activity_replacement_c is populated and not blank for in-scope records.Profiling results were used to identify current null/blank exposure where available. | L48: Completeness | M48: Attribute | N48: Business Registration & Licensing | تسجيل الأعمال والتراخيص | O48: rfmdaas@adra.gov.ae, bmalkindi@adra.gov.ae | P48: asalmehiry@adra.gov.ae, rfmdaas@adra.gov.ae | Q48: Accela | R48: DED_Data_Table_179 | S48: DED_Attribute_2662 | T48: Custom | U48: !isNull({activity_replacement_c}) | V48: 0.95 | W48: Weekly | X48: DQI | Y48: High | Z48: {rec_status} == 'A' | AA48: Active | AB48: 46310 | AD48: Technical | AE48: No | AF48: In Review | AJ48: Yes | AK48: Rejected | AL48: Samer | AM48: 30/09/2026 - No | AO48: Signed Off
A49: Sprint 3 | B49: amendment_type | C49: DED_Data_Table_179 | D49: authorized_signatories_amendment | E49: DED_Attribute_2663 | F49: 1bf636f3-fd05-4276-88f0-3463d781525f | G49: 7125e79c-064f-4a41-8808-468548c87083 | H49: DQP-2968 | I49: DQO-2968 | J49: Comp_Chk-amen_typ-authorized_signator_amendment | K49: Validate that the critical data element amendment_type.authorized_signatories_amendment is populated and not blank for in-scope records.Profiling results were used to identify current null/blank exposure where available. | L49: Completeness | M49: Attribute | N49: Business Registration & Licensing | تسجيل الأعمال والتراخيص | O49: rfmdaas@adra.gov.ae, bmalkindi@adra.gov.ae | P49: asalmehiry@adra.gov.ae, rfmdaas@adra.gov.ae | Q49: Accela | R49: DED_Data_Table_179 | S49: DED_Attribute_2663 | T49: Custom | U49: !isNull({authorized_signatories_amendment}) | V49: 0.95 | W49: Weekly | X49: DQI | Y49: High | Z49: {rec_status} == 'A' | AA49: Active | AB49: 46310 | AD49: Technical | AE49: No | AF49: In Review | AJ49: Yes | AK49: Approved | AL49: Samer | AM49: 30/09/2026 - Yes Service: Licenses / License / Amendment / NA. REC_STATUS = 'A'; evaluate only where authorized_signatories_amendment is mandatory for the service/stage; Confirm applicable amendment options; do not require every flag to be selected; an explicit No counts as populated; Non-applicable records excluded from denominator. Business confirmation required. | AO49: Signed Off
A50: Sprint 3 | B50: amendment_type | C50: DED_Data_Table_179 | D50: signboard_amendment_c | E50: DED_Attribute_2664 | F50: bd2d4717-c077-4673-9186-6613ab1cfb84 | G50: b9012925-d964-4fe1-a174-3b7226564938 | H50: DQP-2969 | I50: DQO-2969 | J50: Compl_Chk-amendment_type-signboard_amendment_c | K50: Validate that the critical data element amendment_type.signboard_amendment_c is populated and not blank for in-scope records.Profiling results were used to identify current null/blank exposure where available. | L50: Completeness | M50: Attribute | N50: Business Registration & Licensing | تسجيل الأعمال والتراخيص | O50: rfmdaas@adra.gov.ae, bmalkindi@adra.gov.ae | P50: asalmehiry@adra.gov.ae, rfmdaas@adra.gov.ae | Q50: Accela | R50: DED_Data_Table_179 | S50: DED_Attribute_2664 | T50: Custom | U50: !isNull({signboard_amendment_c}) | V50: 0.95 | W50: Weekly | X50: DQI | Y50: High | Z50: {rec_status} == 'A' | AA50: Active | AB50: 46310 | AD50: Technical | AE50: No | AF50: In Review | AJ50: Yes | AK50: Rejected | AL50: Samer | AM50: 30/09/2026 - No | AO50: Signed Off
A51: Sprint 3 | B51: amendment_type | C51: DED_Data_Table_179 | D51: trade_name_amendment_c | E51: DED_Attribute_2665 | F51: dcc0a4ea-586b-4e2c-8293-28495b4753c9 | G51: b4adee4a-40b2-494a-b2ea-c902521019ca | H51: DQP-2970 | I51: DQO-2970 | J51: Compl_Chk-amendment_type-trade_name_amendment_c | K51: Validate that the critical data element amendment_type.trade_name_amendment_c is populated and not blank for in-scope records.Profiling results were used to identify current null/blank exposure where available. | L51: Completeness | M51: Attribute | N51: Business Registration & Licensing | تسجيل الأعمال والتراخيص | O51: rfmdaas@adra.gov.ae, bmalkindi@adra.gov.ae | P51: asalmehiry@adra.gov.ae, rfmdaas@adra.gov.ae | Q51: Accela | R51: DED_Data_Table_179 | S51: DED_Attribute_2665 | T51: Custom | U51: !isNull({trade_name_amendment_c}) | V51: 0.95 | W51: Weekly | X51: DQI | Y51: High | Z51: {rec_status} == 'A' | AA51: Active | AB51: 46310 | AD51: Technical | AE51: No | AF51: In Review | AJ51: Yes | AK51: Rejected | AL51: Samer | AM51: 30/09/2026 - No | AO51: Signed Off
A52: Sprint 3 | B52: amendment_type | C52: DED_Data_Table_179 | D52: manager_amendment_c | E52: DED_Attribute_2666 | F52: 0a30d424-bd38-4fce-9614-3b56ce5d2dcd | G52: e7c9d715-3d3f-4633-9f9e-dc3da8a8cc66 | H52: DQP-2971 | I52: DQO-2971 | J52: Compl_Chk-amendment_type-manager_amendment_c | K52: Validate that the critical data element amendment_type.manager_amendment_c is populated and not blank for in-scope records.Profiling results were used to identify current null/blank exposure where available. | L52: Completeness | M52: Attribute | N52: Business Registration & Licensing | تسجيل الأعمال والتراخيص | O52: rfmdaas@adra.gov.ae, bmalkindi@adra.gov.ae | P52: asalmehiry@adra.gov.ae, rfmdaas@adra.gov.ae | Q52: Accela | R52: DED_Data_Table_179 | S52: DED_Attribute_2666 | T52: Custom | U52: !isNull({manager_amendment_c}) | V52: 0.95 | W52: Weekly | X52: DQI | Y52: High | Z52: {rec_status} == 'A' | AA52: Active | AB52: 46310 | AD52: Technical | AE52: No | AF52: In Review | AJ52: Yes | AK52: Rejected | AL52: Samer | AM52: 30/09/2026 - No | AO52: Signed Off
A53: Sprint 3 | B53: amendment_type | C53: DED_Data_Table_179 | D53: technical_amendment | E53: DED_Attribute_2667 | F53: 4b8a9abf-c937-4228-a672-6ff9e6ae2684 | G53: db21bb2b-2cc5-435a-9fde-2e3b992ec855 | H53: DQP-2741 | I53: DQO-2741 | J53: Compl_Chk-amendment_type-technical_amendment | K53: Validate that the critical data element amendment_type.technical_amendment is populated and not blank for in-scope records.Profiling results were used to identify current null/blank exposure where available. | L53: Completeness | M53: Attribute | N53: Business Registration & Licensing | تسجيل الأعمال والتراخيص | O53: rfmdaas@adra.gov.ae, bmalkindi@adra.gov.ae | P53: asalmehiry@adra.gov.ae, rfmdaas@adra.gov.ae | Q53: Accela | R53: DED_Data_Table_179 | S53: DED_Attribute_2667 | T53: Custom | U53: !isNull({technical_amendment}) | V53: 0.95 | W53: Weekly | X53: DQI | Y53: High | Z53: {rec_status} == 'A' | AA53: Active | AB53: 46310 | AD53: Business | AE53: Yes | AF53: Approved | AG53: 9/17 approve | AJ53: No | AO53: Signed Off
A54: Sprint 3 | B54: amendment_type | C54: DED_Data_Table_179 | D54: amend_managers | E54: DED_Attribute_2668 | F54: 743ee8fa-7013-4a5c-9283-81240cad9db5 | G54: c8fbe611-e4cc-4f73-8f20-13dbe3848a30 | H54: DQP-2972 | I54: DQO-2972 | J54: Compl_Chk-amendment_type-amend_managers | K54: Validate that the critical data element amendment_type.amend_managers is populated and not blank for in-scope records.Profiling results were used to identify current null/blank exposure where available. | L54: Completeness | M54: Attribute | N54: Business Registration & Licensing | تسجيل الأعمال والتراخيص | O54: rfmdaas@adra.gov.ae, bmalkindi@adra.gov.ae | P54: asalmehiry@adra.gov.ae, rfmdaas@adra.gov.ae | Q54: Accela | R54: DED_Data_Table_179 | S54: DED_Attribute_2668 | T54: Custom | U54: !isNull({amend_managers}) | V54: 0.95 | W54: Weekly | X54: DQI | Y54: High | Z54: {rec_status} == 'A' | AA54: Active | AB54: 46310 | AD54: Technical | AE54: No | AF54: In Review | AJ54: Yes | AK54: Approved | AL54: Samer | AM54: 30/09/2026 - Yes Approved exact four-level service paths from O:R; do not cross-combine listed subtypes/categories. REC_STATUS = 'A'; evaluate only where amend_managers is mandatory for the service/stage; Confirm applicable amendment options; do not require every flag to be selected; an explicit No counts as populated; Non-applicable records excluded from denominator. Business confirmation required. | AO54: Signed Off
A55: Sprint 3 | B55: amendment_type | C55: DED_Data_Table_179 | D55: heirs_amendment_c | E55: DED_Attribute_2669 | F55: b1696f47-0b4f-467f-be92-88f693a0776e | G55: 3eb7994c-0fe4-4275-b1c4-7392fcba6471 | H55: DQP-2973 | I55: DQO-2973 | J55: Compl_Chk-amendment_type-heirs_amendment_c | K55: Validate that the critical data element amendment_type.heirs_amendment_c is populated and not blank for in-scope records.Profiling results were used to identify current null/blank exposure where available. | L55: Completeness | M55: Attribute | N55: Business Registration & Licensing | تسجيل الأعمال والتراخيص | O55: rfmdaas@adra.gov.ae, bmalkindi@adra.gov.ae | P55: asalmehiry@adra.gov.ae, rfmdaas@adra.gov.ae | Q55: Accela | R55: DED_Data_Table_179 | S55: DED_Attribute_2669 | T55: Custom | U55: !isNull({heirs_amendment_c}) | V55: 0.95 | W55: Weekly | X55: DQI | Y55: High | Z55: {rec_status} == 'A' | AA55: Active | AB55: 46310 | AD55: Technical | AE55: No | AF55: In Review | AJ55: Yes | AK55: Rejected | AL55: Samer | AM55: 30/09/2026 - No | AO55: Signed Off
A56: Sprint 3 | B56: amendment_type | C56: DED_Data_Table_179 | D56: license_type_amendment_c | E56: DED_Attribute_2670 | F56: 63635034-e526-4fdc-9a7c-db914c781bb5 | G56: bb22074b-2df1-43e6-a259-82cd076d068f | H56: DQP-2974 | I56: DQO-2974 | J56: Comp_Chk-amendme_type-license_type_amendment_c | K56: Validate that the critical data element amendment_type.license_type_amendment_c is populated and not blank for in-scope records.Profiling results were used to identify current null/blank exposure where available. | L56: Completeness | M56: Attribute | N56: Business Registration & Licensing | تسجيل الأعمال والتراخيص | O56: rfmdaas@adra.gov.ae, bmalkindi@adra.gov.ae | P56: asalmehiry@adra.gov.ae, rfmdaas@adra.gov.ae | Q56: Accela | R56: DED_Data_Table_179 | S56: DED_Attribute_2670 | T56: Custom | U56: !isNull({license_type_amendment_c}) | V56: 0.95 | W56: Weekly | X56: DQI | Y56: High | Z56: {rec_status} == 'A' | AA56: Active | AB56: 46310 | AD56: Technical | AE56: No | AF56: In Review | AJ56: Yes | AK56: Rejected | AL56: Samer | AM56: 30/09/2026 - No | AO56: Signed Off
A57: Sprint 3 | B57: amendment_type | C57: DED_Data_Table_179 | D57: sponsor_amendment_c | E57: DED_Attribute_2671 | F57: ceb88951-2d9a-4247-bc35-9a0281ee7029 | G57: 97510b17-463e-45a9-8e91-2314e24a6726 | H57: DQP-2975 | I57: DQO-2975 | J57: Compl_Chk-amendment_type-sponsor_amendment_c | K57: Validate that the critical data element amendment_type.sponsor_amendment_c is populated and not blank for in-scope records.Profiling results were used to identify current null/blank exposure where available. | L57: Completeness | M57: Attribute | N57: Business Registration & Licensing | تسجيل الأعمال والتراخيص | O57: rfmdaas@adra.gov.ae, bmalkindi@adra.gov.ae | P57: asalmehiry@adra.gov.ae, rfmdaas@adra.gov.ae | Q57: Accela | R57: DED_Data_Table_179 | S57: DED_Attribute_2671 | T57: Custom | U57: !isNull({sponsor_amendment_c}) | V57: 0.95 | W57: Weekly | X57: DQI | Y57: High | Z57: {rec_status} == 'A' | AA57: Active | AB57: 46310 | AD57: Technical | AE57: No | AF57: In Review | AJ57: Yes | AK57: Rejected | AL57: Samer | AM57: 30/09/2026 - No | AO57: Signed Off
A58: Sprint 3 | B58: amendment_type | C58: DED_Data_Table_179 | D58: partners_amendment_c | E58: DED_Attribute_2672 | F58: 15601fe5-cf04-493f-89b3-86257bb07f2e | G58: 14f3a6e8-17c6-4cc9-be33-69ad36afb098 | H58: DQP-2976 | I58: DQO-2976 | J58: Compl_Chk-amendment_type-partners_amendment_c | K58: Validate that the critical data element amendment_type.partners_amendment_c is populated and not blank for in-scope records.Profiling results were used to identify current null/blank exposure where available. | L58: Completeness | M58: Attribute | N58: Business Registration & Licensing | تسجيل الأعمال والتراخيص | O58: rfmdaas@adra.gov.ae, bmalkindi@adra.gov.ae | P58: asalmehiry@adra.gov.ae, rfmdaas@adra.gov.ae | Q58: Accela | R58: DED_Data_Table_179 | S58: DED_Attribute_2672 | T58: Custom | U58: !isNull({partners_amendment_c}) | V58: 0.95 | W58: Weekly | X58: DQI | Y58: High | Z58: {rec_status} == 'A' | AA58: Active | AB58: 46310 | AD58: Technical | AE58: No | AF58: In Review | AJ58: Yes | AK58: Rejected | AL58: Samer | AM58: 30/09/2026 - No | AO58: Signed Off
A59: Sprint 3 | B59: amendment_type | C59: DED_Data_Table_179 | D59: partners_nationality_amendment | E59: DED_Attribute_2673 | F59: d87d0766-dd89-43f0-acc1-20cafd77e040 | G59: dbe264b8-f797-4750-a4f8-a114134540a9 | H59: DQP-2977 | I59: DQO-2977 | J59: Comp_Chk-amen_type-partners_nationali_amendment | K59: Validate that the critical data element amendment_type.partners_nationality_amendment is populated and not blank for in-scope records.Profiling results were used to identify current null/blank exposure where available. | L59: Completeness | M59: Attribute | N59: Business Registration & Licensing | تسجيل الأعمال والتراخيص | O59: rfmdaas@adra.gov.ae, bmalkindi@adra.gov.ae | P59: asalmehiry@adra.gov.ae, rfmdaas@adra.gov.ae | Q59: Accela | R59: DED_Data_Table_179 | S59: DED_Attribute_2673 | T59: Custom | U59: !isNull({partners_nationality_amendment}) | V59: 0.95 | W59: Weekly | X59: DQI | Y59: High | Z59: {rec_status} == 'A' | AA59: Active | AB59: 46310 | AD59: Technical | AE59: No | AF59: In Review | AJ59: Yes | AK59: Rejected | AL59: Samer | AM59: 30/09/2026 - No | AO59: Signed Off
A60: Sprint 3 | B60: amendment_type | C60: DED_Data_Table_179 | D60: legal_form_amendment_c | E60: DED_Attribute_2674 | F60: 76899b4a-31a0-4a82-bfb8-5eb624a66c34 | G60: 39307484-0dea-4a0b-bea5-17ce95dd4aea | H60: DQP-2978 | I60: DQO-2978 | J60: Compl_Chk-amendment_type-legal_form_amendment_c | K60: Validate that the critical data element amendment_type.legal_form_amendment_c is populated and not blank for in-scope records.Profiling results were used to identify current null/blank exposure where available. | L60: Completeness | M60: Attribute | N60: Business Registration & Licensing | تسجيل الأعمال والتراخيص | O60: rfmdaas@adra.gov.ae, bmalkindi@adra.gov.ae | P60: asalmehiry@adra.gov.ae, rfmdaas@adra.gov.ae | Q60: Accela | R60: DED_Data_Table_179 | S60: DED_Attribute_2674 | T60: Custom | U60: !isNull({legal_form_amendment_c}) | V60: 0.95 | W60: Weekly | X60: DQI | Y60: High | Z60: {rec_status} == 'A' | AA60: Active | AB60: 46310 | AD60: Technical | AE60: No | AF60: In Review | AJ60: Yes | AK60: Rejected | AL60: Samer | AM60: 30/09/2026 - No | AO60: Signed Off
A61: Sprint 3 | B61: amendment_type | C61: DED_Data_Table_179 | D61: amend_companies | E61: DED_Attribute_2675 | F61: c24e614a-ac9a-4a55-92e4-e5f104973f6e | G61: e90e151c-c01d-4228-b213-10005ff36f1b | H61: DQP-2742 | I61: DQO-2742 | J61: Compl_Chk-amendment_type-amend_companies | K61: Validate that the critical data element amendment_type.amend_companies is populated and not blank for in-scope records.Profiling results were used to identify current null/blank exposure where available. | L61: Completeness | M61: Attribute | N61: Business Registration & Licensing | تسجيل الأعمال والتراخيص | O61: rfmdaas@adra.gov.ae, bmalkindi@adra.gov.ae | P61: asalmehiry@adra.gov.ae, rfmdaas@adra.gov.ae | Q61: Accela | R61: DED_Data_Table_179 | S61: DED_Attribute_2675 | T61: Custom | U61: !isNull({amend_companies}) | V61: 0.95 | W61: Weekly | X61: DQI | Y61: High | Z61: {rec_status} == 'A' | AA61: Active | AB61: 46310 | AD61: Business | AE61: Yes | AF61: Approved | AG61: 9/17 approve | AJ61: No | AO61: Signed Off
A62: Sprint 1 | B62: Financial_Audit_Trail | C62: DED_Data_Table_001 | D62: INVOICE_NBR | E62: DED_Attribute_0006 | F62: 542acace-5df0-4cf5-afdd-0221a8be8c34 | G62: 84f30632-746a-4471-92b1-f5d36576bcb5 | H62: DQP-164 | I62: DQO-164 | J62: Comp_Chk-financial_audit_trail-invoice_nbr | K62: Checks that INVOICE_NBR in ACCOUNTING_AUDIT_TRAIL is populated for every in-scope record and is not null, blank, or whitespace-only. | L62: Completeness | M62: Attribute | N62: Financial Operations | العمليات المالية | O62: aiaalsheebani@ded.abudhabi.ae, rfmdaas@adra.gov.ae | P62: sraalbadi@ded.abudhabi.ae, rfmdaas@adra.gov.ae | Q62: Accela | R62: DED_Data_Table_001 | S62: DED_Attribute_0006 | T62: NotNull | V62: 0.95 | W62: Weekly | X62: DQI | Y62: Critical | Z62: NA | AA62: active | AB62: 46310 | AD62: Technical | AE62: No | AJ62: No | AO62: Signed Off
A63: Sprint 1 | B63: Financial_Audit_Trail | C63: DED_Data_Table_001 | D63: INVOICE_NBR | E63: DED_Attribute_0006 | F63: b33136b1-1f86-4444-8e5f-903f0d6c7870 | G63: 1e037027-b83d-468f-b806-e2058015450d | H63: DQP-165 | I63: DQO-165 | J63: Data_Val_Chk-financial_audit_trail-invoice_nbr | K63: Checks that INVOICE_NBR in ACCOUNTING_AUDIT_TRAIL conforms to the expected source/Purview data type (NUMBER) so the value can be parsed and used consistently. | L63: Validity | M63: Attribute | N63: Financial Operations | العمليات المالية | O63: aiaalsheebani@ded.abudhabi.ae, rfmdaas@adra.gov.ae | P63: sraalbadi@ded.abudhabi.ae, rfmdaas@adra.gov.ae | Q63: Accela | R63: DED_Data_Table_001 | S63: DED_Attribute_0006 | T63: TypeMatch | V63: 1 | W63: Weekly | X63: DQI | Y63: Critical | Z63: NA | AA63: active | AB63: 46310 | AD63: Technical | AE63: No | AJ63: No | AO63: Signed Off
A64: Sprint 1 | B64: Financial_Audit_Trail | C64: DED_Data_Table_001 | D64: INVOICE_NBR | E64: DED_Attribute_0006 | F64: deb91b5e-c5be-4fb3-ad7a-621d312a17e3 | G64: 1855b132-483e-43ce-9306-8067e7653d53 | H64: DQP-166 | I64: DQO-166 | J64: Numeric_Val_Chk-financial_audit_trail-INVOICE_NBR | K64: Checks that non-null INVOICE_NBR values are positive whole-number identifiers, rejecting decimals, zero, negative, and non-numeric values. | L64: Validity | M64: Attribute | N64: Financial Operations | العمليات المالية | O64: aiaalsheebani@ded.abudhabi.ae, rfmdaas@adra.gov.ae | P64: sraalbadi@ded.abudhabi.ae, rfmdaas@adra.gov.ae | Q64: Accela | R64: DED_Data_Table_001 | S64: DED_Attribute_0006 | T64: CustomSQL | U64: TRY_CAST(CAST( invoice_nbr AS STRING) AS DECIMAL(38, 18)) IS NOT NULL AND TRY_CAST(CAST( invoice_nbr AS STRING) AS DECIMAL(38, 18)) >= 0 | V64: 1 | W64: Weekly | X64: DQI | Y64: Critical | Z64: NA | AA64: active | AB64: 46310 | AD64: Technical | AE64: No | AJ64: No | AO64: Signed Off
A65: Sprint 1 | B65: Financial_Audit_Trail | C65: DED_Data_Table_001 | D65: RECEIPT_NBR | E65: DED_Attribute_0007 | F65: af3b5732-4bc8-4263-bc33-8ef11a8ebb7f | G65: 2258403d-6d74-4376-863d-14235aff50c9 | H65: DQP-167 | I65: DQO-167 | J65: Comp_Chk-financial_audit_trail-RECEIPT_NBR | K65: Checks that RECEIPT_NBR in ACCOUNTING_AUDIT_TRAIL is populated for every in-scope record and is not null, blank, or whitespace-only. | L65: Completeness | M65: Attribute | N65: Financial Operations | العمليات المالية | O65: aiaalsheebani@ded.abudhabi.ae, rfmdaas@adra.gov.ae | P65: sraalbadi@ded.abudhabi.ae, rfmdaas@adra.gov.ae | Q65: Accela | R65: DED_Data_Table_001 | S65: DED_Attribute_0007 | T65: NotNull | V65: 0.95 | W65: Weekly | X65: DQI | Y65: Critical | Z65: NA | AA65: active | AB65: 46310 | AD65: Technical | AE65: No | AJ65: No | AO65: Signed Off
A66: Sprint 1 | B66: Financial_Audit_Trail | C66: DED_Data_Table_001 | D66: RECEIPT_NBR | E66: DED_Attribute_0007 | F66: 38f986ec-4496-4bdb-9400-746913c8793e | G66: d52168c2-0683-49e1-ac0c-8c0e3cb585e8 | H66: DQP-168 | I66: DQO-168 | J66: Data_Val_Chk-financial_audit_trail-RECEIPT_NBR | K66: Checks that RECEIPT_NBR in ACCOUNTING_AUDIT_TRAIL conforms to the expected source/Purview data type (NUMBER) so the value can be parsed and used consistently. | L66: Validity | M66: Attribute | N66: Financial Operations | العمليات المالية | O66: aiaalsheebani@ded.abudhabi.ae, rfmdaas@adra.gov.ae | P66: sraalbadi@ded.abudhabi.ae, rfmdaas@adra.gov.ae | Q66: Accela | R66: DED_Data_Table_001 | S66: DED_Attribute_0007 | T66: TypeMatch | V66: 1 | W66: Weekly | X66: DQI | Y66: Critical | Z66: NA | AA66: active | AB66: 46310 | AD66: Technical | AE66: No | AJ66: No | AO66: Signed Off
A67: Sprint 1 | B67: Financial_Audit_Trail | C67: DED_Data_Table_001 | D67: RECEIPT_NBR | E67: DED_Attribute_0007 | F67: 3a87aa34-23b2-47de-8675-24e13d5348eb | G67: 9e5fe622-c022-475b-8373-e6620c7d1fbf | H67: DQP-169 | I67: DQO-169 | J67: Num_Val_Chk-financial_audit_trail-RECEIPT_NBR | K67: Checks that non-null RECEIPT_NBR values in ACCOUNTING_AUDIT_TRAIL are positive whole-number identifiers, rejecting decimals, zero, negative, and non-numeric values. It is the receipt number issued for the payment related to the transaction. | L67: Validity | M67: Attribute | N67: Financial Operations | العمليات المالية | O67: aiaalsheebani@ded.abudhabi.ae, rfmdaas@adra.gov.ae | P67: sraalbadi@ded.abudhabi.ae, rfmdaas@adra.gov.ae | Q67: Accela | R67: DED_Data_Table_001 | S67: DED_Attribute_0007 | T67: CustomSQL | U67: TRY_CAST(CAST( receipt_nbr AS STRING) AS DECIMAL(38, 18)) IS NOT NULL AND TRY_CAST(CAST( receipt_nbr AS STRING) AS DECIMAL(38, 18)) >= 0 | V67: 1 | W67: Weekly | X67: DQI | Y67: Critical | Z67: NA | AA67: active | AB67: 46310 | AD67: Technical | AE67: No | AJ67: No | AO67: Signed Off
A68: Sprint 1 | B68: Financial_Audit_Trail | C68: DED_Data_Table_001 | D68: PAYMENT_SEQ_NBR | E68: DED_Attribute_0008 | F68: deb51cdd-4f14-422e-b0d5-7f309bea9994 | G68: 14e0106e-67c4-4b0e-a1b6-8aa7e58486f0 | H68: DQP-170 | I68: DQO-170 | J68: Data_Val_Chk- fincl_audit_trail-PAYMENT_SEQ_NBR | K68: Checks that PAYMENT_SEQ_NBR in ACCOUNTING_AUDIT_TRAIL conforms to the expected source/Purview data type (NUMBER) so the value can be parsed and used consistently. | L68: Validity | M68: Attribute | N68: Financial Operations | العمليات المالية | O68: aiaalsheebani@ded.abudhabi.ae, rfmdaas@adra.gov.ae | P68: sraalbadi@ded.abudhabi.ae, rfmdaas@adra.gov.ae | Q68: Accela | R68: DED_Data_Table_001 | S68: DED_Attribute_0008 | T68: TypeMatch | V68: 1 | W68: Weekly | X68: DQI | Y68: Critical | Z68: NA | AA68: active | AB68: 46310 | AD68: Technical | AE68: No | AJ68: No | AO68: Signed Off
A69: Sprint 1 | B69: Financial_Audit_Trail | C69: DED_Data_Table_001 | D69: PAYMENT_SEQ_NBR | E69: DED_Attribute_0008 | F69: 7be25b54-04e2-4dab-a55d-84918d6ac79a | G69: a972de03-0c7c-434b-9de1-c1e153407f0e | H69: DQP-171 | I69: DQO-171 | J69: Num_Val_Chk- financial_audit_trail-PAYMENT_SEQ_NBR | K69: Checks that non-null PAYMENT_SEQ_NBR values in ACCOUNTING_AUDIT_TRAIL are positive whole-number identifiers, rejecting decimals, zero, negative, and non-numeric values. | L69: Validity | M69: Attribute | N69: Financial Operations | العمليات المالية | O69: aiaalsheebani@ded.abudhabi.ae, rfmdaas@adra.gov.ae | P69: sraalbadi@ded.abudhabi.ae, rfmdaas@adra.gov.ae | Q69: Accela | R69: DED_Data_Table_001 | S69: DED_Attribute_0008 | T69: CustomSQL | U69: TRY_CAST(CAST( payment_seq_nbr AS STRING) AS DECIMAL(38, 18)) IS NOT NULL AND TRY_CAST(CAST( payment_seq_nbr AS STRING) AS DECIMAL(38, 18)) >= 0 | V69: 1 | W69: Weekly | X69: DQI | Y69: Critical | Z69: NA | AA69: active | AB69: 46310 | AD69: Technical | AE69: No | AJ69: No | AO69: Signed Off
A70: Sprint 1 | B70: Financial_Audit_Trail | C70: DED_Data_Table_001 | D70: PAYMENT_SEQ_NBR | E70: DED_Attribute_0008 | F70: 0f66946d-45fb-401f-b7a7-5479d5a17e54 | G70: b1a14868-6a4f-4483-9f20-00e940b699d6 | H70: DQP-9009 | I70: DQO-9009 | J70: Comp_Chk- financial_audit_trail-PAYMENT_SEQ_NBR | K70: Checks that PAYMENT_SEQ_NBR in ACCOUNTING_AUDIT_TRAIL is populated for every in-scope record and is not null, blank, or whitespace-only. | L70: Completeness | M70: Attribute | N70: Financial Operations | العمليات المالية | O70: aiaalsheebani@ded.abudhabi.ae, rfmdaas@adra.gov.ae | P70: sraalbadi@ded.abudhabi.ae, rfmdaas@adra.gov.ae | Q70: Accela | R70: DED_Data_Table_001 | S70: DED_Attribute_0008 | T70: NotNull | V70: 0.95 | W70: Weekly | X70: DQI | Y70: Critical | Z70: NA | AA70: active | AB70: 46310 | AD70: Technical | AO70: Signed Off
A71: Sprint 1 | B71: Financial_Audit_Trail | C71: DED_Data_Table_001 | D71: FEEITEM_SEQ_NBR | E71: DED_Attribute_0011 | F71: facaeb31-8daf-4753-aec2-90ce418eabac | G71: e43a031f-0768-4b10-bf53-bb1c361a3318 | H71: DQP-172 | I71: DQO-172 | J71: Comp_Chk- financial_audit_trail-FEEITEM_SEQ_NBR | K71: Checks that FEEITEM_SEQ_NBR in ACCOUNTING_AUDIT_TRAIL is populated for every in-scope record and is not null, blank, or whitespace-only. | L71: Completeness | M71: Attribute | N71: Financial Operations | العمليات المالية | O71: aiaalsheebani@ded.abudhabi.ae, rfmdaas@adra.gov.ae | P71: sraalbadi@ded.abudhabi.ae, rfmdaas@adra.gov.ae | Q71: Accela | R71: DED_Data_Table_001 | S71: DED_Attribute_0011 | T71: NotNull | V71: 0.95 | W71: Weekly | X71: DQI | Y71: Critical | Z71: NA | AA71: active | AB71: 46310 | AD71: Technical | AE71: No | AJ71: No | AO71: Signed Off
A72: Sprint 1 | B72: Financial_Audit_Trail | C72: DED_Data_Table_001 | D72: FEEITEM_SEQ_NBR | E72: DED_Attribute_0011 | F72: bd7570c7-96c2-45f1-be25-9aea0efa7668 | G72: 47ebbcd8-3465-4acc-942a-c0354b7aee88 | H72: DQP-173 | I72: DQO-173 | J72: Data_Val_Chk- fincl_audit_trail-FEEITEM_SEQ_NBR | K72: Checks that FEEITEM_SEQ_NBR in ACCOUNTING_AUDIT_TRAIL conforms to the expected source/Purview data type (NUMBER) so the value can be parsed and used consistently. | L72: Validity | M72: Attribute | N72: Financial Operations | العمليات المالية | O72: aiaalsheebani@ded.abudhabi.ae, rfmdaas@adra.gov.ae | P72: sraalbadi@ded.abudhabi.ae, rfmdaas@adra.gov.ae | Q72: Accela | R72: DED_Data_Table_001 | S72: DED_Attribute_0011 | T72: TypeMatch | V72: 1 | W72: Weekly | X72: DQI | Y72: Critical | Z72: NA | AA72: active | AB72: 46310 | AD72: Technical | AE72: No | AJ72: No | AO72: Signed Off
A73: Sprint 1 | B73: Financial_Audit_Trail | C73: DED_Data_Table_001 | D73: FEEITEM_SEQ_NBR | E73: DED_Attribute_0011 | F73: d897d73b-0402-4aca-97ae-56c9733feaee | G73: 23b7de4e-9f1f-495e-9dec-ebd804c49534 | H73: DQP-174 | I73: DQO-174 | J73: Num_Val_Chk- financial_audit_trail-FEEITEM_SEQ_NBR | K73: Checks that non-null FEEITEM_SEQ_NBR values in ACCOUNTING_AUDIT_TRAIL are positive whole-number identifiers, rejecting decimals, zero, negative, and non-numeric values. | L73: Validity | M73: Attribute | N73: Financial Operations | العمليات المالية | O73: aiaalsheebani@ded.abudhabi.ae, rfmdaas@adra.gov.ae | P73: sraalbadi@ded.abudhabi.ae, rfmdaas@adra.gov.ae | Q73: Accela | R73: DED_Data_Table_001 | S73: DED_Attribute_0011 | T73: CustomSQL | U73: CAST(feeitem_seq_nbr AS INT) IS NOT NULL AND CAST(feeitem_seq_nbr AS INT) >= 0 AND CAST(feeitem_seq_nbr AS INT) = FLOOR(CAST(feeitem_seq_nbr AS INT)) | V73: 1 | W73: Weekly | X73: DQI | Y73: Critical | Z73: NA | AA73: active | AB73: 46310 | AD73: Technical | AE73: No | AJ73: No | AO73: Signed Off
A74: Sprint 1 | B74: Status_Lookup | C74: DED_Data_Table_002 | D74: APP_STATUS_GROUP_CODE | E74: DED_Attribute_0016 | F74: a2b86782-b81d-4eb6-bc6a-8fbb931b79a9 | G74: 6e8a7aba-a065-4589-9803-58dbeb77e7c2 | H74: DQP-226 | I74: DQO-226 | J74: Validity_Chk-Status_Lookup-APP_STATUS_GROUP_CODE | K74: Checks that the application status group matches an approved value, so the information remains valid and consistent. | L74: Validity | M74: Attribute | N74: Business Registration & Licensing | تسجيل الأعمال والتراخيص | O74: bmalkindi@adra.gov.ae, rfmdaas@adra.gov.ae | P74: asalmehiry@adra.gov.ae, rfmdaas@adra.gov.ae | Q74: Accela | R74: DED_Data_Table_002 | S74: DED_Attribute_0016 | T74: Regex | U74: ^[A-Za-z_.\- ]+$ | V74: 1 | W74: Weekly | X74: DQI | Y74: Critical | Z74: NA | AA74: active | AB74: 46310 | AD74: Technical | AE74: No | AJ74: No | AO74: Signed Off
A75: Sprint 1 | B75: Status_Lookup | C75: DED_Data_Table_002 | D75: APP_STATUS_GROUP_CODE | E75: DED_Attribute_0016 | F75: 698bb391-591a-417a-ab72-5338c7c265cd | G75: 177c164b-dff0-4bf9-9b6f-b4e1b0207a3a | H75: DQP-227 | I75: DQO-227 | J75: Completeness_Chk-Stat_Lookup-APP_STATUS_GROUP_CODE | K75: Checks that the application status group is provided for every status record, so the information is complete. | L75: Completeness | M75: Attribute | N75: Business Registration & Licensing | تسجيل الأعمال والتراخيص | O75: bmalkindi@adra.gov.ae, rfmdaas@adra.gov.ae | P75: asalmehiry@adra.gov.ae, rfmdaas@adra.gov.ae | Q75: Accela | R75: DED_Data_Table_002 | S75: DED_Attribute_0016 | T75: NotNull | V75: 0.95 | W75: Weekly | X75: DQI | Y75: Critical | Z75: NA | AA75: active | AB75: 46310 | AD75: Technical | AE75: No | AJ75: No | AO75: Signed Off
A76: Sprint 1 | B76: Status_Lookup | C76: DED_Data_Table_002 | D76: STATUS | E76: DED_Attribute_0017 | F76: 3f6e9cce-d832-4b48-84ec-fcd4e742e4f1 | G76: 490f82d6-f146-4f11-a8cb-2cc7d3f32a14 | H76: DQP-219 | I76: DQO-219 | J76: Completeness_Check-status-lookup-status | K76: Checks if STATUS is populated for every in-scope record and is not null, blank, or whitespace-only. Business meaning: Business data element 'status' captured in the APP_STATUS_GROUP dataset to support operational processing, compliance tracking, and reporting. | L76: Completeness | M76: Attribute | N76: Business Registration & Licensing | تسجيل الأعمال والتراخيص | O76: bmalkindi@adra.gov.ae, rfmdaas@adra.gov.ae | P76: asalmehiry@adra.gov.ae, rfmdaas@adra.gov.ae | Q76: Accela | R76: DED_Data_Table_002 | S76: DED_Attribute_0017 | T76: NotNull | V76: 0.95 | W76: Weekly | X76: DQI | Y76: Critical | Z76: NA | AA76: active | AB76: 46310 | AD76: Technical | AE76: No | AJ76: No | AO76: Signed Off
A77: Sprint 1 | B77: Status_Lookup | C77: DED_Data_Table_002 | D77: STATUS | E77: DED_Attribute_0017 | F77: 78ab3718-da96-4bad-909b-aabc959ece70 | G77: fa8023d3-b018-45af-9dc0-96115f5aecfa | H77: DQP-220 | I77: DQO-220 | J77: Data_Validity_Check-status_lookup-status | K77: Checks if STATUS conforms to the expected source/Purview data type (VARCHAR2) so the value can be parsed and used consistently. | L77: Validity | M77: Attribute | N77: Business Registration & Licensing | تسجيل الأعمال والتراخيص | O77: bmalkindi@adra.gov.ae, rfmdaas@adra.gov.ae | P77: asalmehiry@adra.gov.ae, rfmdaas@adra.gov.ae | Q77: Accela | R77: DED_Data_Table_002 | S77: DED_Attribute_0017 | T77: TypeMatch | V77: 1 | W77: Weekly | X77: DQI | Y77: Critical | Z77: NA | AA77: active | AB77: 46310 | AD77: Technical | AE77: No | AJ77: No | AO77: Signed Off
A78: Sprint 1 | B78: Status_Lookup | C78: DED_Data_Table_002 | D78: STATUS | E78: DED_Attribute_0017 | F78: 09fd7e26-fa24-4c5e-b648-d5f630ce5773 | G78: 2fdee6f1-865f-411f-a684-5ab42bc5a2b6 | H78: DQP-222 | I78: DQO-222 | J78: String_Format_Check-status_lookup-status | K78: Checks that non-null STATUS values follow the approved code/identifier format and length, preventing malformed values from entering reporting or integrations. | L78: Validity | M78: Attribute | N78: Business Registration & Licensing | تسجيل الأعمال والتراخيص | O78: bmalkindi@adra.gov.ae, rfmdaas@adra.gov.ae | P78: asalmehiry@adra.gov.ae, rfmdaas@adra.gov.ae | Q78: Accela | R78: DED_Data_Table_002 | S78: DED_Attribute_0017 | T78: Regex | U78: ^[A-Za-z_-]+(?: [A-Za-z_-]+)*$ | V78: 1 | W78: Weekly | X78: DQI | Y78: Critical | Z78: NA | AA78: active | AB78: 46310 | AD78: Technical | AE78: No | AJ78: No | AO78: Signed Off
A79: Sprint 1 | B79: Status_Lookup | C79: DED_Data_Table_002 | D79: STATUS | E79: DED_Attribute_0017 | F79: DQP-CR-00017 | G79: DQP-CR-00027 | H79: DQP-493 | I79: DQO-493 | J79: Accuracy_Check-Status_Lookup-STATUS | K79: Compares App_Status_Group.STATUS with App_Status_Group_i18n.STATUS for the same Silver business record. | L79: Accuracy | M79: Attribute | N79: DD - Economic Data | O79: bmalkindi@adra.gov.ae, rfmdaas@adra.gov.ae | P79: asalmehiry@adra.gov.ae, rfmdaas@adra.gov.ae | Q79: Accela | R79: DED_Data_Table_002 | S79: DED_Attribute_0017 | T79: Complex | V79: 0.9 | W79: Weekly | X79: DQI | Y79: Critical | Z79: NA | AA79: Draft | AB79: 30/07/26 | AD79: Technical | AE79: No | AJ79: No | AO79: Signed Off
A80: Sprint 1 | B80: Status_Lookup | C80: DED_Data_Table_002 | D80: SERV_PROV_CODE | E80: DED_Attribute_0019 | F80: fbebba0c-1dbe-4e32-9012-4397d0843136 | G80: 2fc3f137-a58d-45c1-8ff7-554d6c85222e | H80: DQP-217 | I80: DQO-217 | J80: Cus_Allow_Val_Chk-status_lookup-serv_prov_code | K80: Custom rule to validate for the list of allowed values for SERV_PROV_CODE. Allowed Values = "ADBC" | L80: Validity | M80: Attribute | N80: Business Registration & Licensing | تسجيل الأعمال والتراخيص | O80: bmalkindi@adra.gov.ae, rfmdaas@adra.gov.ae | P80: asalmehiry@adra.gov.ae, rfmdaas@adra.gov.ae | Q80: Accela | R80: DED_Data_Table_002 | S80: DED_Attribute_0019 | T80: CustomSQL | U80: serv_prov_code = "ADBC" | V80: 1 | W80: Weekly | X80: DQI | Y80: Critical | Z80: NA | AA80: active | AB80: 46310 | AD80: Technical | AE80: No | AJ80: No | AO80: Signed Off
A81: Sprint 1 | B81: Status_Lookup | C81: DED_Data_Table_002 | D81: SERV_PROV_CODE | E81: DED_Attribute_0019 | F81: eaf38526-585f-4382-9e68-84a321f3d459 | G81: 90536ccc-3a47-46b3-a82f-0b8c9f0c9da4 | H81: DQP-218 | I81: DQO-218 | J81: Completeness_Check-status_lookup-serv-prov-code | K81: Checks that SERV_PROV_CODE is populated for every in-scope record and is not either of null, blank, or whitespace-only. | L81: Completeness | M81: Attribute | N81: Business Registration & Licensing | تسجيل الأعمال والتراخيص | O81: bmalkindi@adra.gov.ae, rfmdaas@adra.gov.ae | P81: asalmehiry@adra.gov.ae, rfmdaas@adra.gov.ae | Q81: Accela | R81: DED_Data_Table_002 | S81: DED_Attribute_0019 | T81: NotNull | V81: 0.95 | W81: Weekly | X81: DQI | Y81: Critical | Z81: NA | AA81: active | AB81: 46310 | AD81: Technical | AE81: No | AJ81: No | AO81: Signed Off
A82: Sprint 1 | B82: Status_Lookup | C82: DED_Data_Table_002 | D82: SERV_PROV_CODE | E82: DED_Attribute_0019 | F82: 2cfec829-7f5e-498b-a7f7-9e47677c6bc3 | G82: 00c65898-58e1-47f3-b605-0d078930188c | H82: DQP-223 | I82: DQO-223 | J82: Data_Val_Chk-status_lookup-serv_prov_code | K82: Checks that SERV_PROV_CODE conforms to the expected source/Purview data type (VARCHAR2) so the value can be parsed and used consistently. | L82: Validity | M82: Attribute | N82: Business Registration & Licensing | تسجيل الأعمال والتراخيص | O82: bmalkindi@adra.gov.ae, rfmdaas@adra.gov.ae | P82: asalmehiry@adra.gov.ae, rfmdaas@adra.gov.ae | Q82: Accela | R82: DED_Data_Table_002 | S82: DED_Attribute_0019 | T82: TypeMatch | V82: 1 | W82: Weekly | X82: DQI | Y82: Critical | Z82: NA | AA82: active | AB82: 46310 | AD82: Technical | AE82: No | AJ82: No | AO82: Signed Off
A83: Sprint 1 | B83: Status_Lookup | C83: DED_Data_Table_002 | D83: SERV_PROV_CODE | E83: DED_Attribute_0019 | F83: 4e826247-6f90-442b-afa7-d316a3e1d9f7 | G83: 80a46cf3-06c7-4a66-b4a8-d55bb0513d8f | H83: DQP-224 | I83: DQO-224 | J83: Str_Check-status_lookup-serv_prov_code | K83: Checks that non-null SERV_PROV_CODE values follow the approved code/identifier format and length, preventing malformed values from entering reporting or integrations. | L83: Validity | M83: Attribute | N83: Business Registration & Licensing | تسجيل الأعمال والتراخيص | O83: bmalkindi@adra.gov.ae, rfmdaas@adra.gov.ae | P83: asalmehiry@adra.gov.ae, rfmdaas@adra.gov.ae | Q83: Accela | R83: DED_Data_Table_002 | S83: DED_Attribute_0019 | T83: CustomSQL | U83: serv_prov_code = "ADBC" | V83: 1 | W83: Weekly | X83: DQI | Y83: Critical | Z83: NA | AA83: active | AB83: 46310 | AD83: Technical | AE83: No | AJ83: No | AO83: Signed Off
A84: Sprint 1 | B84: Status_Lookup_Language | C84: DED_Data_Table_003 | D84: RES_ID | E84: DED_Attribute_0022 | F84: a1bf6c71-f317-4159-a4fe-75d86f072de7 | G84: b7bf4305-14c7-4b60-aa84-b36e3c10ecdc | H84: DQP-239 | I84: DQO-239 | J84: Completeness_Check-Status_Lookup_Language-RES_ID | K84: Checks that RES_ID in APP_STATUS_GROUP_I18N is populated for every in-scope record and is not null, blank, or whitespace-only. | L84: Completeness | M84: Attribute | N84: Business Registration & Licensing | تسجيل الأعمال والتراخيص | O84: bmalkindi@adra.gov.ae, rfmdaas@adra.gov.ae | P84: asalmehiry@adra.gov.ae, rfmdaas@adra.gov.ae | Q84: Accela | R84: DED_Data_Table_003 | S84: DED_Attribute_0022 | T84: NotNull | V84: 0.95 | W84: Weekly | X84: DQI | Y84: Critical | Z84: NA | AA84: active | AB84: 46310 | AD84: Technical | AE84: No | AJ84: No | AO84: Signed Off
A85: Sprint 1 | B85: Status_Lookup_Language | C85: DED_Data_Table_003 | D85: RES_ID | E85: DED_Attribute_0022 | F85: 426305da-c4e0-4e37-93a2-66971640d212 | G85: 0c5de629-a1ef-4b77-8074-c4997ad975ae | H85: DQP-240 | I85: DQO-240 | J85: Data_Validity_Check-Status_Lookup_Language-RES_ID | K85: Checks that RES_ID in APP_STATUS_GROUP_I18N conforms to the expected source/Purview data type (NUMBER) so the value can be parsed and used consistently. | L85: Validity | M85: Attribute | N85: Business Registration & Licensing | تسجيل الأعمال والتراخيص | O85: bmalkindi@adra.gov.ae, rfmdaas@adra.gov.ae | P85: asalmehiry@adra.gov.ae, rfmdaas@adra.gov.ae | Q85: Accela | R85: DED_Data_Table_003 | S85: DED_Attribute_0022 | T85: TypeMatch | V85: 1 | W85: Weekly | X85: DQI | Y85: Critical | Z85: NA | AA85: active | AB85: 46310 | AD85: Technical | AE85: No | AJ85: No | AO85: Signed Off
A86: Sprint 1 | B86: Status_Lookup_Language | C86: DED_Data_Table_003 | D86: RES_ID | E86: DED_Attribute_0022 | F86: ba6b58e3-4c09-4b68-bd92-ae3fc2591b96 | G86: e35c0863-a460-4e46-ae1f-d1ad43df7a9a | H86: DQP-241 | I86: DQO-241 | J86: Num_Val_Check-Status_Lookup_Language-RES_ID | K86: Checks that non-null RES_ID values in APP_STATUS_GROUP_I18N are positive whole-number identifiers, rejecting decimals, zero, negative, and non-numeric values. | L86: Validity | M86: Attribute | N86: Business Registration & Licensing | تسجيل الأعمال والتراخيص | O86: bmalkindi@adra.gov.ae, rfmdaas@adra.gov.ae | P86: asalmehiry@adra.gov.ae, rfmdaas@adra.gov.ae | Q86: Accela | R86: DED_Data_Table_003 | S86: DED_Attribute_0022 | T86: CustomSQL | U86: TRY_CAST(res_id AS DECIMAL(38, 10)) IS NOT NULL AND TRY_CAST(res_id AS DECIMAL(38, 10)) >= 0 | V86: 1 | W86: Weekly | X86: DQI | Y86: Critical | Z86: NA | AA86: active | AB86: 46310 | AD86: Technical | AE86: No | AJ86: No | AO86: Signed Off
A87: Sprint 1 | B87: Status_Lookup_Language | C87: DED_Data_Table_003 | D87: RES_ID | E87: DED_Attribute_0022 | F87: 5c26b732-8b57-4eee-8b45-26038cd009f1 | G87: abc58c13-5b29-4406-8509-f8143646fd2a | H87: DQP-250 | I87: DQO-250 | J87: Table_lookup_Check-Status_Lookup_Language-res_id | K87: This rule ensures if all the RES_ID values that are present in the APP_STATUS_I18 table exists in the APP_STATUS_GROUP table | L87: Accuracy | M87: Attribute | N87: Business Registration & Licensing | تسجيل الأعمال والتراخيص | O87: bmalkindi@adra.gov.ae, rfmdaas@adra.gov.ae | P87: asalmehiry@adra.gov.ae, rfmdaas@adra.gov.ae | Q87: Accela | R87: DED_Data_Table_003 | S87: DED_Attribute_0022 | T87: ReferenceCheck | V87: 0.9 | W87: Weekly | X87: DQI | Y87: Critical | Z87: NA | AA87: active | AB87: 46310 | AD87: Technical | AE87: No | AJ87: No | AO87: Signed Off
A88: Sprint 1 | B88: Status_Lookup_Language | C88: DED_Data_Table_003 | D88: LANG_ID | E88: DED_Attribute_0023 | F88: 99fd2a81-44ef-4a01-9cfd-d092c0227ba7 | G88: 097dc2a5-9022-4206-bc29-2a6891c7ef9f | H88: DQP-238 | I88: DQO-238 | J88: Completeness_Check-Status_Lookup_Language-lang_id | K88: Checks that LANG_ID in APP_STATUS_GROUP_I18N is populated for every in-scope record and is not null, blank, or whitespace-only. | L88: Completeness | M88: Attribute | N88: Business Registration & Licensing | تسجيل الأعمال والتراخيص | O88: bmalkindi@adra.gov.ae, rfmdaas@adra.gov.ae | P88: asalmehiry@adra.gov.ae, rfmdaas@adra.gov.ae | Q88: Accela | R88: DED_Data_Table_003 | S88: DED_Attribute_0023 | T88: NotNull | V88: 0.95 | W88: Weekly | X88: DQI | Y88: Critical | Z88: NA | AA88: active | AB88: 46310 | AD88: Technical | AE88: No | AJ88: No | AO88: Signed Off
A89: Sprint 1 | B89: Status_Lookup_Language | C89: DED_Data_Table_003 | D89: LANG_ID | E89: DED_Attribute_0023 | F89: 4defcb72-fc6f-4234-89e8-23135413d0bf | G89: afab7a45-454a-4d36-a41f-fad5492b9617 | H89: DQP-242 | I89: DQO-242 | J89: String_Format_Check-Status_Lookup_Language-LAN_ID | K89: Validates for allowed languages (English and Arabic) | L89: Validity | M89: Attribute | N89: Business Registration & Licensing | تسجيل الأعمال والتراخيص | O89: bmalkindi@adra.gov.ae, rfmdaas@adra.gov.ae | P89: asalmehiry@adra.gov.ae, rfmdaas@adra.gov.ae | Q89: Accela | R89: DED_Data_Table_003 | S89: DED_Attribute_0023 | T89: CustomTruth | U89: regexMatch({lang_id} ,'ar_AE') || regexMatch({lang_id} ,'en_US') | V89: 1 | W89: Weekly | X89: DQI | Y89: Critical | Z89: NA | AA89: active | AB89: 46310 | AD89: Technical | AE89: No | AJ89: No | AO89: Signed Off
A90: Sprint 1 | B90: Status_Lookup_Language | C90: DED_Data_Table_003 | D90: LANG_ID | E90: DED_Attribute_0023 | F90: de1bfbfb-c914-40b7-aa68-d5f3d82c09a4 | G90: 527d335c-6c5a-4e9d-8f67-30e9f7ba0e1e | H90: DQP-248 | I90: DQO-248 | J90: CustomCheck-status_lkp_lang-status_lang1 | K90: If LANG_ID is EN then Status Column's values should be in English | L90: Validity | M90: Attribute | N90: Business Registration & Licensing | تسجيل الأعمال والتراخيص | O90: bmalkindi@adra.gov.ae, rfmdaas@adra.gov.ae | P90: asalmehiry@adra.gov.ae, rfmdaas@adra.gov.ae | Q90: Accela | R90: DED_Data_Table_003 | S90: DED_Attribute_0023 | T90: CustomTruth | U90: {lang_id} != 'en_US' || regexMatch(trim(toString({status})), '^[a-zA-Z ]+$') | V90: 1 | W90: Weekly | X90: DQI | Y90: Critical | Z90: NA | AA90: active | AB90: 46310 | AD90: Technical | AE90: No | AJ90: No | AO90: Signed Off
A91: Sprint 1 | B91: Status_Lookup_Language | C91: DED_Data_Table_003 | D91: LANG_ID | E91: DED_Attribute_0023 | F91: bad2f0df-2b36-4fe5-9ad3-7ac22bc5609f | G91: b4f41f91-9e8a-4cff-bc54-3a05e204e9b3 | H91: DQP-249 | I91: DQO-249 | J91: CustomCheck-status_lkp_lang-status_lang | K91: If LANG_ID is AR then Status Column's values should be in Arabic | L91: Validity | M91: Attribute | N91: Business Registration & Licensing | تسجيل الأعمال والتراخيص | O91: bmalkindi@adra.gov.ae, rfmdaas@adra.gov.ae | P91: asalmehiry@adra.gov.ae, rfmdaas@adra.gov.ae | Q91: Accela | R91: DED_Data_Table_003 | S91: DED_Attribute_0023 | T91: CustomTruth | U91: {lang_id} != 'ar_AE'|| regexMatch(trim(toString({status})), '^[؀-ۿ ]+$') | V91: 1 | W91: Weekly | X91: DQI | Y91: Critical | Z91: NA | AA91: active | AB91: 46310 | AD91: Technical | AE91: No | AJ91: No | AO91: Signed Off
A92: Sprint 1 | B92: Status_Lookup_Language | C92: DED_Data_Table_003 | D92: STATUS | E92: DED_Attribute_0024 | F92: f2b601fa-6e66-419f-91ca-42480e542666 | G92: 7ddd8841-3457-40d0-8ddb-b49b68f16fb0 | H92: DQP-243 | I92: DQO-243 | J92: Completeness_Check-Status_Lookup_Language-STATUS | K92: Checks that STATUS in APP_STATUS_GROUP_I18N is populated for every in-scope record and is not null, blank, or whitespace-only. | L92: Completeness | M92: Attribute | N92: Business Registration & Licensing | تسجيل الأعمال والتراخيص | O92: bmalkindi@adra.gov.ae, rfmdaas@adra.gov.ae | P92: asalmehiry@adra.gov.ae, rfmdaas@adra.gov.ae | Q92: Accela | R92: DED_Data_Table_003 | S92: DED_Attribute_0024 | T92: NotNull | V92: 0.95 | W92: Weekly | X92: DQI | Y92: Critical | Z92: NA | AA92: active | AB92: 46310 | AD92: Technical | AE92: No | AJ92: No | AO92: Signed Off
A93: Sprint 1 | B93: Status_Lookup_Language | C93: DED_Data_Table_003 | D93: STATUS | E93: DED_Attribute_0024 | F93: 6c594b21-d671-4f87-bc46-ff353ec56657 | G93: 2d16c59b-da17-4d8a-acf6-4c641bebccb5 | H93: DQP-244 | I93: DQO-244 | J93: Data_Validity_Check-Status_Lookup_Language-STATUS | K93: Checks that STATUS in APP_STATUS_GROUP_I18N conforms to the expected source/Purview data type (VARCHAR2) so the value can be parsed and used consistently. | L93: Validity | M93: Attribute | N93: Business Registration & Licensing | تسجيل الأعمال والتراخيص | O93: bmalkindi@adra.gov.ae, rfmdaas@adra.gov.ae | P93: asalmehiry@adra.gov.ae, rfmdaas@adra.gov.ae | Q93: Accela | R93: DED_Data_Table_003 | S93: DED_Attribute_0024 | T93: TypeMatch | V93: 1 | W93: Weekly | X93: DQI | Y93: Critical | Z93: NA | AA93: active | AB93: 46310 | AD93: Technical | AE93: No | AJ93: No | AO93: Signed Off
A94: Sprint 1 | B94: Status_Lookup_Language | C94: DED_Data_Table_003 | D94: STATUS | E94: DED_Attribute_0024 | F94: 41f2960d-3440-4926-ad1d-1d7d1999587a | G94: 968b0869-072f-4c05-a3d2-9ae1a7278694 | H94: DQP-245 | I94: DQO-245 | J94: String_Format_Check-Status_Lookup_Language-STATUS | K94: Checks that non-null STATUS values in APP_STATUS_GROUP_I18N follow the approved code/identifier format and length, preventing malformed values from entering reporting or integrations. | L94: Validity | M94: Attribute | N94: Business Registration & Licensing | تسجيل الأعمال والتراخيص | O94: bmalkindi@adra.gov.ae, rfmdaas@adra.gov.ae | P94: asalmehiry@adra.gov.ae, rfmdaas@adra.gov.ae | Q94: Accela | R94: DED_Data_Table_003 | S94: DED_Attribute_0024 | T94: CustomTruth | U94: regexMatch(lower({status}), `^[a-z_-]+( [a-z_-]+)*$`) || regexMatch({status}, `^[؀-ۿ_-]+( [؀-ۿ_-]+)*$`) | V94: 1 | W94: Weekly | X94: DQI | Y94: Critical | Z94: NA | AA94: active | AB94: 46310 | AD94: Technical | AE94: No | AJ94: No | AO94: Signed Off
A95: Sprint 1 | B95: Application_Master | C95: DED_Data_Table_004 | D95: SERV_PROV_CODE | E95: DED_Attribute_0026 | F95: d9f6c1c0-2c68-4480-96cd-a740a92f0973 | G95: 4ec21fe3-07df-45b8-8122-19a6b001e9b7 | H95: DQP-192 | I95: DQO-192 | J95: Completeness_Check-appl_master-SERV_PROV_CODE | K95: Checks that B1PERMIT-SERV_PROV_CODE is populated for every in-scope record and is not null, blank, or whitespace-only. Business meaning: Unique code identifying the service provider (agency or jurisdiction) within the Accela system. | L95: Completeness | M95: Attribute | N95: Business Registration & Licensing | تسجيل الأعمال والتراخيص | O95: bmalkindi@adra.gov.ae, rfmdaas@adra.gov.ae | P95: asalmehiry@adra.gov.ae, rfmdaas@adra.gov.ae | Q95: Accela | R95: DED_Data_Table_004 | S95: DED_Attribute_0026 | T95: NotNull | V95: 0.95 | W95: Weekly | X95: DQI | Y95: Critical | Z95: NA | AA95: active | AB95: 46310 | AD95: Technical | AE95: No | AJ95: No | AO95: Signed Off
A96: Sprint 1 | B96: Application_Master | C96: DED_Data_Table_004 | D96: SERV_PROV_CODE | E96: DED_Attribute_0026 | F96: e902fb46-e479-4e09-b337-90bfe818db9f | G96: f8843268-1455-42e4-921c-77be66509ab4 | H96: DQP-193 | I96: DQO-193 | J96: FormatValidity_Check-appl_master-SERV_PROV_CODE | K96: Validates if SERV_PROV_CODE's values match 'ADBC' | L96: Validity | M96: Attribute | N96: Business Registration & Licensing | تسجيل الأعمال والتراخيص | O96: bmalkindi@adra.gov.ae, rfmdaas@adra.gov.ae | P96: asalmehiry@adra.gov.ae, rfmdaas@adra.gov.ae | Q96: Accela | R96: DED_Data_Table_004 | S96: DED_Attribute_0026 | T96: Custom SQL | U96: serv_prov_code = "ADBC" | V96: 1 | W96: Weekly | X96: DQI | Y96: Critical | Z96: NA | AA96: active | AB96: 46310 | AD96: Technical | AE96: No | AJ96: No | AO96: Signed Off
A97: Sprint 1 | B97: Application_Master | C97: DED_Data_Table_004 | D97: B1_PER_ID1 | E97: DED_Attribute_0027 | F97: 57a9827c-4d4b-49e6-abac-e68e27b323bb | G97: 656890f2-98d0-4fb2-9860-f01034cb84f2 | H97: DQP-194 | I97: DQO-194 | J97: Completeness_Check-Application_Master-B1_PER_ID1 | K97: Checks that B1PERMIT-B1_PER_ID1 is populated for every in-scope record and is not null, blank, or whitespace-only. Business meaning: First part of the permit/record identifier used to uniquely identify a business record in Accela. | L97: Completeness | M97: Attribute | N97: Business Registration & Licensing | تسجيل الأعمال والتراخيص | O97: bmalkindi@adra.gov.ae, rfmdaas@adra.gov.ae | P97: asalmehiry@adra.gov.ae, rfmdaas@adra.gov.ae | Q97: Accela | R97: DED_Data_Table_004 | S97: DED_Attribute_0027 | T97: NotNull | V97: 0.95 | W97: Weekly | X97: DQI | Y97: Critical | Z97: NA | AA97: active | AB97: 46310 | AD97: Technical | AE97: No | AJ97: No | AO97: Signed Off
A98: Sprint 1 | B98: Application_Master | C98: DED_Data_Table_004 | D98: B1_PER_ID1 | E98: DED_Attribute_0027 | F98: 98efd943-b582-483d-a721-4abf08c61a45 | G98: 24f59ed3-b4b9-4680-aa35-50e11fbd7ec5 | H98: DQP-195 | I98: DQO-195 | J98: Data_Val_Check-Application_Master-B1_PER_ID1 | K98: Checks that B1PERMIT-B1_PER_ID1 conforms to the expected source/Purview data type (VARCHAR2) so the value can be parsed and used consistently. Business meaning: First part of the permit/record identifier used to uniquely identify a business record in Accela. | L98: Validity | M98: Attribute | N98: Business Registration & Licensing | تسجيل الأعمال والتراخيص | O98: bmalkindi@adra.gov.ae, rfmdaas@adra.gov.ae | P98: asalmehiry@adra.gov.ae, rfmdaas@adra.gov.ae | Q98: Accela | R98: DED_Data_Table_004 | S98: DED_Attribute_0027 | T98: TypeMatch | V98: 1 | W98: Weekly | X98: DQI | Y98: Critical | Z98: NA | AA98: active | AB98: 46310 | AD98: Technical | AE98: No | AJ98: No | AO98: Signed Off
A99: Sprint 1 | B99: Application_Master | C99: DED_Data_Table_004 | D99: B1_PER_ID2 | E99: DED_Attribute_0028 | F99: c505da6d-fd19-4539-96f3-331f30c8d0a2 | G99: 413b2286-838c-4fa9-a7b5-f5c4adbeee61 | H99: DQP-196 | I99: DQO-196 | J99: Completeness_Check-Application_Master-B1_PER_ID2 | K99: Checks that B1PERMIT-B1_PER_ID2 is populated for every in-scope record and is not null, blank, or whitespace-only. Business meaning: Second part of the permit/record identifier used together with other ID parts to uniquely identify the record. | L99: Completeness | M99: Attribute | N99: Business Registration & Licensing | تسجيل الأعمال والتراخيص | O99: bmalkindi@adra.gov.ae, rfmdaas@adra.gov.ae | P99: asalmehiry@adra.gov.ae, rfmdaas@adra.gov.ae | Q99: Accela | R99: DED_Data_Table_004 | S99: DED_Attribute_0028 | T99: NotNull | V99: 0.95 | W99: Weekly | X99: DQI | Y99: Critical | Z99: NA | AA99: active | AB99: 46310 | AD99: Technical | AE99: No | AJ99: No | AO99: Signed Off
A100: Sprint 1 | B100: Application_Master | C100: DED_Data_Table_004 | D100: B1_PER_ID2 | E100: DED_Attribute_0028 | F100: a1b133ec-c6ec-440a-9717-c0ba2143e9d2 | G100: bd6e4f90-e7aa-4a45-8fe8-8edaea2b92e2 | H100: DQP-197 | I100: DQO-197 | J100: Data_Validity_Check-Application_Master-B1_PER_ID2 | K100: Checks that B1PERMIT-B1_PER_ID2 conforms to the expected source/Purview data type (VARCHAR2) so the value can be parsed and used consistently. Business meaning: Second part of the permit/record identifier used together with other ID parts to uniquely identify the record. | L100: Validity | M100: Attribute | N100: Business Registration & Licensing | تسجيل الأعمال والتراخيص | O100: bmalkindi@adra.gov.ae, rfmdaas@adra.gov.ae | P100: asalmehiry@adra.gov.ae, rfmdaas@adra.gov.ae | Q100: Accela | R100: DED_Data_Table_004 | S100: DED_Attribute_0028 | T100: TypeMatch | V100: 1 | W100: Weekly | X100: DQI | Y100: Critical | Z100: NA | AA100: active | AB100: 46310 | AD100: Technical | AE100: No | AJ100: No | AO100: Signed Off
A101: Sprint 1 | B101: Application_Master | C101: DED_Data_Table_004 | D101: B1_PER_ID3 | E101: DED_Attribute_0029 | F101: e9b233c4-999d-4b60-a6aa-5a0e431a0886 | G101: 3da49399-2a29-477c-bd75-433eda57b232 | H101: DQP-198 | I101: DQO-198 | J101: Completeness_Check-Application_Master-B1_PER_ID3 | K101: Checks that B1PERMIT-B1_PER_ID3 is populated for every in-scope record and is not null, blank, or whitespace-only. Business meaning: Third part of the permit/record identifier used together with other ID parts to uniquely identify the record. | L101: Completeness | M101: Attribute | N101: Business Registration & Licensing | تسجيل الأعمال والتراخيص | O101: bmalkindi@adra.gov.ae, rfmdaas@adra.gov.ae | P101: asalmehiry@adra.gov.ae, rfmdaas@adra.gov.ae | Q101: Accela | R101: DED_Data_Table_004 | S101: DED_Attribute_0029 | T101: NotNull | V101: 0.95 | W101: Weekly | X101: DQI | Y101: Critical | Z101: NA | AA101: active | AB101: 46310 | AD101: Technical | AE101: No | AJ101: No | AO101: Signed Off
A102: Sprint 1 | B102: Application_Master | C102: DED_Data_Table_004 | D102: B1_PER_ID3 | E102: DED_Attribute_0029 | F102: 171055d0-6040-46d1-9289-1252dccc3c2d | G102: 5f03d8d8-70d9-4303-9181-d0dc63e09977 | H102: DQP-199 | I102: DQO-199 | J102: Data_Validity_Check-Application_Master-B1_PER_ID3 | K102: Checks that B1PERMIT-B1_PER_ID3 conforms to the expected source/Purview data type (VARCHAR2) so the value can be parsed and used consistently. Business meaning: Third part of the permit/record identifier used together with other ID parts to uniquely identify the record. | L102: Validity | M102: Attribute | N102: Business Registration & Licensing | تسجيل الأعمال والتراخيص | O102: bmalkindi@adra.gov.ae, rfmdaas@adra.gov.ae | P102: asalmehiry@adra.gov.ae, rfmdaas@adra.gov.ae | Q102: Accela | R102: DED_Data_Table_004 | S102: DED_Attribute_0029 | T102: TypeMatch | V102: 1 | W102: Weekly | X102: DQI | Y102: Critical | Z102: NA | AA102: active | AB102: 46310 | AD102: Technical | AE102: No | AJ102: No | AO102: Signed Off
A103: Sprint 1 | B103: Application_Master | C103: DED_Data_Table_004 | D103: B1_PER_GROUP | E103: DED_Attribute_0030 | F103: 5371cb39-0aeb-4144-bee6-12f1ad88fe46 | G103: 3d7eb768-7d97-42e8-9bc4-f95332f307e9 | H103: DQP-200 | I103: DQO-200 | J103: Comp_Check-Application_Master-B1_PER_GROUP | K103: Checks that B1PERMIT-B1_PER_GROUP is populated for every in-scope record and is not null, blank, or whitespace-only. Business meaning: Business data element 'record permit group' captured in the ACCELAB1PERMIT dataset to support operational processing, compliance tracking, and reporting. | L103: Completeness | M103: Attribute | N103: Business Registration & Licensing | تسجيل الأعمال والتراخيص | O103: bmalkindi@adra.gov.ae, rfmdaas@adra.gov.ae | P103: asalmehiry@adra.gov.ae, rfmdaas@adra.gov.ae | Q103: Accela | R103: DED_Data_Table_004 | S103: DED_Attribute_0030 | T103: NotNull | V103: 0.95 | W103: Weekly | X103: DQI | Y103: Critical | Z103: NA | AA103: active | AB103: 46310 | AD103: Technical | AE103: No | AJ103: No | AO103: Signed Off
A104: Sprint 1 | B104: Application_Master | C104: DED_Data_Table_004 | D104: B1_PER_GROUP | E104: DED_Attribute_0030 | F104: 185f45d6-5e22-427d-825b-fe45d111e77d | G104: 99420535-689a-4ec1-984f-dfdec59b0508 | H104: DQP-201 | I104: DQO-201 | J104: Data_Val_Check-Application_Master-B1_PER_GROUP | K104: Checks that B1PERMIT-B1_PER_GROUP conforms to the expected source/Purview data type (VARCHAR2) so the value can be parsed and used consistently. Business meaning: Business data element 'record permit group' captured in the ACCELAB1PERMIT dataset to support operational processing, compliance tracking, and reporting. | L104: Validity | M104: Attribute | N104: Business Registration & Licensing | تسجيل الأعمال والتراخيص | O104: bmalkindi@adra.gov.ae, rfmdaas@adra.gov.ae | P104: asalmehiry@adra.gov.ae, rfmdaas@adra.gov.ae | Q104: Accela | R104: DED_Data_Table_004 | S104: DED_Attribute_0030 | T104: TypeMatch | V104: 1 | W104: Weekly | X104: DQI | Y104: Critical | Z104: NA | AA104: active | AB104: 46310 | AD104: Technical | AE104: No | AJ104: No | AO104: Signed Off
A105: Sprint 1 | B105: Application_Master | C105: DED_Data_Table_004 | D105: B1_PER_GROUP | E105: DED_Attribute_0030 | F105: f71c0b9b-61d5-4abe-a4c9-614cf70e0648 | G105: edcbfc66-c12f-4b93-b1ef-a3afb86c4d12 | H105: DQP-202 | I105: DQO-202 | J105: Format_Val_Chk-Application_Master-B1_PER_GROUP | K105: Checks that non-null B1PERMIT-B1_PER_GROUP values are only string values preventing malformed values from entering reporting or integrations. Business meaning: Business data element 'record permit group' captured in the ACCELAB1PERMIT dataset to support operational processing, compliance tracking, and reporting. | L105: Validity | M105: Attribute | N105: Business Registration & Licensing | تسجيل الأعمال والتراخيص | O105: bmalkindi@adra.gov.ae, rfmdaas@adra.gov.ae | P105: asalmehiry@adra.gov.ae, rfmdaas@adra.gov.ae | Q105: Accela | R105: DED_Data_Table_004 | S105: DED_Attribute_0030 | T105: Regex | U105: ^[A-Za-z]+(?: [A-Za-z]+)*$ | V105: 1 | W105: Weekly | X105: DQI | Y105: Critical | Z105: NA | AA105: active | AB105: 46310 | AD105: Technical | AE105: No | AJ105: No | AO105: Signed Off
A106: Sprint 1 | B106: Application_Master | C106: DED_Data_Table_004 | D106: B1_PER_CATEGORY | E106: DED_Attribute_0033 | F106: f6641317-ac4e-4e73-9b69-27ff5d229bff | G106: 6a281ddf-a531-4251-8f59-78027dd790d1 | H106: DQP-203 | I106: DQO-203 | J106: Comp_Check-Application_Master-B1_PER_CATEGORY | K106: Checks that B1PERMIT-B1_PER_CATEGORY is populated for every in-scope record and is not null, blank, or whitespace-only. Business meaning: Business data element 'record permit category' captured in the ACCELAB1PERMIT dataset to support operational processing, compliance tracking, and reporting. | L106: Completeness | M106: Attribute | N106: Business Registration & Licensing | تسجيل الأعمال والتراخيص | O106: bmalkindi@adra.gov.ae, rfmdaas@adra.gov.ae | P106: asalmehiry@adra.gov.ae, rfmdaas@adra.gov.ae | Q106: Accela | R106: DED_Data_Table_004 | S106: DED_Attribute_0033 | T106: NotNull | V106: 0.95 | W106: Weekly | X106: DQI | Y106: Critical | Z106: NA | AA106: active | AB106: 46310 | AD106: Technical | AE106: No | AJ106: No | AO106: Signed Off
A107: Sprint 1 | B107: Application_Master | C107: DED_Data_Table_004 | D107: B1_PER_CATEGORY | E107: DED_Attribute_0033 | F107: 6ccfe948-e369-4c89-bc27-dc16990ef9c4 | G107: 2e20bde9-2f32-4461-8ddc-800754282f69 | H107: DQP-204 | I107: DQO-204 | J107: Data_Val_Check-Application_Master-B1_PER_CATEGORY | K107: Checks that B1PERMIT-B1_PER_CATEGORY conforms to the expected source/Purview data type (VARCHAR2) so the value can be parsed and used consistently. Business meaning: Business data element 'record permit category' captured in the ACCELAB1PERMIT dataset to support operational processing, compliance tracking, and reporting. | L107: Validity | M107: Attribute | N107: Business Registration & Licensing | تسجيل الأعمال والتراخيص | O107: bmalkindi@adra.gov.ae, rfmdaas@adra.gov.ae | P107: asalmehiry@adra.gov.ae, rfmdaas@adra.gov.ae | Q107: Accela | R107: DED_Data_Table_004 | S107: DED_Attribute_0033 | T107: TypeMatch | V107: 1 | W107: Weekly | X107: DQI | Y107: Critical | Z107: NA | AA107: active | AB107: 46310 | AD107: Technical | AE107: No | AJ107: No | AO107: Signed Off
A108: Sprint 1 | B108: Application_Master | C108: DED_Data_Table_004 | D108: B1_PER_CATEGORY | E108: DED_Attribute_0033 | F108: 46d8da54-0f3e-45b6-9253-f869967359bc | G108: 233c368f-4edf-469a-8a54-7574355d1eb8 | H108: DQP-205 | I108: DQO-205 | J108: Format_Check-Application_Master-B1_PER_CATEGORY | K108: Checks that non-null B1PERMIT-B1_PER_CATEGORY values are only string values preventing malformed values from entering reporting or integrations. Business meaning: Business data element 'record permit category' captured in the ACCELAB1PERMIT dataset to support operational processing, compliance tracking, and reporting. | L108: Validity | M108: Attribute | N108: Business Registration & Licensing | تسجيل الأعمال والتراخيص | O108: bmalkindi@adra.gov.ae, rfmdaas@adra.gov.ae | P108: asalmehiry@adra.gov.ae, rfmdaas@adra.gov.ae | Q108: Accela | R108: DED_Data_Table_004 | S108: DED_Attribute_0033 | T108: Regex | U108: ^[A-Za-z]+(?: [A-Za-z]+)*$ | V108: 1 | W108: Weekly | X108: DQI | Y108: Critical | Z108: NA | AA108: active | AB108: 46310 | AD108: Technical | AE108: No | AJ108: No | AO108: Signed Off
A109: Sprint 1 | B109: Application_Master | C109: DED_Data_Table_004 | D109: B1_FILE_DD | E109: DED_Attribute_0034 | F109: ede3fc7f-4b89-40bd-a902-97a1b312d9d2 | G109: 1d71f098-b7ee-49d1-b843-e14c755fcfc1 | H109: DQP-206 | I109: DQO-206 | J109: Comp_Check-Application_Master-B1_FILE_DD | K109: Checks that B1PERMIT-B1_FILE_DD is populated for every in-scope record and is not null, blank, or whitespace-only. Business meaning: Business data element 'record file dd' captured in the ACCELAB1PERMIT dataset to support operational processing, compliance tracking, and reporting. | L109: Completeness | M109: Attribute | N109: Business Registration & Licensing | تسجيل الأعمال والتراخيص | O109: bmalkindi@adra.gov.ae, rfmdaas@adra.gov.ae | P109: asalmehiry@adra.gov.ae, rfmdaas@adra.gov.ae | Q109: Accela | R109: DED_Data_Table_004 | S109: DED_Attribute_0034 | T109: NotNull | V109: 0.95 | W109: Weekly | X109: DQI | Y109: Critical | Z109: NA | AA109: active | AB109: 46310 | AD109: Technical | AE109: No | AJ109: No | AO109: Signed Off
A110: Sprint 1 | B110: Application_Master | C110: DED_Data_Table_004 | D110: B1_FILE_DD | E110: DED_Attribute_0034 | F110: 0a9854ef-f0a2-41a4-8bd8-21566847244a | G110: 93a43d2c-5de0-4512-aeea-8ce3040454cb | H110: DQP-207 | I110: DQO-207 | J110: Data_Validity_Check-Application_Master-B1_FILE_DD | K110: Checks that B1PERMIT-B1_FILE_DD conforms to the expected source/Purview data type (DATE) so the value can be parsed and used consistently. Business meaning: Business data element 'record file dd' captured in the ACCELAB1PERMIT dataset to support operational processing, compliance tracking, and reporting. | L110: Validity | M110: Attribute | N110: Business Registration & Licensing | تسجيل الأعمال والتراخيص | O110: bmalkindi@adra.gov.ae, rfmdaas@adra.gov.ae | P110: asalmehiry@adra.gov.ae, rfmdaas@adra.gov.ae | Q110: Accela | R110: DED_Data_Table_004 | S110: DED_Attribute_0034 | T110: TypeMatch | V110: 1 | W110: Weekly | X110: DQI | Y110: Critical | Z110: NA | AA110: active | AB110: 46310 | AD110: Technical | AE110: No | AJ110: No | AO110: Signed Off
A111: Sprint 1 | B111: Application_Master | C111: DED_Data_Table_004 | D111: B1_ALT_ID | E111: DED_Attribute_0036 | F111: 102735f4-8f47-4c5b-8788-cf0342528d79 | G111: b03e68f3-5ae0-4635-aa66-1d2521295edb | H111: DQP-208 | I111: DQO-208 | J111: Completeness_Check-Application_Master-B1_ALT_ID | K111: Checks that B1PERMIT-B1_ALT_ID is populated for every in-scope record and is not null, blank, or whitespace-only. Business meaning: Alternate ID or user-friendly record number associated with the permit or business record. | L111: Completeness | M111: Attribute | N111: Business Registration & Licensing | تسجيل الأعمال والتراخيص | O111: bmalkindi@adra.gov.ae, rfmdaas@adra.gov.ae | P111: asalmehiry@adra.gov.ae, rfmdaas@adra.gov.ae | Q111: Accela | R111: DED_Data_Table_004 | S111: DED_Attribute_0036 | T111: NotNull | V111: 0.95 | W111: Weekly | X111: DQI | Y111: Critical | Z111: NA | AA111: active | AB111: 46310 | AD111: Technical | AE111: No | AJ111: No | AO111: Signed Off
A112: Sprint 1 | B112: Application_Master | C112: DED_Data_Table_004 | D112: B1_ALT_ID | E112: DED_Attribute_0036 | F112: 66fb7574-49bb-4787-9b9c-eab47ac0d7d3 | G112: b8d01a9e-6f89-4737-be11-58657d95750a | H112: DQP-209 | I112: DQO-209 | J112: Data_Validity_Check-Application_Master-B1_ALT_ID | K112: Checks that B1PERMIT-B1_ALT_ID conforms to the expected source/Purview data type (VARCHAR2) so the value can be parsed and used consistently. Business meaning: Alternate ID or user-friendly record number associated with the permit or business record. | L112: Validity | M112: Attribute | N112: Business Registration & Licensing | تسجيل الأعمال والتراخيص | O112: bmalkindi@adra.gov.ae, rfmdaas@adra.gov.ae | P112: asalmehiry@adra.gov.ae, rfmdaas@adra.gov.ae | Q112: Accela | R112: DED_Data_Table_004 | S112: DED_Attribute_0036 | T112: TypeMatch | V112: 1 | W112: Weekly | X112: DQI | Y112: Critical | Z112: NA | AA112: active | AB112: 46310 | AD112: Technical | AE112: No | AJ112: No | AO112: Signed Off
A113: Sprint 1 | B113: License_Expiration | C113: DED_Data_Table_005 | D113: EXPIRATION_DATE | E113: DED_Attribute_0042 | F113: 3067e51c-4691-4bd5-93a0-092e8b89b8c8 | G113: 31cfb4f9-bb7f-4ad1-ade0-ba4a7041991f | H113: DQP-212 | I113: DQO-212 | J113: Comp_Chk-License_Expiration-expiration_date | K113: Checks if there are any empty or blank values in the Expiration Date Column. | L113: Completeness | M113: Attribute | N113: Business Registration & Licensing | تسجيل الأعمال والتراخيص | O113: bmalkindi@adra.gov.ae, rfmdaas@adra.gov.ae | P113: asalmehiry@adra.gov.ae, rfmdaas@adra.gov.ae | Q113: Accela | R113: DED_Data_Table_005 | S113: DED_Attribute_0042 | T113: NotNull | V113: 0.95 | W113: Weekly | X113: DQI | Y113: Critical | Z113: NA | AA113: active | AB113: 46310 | AD113: Technical | AE113: No | AJ113: No | AO113: Signed Off
A114: Sprint 1 | B114: License_Expiration | C114: DED_Data_Table_005 | D114: EXPIRATION_DATE | E114: DED_Attribute_0042 | F114: 1124d4e0-0a4d-4e42-a76f-6e9ca31fcbe2 | G114: 208e0a3d-9313-44eb-9b97-d288a7a612c6 | H114: DQP-213 | I114: DQO-213 | J114: Date_Val_Chk-License_Expiration-expiration_date | K114: Verifies for the expected source/Purview data type (DATE) so the value can be parsed and used consistently. | L114: Validity | M114: Attribute | N114: Business Registration & Licensing | تسجيل الأعمال والتراخيص | O114: bmalkindi@adra.gov.ae, rfmdaas@adra.gov.ae | P114: asalmehiry@adra.gov.ae, rfmdaas@adra.gov.ae | Q114: Accela | R114: DED_Data_Table_005 | S114: DED_Attribute_0042 | T114: TypeMatch | V114: 1 | W114: Weekly | X114: DQI | Y114: Critical | Z114: NA | AA114: active | AB114: 46310 | AD114: Technical | AE114: No | AJ114: No | AO114: Signed Off
A115: Sprint 1 | B115: License_Expiration | C115: DED_Data_Table_005 | D115: EXPIRATION_DATE | E115: DED_Attribute_0042 | F115: d0948cce-d137-49a2-b938-6f37beae6036 | G115: cc2b404a-0de4-46b2-b5ab-861674b3f95d | H115: DQP-214 | I115: DQO-214 | J115: Cus_Date_Val_Chk-license_exp-expiration_date | K115: Checks the non-null EXPIRATION_DATE in B1_EXPIRATION table has values that are plausible business dates within the approved date boundary for the process. | L115: Validity | M115: Attribute | N115: Business Registration & Licensing | تسجيل الأعمال والتراخيص | O115: bmalkindi@adra.gov.ae, rfmdaas@adra.gov.ae | P115: asalmehiry@adra.gov.ae, rfmdaas@adra.gov.ae | Q115: Accela | R115: DED_Data_Table_005 | S115: DED_Attribute_0042 | T115: CustomTruth | U115: rlike(toString({expiration_date}), '^[0-9]{4}-[0-9]{2}-[0-9]{2}$') | V115: 1 | W115: Weekly | X115: DQI | Y115: Critical | Z115: NA | AA115: active | AB115: 46310 | AD115: Technical | AE115: No | AJ115: No | AO115: Signed Off
A116: Sprint 1 | B116: Application_Address | C116: DED_Data_Table_006 | D116: B1_ADDRESS_NBR | E116: DED_Attribute_0048 | F116: 32bddcc1-a987-44e2-b02c-a9814b89c2e5 | G116: f15ea80f-7828-4b7f-b669-26e2b8371b55 | H116: DQP-228 | I116: DQO-228 | J116: Completeness_Check-application_address-b1_add_nbr | K116: Checks that B1_ADDRESS_NBR in B3ADDRES is populated for every in-scope record and is not null, blank, or whitespace-only. | L116: Completeness | M116: Attribute | N116: Business Registration & Licensing | تسجيل الأعمال والتراخيص | O116: bmalkindi@adra.gov.ae, rfmdaas@adra.gov.ae | P116: asalmehiry@adra.gov.ae, rfmdaas@adra.gov.ae | Q116: Accela | R116: DED_Data_Table_006 | S116: DED_Attribute_0048 | T116: NotNull | V116: 0.95 | W116: Weekly | X116: DQI | Y116: Critical | Z116: NA | AA116: active | AB116: 46310 | AD116: Technical | AE116: No | AJ116: No | AO116: Signed Off
...

Sheet In-scope Tables
B1: Total Tables
B2: =COUNTA(_xlfn.UNIQUE($B$5:$B$142)) -> 138
E3: Aligned with DRS, Jude latest confirmed 5 tables, Shweta confirmation of 2 tables descrepencies with Samer
A4: No. | B4: Data Asset ID | C4: Data Asset Name (English, Silver) | D4: Sprint | E4: Domain | F4: Bronze Name | G4: DATA AT SOURCE | H4: DATA AT BRONZE | I4: COMMENTS | J4: LAST UPDATED AT | K4: TABLE_TYPE | L4: Accela Table | M4: Accela Variable | O4: Sprint | P4: TABLE_TYPE | Q4: COMMENTS | R4: Count of DATA AT SOURCE | S4: Count of DATA AT BRONZE
A5: 1 | B5: DED_Data_Table_001 | C5: Financial_Audit_Trail | D5: Sprint 1 | E5: Financial Information | F5: ACCOUNTING_AUDIT_TRAIL | G5: DATA AVAILABLE | H5: OUTDATED DATA AVAILABLE | I5: Updated filter logic provided by Samer, blocked by Pipeline error | J5: 46252 | K5: P | L5: All Module | M5: Payments | O5: Sprint 1 | P5: P | Q5: Updated filter logic provided by Samer, blocked by Pipeline error | R5: 31 | S5: 31
A6: 2 | B6: DED_Data_Table_002 | C6: Status_Lookup | D6: Sprint 1 | E6: Economic Licenses | F6: APP_STATUS_GROUP | G6: DATA AVAILABLE | H6: OUTDATED DATA AVAILABLE | I6: Updated filter logic provided by Samer, blocked by Pipeline error | J6: 46252 | K6: P | P6: V | Q6: (blank) | R6: 18 | S6: 18
A7: 3 | B7: DED_Data_Table_003 | C7: Status_Lookup_Language | D7: Sprint 1 | E7: Economic Licenses | F7: APP_STATUS_GROUP_I18N | G7: DATA AVAILABLE | H7: OUTDATED DATA AVAILABLE | I7: Updated filter logic provided by Samer, blocked by Pipeline error | J7: 46252 | K7: P | O7: Sprint 2 | P7: P | Q7: Updated filter logic provided by Samer, blocked by Pipeline error | R7: 2 | S7: 2
A8: 4 | B8: DED_Data_Table_004 | C8: Application_Master | D8: Sprint 1 | E8: Economic Licenses | F8: B1PERMIT | G8: DATA AVAILABLE | H8: OUTDATED DATA AVAILABLE | I8: Updated filter logic provided by Samer, blocked by Pipeline error | J8: 46252 | K8: P | L8: All Module | M8: Record | Q8: (blank) | R8: 4 | S8: 4
A9: 5 | B9: DED_Data_Table_005 | C9: License_Expiration | D9: Sprint 1 | E9: Economic Licenses | F9: B1_EXPIRATION | G9: DATA AVAILABLE | H9: OUTDATED DATA AVAILABLE | I9: Updated filter logic provided by Samer, blocked by Pipeline error | J9: 46252 | K9: P | L9: All Module | M9: Renewal info | P9: V | Q9: (blank) | R9: 28 | S9: 28
A10: 6 | B10: DED_Data_Table_006 | C10: Application_Address | D10: Sprint 1 | E10: Economic Licenses | F10: B3ADDRES | G10: DATA AVAILABLE | H10: OUTDATED DATA AVAILABLE | I10: Updated filter logic provided by Samer, blocked by Pipeline error | J10: 46252 | K10: P | L10: All Module | M10: Address | P10: VP | Q10: (blank) | R10: 3 | S10: 3
A11: 7 | B11: DED_Data_Table_007 | C11: Application_District | D11: Sprint 1 | E11: Economic Licenses | F11: B3ADDRES_DISTRICT | G11: DATA AVAILABLE | H11: OUTDATED DATA AVAILABLE | I11: Updated filter logic provided by Samer, blocked by Pipeline error | J11: 46252 | K11: P | O11: Sprint 3 | P11: VP | Q11: (blank)
A12: 8 | B12: DED_Data_Table_008 | C12: Investor | D12: Sprint 1 | E12: Economic Licenses | F12: B3CONTACT | G12: DATA AVAILABLE | H12: OUTDATED DATA AVAILABLE | I12: Updated filter logic provided by Samer, blocked by Pipeline error | J12: 46252 | K12: P | L12: All Module | M12: Contact | O12: Grand Total | R12: 86 | S12: 86
A13: 9 | B13: DED_Data_Table_009 | C13: Company_Name | D13: Sprint 1 | E13: Economic Licenses | F13: B3CONTRA | G13: DATA AVAILABLE | H13: OUTDATED DATA AVAILABLE | I13: Updated filter logic provided by Samer, blocked by Pipeline error | J13: 46252 | K13: P | L13: All Module | M13: Licenses
A14: 10 | B14: DED_Data_Table_010 | C14: Requirement_Condition | D14: Sprint 1 | E14: Economic Licenses | F14: B6CONDIT | G14: DATA AVAILABLE | H14: OUTDATED DATA AVAILABLE | I14: Updated filter logic provided by Samer, blocked by Pipeline error | J14: 46252 | K14: P | L14: All Module | M14: Suspensions
A15: 11 | B15: DED_Data_Table_011 | C15: Requirement_Condition_Dtl | D15: Sprint 1 | E15: Economic Licenses | F15: B6CONDIT_DETAIL | G15: DATA AVAILABLE | H15: OUTDATED DATA AVAILABLE | I15: Updated filter logic provided by Samer, blocked by Pipeline error | J15: 46252 | K15: P
A16: 12 | B16: DED_Data_Table_012 | C16: Requirement_Condition_Dtl_Language | D16: Sprint 1 | E16: Economic Licenses | F16: B6CONDIT_DETAIL_I18N | G16: DATA AVAILABLE | H16: OUTDATED DATA AVAILABLE | I16: Updated filter logic provided by Samer, blocked by Pipeline error | J16: 46252 | K16: P
A17: 13 | B17: DED_Data_Table_013 | C17: Requirement_Condition_History | D17: Sprint 1 | E17: Economic Licenses | F17: B6CONDIT_HISTORY | G17: DATA AVAILABLE | H17: OUTDATED DATA AVAILABLE | I17: Updated filter logic provided by Samer, blocked by Pipeline error | J17: 46252 | K17: P | L17: All Module | M17: Suspensions / Condition History
A18: 14 | B18: DED_Data_Table_014 | C18: Requirement_Condition_History_Dtl | D18: Sprint 1 | E18: Economic Licenses | F18: B6CONDIT_HISTORY_DETAIL | G18: DATA AVAILABLE | H18: OUTDATED DATA AVAILABLE | I18: Updated filter logic provided by Samer, blocked by Pipeline error | J18: 46252 | K18: P
A19: 15 | B19: DED_Data_Table_015 | C19: Requirement_Condition_Language | D19: Sprint 1 | E19: Economic Licenses | F19: B6CONDIT_I18N | G19: DATA AVAILABLE | H19: OUTDATED DATA AVAILABLE | I19: Updated filter logic provided by Samer, blocked by Pipeline error | J19: 46252 | K19: P
A20: 16 | B20: DED_Data_Table_017 | C20: Application_Master_Dtl | D20: Sprint 1 | E20: Economic Licenses | F20: BPERMIT_DETAIL | G20: DATA AVAILABLE | H20: OUTDATED DATA AVAILABLE | I20: Updated filter logic provided by Samer, blocked by Pipeline error | J20: 46252 | K20: P | L20: All Module | M20: Record
A21: 17 | B21: DED_Data_Table_019 | C21: Application_Fee | D21: Sprint 1 | E21: Financial Information | F21: F4FEEITEM | G21: DATA AVAILABLE | H21: OUTDATED DATA AVAILABLE | I21: Updated filter logic provided by Samer, blocked by Pipeline error | J21: 46252 | K21: P | L21: All Module | M21: Fees / Fee Detail
A22: 18 | B22: DED_Data_Table_020 | C22: Application_Fee_Audit | D22: Sprint 1 | E22: Financial Information | F22: F4FEEITEM_AUDIT_TRAIL | G22: DATA AVAILABLE | H22: OUTDATED DATA AVAILABLE | I22: Updated filter logic provided by Samer, blocked by Pipeline error | J22: 46252 | K22: P
A23: 19 | B23: DED_Data_Table_021 | C23: Application_Invoice | D23: Sprint 1 | E23: Financial Information | F23: F4INVOICE | G23: DATA AVAILABLE | H23: OUTDATED DATA AVAILABLE | I23: Updated filter logic provided by Samer, blocked by Pipeline error | J23: 46252 | K23: P | L23: All Module | M23: Fees
A24: 20 | B24: DED_Data_Table_022 | C24: Application_Payment | D24: Sprint 1 | E24: Financial Information | F24: F4PAYMENT | G24: DATA AVAILABLE | H24: OUTDATED DATA AVAILABLE | I24: Updated filter logic provided by Samer, blocked by Pipeline error | J24: 46252 | K24: P | L24: All Module | M24: Payments / Transactions
A25: 21 | B25: DED_Data_Table_023 | C25: Application_Receipt | D25: Sprint 1 | E25: Financial Information | F25: F4RECEIPT | G25: DATA AVAILABLE | H25: OUTDATED DATA AVAILABLE | I25: Updated filter logic provided by Samer, blocked by Pipeline error | J25: 46252 | K25: P | L25: All Module | M25: Payments / Transactions
A26: 22 | B26: DED_Data_Table_024 | C26: Investor_Reference | D26: Sprint 1 | E26: Economic Licenses | F26: G3CONTACT | G26: DATA AVAILABLE | H26: OUTDATED DATA AVAILABLE | I26: Updated filter logic provided by Samer, blocked by Pipeline error | J26: 46252 | K26: P | L26: All Module | M26: Reference Contact
A27: 23 | B27: DED_Data_Table_025 | C27: Inspection_Suspension | D27: Sprint 1 | E27: Inspection | F27: G6ACTION | G27: DATA AVAILABLE | H27: OUTDATED DATA AVAILABLE | I27: Updated filter logic provided by Samer, blocked by Pipeline error | J27: 46252 | K27: P | L27: All Module | M27: Inspections
A28: 24 | B28: DED_Data_Table_028 | C28: Workflow | D28: Sprint 1 | E28: Economic Licenses | F28: GPROCESS | G28: DATA AVAILABLE | H28: OUTDATED DATA AVAILABLE | I28: Updated filter logic provided by Samer, blocked by Pipeline error | J28: 46252 | K28: P | L28: All Module | M28: Workflow
A29: 25 | B29: DED_Data_Table_032 | C29: Workflow_Language | D29: Sprint 1 | E29: Economic Licenses | F29: GPROCESS_I18N | G29: DATA AVAILABLE | H29: OUTDATED DATA AVAILABLE | I29: Updated filter logic provided by Samer, blocked by Pipeline error | J29: 46252 | K29: P | L29: All Module | M29: Workflow
A30: 26 | B30: DED_Data_Table_034 | C30: Application_Address_Reference | D30: Sprint 1 | E30: Economic Licenses | F30: L3ADDRES | G30: DATA AVAILABLE | H30: OUTDATED DATA AVAILABLE | I30: Updated filter logic provided by Samer, blocked by Pipeline error | J30: 46252 | K30: P | L30: All Module | M30: Refrence Address
A31: 27 | B31: DED_Data_Table_035 | C31: Application_District_Reference | D31: Sprint 1 | E31: Economic Licenses | F31: L3ADDRES_DISTRICT | G31: DATA AVAILABLE | H31: OUTDATED DATA AVAILABLE | I31: Updated filter logic provided by Samer, blocked by Pipeline error | J31: 46252 | K31: P | L31: All Module | M31: Refrence Address / District
A32: 28 | B32: DED_Data_Table_038 | C32: application_Configuration_Language | D32: Sprint 1 | E32: Economic Licenses | F32: R3APPTYP_I18N | G32: DATA AVAILABLE | H32: OUTDATED DATA AVAILABLE | I32: Updated filter logic provided by Samer, blocked by Pipeline error | J32: 46252 | K32: P
A33: 29 | B33: DED_Data_Table_041 | C33: Application_Fee_Reference | D33: Sprint 1 | E33: Financial Information | F33: RFEEITEM | G33: DATA AVAILABLE | H33: OUTDATED DATA AVAILABLE | I33: Updated filter logic provided by Samer, blocked by Pipeline error | J33: 46252 | K33: P | L33: All Module | M33: AA / Fee Item
A34: 30 | B34: DED_Data_Table_043 | C34: Inspection_Types | D34: Sprint 1 | E34: Inspection | F34: RINSPTYP | G34: DATA AVAILABLE | H34: OUTDATED DATA AVAILABLE | I34: Updated filter logic provided by Samer, blocked by Pipeline error | J34: 46252 | K34: P | L34: All Module | M34: AA / Inspection
A35: 31 | B35: DED_Data_Table_044 | C35: Inspection_Types_Language | D35: Sprint 1 | E35: Inspection | F35: RINSPTYP_I18N | G35: DATA AVAILABLE | H35: OUTDATED DATA AVAILABLE | I35: Updated filter logic provided by Samer, blocked by Pipeline error | J35: 46252 | K35: P | L35: All Module | M35: AA / Inspection
A36: 32 | B36: DED_Data_Table_045 | C36: Inspection_Relationship | D36: Sprint 2 | E36: Inspection | F36: RINSP_RESULT_GROUP | G36: DATA AVAILABLE | H36: DATA AVAILABLE | J36: 46252 | K36: P | L36: All Module | M36: Inspections
A37: 33 | B37: DED_Data_Table_046 | C37: Inspection_Relationship_Language | D37: Sprint 2 | E37: Inspection | F37: RINSP_RESULT_GROUP_I18N | G37: NO DATA | H37: NEED DE WORK FOR INGESTION | I37: Updated filter logic provided by Samer, blocked by Pipeline error | J37: 46252 | K37: P
A38: 34 | B38: DED_Data_Table_047 | C38: License_Professional | D38: Sprint 2 | E38: Economic Licenses | F38: RSTATE_LIC | G38: DATA AVAILABLE | H38: DATA AVAILABLE | J38: 46252 | K38: P | L38: Licenses | M38: License Professional
A39: 35 | B39: DED_Data_Table_048 | C39: Application_Status_History | D39: Sprint 2 | E39: Economic Licenses | F39: STATUS_HISTORY | G39: DATA AVAILABLE | H39: DATA AVAILABLE | J39: 46252 | K39: P | L39: Licenses | M39: License History
A40: 36 | B40: DED_Data_Table_052 | C40: Hierarchy | D40: Sprint 2 | E40: Economic Licenses | F40: XAPP2REF | G40: DATA AVAILABLE | H40: DATA AVAILABLE | J40: 46252 | K40: P
A41: 37 | B41: DED_Data_Table_054 | C41: Industrial_Activities | D41: Sprint 1 | E41: Economic Licenses | F41: VIRTUAL_ACTIVITY_DETAILS | G41: DATA AVAILABLE | H41: OUTDATED DATA AVAILABLE | J41: 46252 | K41: V | L41: Industrials | M41: Info Tables
A42: 38 | B42: DED_Data_Table_056 | C42: Permit_Air | D42: Sprint 1 | E42: Permit | F42: VIRTUAL_AIR | G42: DATA AVAILABLE | H42: NO DATA AVAILABLE | J42: 46252 | K42: V | L42: Template | M42: Permit
A43: 39 | B43: DED_Data_Table_057 | C43: Allocated_Quota | D43: Sprint 1 | E43: Economic Licenses | F43: VIRTUAL_ALLOCATED_QUOTA | G43: DATA AVAILABLE | H43: OUTDATED DATA AVAILABLE | J43: 46252 | K43: V | L43: Licenses | M43: Activities
A44: 40 | B44: DED_Data_Table_058 | C44: Entity_Identifier | D44: Sprint 1 | E44: Economic Licenses | F44: VIRTUAL_APPROVING_ENTITY_IDENT | G44: DATA AVAILABLE | H44: NO DATA AVAILABLE | J44: 46252 | K44: V | L44: Licenses | M44: Info Tables
A45: 41 | B45: DED_Data_Table_059 | C45: RB_PEP_Association | D45: Sprint 2 | E45: Real Beneficiary (RB) | F45: VIRTUAL_ASSOCIATIONS_WITH_PEPS | G45: DATA AVAILABLE | H45: DATA AVAILABLE | J45: 46253 | K45: V | L45: IDB Template | M45: Activities
A46: 42 | B46: DED_Data_Table_060 | C46: Permit_Balloons | D46: Sprint 1 | E46: Permit | F46: VIRTUAL_BALLOONS | G46: NO DATA | H46: NO DATA AVAILABLE | J46: 46252 | K46: V | L46: Template | M46: Permit
A47: 43 | B47: DED_Data_Table_061 | C47: RB_Basic_Information_PEP | D47: Sprint 1 | E47: Real Beneficiary (RB) | F47: VIRTUAL_BASIC_INFORMATION_PEPS | G47: DATA AVAILABLE | H47: NO DATA AVAILABLE | J47: 46252 | K47: V | L47: Licenses | M47: PEP Basic Information
A48: 44 | B48: DED_Data_Table_062 | C48: RB_Beneficial_Owner | D48: Sprint 2 | E48: Real Beneficiary (RB) | F48: VIRTUAL_BENEFICIAL_OWNER | G48: DATA AVAILABLE | H48: DATA AVAILABLE | J48: 46253 | K48: V | L48: IDB Template | M48: Activities
A49: 45 | B49: DED_Data_Table_063 | C49: RB_Business_Interests | D49: Sprint 2 | E49: Real Beneficiary (RB) | F49: VIRTUAL_BUSINESS_INTERESTS_OF_ | G49: DATA AVAILABLE | H49: DATA AVAILABLE | J49: 46253 | K49: V | L49: IDB Template | M49: Activities
A50: 46 | B50: DED_Data_Table_064 | C50: Commercial_Activities | D50: Sprint 2 | E50: Economic Licenses | F50: VIRTUAL_COMMERCIAL_ACTIVITIES | G50: DATA AVAILABLE | H50: DATA AVAILABLE | J50: 46253 | K50: V | L50: IDB Template | M50: Activities
A51: 47 | B51: DED_Data_Table_065 | C51: Customs_Quota | D51: Sprint 1 | E51: Economic Licenses | F51: VIRTUAL_CUSTOMS_QUOTA | G51: DATA AVAILABLE | H51: OUTDATED DATA AVAILABLE | J51: 46252 | K51: V | L51: Industrial | M51: Info Tables
A52: 48 | B52: DED_Data_Table_066 | C52: Customs_Quota_History | D52: Sprint 1 | E52: Economic Licenses | F52: VIRTUAL_CUSTOMS_QUOTA_HISTORY | G52: DATA AVAILABLE | H52: OUTDATED DATA AVAILABLE | J52: 46252 | K52: V | L52: Industrial | M52: Info Tables
... A55: 51 | B55: DED_Data_Table_069 | C55: Entity_Follow_Up | D55: Sprint 1 | E55: Economic Licenses | F55: VIRTUAL_ENTITY_FOLLOW_UP | G55: DATA AVAILABLE | H55: OUTDATED DATA AVAILABLE | J55: 46252 | K55: V | L55: Licenses | M55: Activities
A56: 52 | B56: DED_Data_Table_070 | C56: Exemption_Change_Log | D56: Sprint 1 | E56: Economic Licenses | F56: VIRTUAL_EXEMPTION_CHANGE_LOG | G56: DATA AVAILABLE | H56: OUTDATED DATA AVAILABLE | J56: 46252 | K56: V | L56: Licenses | M56: Activities | O56: =(M56=B56) -> FALSE
A57: 53 | B57: DED_Data_Table_071 | C57: Expiry_Date_History | D57: Sprint 1 | E57: Economic Licenses | F57: VIRTUAL_EXPIRY_DATE_HISTORY | G57: DATA AVAILABLE | H57: OUTDATED DATA AVAILABLE | J57: 46252 | K57: V | L57: Licenses | M57: Activities
A58: 54 | B58: DED_Data_Table_073 | C58: IDB_Products | D58: Sprint 2 | E58: Economic Licenses | F58: VIRTUAL_IDB_PRODUCTS | G58: DATA AVAILABLE | H58: DATA AVAILABLE | J58: 46253 | K58: V | L58: IDB Template | M58: Activities
A59: 55 | B59: DED_Data_Table_074 | C59: Inspector_Coordinates | D59: Sprint 1 | E59: Inspection | F59: VIRTUAL_INSPECTORCOORDINATES | G59: DATA AVAILABLE | H59: OUTDATED DATA AVAILABLE | J59: 46252 | K59: V | L59: Industrials | M59: Info Tables
A60: 56 | B60: DED_Data_Table_075 | C60: Instant_Activities | D60: Sprint 1 | E60: Economic Licenses | F60: VIRTUAL_ISIC_4_ACTIVITIES | G60: DATA AVAILABLE | H60: OUTDATED DATA AVAILABLE | J60: 46252 | K60: V | L60: Licenses | M60: Activities
A61: 57 | B61: DED_Data_Table_076 | C61: Permit_Kiosk | D61: Sprint 1 | E61: Permit | F61: VIRTUAL_KIOSK | G61: DATA AVAILABLE | H61: NO DATA AVAILABLE | J61: 46252 | K61: V | L61: Template | M61: Permit
A62: 58 | B62: DED_Data_Table_077 | C62: License_Local_Branch | D62: Sprint 2 | E62: Economic Licenses | F62: VIRTUAL_LICENSE_LOCAL_BRANCH | G62: DATA AVAILABLE | H62: DATA AVAILABLE | J62: 46253 | K62: V | L62: IDB Template | M62: Activities
A63: 59 | B63: DED_Data_Table_078 | C63: IDB_Machines | D63: Sprint 1 | E63: Economic Licenses | F63: VIRTUAL_MACHINES | G63: DATA AVAILABLE | H63: NO DATA AVAILABLE | J63: 46252 | K63: V | L63: Industrials | M63: Machine Details
A64: 60 | B64: DED_Data_Table_079 | C64: IDB_Machine_Details | D64: Sprint 2 | E64: Economic Licenses | F64: VIRTUAL_MACHINE_DETAILS | G64: DATA AVAILABLE | H64: DATA AVAILABLE | J64: 46253 | K64: V | L64: IDB Template | M64: Activities
A65: 61 | B65: DED_Data_Table_080 | C65: Manager_Information | D65: Sprint 2 | E65: Real Beneficiary (RB), Economic Licenses | F65: VIRTUAL_MANAGER_INFOMATION | G65: DATA AVAILABLE | H65: DATA AVAILABLE | J65: 46253 | K65: V | L65: IDB Template | M65: Activities
A66: 62 | B66: DED_Data_Table_083 | C66: Mortgage_Records | D66: Sprint 2 | E66: Economic Licenses | F66: VIRTUAL_MORTGAGE_RECORDS | G66: DATA AVAILABLE | H66: DATA AVAILABLE | J66: 46253 | K66: V | L66: IDB Template | M66: Activities
A67: 63 | B67: DED_Data_Table_084 | C67: Mortgage_Shares | D67: Sprint 2 | E67: Economic Licenses | F67: VIRTUAL_MORTGAGE_SHARES | G67: DATA AVAILABLE | H67: DATA AVAILABLE | J67: 46252 | K67: V | L67: IDB Template | M67: Activities
A68: 64 | B68: DED_Data_Table_085 | C68: Offer_Tasting_Campaign | D68: Sprint 2 | E68: Permit | F68: VIRTUAL_OFFER_TASTING_CAMPAIGN | G68: DATA AVAILABLE | H68: DATA AVAILABLE | J68: 46253 | K68: V | L68: IDB Template | M68: Activities
... A89: 84 | B89: DED_Data_Table_116 | C89: Investor_Dtl_Reference | D89: Sprint 2 | E89: Economic Licenses | F89: Investor_Dtl_Reference(G3CONTACT_ATTRIBUTE) | G89: DATA AVAILABLE | H89: DATA AVAILABLE | J89: 46252 | K89: VP | L89: All modules | M89: Contact
A90: 87 | B90: DED_Data_Table_177 | C90: activity_detail | D90: Sprint 3 | E90: Economic Licenses | F90: br_activity_detail | K90: VP | L90: IDB Template | M90: Activity
A91: 88 | B91: DED_Data_Table_178 | C91: address | D91: Sprint 3 | E91: Economic Licenses | F91: br_address | K91: VP | L91: Industrial | M91: License
A92: 89 | B92: DED_Data_Table_179 | C92: amendment_type | D92: Sprint 3 | E92: Economic Licenses | F92: br_amendment_type | K92: VP | L92: Industrial,Licenses | M92: License,Adds On
A93: 90 | B93: DED_Data_Table_180 | C93: ap_common | D93: Sprint 3 | E93: Permit | F93: br_ap_common | K93: VP | L93: Services | M93: Advertising Permit
A94: 91 | B94: DED_Data_Table_181 | C94: basic_information | D94: Sprint 3 | E94: Economic Licenses, Violations and Fines | F94: br_basic_information | K94: VP | L94: Industrial,Licenses | M94: License,Fines
A95: 92 | B95: DED_Data_Table_182 | C95: branches_list | D95: Sprint 3 | E95: Permit | F95: br_branches_list | K95: VP | L95: Services | M95: Advertising Permit
A96: 93 | B96: DED_Data_Table_183 | C96: branches | D96: Sprint 3 | E96: Economic Licenses | F96: br_branches | K96: VP | L96: Industrial | M96: License
A97: 94 | B97: DED_Data_Table_184 | C97: cancellation_information | D97: Sprint 3 | E97: Economic Licenses | F97: br_cancellation_information | K97: VP | L97: Licenses | M97: Mortgage
A98: 95 | B98: DED_Data_Table_185 | C98: capital_type | D98: Sprint 3 | E98: Financial Information & Economic Licenses | F98: br_capital_type | K98: VP | L98: Licenses | M98: License
A99: 96 | B99: DED_Data_Table_186 | C99: commercial_feature | D99: Sprint 3 | E99: Economic Licenses | F99: br_commercial_feature | K99: VP | L99: Licenses | M99: License
A100: 97 | B100: DED_Data_Table_187 | C100: communication_information | D100: Sprint 3 | E100: Economic Licenses | F100: br_communication_information | K100: VP | L100: Licenses | M100: Mortgage
A101: 98 | B101: DED_Data_Table_188 | C101: company_contact | D101: Sprint 3 | E101: Economic Licenses | F101: br_company_contact | K101: VP | L101: Industrial | M101: License
... A141: 145 | B141: DED_Data_Table_235 | C141: virtual_inspection_confirmation | D141: Sprint 3 | E141: Inspection | F141: br_virtual_inspection_confirmation | K141: VP | L141: Industrial | M141: License
A142: 85 | B142: DED_Data_Table_236 | C142: rapo_attribute_i18n | D142: Sprint 2 | E142: Economic Licenses | F142: RAPO_ATTRIBUTE_I18N | G142: DATA AVAILABLE | H142: NEED DE WORK FOR INGESTION | I142: Updated filter logic provided by Samer, blocked by Pipeline error | J142: 46252 | K142: P

Sheet CDE Coverage Report
B3: Sprint 1 | C3: Total Rules | D3: Total Table | E3: Total CDEs | F3: Rule Density | G3: DDA Coverage Requirement | H3: CDE / Tables covered | I3: Coverage % | J3: Additional CDEs / Tables to cover
B4: Completeness | C4: =SUMIFS($G$29:$G$1297,$B$29:$B$1297,$B$3) -> 230 | D4: CDE level | E4: =COUNTIFS($B$29:$B$1297,$B$3,$C$29:$C$1297,"<>") -> 230 | F4: =IF(E4=0,"N/A",C4/E4) -> 1 | G4: =$X$28 -> 1 | H4: =COUNTIFS($B$29:$B$1297,$B$3,$C$29:$C$1297,"<>",$G$29:$G$1297,">0") -> 230 | I4: =IF(E4=0,"N/A",H4/E4) -> 1 | J4: =MAX(0,ROUNDUP(E4*G4,0)-H4) -> 0
B5: Validity | C5: =SUMIFS($J$29:$J$1297,$B$29:$B$1297,$B$3) -> 400 | D5: CDE level | E5: =COUNTIFS($B$29:$B$1297,$B$3,$C$29:$C$1297,"<>") -> 230 | F5: =IF(E5=0,"N/A",C5/E5) -> 1.7391304 | G5: =$X$29 -> 0.9 | H5: =COUNTIFS($B$29:$B$1297,$B$3,$C$29:$C$1297,"<>",$J$29:$J$1297,">0") -> 230 | I5: =IF(E5=0,"N/A",H5/E5) -> 1 | J5: =MAX(0,ROUNDUP(E5*G5,0)-H5) -> 0
B6: Consistenct | C6: =SUMIFS($H$29:$H$1297,$B$29:$B$1297,$B$3) -> 172 | D6: CDE level | E6: =COUNTIFS($B$29:$B$1297,$B$3,$C$29:$C$1297,"<>") -> 230 | F6: =IF(E6=0,"N/A",C6/E6) -> 0.74782609 | G6: =$X$30 -> 0.5 | H6: =COUNTIFS($B$29:$B$1297,$B$3,$C$29:$C$1297,"<>",$H$29:$H$1297,">0") -> 166 | I6: =IF(E6=0,"N/A",H6/E6) -> 0.72173913 | J6: =MAX(0,ROUNDUP(E6*G6,0)-H6) -> 0
B7: Timeliness | C7: =SUMIFS($P$29:$P$180,$L$29:$L$180,$B$3) -> 49 | D7: =COUNTIFS($L$29:$L$180,$B$3,$M$29:$M$180,"<>") -> 49 | E7: Table level | F7: Table level | G7: =$X$31 -> 1 | H7: =COUNTIFS($L$29:$L$180,$B$3,$M$29:$M$180,"<>",$P$29:$P$180,">0") -> 49 | I7: =IF(D7=0,"N/A",H7/D7) -> 1 | J7: =MAX(0,ROUNDUP(D7*G7,0)-H7) -> 0
B8: Uniqueness | C8: =SUMIFS($O$29:$O$180,$L$29:$L$180,$B$3) -> 49 | D8: =COUNTIFS($L$29:$L$180,$B$3,$M$29:$M$180,"<>") -> 49 | E8: Table level | F8: Table level | G8: =$X$32 -> 1 | H8: =COUNTIFS($L$29:$L$180,$B$3,$M$29:$M$180,"<>",$O$29:$O$180,">0") -> 49 | I8: =IF(D8=0,"N/A",H8/D8) -> 1 | J8: =MAX(0,ROUNDUP(D8*G8,0)-H8) -> 0
B9: Accuracy | C9: =SUMIFS($I$29:$I$1297,$B$29:$B$1297,$B$3) -> 37 | D9: CDE level | E9: =COUNTIFS($B$29:$B$1297,$B$3,$C$29:$C$1297,"<>") -> 230 | F9: =IF(E9=0,"N/A",C9/E9) -> 0.16086957 | G9: =$X$33 -> 0.5 | H9: =COUNTIFS($B$29:$B$1297,$B$3,$C$29:$C$1297,"<>",$I$29:$I$1297,">0") -> 35 | I9: =IF(E9=0,"N/A",H9/E9) -> 0.15217391 | J9: =MAX(0,ROUNDUP(E9*G9,0)-H9) -> 80
B11: Sprint 2 | C11: Total Rules | D11: Total Table | E11: Total CDEs | F11: Rule Density | G11: DDA Coverage Requirement | H11: CDE / Tables covered | I11: Coverage % | J11: Additional CDEs / Tables to cover
B12: Completeness | C12: =SUMIFS($G$29:$G$1297,$B$29:$B$1297,$B$11) -> 465 | D12: CDE level | E12: =COUNTIFS($B$29:$B$1297,$B$11,$C$29:$C$1297,"<>") -> 464 | F12: =IF(E12=0,"N/A",C12/E12) -> 1.0021552 | G12: =$X$28 -> 1 | H12: =COUNTIFS($B$29:$B$1297,$B$11,$C$29:$C$1297,"<>",$G$29:$G$1297,">0") -> 464 | I12: =IF(E12=0,"N/A",H12/E12) -> 1 | J12: =MAX(0,ROUNDUP(E12*G12,0)-H12) -> 0
B13: Validity | C13: =SUMIFS($J$29:$J$1297,$B$29:$B$1297,$B$11) -> 740 | D13: CDE level | E13: =COUNTIFS($B$29:$B$1297,$B$11,$C$29:$C$1297,"<>") -> 464 | F13: =IF(E13=0,"N/A",C13/E13) -> 1.5948276 | G13: =$X$29 -> 0.9 | H13: =COUNTIFS($B$29:$B$1297,$B$11,$C$29:$C$1297,"<>",$J$29:$J$1297,">0") -> 446 | I13: =IF(E13=0,"N/A",H13/E13) -> 0.9612069 | J13: =MAX(0,ROUNDUP(E13*G13,0)-H13) -> 0
B14: Consistenct | C14: =SUMIFS($H$29:$H$1297,$B$29:$B$1297,$B$11) -> 267 | D14: CDE level | E14: =COUNTIFS($B$29:$B$1297,$B$11,$C$29:$C$1297,"<>") -> 464 | F14: =IF(E14=0,"N/A",C14/E14) -> 0.57543103 | G14: =$X$30 -> 0.5 | H14: =COUNTIFS($B$29:$B$1297,$B$11,$C$29:$C$1297,"<>",$H$29:$H$1297,">0") -> 256 | I14: =IF(E14=0,"N/A",H14/E14) -> 0.55172414 | J14: =MAX(0,ROUNDUP(E14*G14,0)-H14) -> 0
B15: Timeliness | C15: =SUMIFS($P$29:$P$180,$L$29:$L$180,$B$11) -> 37 | D15: =COUNTIFS($L$29:$L$180,$B$11,$M$29:$M$180,"<>") -> 37 | E15: Table level | F15: Table level | G15: =$X$31 -> 1 | H15: =COUNTIFS($L$29:$L$180,$B$11,$M$29:$M$180,"<>",$P$29:$P$180,">0") -> 37 | I15: =IF(D15=0,"N/A",H15/D15) -> 1 | J15: =MAX(0,ROUNDUP(D15*G15,0)-H15) -> 0
B16: Uniqueness | C16: =SUMIFS($O$29:$O$180,$L$29:$L$180,$B$11) -> 37 | D16: =COUNTIFS($L$29:$L$180,$B$11,$M$29:$M$180,"<>") -> 37 | E16: Table level | F16: Table level | G16: =$X$32 -> 1 | H16: =COUNTIFS($L$29:$L$180,$B$11,$M$29:$M$180,"<>",$O$29:$O$180,">0") -> 37 | I16: =IF(D16=0,"N/A",H16/D16) -> 1 | J16: =MAX(0,ROUNDUP(D16*G16,0)-H16) -> 0
B17: Accuracy | C17: =SUMIFS($I$29:$I$1297,$B$29:$B$1297,$B$11) -> 4 | D17: CDE level | E17: =COUNTIFS($B$29:$B$1297,$B$11,$C$29:$C$1297,"<>") -> 464 | F17: =IF(E17=0,"N/A",C17/E17) -> 0.0086206897 | G17: =$X$33 -> 0.5 | H17: =COUNTIFS($B$29:$B$1297,$B$11,$C$29:$C$1297,"<>",$I$29:$I$1297,">0") -> 4 | I17: =IF(E17=0,"N/A",H17/E17) -> 0.0086206897 | J17: =MAX(0,ROUNDUP(E17*G17,0)-H17) -> 228
B19: Sprint 3 | C19: Total Rules | D19: Total Table | E19: Total CDEs | F19: Rule Density | G19: DDA Coverage Requirement | H19: CDE / Tables covered | I19: Coverage % | J19: Additional CDEs / Tables to cover
B20: Completeness | C20: =SUMIFS($G$29:$G$1297,$B$29:$B$1297,$B$19) -> 505 | D20: CDE level | E20: =COUNTIFS($B$29:$B$1297,$B$19,$C$29:$C$1297,"<>") -> 505 | F20: =IF(E20=0,"N/A",C20/E20) -> 1 | G20: =$X$28 -> 1 | H20: =COUNTIFS($B$29:$B$1297,$B$19,$C$29:$C$1297,"<>",$G$29:$G$1297,">0") -> 505 | I20: =IF(E20=0,"N/A",H20/E20) -> 1 | J20: =MAX(0,ROUNDUP(E20*G20,0)-H20) -> 0
B21: Validity | C21: =SUMIFS($J$29:$J$1297,$B$29:$B$1297,$B$19) -> 1146 | D21: CDE level | E21: =COUNTIFS($B$29:$B$1297,$B$19,$C$29:$C$1297,"<>") -> 505 | F21: =IF(E21=0,"N/A",C21/E21) -> 2.2693069 | G21: =$X$29 -> 0.9 | H21: =COUNTIFS($B$29:$B$1297,$B$19,$C$29:$C$1297,"<>",$J$29:$J$1297,">0") -> 505 | I21: =IF(E21=0,"N/A",H21/E21) -> 1 | J21: =MAX(0,ROUNDUP(E21*G21,0)-H21) -> 0
B22: Consistenct | C22: =SUMIFS($H$29:$H$1297,$B$29:$B$1297,$B$19) -> 214 | D22: CDE level | E22: =COUNTIFS($B$29:$B$1297,$B$19,$C$29:$C$1297,"<>") -> 505 | F22: =IF(E22=0,"N/A",C22/E22) -> 0.42376238 | G22: =$X$30 -> 0.5 | H22: =COUNTIFS($B$29:$B$1297,$B$19,$C$29:$C$1297,"<>",$H$29:$H$1297,">0") -> 195 | I22: =IF(E22=0,"N/A",H22/E22) -> 0.38613861 | J22: =MAX(0,ROUNDUP(E22*G22,0)-H22) -> 58
B23: Timeliness | C23: =SUMIFS($P$29:$P$180,$L$29:$L$180,$B$19) -> 52 | D23: =COUNTIFS($L$29:$L$180,$B$19,$M$29:$M$180,"<>") -> 52 | E23: Table level | F23: Table level | G23: =$X$31 -> 1 | H23: =COUNTIFS($L$29:$L$180,$B$19,$M$29:$M$180,"<>",$P$29:$P$180,">0") -> 52 | I23: =IF(D23=0,"N/A",H23/D23) -> 1 | J23: =MAX(0,ROUNDUP(D23*G23,0)-H23) -> 0
B24: Uniqueness | C24: =SUMIFS($O$29:$O$180,$L$29:$L$180,$B$19) -> 52 | D24: =COUNTIFS($L$29:$L$180,$B$19,$M$29:$M$180,"<>") -> 52 | E24: Table level | F24: Table level | G24: =$X$32 -> 1 | H24: =COUNTIFS($L$29:$L$180,$B$19,$M$29:$M$180,"<>",$O$29:$O$180,">0") -> 52 | I24: =IF(D24=0,"N/A",H24/D24) -> 1 | J24: =MAX(0,ROUNDUP(D24*G24,0)-H24) -> 0
B25: Accuracy | C25: =SUMIFS($I$29:$I$1297,$B$29:$B$1297,$B$19) -> 4 | D25: CDE level | E25: =COUNTIFS($B$29:$B$1297,$B$19,$C$29:$C$1297,"<>") -> 505 | F25: =IF(E25=0,"N/A",C25/E25) -> 0.0079207921 | G25: =$X$33 -> 0.5 | H25: =COUNTIFS($B$29:$B$1297,$B$19,$C$29:$C$1297,"<>",$I$29:$I$1297,">0") -> 4 | I25: =IF(E25=0,"N/A",H25/E25) -> 0.0079207921 | J25: =MAX(0,ROUNDUP(E25*G25,0)-H25) -> 249
B28: Sprint | C28: Data Attribute ID | D28: Data Attribute Name (English, Silver) | E28: Data Asset ID | F28: Data Asset Name (English, Silver) | G28: Completeness | H28: Consistency | I28: Accuracy | J28: Validity | L28: Sprint | M28: Data Asset ID | N28: Data Asset Name (English, Silver) | O28: Uniqueness | P28: Timeliness | S28: Completeness | T28: =SUM(G29:G1297) -> 1200 | U28: CDE level | V28: =SUM(E4,E12,E20) -> 1199 | W28: =T28/V28 -> 1.000834 | X28: 1 | Y28: =SUM(H4,H12,H20) -> 1199 | Z28: =Y28/V28 -> 1
B29: =_xlfn.XLOOKUP(C29,'In-scope Attributes'!B:B,'In-scope Attributes'!H:H,"") -> Sprint 1 | C29: DED_Attribute_0006 | D29: INVOICE_NBR | E29: DED_Data_Table_001 | F29: Financial_Audit_Trail | G29: =COUNTIFS('Golden Rulebook-CDErule level'!$E:$E,$C29,'Golden Rulebook-CDErule level'!$L:$L,G$28,'Golden Rulebook-CDErule level'!$A:$A,$B29,'Golden Rulebook-CDErule level'!$AA:$AA,"Active") -> 1 | H29: {=_xlfn.LET(_xlpm.ids,_xlfn._xlws.FILTER('Golden Rulebook-CDErule level'!$S$4:$S$4620,('Golden Rulebook-CDErule level'!$L$4:$L$4620=H$28)*('Golden Rulebook-CDErule level'!$A$4:$A$4620=$B29)*('Golden Rulebook-CDErule level'!$AA$4:$AA$4620="Active"),""),SUM(--ISNUMBER(SEARCH(","&SUBSTITUTE(SUBSTITUTE($C29," ",""),CHAR(160),"")&",",","&SUBSTITUTE(SUBSTITUTE(_xlpm.ids," ",""),CHAR(160),"")&","))))} -> 1 | I29: =COUNTIFS('Golden Rulebook-CDErule level'!$E:$E,$C29,'Golden Rulebook-CDErule level'!$L:$L,I$28,'Golden Rulebook-CDErule level'!$A:$A,$B29,'Golden Rulebook-CDErule level'!$AA:$AA,"Active") -> 0 | J29: =COUNTIFS('Golden Rulebook-CDErule level'!$E:$E,$C29,'Golden Rulebook-CDErule level'!$L:$L,J$28,'Golden Rulebook-CDErule level'!$A:$A,$B29,'Golden Rulebook-CDErule level'!$AA:$AA,"Active") -> 2 | L29: =_xlfn.XLOOKUP(M29,'In-scope Tables'!B:B,'In-scope Tables'!D:D,"") -> Sprint 1 | M29: DED_Data_Table_001 | N29: Financial_Audit_Trail | O29: =COUNTIFS('Golden Rulebook-CDErule level'!$C:$C,$M29,'Golden Rulebook-CDErule level'!$L:$L,O$28,'Golden Rulebook-CDErule level'!$A:$A,$L29,'Golden Rulebook-CDErule level'!$AA:$AA,"Active") -> 1 | P29: =COUNTIFS('Golden Rulebook-CDErule level'!$C:$C,$M29,'Golden Rulebook-CDErule level'!$L:$L,P$28,'Golden Rulebook-CDErule level'!$A:$A,$L29,'Golden Rulebook-CDErule level'!$AA:$AA,"Active") -> 1 | S29: Validity | T29: =SUM(J29:J1297) -> 2286 | U29: =$U$28 -> CDE level | V29: =V28 -> 1199 | W29: =T29/V29 -> 1.9065888 | X29: 0.9 | Y29: =SUM(H5,H13,H21) -> 1181 | Z29: =Y29/V29 -> 0.98498749
B30: =_xlfn.XLOOKUP(C30,'In-scope Attributes'!B:B,'In-scope Attributes'!H:H,"") -> Sprint 1 | C30: DED_Attribute_0007 | D30: RECEIPT_NBR | E30: DED_Data_Table_001 | F30: Financial_Audit_Trail | G30: =COUNTIFS('Golden Rulebook-CDErule level'!$E:$E,$C30,'Golden Rulebook-CDErule level'!$L:$L,G$28,'Golden Rulebook-CDErule level'!$A:$A,$B30,'Golden Rulebook-CDErule level'!$AA:$AA,"Active") -> 1 | H30: {=_xlfn.LET(_xlpm.ids,_xlfn._xlws.FILTER('Golden Rulebook-CDErule level'!$S$4:$S$4620,('Golden Rulebook-CDErule level'!$L$4:$L$4620=H$28)*('Golden Rulebook-CDErule level'!$A$4:$A$4620=$B30)*('Golden Rulebook-CDErule level'!$AA$4:$AA$4620="Active"),""),SUM(--ISNUMBER(SEARCH(","&SUBSTITUTE(SUBSTITUTE($C30," ",""),CHAR(160),"")&",",","&SUBSTITUTE(SUBSTITUTE(_xlpm.ids," ",""),CHAR(160),"")&","))))} -> 1 | I30: =COUNTIFS('Golden Rulebook-CDErule level'!$E:$E,$C30,'Golden Rulebook-CDErule level'!$L:$L,I$28,'Golden Rulebook-CDErule level'!$A:$A,$B30,'Golden Rulebook-CDErule level'!$AA:$AA,"Active") -> 0 | J30: =COUNTIFS('Golden Rulebook-CDErule level'!$E:$E,$C30,'Golden Rulebook-CDErule level'!$L:$L,J$28,'Golden Rulebook-CDErule level'!$A:$A,$B30,'Golden Rulebook-CDErule level'!$AA:$AA,"Active") -> 2 | L30: =_xlfn.XLOOKUP(M30,'In-scope Tables'!B:B,'In-scope Tables'!D:D,"") -> Sprint 1 | M30: DED_Data_Table_002 | N30: Status_Lookup | O30: =COUNTIFS('Golden Rulebook-CDErule level'!$C:$C,$M30,'Golden Rulebook-CDErule level'!$L:$L,O$28,'Golden Rulebook-CDErule level'!$A:$A,$L30,'Golden Rulebook-CDErule level'!$AA:$AA,"Active") -> 1 | P30: =COUNTIFS('Golden Rulebook-CDErule level'!$C:$C,$M30,'Golden Rulebook-CDErule level'!$L:$L,P$28,'Golden Rulebook-CDErule level'!$A:$A,$L30,'Golden Rulebook-CDErule level'!$AA:$AA,"Active") -> 1 | S30: Consistenct | T30: =SUM(H29:H1297) -> 653 | U30: =$U$28 -> CDE level | V30: =V29 -> 1199 | W30: =T30/V30 -> 0.54462052 | X30: 0.5 | Y30: =SUM(H6,H14,H22) -> 617 | Z30: =Y30/V30 -> 0.5145955
B31: =_xlfn.XLOOKUP(C31,'In-scope Attributes'!B:B,'In-scope Attributes'!H:H,"") -> Sprint 1 | C31: DED_Attribute_0008 | D31: PAYMENT_SEQ_NBR | E31: DED_Data_Table_001 | F31: Financial_Audit_Trail | G31: =COUNTIFS('Golden Rulebook-CDErule level'!$E:$E,$C31,'Golden Rulebook-CDErule level'!$L:$L,G$28,'Golden Rulebook-CDErule level'!$A:$A,$B31,'Golden Rulebook-CDErule level'!$AA:$AA,"Active") -> 1 | H31: {=_xlfn.LET(_xlpm.ids,_xlfn._xlws.FILTER('Golden Rulebook-CDErule level'!$S$4:$S$4620,('Golden Rulebook-CDErule level'!$L$4:$L$4620=H$28)*('Golden Rulebook-CDErule level'!$A$4:$A$4620=$B31)*('Golden Rulebook-CDErule level'!$AA$4:$AA$4620="Active"),""),SUM(--ISNUMBER(SEARCH(","&SUBSTITUTE(SUBSTITUTE($C31," ",""),CHAR(160),"")&",",","&SUBSTITUTE(SUBSTITUTE(_xlpm.ids," ",""),CHAR(160),"")&","))))} -> 1 | I31: =COUNTIFS('Golden Rulebook-CDErule level'!$E:$E,$C31,'Golden Rulebook-CDErule level'!$L:$L,I$28,'Golden Rulebook-CDErule level'!$A:$A,$B31,'Golden Rulebook-CDErule level'!$AA:$AA,"Active") -> 0 | J31: =COUNTIFS('Golden Rulebook-CDErule level'!$E:$E,$C31,'Golden Rulebook-CDErule level'!$L:$L,J$28,'Golden Rulebook-CDErule level'!$A:$A,$B31,'Golden Rulebook-CDErule level'!$AA:$AA,"Active") -> 2 | L31: =_xlfn.XLOOKUP(M31,'In-scope Tables'!B:B,'In-scope Tables'!D:D,"") -> Sprint 1 | M31: DED_Data_Table_003 | N31: Status_Lookup_Language | O31: =COUNTIFS('Golden Rulebook-CDErule level'!$C:$C,$M31,'Golden Rulebook-CDErule level'!$L:$L,O$28,'Golden Rulebook-CDErule level'!$A:$A,$L31,'Golden Rulebook-CDErule level'!$AA:$AA,"Active") -> 1 | P31: =COUNTIFS('Golden Rulebook-CDErule level'!$C:$C,$M31,'Golden Rulebook-CDErule level'!$L:$L,P$28,'Golden Rulebook-CDErule level'!$A:$A,$L31,'Golden Rulebook-CDErule level'!$AA:$AA,"Active") -> 1 | S31: Timeliness | T31: =SUM(P29:P180) -> 138 | U31: 138 | V31: Table level | W31: Table level | X31: 1 | Y31: =SUM(H7,H15,H23) -> 138 | Z31: =Y31/U31 -> 1
B32: =_xlfn.XLOOKUP(C32,'In-scope Attributes'!B:B,'In-scope Attributes'!H:H,"") -> Sprint 1 | C32: DED_Attribute_0009 | D32: RECEIPT_AMOUNT | E32: DED_Data_Table_001 | F32: Financial_Audit_Trail | G32: =COUNTIFS('Golden Rulebook-CDErule level'!$E:$E,$C32,'Golden Rulebook-CDErule level'!$L:$L,G$28,'Golden Rulebook-CDErule level'!$A:$A,$B32,'Golden Rulebook-CDErule level'!$AA:$AA,"Active") -> 1 | H32: {=_xlfn.LET(_xlpm.ids,_xlfn._xlws.FILTER('Golden Rulebook-CDErule level'!$S$4:$S$4620,('Golden Rulebook-CDErule level'!$L$4:$L$4620=H$28)*('Golden Rulebook-CDErule level'!$A$4:$A$4620=$B32)*('Golden Rulebook-CDErule level'!$AA$4:$AA$4620="Active"),""),SUM(--ISNUMBER(SEARCH(","&SUBSTITUTE(SUBSTITUTE($C32," ",""),CHAR(160),"")&",",","&SUBSTITUTE(SUBSTITUTE(_xlpm.ids," ",""),CHAR(160),"")&","))))} -> 1 | I32: =COUNTIFS('Golden Rulebook-CDErule level'!$E:$E,$C32,'Golden Rulebook-CDErule level'!$L:$L,I$28,'Golden Rulebook-CDErule level'!$A:$A,$B32,'Golden Rulebook-CDErule level'!$AA:$AA,"Active") -> 0 | J32: =COUNTIFS('Golden Rulebook-CDErule level'!$E:$E,$C32,'Golden Rulebook-CDErule level'!$L:$L,J$28,'Golden Rulebook-CDErule level'!$A:$A,$B32,'Golden Rulebook-CDErule level'!$AA:$AA,"Active") -> 2 | L32: =_xlfn.XLOOKUP(M32,'In-scope Tables'!B:B,'In-scope Tables'!D:D,"") -> Sprint 1 | M32: DED_Data_Table_004 | N32: Application_Master | O32: =COUNTIFS('Golden Rulebook-CDErule level'!$C:$C,$M32,'Golden Rulebook-CDErule level'!$L:$L,O$28,'Golden Rulebook-CDErule level'!$A:$A,$L32,'Golden Rulebook-CDErule level'!$AA:$AA,"Active") -> 1 | P32: =COUNTIFS('Golden Rulebook-CDErule level'!$C:$C,$M32,'Golden Rulebook-CDErule level'!$L:$L,P$28,'Golden Rulebook-CDErule level'!$A:$A,$L32,'Golden Rulebook-CDErule level'!$AA:$AA,"Active") -> 1 | S32: Uniqueness | T32: =SUM(O29:O180) -> 138 | U32: 138 | V32: =V31 -> Table level | W32: Table level | X32: 1 | Y32: =SUM(H8,H16,H24) -> 138 | Z32: =Y32/U32 -> 1
B33: =_xlfn.XLOOKUP(C33,'In-scope Attributes'!B:B,'In-scope Attributes'!H:H,"") -> Sprint 1 | C33: DED_Attribute_0011 | D33: FEEITEM_SEQ_NBR | E33: DED_Data_Table_001 | F33: Financial_Audit_Trail | G33: =COUNTIFS('Golden Rulebook-CDErule level'!$E:$E,$C33,'Golden Rulebook-CDErule level'!$L:$L,G$28,'Golden Rulebook-CDErule level'!$A:$A,$B33,'Golden Rulebook-CDErule level'!$AA:$AA,"Active") -> 1 | H33: {=_xlfn.LET(_xlpm.ids,_xlfn._xlws.FILTER('Golden Rulebook-CDErule level'!$S$4:$S$4620,('Golden Rulebook-CDErule level'!$L$4:$L$4620=H$28)*('Golden Rulebook-CDErule level'!$A$4:$A$4620=$B33)*('Golden Rulebook-CDErule level'!$AA$4:$AA$4620="Active"),""),SUM(--ISNUMBER(SEARCH(","&SUBSTITUTE(SUBSTITUTE($C33," ",""),CHAR(160),"")&",",","&SUBSTITUTE(SUBSTITUTE(_xlpm.ids," ",""),CHAR(160),"")&","))))} -> 1 | I33: =COUNTIFS('Golden Rulebook-CDErule level'!$E:$E,$C33,'Golden Rulebook-CDErule level'!$L:$L,I$28,'Golden Rulebook-CDErule level'!$A:$A,$B33,'Golden Rulebook-CDErule level'!$AA:$AA,"Active") -> 0 | J33: =COUNTIFS('Golden Rulebook-CDErule level'!$E:$E,$C33,'Golden Rulebook-CDErule level'!$L:$L,J$28,'Golden Rulebook-CDErule level'!$A:$A,$B33,'Golden Rulebook-CDErule level'!$AA:$AA,"Active") -> 2 | L33: =_xlfn.XLOOKUP(M33,'In-scope Tables'!B:B,'In-scope Tables'!D:D,"") -> Sprint 1 | M33: DED_Data_Table_005 | N33: License_Expiration | O33: =COUNTIFS('Golden Rulebook-CDErule level'!$C:$C,$M33,'Golden Rulebook-CDErule level'!$L:$L,O$28,'Golden Rulebook-CDErule level'!$A:$A,$L33,'Golden Rulebook-CDErule level'!$AA:$AA,"Active") -> 1 | P33: =COUNTIFS('Golden Rulebook-CDErule level'!$C:$C,$M33,'Golden Rulebook-CDErule level'!$L:$L,P$28,'Golden Rulebook-CDErule level'!$A:$A,$L33,'Golden Rulebook-CDErule level'!$AA:$AA,"Active") -> 1 | S33: Accuracy | T33: =SUM(I29:I1297) -> 45 | U33: =$U$28 -> CDE level | V33: =V28 -> 1199 | W33: =T33/V33 -> 0.037531276 | X33: 0.5 | Y33: =SUM(H9,H17,H25) -> 43 | Z33: =Y33/V33 -> 0.035863219
B34: =_xlfn.XLOOKUP(C34,'In-scope Attributes'!B:B,'In-scope Attributes'!H:H,"") -> Sprint 1 | C34: DED_Attribute_0016 | D34: APP_STATUS_GROUP_CODE | E34: DED_Data_Table_002 | F34: Status_Lookup | G34: =COUNTIFS('Golden Rulebook-CDErule level'!$E:$E,$C34,'Golden Rulebook-CDErule level'!$L:$L,G$28,'Golden Rulebook-CDErule level'!$A:$A,$B34,'Golden Rulebook-CDErule level'!$AA:$AA,"Active") -> 1 | H34: {=_xlfn.LET(_xlpm.ids,_xlfn._xlws.FILTER('Golden Rulebook-CDErule level'!$S$4:$S$4620,('Golden Rulebook-CDErule level'!$L$4:$L$4620=H$28)*('Golden Rulebook-CDErule level'!$A$4:$A$4620=$B34)*('Golden Rulebook-CDErule level'!$AA$4:$AA$4620="Active"),""),SUM(--ISNUMBER(SEARCH(","&SUBSTITUTE(SUBSTITUTE($C34," ",""),CHAR(160),"")&",",","&SUBSTITUTE(SUBSTITUTE(_xlpm.ids," ",""),CHAR(160),"")&","))))} -> 1 | I34: =COUNTIFS('Golden Rulebook-CDErule level'!$E:$E,$C34,'Golden Rulebook-CDErule level'!$L:$L,I$28,'Golden Rulebook-CDErule level'!$A:$A,$B34,'Golden Rulebook-CDErule level'!$AA:$AA,"Active") -> 0 | J34: =COUNTIFS('Golden Rulebook-CDErule level'!$E:$E,$C34,'Golden Rulebook-CDErule level'!$L:$L,J$28,'Golden Rulebook-CDErule level'!$A:$A,$B34,'Golden Rulebook-CDErule level'!$AA:$AA,"Active") -> 1 | L34: =_xlfn.XLOOKUP(M34,'In-scope Tables'!B:B,'In-scope Tables'!D:D,"") -> Sprint 1 | M34: DED_Data_Table_006 | N34: Application_Address | O34: =COUNTIFS('Golden Rulebook-CDErule level'!$C:$C,$M34,'Golden Rulebook-CDErule level'!$L:$L,O$28,'Golden Rulebook-CDErule level'!$A:$A,$L34,'Golden Rulebook-CDErule level'!$AA:$AA,"Active") -> 1 | P34: =COUNTIFS('Golden Rulebook-CDErule level'!$C:$C,$M34,'Golden Rulebook-CDErule level'!$L:$L,P$28,'Golden Rulebook-CDErule level'!$A:$A,$L34,'Golden Rulebook-CDErule level'!$AA:$AA,"Active") -> 1
B35: =_xlfn.XLOOKUP(C35,'In-scope Attributes'!B:B,'In-scope Attributes'!H:H,"") -> Sprint 1 | C35: DED_Attribute_0017 | D35: STATUS | E35: DED_Data_Table_002 | F35: Status_Lookup | G35: =COUNTIFS('Golden Rulebook-CDErule level'!$E:$E,$C35,'Golden Rulebook-CDErule level'!$L:$L,G$28,'Golden Rulebook-CDErule level'!$A:$A,$B35,'Golden Rulebook-CDErule level'!$AA:$AA,"Active") -> 1 | H35: {=_xlfn.LET(_xlpm.ids,_xlfn._xlws.FILTER('Golden Rulebook-CDErule level'!$S$4:$S$4620,('Golden Rulebook-CDErule level'!$L$4:$L$4620=H$28)*('Golden Rulebook-CDErule level'!$A$4:$A$4620=$B35)*('Golden Rulebook-CDErule level'!$AA$4:$AA$4620="Active"),""),SUM(--ISNUMBER(SEARCH(","&SUBSTITUTE(SUBSTITUTE($C35," ",""),CHAR(160),"")&",",","&SUBSTITUTE(SUBSTITUTE(_xlpm.ids," ",""),CHAR(160),"")&","))))} -> 1 | I35: =COUNTIFS('Golden Rulebook-CDErule level'!$E:$E,$C35,'Golden Rulebook-CDErule level'!$L:$L,I$28,'Golden Rulebook-CDErule level'!$A:$A,$B35,'Golden Rulebook-CDErule level'!$AA:$AA,"Active") -> 0 | J35: =COUNTIFS('Golden Rulebook-CDErule level'!$E:$E,$C35,'Golden Rulebook-CDErule level'!$L:$L,J$28,'Golden Rulebook-CDErule level'!$A:$A,$B35,'Golden Rulebook-CDErule level'!$AA:$AA,"Active") -> 2 | L35: =_xlfn.XLOOKUP(M35,'In-scope Tables'!B:B,'In-scope Tables'!D:D,"") -> Sprint 1 | M35: DED_Data_Table_007 | N35: Application_District | O35: =COUNTIFS('Golden Rulebook-CDErule level'!$C:$C,$M35,'Golden Rulebook-CDErule level'!$L:$L,O$28,'Golden Rulebook-CDErule level'!$A:$A,$L35,'Golden Rulebook-CDErule level'!$AA:$AA,"Active") -> 1 | P35: =COUNTIFS('Golden Rulebook-CDErule level'!$C:$C,$M35,'Golden Rulebook-CDErule level'!$L:$L,P$28,'Golden Rulebook-CDErule level'!$A:$A,$L35,'Golden Rulebook-CDErule level'!$AA:$AA,"Active") -> 1
B36: =_xlfn.XLOOKUP(C36,'In-scope Attributes'!B:B,'In-scope Attributes'!H:H,"") -> Sprint 1 | C36: DED_Attribute_0019 | D36: SERV_PROV_CODE | E36: DED_Data_Table_002 | F36: Status_Lookup | G36: =COUNTIFS('Golden Rulebook-CDErule level'!$E:$E,$C36,'Golden Rulebook-CDErule level'!$L:$L,G$28,'Golden Rulebook-CDErule level'!$A:$A,$B36,'Golden Rulebook-CDErule level'!$AA:$AA,"Active") -> 1 | H36: {=_xlfn.LET(_xlpm.ids,_xlfn._xlws.FILTER('Golden Rulebook-CDErule level'!$S$4:$S$4620,('Golden Rulebook-CDErule level'!$L$4:$L$4620=H$28)*('Golden Rulebook-CDErule level'!$A$4:$A$4620=$B36)*('Golden Rulebook-CDErule level'!$AA$4:$AA$4620="Active"),""),SUM(--ISNUMBER(SEARCH(","&SUBSTITUTE(SUBSTITUTE($C36," ",""),CHAR(160),"")&",",","&SUBSTITUTE(SUBSTITUTE(_xlpm.ids," ",""),CHAR(160),"")&","))))} -> 0 | I36: =COUNTIFS('Golden Rulebook-CDErule level'!$E:$E,$C36,'Golden Rulebook-CDErule level'!$L:$L,I$28,'Golden Rulebook-CDErule level'!$A:$A,$B36,'Golden Rulebook-CDErule level'!$AA:$AA,"Active") -> 0 | J36: =COUNTIFS('Golden Rulebook-CDErule level'!$E:$E,$C36,'Golden Rulebook-CDErule level'!$L:$L,J$28,'Golden Rulebook-CDErule level'!$A:$A,$B36,'Golden Rulebook-CDErule level'!$AA:$AA,"Active") -> 3 | L36: =_xlfn.XLOOKUP(M36,'In-scope Tables'!B:B,'In-scope Tables'!D:D,"") -> Sprint 1 | M36: DED_Data_Table_008 | N36: Investor | O36: =COUNTIFS('Golden Rulebook-CDErule level'!$C:$C,$M36,'Golden Rulebook-CDErule level'!$L:$L,O$28,'Golden Rulebook-CDErule level'!$A:$A,$L36,'Golden Rulebook-CDErule level'!$AA:$AA,"Active") -> 1 | P36: =COUNTIFS('Golden Rulebook-CDErule level'!$C:$C,$M36,'Golden Rulebook-CDErule level'!$L:$L,P$28,'Golden Rulebook-CDErule level'!$A:$A,$L36,'Golden Rulebook-CDErule level'!$AA:$AA,"Active") -> 1
B37: =_xlfn.XLOOKUP(C37,'In-scope Attributes'!B:B,'In-scope Attributes'!H:H,"") -> Sprint 1 | C37: DED_Attribute_0022 | D37: RES_ID | E37: DED_Data_Table_003 | F37: Status_Lookup_Language | G37: =COUNTIFS('Golden Rulebook-CDErule level'!$E:$E,$C37,'Golden Rulebook-CDErule level'!$L:$L,G$28,'Golden Rulebook-CDErule level'!$A:$A,$B37,'Golden Rulebook-CDErule level'!$AA:$AA,"Active") -> 1 | H37: {=_xlfn.LET(_xlpm.ids,_xlfn._xlws.FILTER('Golden Rulebook-CDErule level'!$S$4:$S$4620,('Golden Rulebook-CDErule level'!$L$4:$L$4620=H$28)*('Golden Rulebook-CDErule level'!$A$4:$A$4620=$B37)*('Golden Rulebook-CDErule level'!$AA$4:$AA$4620="Active"),""),SUM(--ISNUMBER(SEARCH(","&SUBSTITUTE(SUBSTITUTE($C37," ",""),CHAR(160),"")&",",","&SUBSTITUTE(SUBSTITUTE(_xlpm.ids," ",""),CHAR(160),"")&","))))} -> 0 | I37: =COUNTIFS('Golden Rulebook-CDErule level'!$E:$E,$C37,'Golden Rulebook-CDErule level'!$L:$L,I$28,'Golden Rulebook-CDErule level'!$A:$A,$B37,'Golden Rulebook-CDErule level'!$AA:$AA,"Active") -> 1 | J37: =COUNTIFS('Golden Rulebook-CDErule level'!$E:$E,$C37,'Golden Rulebook-CDErule level'!$L:$L,J$28,'Golden Rulebook-CDErule level'!$A:$A,$B37,'Golden Rulebook-CDErule level'!$AA:$AA,"Active") -> 2 | L37: =_xlfn.XLOOKUP(M37,'In-scope Tables'!B:B,'In-scope Tables'!D:D,"") -> Sprint 1 | M37: DED_Data_Table_009 | N37: Company_Name | O37: =COUNTIFS('Golden Rulebook-CDErule level'!$C:$C,$M37,'Golden Rulebook-CDErule level'!$L:$L,O$28,'Golden Rulebook-CDErule level'!$A:$A,$L37,'Golden Rulebook-CDErule level'!$AA:$AA,"Active") -> 1 | P37: =COUNTIFS('Golden Rulebook-CDErule level'!$C:$C,$M37,'Golden Rulebook-CDErule level'!$L:$L,P$28,'Golden Rulebook-CDErule level'!$A:$A,$L37,'Golden Rulebook-CDErule level'!$AA:$AA,"Active") -> 1
B38: =_xlfn.XLOOKUP(C38,'In-scope Attributes'!B:B,'In-scope Attributes'!H:H,"") -> Sprint 1 | C38: DED_Attribute_0023 | D38: LANG_ID | E38: DED_Data_Table_003 | F38: Status_Lookup_Language | G38: =COUNTIFS('Golden Rulebook-CDErule level'!$E:$E,$C38,'Golden Rulebook-CDErule level'!$L:$L,G$28,'Golden Rulebook-CDErule level'!$A:$A,$B38,'Golden Rulebook-CDErule level'!$AA:$AA,"Active") -> 1 | H38: {=_xlfn.LET(_xlpm.ids,_xlfn._xlws.FILTER('Golden Rulebook-CDErule level'!$S$4:$S$4620,('Golden Rulebook-CDErule level'!$L$4:$L$4620=H$28)*('Golden Rulebook-CDErule level'!$A$4:$A$4620=$B38)*('Golden Rulebook-CDErule level'!$AA$4:$AA$4620="Active"),""),SUM(--ISNUMBER(SEARCH(","&SUBSTITUTE(SUBSTITUTE($C38," ",""),CHAR(160),"")&",",","&SUBSTITUTE(SUBSTITUTE(_xlpm.ids," ",""),CHAR(160),"")&","))))} -> 1 | I38: =COUNTIFS('Golden Rulebook-CDErule level'!$E:$E,$C38,'Golden Rulebook-CDErule level'!$L:$L,I$28,'Golden Rulebook-CDErule level'!$A:$A,$B38,'Golden Rulebook-CDErule level'!$AA:$AA,"Active") -> 0 | J38: =COUNTIFS('Golden Rulebook-CDErule level'!$E:$E,$C38,'Golden Rulebook-CDErule level'!$L:$L,J$28,'Golden Rulebook-CDErule level'!$A:$A,$B38,'Golden Rulebook-CDErule level'!$AA:$AA,"Active") -> 3 | L38: =_xlfn.XLOOKUP(M38,'In-scope Tables'!B:B,'In-scope Tables'!D:D,"") -> Sprint 1 | M38: DED_Data_Table_010 | N38: Requirement_Condition | O38: =COUNTIFS('Golden Rulebook-CDErule level'!$C:$C,$M38,'Golden Rulebook-CDErule level'!$L:$L,O$28,'Golden Rulebook-CDErule level'!$A:$A,$L38,'Golden Rulebook-CDErule level'!$AA:$AA,"Active") -> 1 | P38: =COUNTIFS('Golden Rulebook-CDErule level'!$C:$C,$M38,'Golden Rulebook-CDErule level'!$L:$L,P$28,'Golden Rulebook-CDErule level'!$A:$A,$L38,'Golden Rulebook-CDErule level'!$AA:$AA,"Active") -> 1
B39: =_xlfn.XLOOKUP(C39,'In-scope Attributes'!B:B,'In-scope Attributes'!H:H,"") -> Sprint 1 | C39: DED_Attribute_0024 | D39: STATUS | E39: DED_Data_Table_003 | F39: Status_Lookup_Language | G39: =COUNTIFS('Golden Rulebook-CDErule level'!$E:$E,$C39,'Golden Rulebook-CDErule level'!$L:$L,G$28,'Golden Rulebook-CDErule level'!$A:$A,$B39,'Golden Rulebook-CDErule level'!$AA:$AA,"Active") -> 1 | H39: {=_xlfn.LET(_xlpm.ids,_xlfn._xlws.FILTER('Golden Rulebook-CDErule level'!$S$4:$S$4620,('Golden Rulebook-CDErule level'!$L$4:$L$4620=H$28)*('Golden Rulebook-CDErule level'!$A$4:$A$4620=$B39)*('Golden Rulebook-CDErule level'!$AA$4:$AA$4620="Active"),""),SUM(--ISNUMBER(SEARCH(","&SUBSTITUTE(SUBSTITUTE($C39," ",""),CHAR(160),"")&",",","&SUBSTITUTE(SUBSTITUTE(_xlpm.ids," ",""),CHAR(160),"")&","))))} -> 1 | I39: =COUNTIFS('Golden Rulebook-CDErule level'!$E:$E,$C39,'Golden Rulebook-CDErule level'!$L:$L,I$28,'Golden Rulebook-CDErule level'!$A:$A,$B39,'Golden Rulebook-CDErule level'!$AA:$AA,"Active") -> 0 | J39: =COUNTIFS('Golden Rulebook-CDErule level'!$E:$E,$C39,'Golden Rulebook-CDErule level'!$L:$L,J$28,'Golden Rulebook-CDErule level'!$A:$A,$B39,'Golden Rulebook-CDErule level'!$AA:$AA,"Active") -> 2 | L39: =_xlfn.XLOOKUP(M39,'In-scope Tables'!B:B,'In-scope Tables'!D:D,"") -> Sprint 1 | M39: DED_Data_Table_011 | N39: Requirement_Condition_Dtl | O39: =COUNTIFS('Golden Rulebook-CDErule level'!$C:$C,$M39,'Golden Rulebook-CDErule level'!$L:$L,O$28,'Golden Rulebook-CDErule level'!$A:$A,$L39,'Golden Rulebook-CDErule level'!$AA:$AA,"Active") -> 1 | P39: =COUNTIFS('Golden Rulebook-CDErule level'!$C:$C,$M39,'Golden Rulebook-CDErule level'!$L:$L,P$28,'Golden Rulebook-CDErule level'!$A:$A,$L39,'Golden Rulebook-CDErule level'!$AA:$AA,"Active") -> 1
B40: =_xlfn.XLOOKUP(C40,'In-scope Attributes'!B:B,'In-scope Attributes'!H:H,"") -> Sprint 1 | C40: DED_Attribute_0026 | D40: SERV_PROV_CODE | E40: DED_Data_Table_004 | F40: Application_Master | G40: =COUNTIFS('Golden Rulebook-CDErule level'!$E:$E,$C40,'Golden Rulebook-CDErule level'!$L:$L,G$28,'Golden Rulebook-CDErule level'!$A:$A,$B40,'Golden Rulebook-CDErule level'!$AA:$AA,"Active") -> 1 | H40: {=_xlfn.LET(_xlpm.ids,_xlfn._xlws.FILTER('Golden Rulebook-CDErule level'!$S$4:$S$4620,('Golden Rulebook-CDErule level'!$L$4:$L$4620=H$28)*('Golden Rulebook-CDErule level'!$A$4:$A$4620=$B40)*('Golden Rulebook-CDErule level'!$AA$4:$AA$4620="Active"),""),SUM(--ISNUMBER(SEARCH(","&SUBSTITUTE(SUBSTITUTE($C40," ",""),CHAR(160),"")&",",","&SUBSTITUTE(SUBSTITUTE(_xlpm.ids," ",""),CHAR(160),"")&","))))} -> 1 | I40: =COUNTIFS('Golden Rulebook-CDErule level'!$E:$E,$C40,'Golden Rulebook-CDErule level'!$L:$L,I$28,'Golden Rulebook-CDErule level'!$A:$A,$B40,'Golden Rulebook-CDErule level'!$AA:$AA,"Active") -> 0 | J40: =COUNTIFS('Golden Rulebook-CDErule level'!$E:$E,$C40,'Golden Rulebook-CDErule level'!$L:$L,J$28,'Golden Rulebook-CDErule level'!$A:$A,$B40,'Golden Rulebook-CDErule level'!$AA:$AA,"Active") -> 1 | L40: =_xlfn.XLOOKUP(M40,'In-scope Tables'!B:B,'In-scope Tables'!D:D,"") -> Sprint 1 | M40: DED_Data_Table_012 | N40: Requirement_Condition_Dtl_Language | O40: =COUNTIFS('Golden Rulebook-CDErule level'!$C:$C,$M40,'Golden Rulebook-CDErule level'!$L:$L,O$28,'Golden Rulebook-CDErule level'!$A:$A,$L40,'Golden Rulebook-CDErule level'!$AA:$AA,"Active") -> 1 | P40: =COUNTIFS('Golden Rulebook-CDErule level'!$C:$C,$M40,'Golden Rulebook-CDErule level'!$L:$L,P$28,'Golden Rulebook-CDErule level'!$A:$A,$L40,'Golden Rulebook-CDErule level'!$AA:$AA,"Active") -> 1
B41: =_xlfn.XLOOKUP(C41,'In-scope Attributes'!B:B,'In-scope Attributes'!H:H,"") -> Sprint 1 | C41: DED_Attribute_0027 | D41: B1_PER_ID1 | E41: DED_Data_Table_004 | F41: Application_Master | G41: =COUNTIFS('Golden Rulebook-CDErule level'!$E:$E,$C41,'Golden Rulebook-CDErule level'!$L:$L,G$28,'Golden Rulebook-CDErule level'!$A:$A,$B41,'Golden Rulebook-CDErule level'!$AA:$AA,"Active") -> 1 | H41: {=_xlfn.LET(_xlpm.ids,_xlfn._xlws.FILTER('Golden Rulebook-CDErule level'!$S$4:$S$4620,('Golden Rulebook-CDErule level'!$L$4:$L$4620=H$28)*('Golden Rulebook-CDErule level'!$A$4:$A$4620=$B41)*('Golden Rulebook-CDErule level'!$AA$4:$AA$4620="Active"),""),SUM(--ISNUMBER(SEARCH(","&SUBSTITUTE(SUBSTITUTE($C41," ",""),CHAR(160),"")&",",","&SUBSTITUTE(SUBSTITUTE(_xlpm.ids," ",""),CHAR(160),"")&","))))} -> 1 | I41: =COUNTIFS('Golden Rulebook-CDErule level'!$E:$E,$C41,'Golden Rulebook-CDErule level'!$L:$L,I$28,'Golden Rulebook-CDErule level'!$A:$A,$B41,'Golden Rulebook-CDErule level'!$AA:$AA,"Active") -> 0 | J41: =COUNTIFS('Golden Rulebook-CDErule level'!$E:$E,$C41,'Golden Rulebook-CDErule level'!$L:$L,J$28,'Golden Rulebook-CDErule level'!$A:$A,$B41,'Golden Rulebook-CDErule level'!$AA:$AA,"Active") -> 1 | L41: =_xlfn.XLOOKUP(M41,'In-scope Tables'!B:B,'In-scope Tables'!D:D,"") -> Sprint 1 | M41: DED_Data_Table_013 | N41: Requirement_Condition_History | O41: =COUNTIFS('Golden Rulebook-CDErule level'!$C:$C,$M41,'Golden Rulebook-CDErule level'!$L:$L,O$28,'Golden Rulebook-CDErule level'!$A:$A,$L41,'Golden Rulebook-CDErule level'!$AA:$AA,"Active") -> 1 | P41: =COUNTIFS('Golden Rulebook-CDErule level'!$C:$C,$M41,'Golden Rulebook-CDErule level'!$L:$L,P$28,'Golden Rulebook-CDErule level'!$A:$A,$L41,'Golden Rulebook-CDErule level'!$AA:$AA,"Active") -> 1
B42: =_xlfn.XLOOKUP(C42,'In-scope Attributes'!B:B,'In-scope Attributes'!H:H,"") -> Sprint 1 | C42: DED_Attribute_0028 | D42: B1_PER_ID2 | E42: DED_Data_Table_004 | F42: Application_Master | G42: =COUNTIFS('Golden Rulebook-CDErule level'!$E:$E,$C42,'Golden Rulebook-CDErule level'!$L:$L,G$28,'Golden Rulebook-CDErule level'!$A:$A,$B42,'Golden Rulebook-CDErule level'!$AA:$AA,"Active") -> 1 | H42: {=_xlfn.LET(_xlpm.ids,_xlfn._xlws.FILTER('Golden Rulebook-CDErule level'!$S$4:$S$4620,('Golden Rulebook-CDErule level'!$L$4:$L$4620=H$28)*('Golden Rulebook-CDErule level'!$A$4:$A$4620=$B42)*('Golden Rulebook-CDErule level'!$AA$4:$AA$4620="Active"),""),SUM(--ISNUMBER(SEARCH(","&SUBSTITUTE(SUBSTITUTE($C42," ",""),CHAR(160),"")&",",","&SUBSTITUTE(SUBSTITUTE(_xlpm.ids," ",""),CHAR(160),"")&","))))} -> 1 | I42: =COUNTIFS('Golden Rulebook-CDErule level'!$E:$E,$C42,'Golden Rulebook-CDErule level'!$L:$L,I$28,'Golden Rulebook-CDErule level'!$A:$A,$B42,'Golden Rulebook-CDErule level'!$AA:$AA,"Active") -> 0 | J42: =COUNTIFS('Golden Rulebook-CDErule level'!$E:$E,$C42,'Golden Rulebook-CDErule level'!$L:$L,J$28,'Golden Rulebook-CDErule level'!$A:$A,$B42,'Golden Rulebook-CDErule level'!$AA:$AA,"Active") -> 1 | L42: =_xlfn.XLOOKUP(M42,'In-scope Tables'!B:B,'In-scope Tables'!D:D,"") -> Sprint 1 | M42: DED_Data_Table_014 | N42: Requirement_Condition_History_Dtl | O42: =COUNTIFS('Golden Rulebook-CDErule level'!$C:$C,$M42,'Golden Rulebook-CDErule level'!$L:$L,O$28,'Golden Rulebook-CDErule level'!$A:$A,$L42,'Golden Rulebook-CDErule level'!$AA:$AA,"Active") -> 1 | P42: =COUNTIFS('Golden Rulebook-CDErule level'!$C:$C,$M42,'Golden Rulebook-CDErule level'!$L:$L,P$28,'Golden Rulebook-CDErule level'!$A:$A,$L42,'Golden Rulebook-CDErule level'!$AA:$AA,"Active") -> 1
B43: =_xlfn.XLOOKUP(C43,'In-scope Attributes'!B:B,'In-scope Attributes'!H:H,"") -> Sprint 1 | C43: DED_Attribute_0029 | D43: B1_PER_ID3 | E43: DED_Data_Table_004 | F43: Application_Master | G43: =COUNTIFS('Golden Rulebook-CDErule level'!$E:$E,$C43,'Golden Rulebook-CDErule level'!$L:$L,G$28,'Golden Rulebook-CDErule level'!$A:$A,$B43,'Golden Rulebook-CDErule level'!$AA:$AA,"Active") -> 1 | H43: {=_xlfn.LET(_xlpm.ids,_xlfn._xlws.FILTER('Golden Rulebook-CDErule level'!$S$4:$S$4620,('Golden Rulebook-CDErule level'!$L$4:$L$4620=H$28)*('Golden Rulebook-CDErule level'!$A$4:$A$4620=$B43)*('Golden Rulebook-CDErule level'!$AA$4:$AA$4620="Active"),""),SUM(--ISNUMBER(SEARCH(","&SUBSTITUTE(SUBSTITUTE($C43," ",""),CHAR(160),"")&",",","&SUBSTITUTE(SUBSTITUTE(_xlpm.ids," ",""),CHAR(160),"")&","))))} -> 1 | I43: =COUNTIFS('Golden Rulebook-CDErule level'!$E:$E,$C43,'Golden Rulebook-CDErule level'!$L:$L,I$28,'Golden Rulebook-CDErule level'!$A:$A,$B43,'Golden Rulebook-CDErule level'!$AA:$AA,"Active") -> 0 | J43: =COUNTIFS('Golden Rulebook-CDErule level'!$E:$E,$C43,'Golden Rulebook-CDErule level'!$L:$L,J$28,'Golden Rulebook-CDErule level'!$A:$A,$B43,'Golden Rulebook-CDErule level'!$AA:$AA,"Active") -> 1 | L43: =_xlfn.XLOOKUP(M43,'In-scope Tables'!B:B,'In-scope Tables'!D:D,"") -> Sprint 1 | M43: DED_Data_Table_015 | N43: Requirement_Condition_Language | O43: =COUNTIFS('Golden Rulebook-CDErule level'!$C:$C,$M43,'Golden Rulebook-CDErule level'!$L:$L,O$28,'Golden Rulebook-CDErule level'!$A:$A,$L43,'Golden Rulebook-CDErule level'!$AA:$AA,"Active") -> 1 | P43: =COUNTIFS('Golden Rulebook-CDErule level'!$C:$C,$M43,'Golden Rulebook-CDErule level'!$L:$L,P$28,'Golden Rulebook-CDErule level'!$A:$A,$L43,'Golden Rulebook-CDErule level'!$AA:$AA,"Active") -> 1
B44: =_xlfn.XLOOKUP(C44,'In-scope Attributes'!B:B,'In-scope Attributes'!H:H,"") -> Sprint 1 | C44: DED_Attribute_0030 | D44: B1_PER_GROUP | E44: DED_Data_Table_004 | F44: Application_Master | G44: =COUNTIFS('Golden Rulebook-CDErule level'!$E:$E,$C44,'Golden Rulebook-CDErule level'!$L:$L,G$28,'Golden Rulebook-CDErule level'!$A:$A,$B44,'Golden Rulebook-CDErule level'!$AA:$AA,"Active") -> 1 | H44: {=_xlfn.LET(_xlpm.ids,_xlfn._xlws.FILTER('Golden Rulebook-CDErule level'!$S$4:$S$4620,('Golden Rulebook-CDErule level'!$L$4:$L$4620=H$28)*('Golden Rulebook-CDErule level'!$A$4:$A$4620=$B44)*('Golden Rulebook-CDErule level'!$AA$4:$AA$4620="Active"),""),SUM(--ISNUMBER(SEARCH(","&SUBSTITUTE(SUBSTITUTE($C44," ",""),CHAR(160),"")&",",","&SUBSTITUTE(SUBSTITUTE(_xlpm.ids," ",""),CHAR(160),"")&","))))} -> 0 | I44: =COUNTIFS('Golden Rulebook-CDErule level'!$E:$E,$C44,'Golden Rulebook-CDErule level'!$L:$L,I$28,'Golden Rulebook-CDErule level'!$A:$A,$B44,'Golden Rulebook-CDErule level'!$AA:$AA,"Active") -> 1 | J44: =COUNTIFS('Golden Rulebook-CDErule level'!$E:$E,$C44,'Golden Rulebook-CDErule level'!$L:$L,J$28,'Golden Rulebook-CDErule level'!$A:$A,$B44,'Golden Rulebook-CDErule level'!$AA:$AA,"Active") -> 2 | L44: =_xlfn.XLOOKUP(M44,'In-scope Tables'!B:B,'In-scope Tables'!D:D,"") -> Sprint 1 | M44: DED_Data_Table_017 | N44: Application_Master_Dtl | O44: =COUNTIFS('Golden Rulebook-CDErule level'!$C:$C,$M44,'Golden Rulebook-CDErule level'!$L:$L,O$28,'Golden Rulebook-CDErule level'!$A:$A,$L44,'Golden Rulebook-CDErule level'!$AA:$AA,"Active") -> 1 | P44: =COUNTIFS('Golden Rulebook-CDErule level'!$C:$C,$M44,'Golden Rulebook-CDErule level'!$L:$L,P$28,'Golden Rulebook-CDErule level'!$A:$A,$L44,'Golden Rulebook-CDErule level'!$AA:$AA,"Active") -> 1
B45: =_xlfn.XLOOKUP(C45,'In-scope Attributes'!B:B,'In-scope Attributes'!H:H,"") -> Sprint 1 | C45: DED_Attribute_0033 | D45: B1_PER_CATEGORY | E45: DED_Data_Table_004 | F45: Application_Master | G45: =COUNTIFS('Golden Rulebook-CDErule level'!$E:$E,$C45,'Golden Rulebook-CDErule level'!$L:$L,G$28,'Golden Rulebook-CDErule level'!$A:$A,$B45,'Golden Rulebook-CDErule level'!$AA:$AA,"Active") -> 1 | H45: {=_xlfn.LET(_xlpm.ids,_xlfn._xlws.FILTER('Golden Rulebook-CDErule level'!$S$4:$S$4620,('Golden Rulebook-CDErule level'!$L$4:$L$4620=H$28)*('Golden Rulebook-CDErule level'!$A$4:$A$4620=$B45)*('Golden Rulebook-CDErule level'!$AA$4:$AA$4620="Active"),""),SUM(--ISNUMBER(SEARCH(","&SUBSTITUTE(SUBSTITUTE($C45," ",""),CHAR(160),"")&",",","&SUBSTITUTE(SUBSTITUTE(_xlpm.ids," ",""),CHAR(160),"")&","))))} -> 1 | I45: =COUNTIFS('Golden Rulebook-CDErule level'!$E:$E,$C45,'Golden Rulebook-CDErule level'!$L:$L,I$28,'Golden Rulebook-CDErule level'!$A:$A,$B45,'Golden Rulebook-CDErule level'!$AA:$AA,"Active") -> 1 | J45: =COUNTIFS('Golden Rulebook-CDErule level'!$E:$E,$C45,'Golden Rulebook-CDErule level'!$L:$L,J$28,'Golden Rulebook-CDErule level'!$A:$A,$B45,'Golden Rulebook-CDErule level'!$AA:$AA,"Active") -> 2 | L45: =_xlfn.XLOOKUP(M45,'In-scope Tables'!B:B,'In-scope Tables'!D:D,"") -> Sprint 1 | M45: DED_Data_Table_019 | N45: Application_Fee | O45: =COUNTIFS('Golden Rulebook-CDErule level'!$C:$C,$M45,'Golden Rulebook-CDErule level'!$L:$L,O$28,'Golden Rulebook-CDErule level'!$A:$A,$L45,'Golden Rulebook-CDErule level'!$AA:$AA,"Active") -> 1 | P45: =COUNTIFS('Golden Rulebook-CDErule level'!$C:$C,$M45,'Golden Rulebook-CDErule level'!$L:$L,P$28,'Golden Rulebook-CDErule level'!$A:$A,$L45,'Golden Rulebook-CDErule level'!$AA:$AA,"Active") -> 1
... B166: =_xlfn.XLOOKUP(C166,'In-scope Attributes'!B:B,'In-scope Attributes'!H:H,"") -> Sprint 1 | C166: DED_Attribute_0543 | D166: air_ad_type | E166: DED_Data_Table_056 | F166: Permit_Air | G166: =COUNTIFS('Golden Rulebook-CDErule level'!$E:$E,$C166,'Golden Rulebook-CDErule level'!$L:$L,G$28,'Golden Rulebook-CDErule level'!$A:$A,$B166,'Golden Rulebook-CDErule level'!$AA:$AA,"Active") -> 1 | H166: {=_xlfn.LET(_xlpm.ids,_xlfn._xlws.FILTER('Golden Rulebook-CDErule level'!$S$4:$S$4620,('Golden Rulebook-CDErule level'!$L$4:$L$4620=H$28)*('Golden Rulebook-CDErule level'!$A$4:$A$4620=$B166)*('Golden Rulebook-CDErule level'!$AA$4:$AA$4620="Active"),""),SUM(--ISNUMBER(SEARCH(","&SUBSTITUTE(SUBSTITUTE($C166," ",""),CHAR(160),"")&",",","&SUBSTITUTE(SUBSTITUTE(_xlpm.ids," ",""),CHAR(160),"")&","))))} -> 1 | I166: =COUNTIFS('Golden Rulebook-CDErule level'!$E:$E,$C166,'Golden Rulebook-CDErule level'!$L:$L,I$28,'Golden Rulebook-CDErule level'!$A:$A,$B166,'Golden Rulebook-CDErule level'!$AA:$AA,"Active") -> 0 | J166: =COUNTIFS('Golden Rulebook-CDErule level'!$E:$E,$C166,'Golden Rulebook-CDErule level'!$L:$L,J$28,'Golden Rulebook-CDErule level'!$A:$A,$B166,'Golden Rulebook-CDErule level'!$AA:$AA,"Active") -> 1 | L166: =_xlfn.XLOOKUP(M166,'In-scope Tables'!B:B,'In-scope Tables'!D:D,"") -> Sprint 2 | M166: DED_Data_Table_236 | N166: rapo_attribute_i18n | O166: =COUNTIFS('Golden Rulebook-CDErule level'!$C:$C,$M166,'Golden Rulebook-CDErule level'!$L:$L,O$28,'Golden Rulebook-CDErule level'!$A:$A,$L166,'Golden Rulebook-CDErule level'!$AA:$AA,"Active") -> 1 | P166: =COUNTIFS('Golden Rulebook-CDErule level'!$C:$C,$M166,'Golden Rulebook-CDErule level'!$L:$L,P$28,'Golden Rulebook-CDErule level'!$A:$A,$L166,'Golden Rulebook-CDErule level'!$AA:$AA,"Active") -> 1
B167: =_xlfn.XLOOKUP(C167,'In-scope Attributes'!B:B,'In-scope Attributes'!H:H,"") -> Sprint 1 | C167: DED_Attribute_0547 | D167: show_dates | E167: DED_Data_Table_056 | F167: Permit_Air | G167: =COUNTIFS('Golden Rulebook-CDErule level'!$E:$E,$C167,'Golden Rulebook-CDErule level'!$L:$L,G$28,'Golden Rulebook-CDErule level'!$A:$A,$B167,'Golden Rulebook-CDErule level'!$AA:$AA,"Active") -> 1 | H167: {=_xlfn.LET(_xlpm.ids,_xlfn._xlws.FILTER('Golden Rulebook-CDErule level'!$S$4:$S$4620,('Golden Rulebook-CDErule level'!$L$4:$L$4620=H$28)*('Golden Rulebook-CDErule level'!$A$4:$A$4620=$B167)*('Golden Rulebook-CDErule level'!$AA$4:$AA$4620="Active"),""),SUM(--ISNUMBER(SEARCH(","&SUBSTITUTE(SUBSTITUTE($C167," ",""),CHAR(160),"")&",",","&SUBSTITUTE(SUBSTITUTE(_xlpm.ids," ",""),CHAR(160),"")&","))))} -> 1 | I167: =COUNTIFS('Golden Rulebook-CDErule level'!$E:$E,$C167,'Golden Rulebook-CDErule level'!$L:$L,I$28,'Golden Rulebook-CDErule level'!$A:$A,$B167,'Golden Rulebook-CDErule level'!$AA:$AA,"Active") -> 0 | J167: =COUNTIFS('Golden Rulebook-CDErule level'!$E:$E,$C167,'Golden Rulebook-CDErule level'!$L:$L,J$28,'Golden Rulebook-CDErule level'!$A:$A,$B167,'Golden Rulebook-CDErule level'!$AA:$AA,"Active") -> 1
B168: =_xlfn.XLOOKUP(C168,'In-scope Attributes'!B:B,'In-scope Attributes'!H:H,"") -> Sprint 1 | C168: DED_Attribute_0556 | D168: allocated_quota | E168: DED_Data_Table_057 | F168: Allocated_Quota | G168: =COUNTIFS('Golden Rulebook-CDErule level'!$E:$E,$C168,'Golden Rulebook-CDErule level'!$L:$L,G$28,'Golden Rulebook-CDErule level'!$A:$A,$B168,'Golden Rulebook-CDErule level'!$AA:$AA,"Active") -> 1 | H168: {=_xlfn.LET(_xlpm.ids,_xlfn._xlws.FILTER('Golden Rulebook-CDErule level'!$S$4:$S$4620,('Golden Rulebook-CDErule level'!$L$4:$L$4620=H$28)*('Golden Rulebook-CDErule level'!$A$4:$A$4620=$B168)*('Golden Rulebook-CDErule level'!$AA$4:$AA$4620="Active"),""),SUM(--ISNUMBER(SEARCH(","&SUBSTITUTE(SUBSTITUTE($C168," ",""),CHAR(160),"")&",",","&SUBSTITUTE(SUBSTITUTE(_xlpm.ids," ",""),CHAR(160),"")&","))))} -> 1 | I168: =COUNTIFS('Golden Rulebook-CDErule level'!$E:$E,$C168,'Golden Rulebook-CDErule level'!$L:$L,I$28,'Golden Rulebook-CDErule level'!$A:$A,$B168,'Golden Rulebook-CDErule level'!$AA:$AA,"Active") -> 0 | J168: =COUNTIFS('Golden Rulebook-CDErule level'!$E:$E,$C168,'Golden Rulebook-CDErule level'!$L:$L,J$28,'Golden Rulebook-CDErule level'!$A:$A,$B168,'Golden Rulebook-CDErule level'!$AA:$AA,"Active") -> 1
B169: =_xlfn.XLOOKUP(C169,'In-scope Attributes'!B:B,'In-scope Attributes'!H:H,"") -> Sprint 1 | C169: DED_Attribute_0558 | D169: profession_description | E169: DED_Data_Table_057 | F169: Allocated_Quota | G169: =COUNTIFS('Golden Rulebook-CDErule level'!$E:$E,$C169,'Golden Rulebook-CDErule level'!$L:$L,G$28,'Golden Rulebook-CDErule level'!$A:$A,$B169,'Golden Rulebook-CDErule level'!$AA:$AA,"Active") -> 1 | H169: {=_xlfn.LET(_xlpm.ids,_xlfn._xlws.FILTER('Golden Rulebook-CDErule level'!$S$4:$S$4620,('Golden Rulebook-CDErule level'!$L$4:$L$4620=H$28)*('Golden Rulebook-CDErule level'!$A$4:$A$4620=$B169)*('Golden Rulebook-CDErule level'!$AA$4:$AA$4620="Active"),""),SUM(--ISNUMBER(SEARCH(","&SUBSTITUTE(SUBSTITUTE($C169," ",""),CHAR(160),"")&",",","&SUBSTITUTE(SUBSTITUTE(_xlpm.ids," ",""),CHAR(160),"")&","))))} -> 1 | I169: =COUNTIFS('Golden Rulebook-CDErule level'!$E:$E,$C169,'Golden Rulebook-CDErule level'!$L:$L,I$28,'Golden Rulebook-CDErule level'!$A:$A,$B169,'Golden Rulebook-CDErule level'!$AA:$AA,"Active") -> 0 | J169: =COUNTIFS('Golden Rulebook-CDErule level'!$E:$E,$C169,'Golden Rulebook-CDErule level'!$L:$L,J$28,'Golden Rulebook-CDErule level'!$A:$A,$B169,'Golden Rulebook-CDErule level'!$AA:$AA,"Active") -> 1
B170: =_xlfn.XLOOKUP(C170,'In-scope Attributes'!B:B,'In-scope Attributes'!H:H,"") -> Sprint 1 | C170: DED_Attribute_0568 | D170: approval_status | E170: DED_Data_Table_058 | F170: Entity_Identifier | G170: =COUNTIFS('Golden Rulebook-CDErule level'!$E:$E,$C170,'Golden Rulebook-CDErule level'!$L:$L,G$28,'Golden Rulebook-CDErule level'!$A:$A,$B170,'Golden Rulebook-CDErule level'!$AA:$AA,"Active") -> 1 | H170: {=_xlfn.LET(_xlpm.ids,_xlfn._xlws.FILTER('Golden Rulebook-CDErule level'!$S$4:$S$4620,('Golden Rulebook-CDErule level'!$L$4:$L$4620=H$28)*('Golden Rulebook-CDErule level'!$A$4:$A$4620=$B170)*('Golden Rulebook-CDErule level'!$AA$4:$AA$4620="Active"),""),SUM(--ISNUMBER(SEARCH(","&SUBSTITUTE(SUBSTITUTE($C170," ",""),CHAR(160),"")&",",","&SUBSTITUTE(SUBSTITUTE(_xlpm.ids," ",""),CHAR(160),"")&","))))} -> 1 | I170: =COUNTIFS('Golden Rulebook-CDErule level'!$E:$E,$C170,'Golden Rulebook-CDErule level'!$L:$L,I$28,'Golden Rulebook-CDErule level'!$A:$A,$B170,'Golden Rulebook-CDErule level'!$AA:$AA,"Active") -> 0 | J170: =COUNTIFS('Golden Rulebook-CDErule level'!$E:$E,$C170,'Golden Rulebook-CDErule level'!$L:$L,J$28,'Golden Rulebook-CDErule level'!$A:$A,$B170,'Golden Rulebook-CDErule level'!$AA:$AA,"Active") -> 1
B171: =_xlfn.XLOOKUP(C171,'In-scope Attributes'!B:B,'In-scope Attributes'!H:H,"") -> Sprint 1 | C171: DED_Attribute_0576 | D171: entity_identifier_name | E171: DED_Data_Table_058 | F171: Entity_Identifier | G171: =COUNTIFS('Golden Rulebook-CDErule level'!$E:$E,$C171,'Golden Rulebook-CDErule level'!$L:$L,G$28,'Golden Rulebook-CDErule level'!$A:$A,$B171,'Golden Rulebook-CDErule level'!$AA:$AA,"Active") -> 1 | H171: {=_xlfn.LET(_xlpm.ids,_xlfn._xlws.FILTER('Golden Rulebook-CDErule level'!$S$4:$S$4620,('Golden Rulebook-CDErule level'!$L$4:$L$4620=H$28)*('Golden Rulebook-CDErule level'!$A$4:$A$4620=$B171)*('Golden Rulebook-CDErule level'!$AA$4:$AA$4620="Active"),""),SUM(--ISNUMBER(SEARCH(","&SUBSTITUTE(SUBSTITUTE($C171," ",""),CHAR(160),"")&",",","&SUBSTITUTE(SUBSTITUTE(_xlpm.ids," ",""),CHAR(160),"")&","))))} -> 1 | I171: =COUNTIFS('Golden Rulebook-CDErule level'!$E:$E,$C171,'Golden Rulebook-CDErule level'!$L:$L,I$28,'Golden Rulebook-CDErule level'!$A:$A,$B171,'Golden Rulebook-CDErule level'!$AA:$AA,"Active") -> 0 | J171: =COUNTIFS('Golden Rulebook-CDErule level'!$E:$E,$C171,'Golden Rulebook-CDErule level'!$L:$L,J$28,'Golden Rulebook-CDErule level'!$A:$A,$B171,'Golden Rulebook-CDErule level'!$AA:$AA,"Active") -> 1
B172: =_xlfn.XLOOKUP(C172,'In-scope Attributes'!B:B,'In-scope Attributes'!H:H,"") -> Sprint 1 | C172: DED_Attribute_0577 | D172: entity_name | E172: DED_Data_Table_058 | F172: Entity_Identifier | G172: =COUNTIFS('Golden Rulebook-CDErule level'!$E:$E,$C172,'Golden Rulebook-CDErule level'!$L:$L,G$28,'Golden Rulebook-CDErule level'!$A:$A,$B172,'Golden Rulebook-CDErule level'!$AA:$AA,"Active") -> 1 | H172: {=_xlfn.LET(_xlpm.ids,_xlfn._xlws.FILTER('Golden Rulebook-CDErule level'!$S$4:$S$4620,('Golden Rulebook-CDErule level'!$L$4:$L$4620=H$28)*('Golden Rulebook-CDErule level'!$A$4:$A$4620=$B172)*('Golden Rulebook-CDErule level'!$AA$4:$AA$4620="Active"),""),SUM(--ISNUMBER(SEARCH(","&SUBSTITUTE(SUBSTITUTE($C172," ",""),CHAR(160),"")&",",","&SUBSTITUTE(SUBSTITUTE(_xlpm.ids," ",""),CHAR(160),"")&","))))} -> 1 | I172: =COUNTIFS('Golden Rulebook-CDErule level'!$E:$E,$C172,'Golden Rulebook-CDErule level'!$L:$L,I$28,'Golden Rulebook-CDErule level'!$A:$A,$B172,'Golden Rulebook-CDErule level'!$AA:$AA,"Active") -> 0 | J172: =COUNTIFS('Golden Rulebook-CDErule level'!$E:$E,$C172,'Golden Rulebook-CDErule level'!$L:$L,J$28,'Golden Rulebook-CDErule level'!$A:$A,$B172,'Golden Rulebook-CDErule level'!$AA:$AA,"Active") -> 1
B173: =_xlfn.XLOOKUP(C173,'In-scope Attributes'!B:B,'In-scope Attributes'!H:H,"") -> Sprint 1 | C173: DED_Attribute_0578 | D173: entry_date | E173: DED_Data_Table_058 | F173: Entity_Identifier | G173: =COUNTIFS('Golden Rulebook-CDErule level'!$E:$E,$C173,'Golden Rulebook-CDErule level'!$L:$L,G$28,'Golden Rulebook-CDErule level'!$A:$A,$B173,'Golden Rulebook-CDErule level'!$AA:$AA,"Active") -> 1 | H173: {=_xlfn.LET(_xlpm.ids,_xlfn._xlws.FILTER('Golden Rulebook-CDErule level'!$S$4:$S$4620,('Golden Rulebook-CDErule level'!$L$4:$L$4620=H$28)*('Golden Rulebook-CDErule level'!$A$4:$A$4620=$B173)*('Golden Rulebook-CDErule level'!$AA$4:$AA$4620="Active"),""),SUM(--ISNUMBER(SEARCH(","&SUBSTITUTE(SUBSTITUTE($C173," ",""),CHAR(160),"")&",",","&SUBSTITUTE(SUBSTITUTE(_xlpm.ids," ",""),CHAR(160),"")&","))))} -> 1 | I173: =COUNTIFS('Golden Rulebook-CDErule level'!$E:$E,$C173,'Golden Rulebook-CDErule level'!$L:$L,I$28,'Golden Rulebook-CDErule level'!$A:$A,$B173,'Golden Rulebook-CDErule level'!$AA:$AA,"Active") -> 0 | J173: =COUNTIFS('Golden Rulebook-CDErule level'!$E:$E,$C173,'Golden Rulebook-CDErule level'!$L:$L,J$28,'Golden Rulebook-CDErule level'!$A:$A,$B173,'Golden Rulebook-CDErule level'!$AA:$AA,"Active") -> 2
B174: =_xlfn.XLOOKUP(C174,'In-scope Attributes'!B:B,'In-scope Attributes'!H:H,"") -> Sprint 1 | C174: DED_Attribute_0583 | D174: status | E174: DED_Data_Table_058 | F174: Entity_Identifier | G174: =COUNTIFS('Golden Rulebook-CDErule level'!$E:$E,$C174,'Golden Rulebook-CDErule level'!$L:$L,G$28,'Golden Rulebook-CDErule level'!$A:$A,$B174,'Golden Rulebook-CDErule level'!$AA:$AA,"Active") -> 1 | H174: {=_xlfn.LET(_xlpm.ids,_xlfn._xlws.FILTER('Golden Rulebook-CDErule level'!$S$4:$S$4620,('Golden Rulebook-CDErule level'!$L$4:$L$4620=H$28)*('Golden Rulebook-CDErule level'!$A$4:$A$4620=$B174)*('Golden Rulebook-CDErule level'!$AA$4:$AA$4620="Active"),""),SUM(--ISNUMBER(SEARCH(","&SUBSTITUTE(SUBSTITUTE($C174," ",""),CHAR(160),"")&",",","&SUBSTITUTE(SUBSTITUTE(_xlpm.ids," ",""),CHAR(160),"")&","))))} -> 0 | I174: =COUNTIFS('Golden Rulebook-CDErule level'!$E:$E,$C174,'Golden Rulebook-CDErule level'!$L:$L,I$28,'Golden Rulebook-CDErule level'!$A:$A,$B174,'Golden Rulebook-CDErule level'!$AA:$AA,"Active") -> 0 | J174: =COUNTIFS('Golden Rulebook-CDErule level'!$E:$E,$C174,'Golden Rulebook-CDErule level'!$L:$L,J$28,'Golden Rulebook-CDErule level'!$A:$A,$B174,'Golden Rulebook-CDErule level'!$AA:$AA,"Active") -> 1
B175: =_xlfn.XLOOKUP(C175,'In-scope Attributes'!B:B,'In-scope Attributes'!H:H,"") -> Sprint 1 | C175: DED_Attribute_0584 | D175: total_employee | E175: DED_Data_Table_058 | F175: Entity_Identifier | G175: =COUNTIFS('Golden Rulebook-CDErule level'!$E:$E,$C175,'Golden Rulebook-CDErule level'!$L:$L,G$28,'Golden Rulebook-CDErule level'!$A:$A,$B175,'Golden Rulebook-CDErule level'!$AA:$AA,"Active") -> 1 | H175: {=_xlfn.LET(_xlpm.ids,_xlfn._xlws.FILTER('Golden Rulebook-CDErule level'!$S$4:$S$4620,('Golden Rulebook-CDErule level'!$L$4:$L$4620=H$28)*('Golden Rulebook-CDErule level'!$A$4:$A$4620=$B175)*('Golden Rulebook-CDErule level'!$AA$4:$AA$4620="Active"),""),SUM(--ISNUMBER(SEARCH(","&SUBSTITUTE(SUBSTITUTE($C175," ",""),CHAR(160),"")&",",","&SUBSTITUTE(SUBSTITUTE(_xlpm.ids," ",""),CHAR(160),"")&","))))} -> 0 | I175: =COUNTIFS('Golden Rulebook-CDErule level'!$E:$E,$C175,'Golden Rulebook-CDErule level'!$L:$L,I$28,'Golden Rulebook-CDErule level'!$A:$A,$B175,'Golden Rulebook-CDErule level'!$AA:$AA,"Active") -> 0 | J175: =COUNTIFS('Golden Rulebook-CDErule level'!$E:$E,$C175,'Golden Rulebook-CDErule level'!$L:$L,J$28,'Golden Rulebook-CDErule level'!$A:$A,$B175,'Golden Rulebook-CDErule level'!$AA:$AA,"Active") -> 2
B176: =_xlfn.XLOOKUP(C176,'In-scope Attributes'!B:B,'In-scope Attributes'!H:H,"") -> Sprint 2 | C176: DED_Attribute_0592 | D176: category | E176: DED_Data_Table_059 | F176: RB_PEP_Association | G176: =COUNTIFS('Golden Rulebook-CDErule level'!$E:$E,$C176,'Golden Rulebook-CDErule level'!$L:$L,G$28,'Golden Rulebook-CDErule level'!$A:$A,$B176,'Golden Rulebook-CDErule level'!$AA:$AA,"Active") -> 1 | H176: {=_xlfn.LET(_xlpm.ids,_xlfn._xlws.FILTER('Golden Rulebook-CDErule level'!$S$4:$S$4620,('Golden Rulebook-CDErule level'!$L$4:$L$4620=H$28)*('Golden Rulebook-CDErule level'!$A$4:$A$4620=$B176)*('Golden Rulebook-CDErule level'!$AA$4:$AA$4620="Active"),""),SUM(--ISNUMBER(SEARCH(","&SUBSTITUTE(SUBSTITUTE($C176," ",""),CHAR(160),"")&",",","&SUBSTITUTE(SUBSTITUTE(_xlpm.ids," ",""),CHAR(160),"")&","))))} -> 1 | I176: =COUNTIFS('Golden Rulebook-CDErule level'!$E:$E,$C176,'Golden Rulebook-CDErule level'!$L:$L,I$28,'Golden Rulebook-CDErule level'!$A:$A,$B176,'Golden Rulebook-CDErule level'!$AA:$AA,"Active") -> 0 | J176: =COUNTIFS('Golden Rulebook-CDErule level'!$E:$E,$C176,'Golden Rulebook-CDErule level'!$L:$L,J$28,'Golden Rulebook-CDErule level'!$A:$A,$B176,'Golden Rulebook-CDErule level'!$AA:$AA,"Active") -> 2
B177: =_xlfn.XLOOKUP(C177,'In-scope Attributes'!B:B,'In-scope Attributes'!H:H,"") -> Sprint 2 | C177: DED_Attribute_0593 | D177: full_name | E177: DED_Data_Table_059 | F177: RB_PEP_Association | G177: =COUNTIFS('Golden Rulebook-CDErule level'!$E:$E,$C177,'Golden Rulebook-CDErule level'!$L:$L,G$28,'Golden Rulebook-CDErule level'!$A:$A,$B177,'Golden Rulebook-CDErule level'!$AA:$AA,"Active") -> 1 | H177: {=_xlfn.LET(_xlpm.ids,_xlfn._xlws.FILTER('Golden Rulebook-CDErule level'!$S$4:$S$4620,('Golden Rulebook-CDErule level'!$L$4:$L$4620=H$28)*('Golden Rulebook-CDErule level'!$A$4:$A$4620=$B177)*('Golden Rulebook-CDErule level'!$AA$4:$AA$4620="Active"),""),SUM(--ISNUMBER(SEARCH(","&SUBSTITUTE(SUBSTITUTE($C177," ",""),CHAR(160),"")&",",","&SUBSTITUTE(SUBSTITUTE(_xlpm.ids," ",""),CHAR(160),"")&","))))} -> 0 | I177: =COUNTIFS('Golden Rulebook-CDErule level'!$E:$E,$C177,'Golden Rulebook-CDErule level'!$L:$L,I$28,'Golden Rulebook-CDErule level'!$A:$A,$B177,'Golden Rulebook-CDErule level'!$AA:$AA,"Active") -> 0 | J177: =COUNTIFS('Golden Rulebook-CDErule level'!$E:$E,$C177,'Golden Rulebook-CDErule level'!$L:$L,J$28,'Golden Rulebook-CDErule level'!$A:$A,$B177,'Golden Rulebook-CDErule level'!$AA:$AA,"Active") -> 1
B178: =_xlfn.XLOOKUP(C178,'In-scope Attributes'!B:B,'In-scope Attributes'!H:H,"") -> Sprint 2 | C178: DED_Attribute_0594 | D178: job_description | E178: DED_Data_Table_059 | F178: RB_PEP_Association | G178: =COUNTIFS('Golden Rulebook-CDErule level'!$E:$E,$C178,'Golden Rulebook-CDErule level'!$L:$L,G$28,'Golden Rulebook-CDErule level'!$A:$A,$B178,'Golden Rulebook-CDErule level'!$AA:$AA,"Active") -> 1 | H178: {=_xlfn.LET(_xlpm.ids,_xlfn._xlws.FILTER('Golden Rulebook-CDErule level'!$S$4:$S$4620,('Golden Rulebook-CDErule level'!$L$4:$L$4620=H$28)*('Golden Rulebook-CDErule level'!$A$4:$A$4620=$B178)*('Golden Rulebook-CDErule level'!$AA$4:$AA$4620="Active"),""),SUM(--ISNUMBER(SEARCH(","&SUBSTITUTE(SUBSTITUTE($C178," ",""),CHAR(160),"")&",",","&SUBSTITUTE(SUBSTITUTE(_xlpm.ids," ",""),CHAR(160),"")&","))))} -> 1 | I178: =COUNTIFS('Golden Rulebook-CDErule level'!$E:$E,$C178,'Golden Rulebook-CDErule level'!$L:$L,I$28,'Golden Rulebook-CDErule level'!$A:$A,$B178,'Golden Rulebook-CDErule level'!$AA:$AA,"Active") -> 0 | J178: =COUNTIFS('Golden Rulebook-CDErule level'!$E:$E,$C178,'Golden Rulebook-CDErule level'!$L:$L,J$28,'Golden Rulebook-CDErule level'!$A:$A,$B178,'Golden Rulebook-CDErule level'!$AA:$AA,"Active") -> 2
... B1227: =_xlfn.XLOOKUP(C1227,'In-scope Attributes'!B:B,'In-scope Attributes'!H:H,"") -> Sprint 1 | C1227: DED_Attribute_5586 | D1227: status_type | E1227: DED_Data_Table_002 | F1227: status_lookup | G1227: =COUNTIFS('Golden Rulebook-CDErule level'!$E:$E,$C1227,'Golden Rulebook-CDErule level'!$L:$L,G$28,'Golden Rulebook-CDErule level'!$A:$A,$B1227,'Golden Rulebook-CDErule level'!$AA:$AA,"Active") -> 1 | H1227: {=_xlfn.LET(_xlpm.ids,_xlfn._xlws.FILTER('Golden Rulebook-CDErule level'!$S$4:$S$4620,('Golden Rulebook-CDErule level'!$L$4:$L$4620=H$28)*('Golden Rulebook-CDErule level'!$A$4:$A$4620=$B1227)*('Golden Rulebook-CDErule level'!$AA$4:$AA$4620="Active"),""),SUM(--ISNUMBER(SEARCH(","&SUBSTITUTE(SUBSTITUTE($C1227," ",""),CHAR(160),"")&",",","&SUBSTITUTE(SUBSTITUTE(_xlpm.ids," ",""),CHAR(160),"")&","))))} -> 1 | I1227: =COUNTIFS('Golden Rulebook-CDErule level'!$E:$E,$C1227,'Golden Rulebook-CDErule level'!$L:$L,I$28,'Golden Rulebook-CDErule level'!$A:$A,$B1227,'Golden Rulebook-CDErule level'!$AA:$AA,"Active") -> 0 | J1227: =COUNTIFS('Golden Rulebook-CDErule level'!$E:$E,$C1227,'Golden Rulebook-CDErule level'!$L:$L,J$28,'Golden Rulebook-CDErule level'!$A:$A,$B1227,'Golden Rulebook-CDErule level'!$AA:$AA,"Active") -> 2

Sheet Table Rep (RB)
A1: DED Phase 2 | DQ Rulebook Governance Summary
A2: Threshold | B2: Completeness | C2: Uniqueness | D2: Timeliness | E2: Validity | F2: Consistency | G2: Accuracy
A3: Minimum | B3: 1 | C3: 1 | D3: 1 | E3: 0.9 | F3: 0.5 | G3: 0.5
A4: Threshold | B4: 0.95 | C4: 0.9 | D4: 0.9 | E4: 1 | F4: 0.95 | G4: 0.9
H6: =COUNTIF(H10:H147,"Fail") -> 0 | K6: =COUNTIF(K10:K147,"Fail") -> 0 | M6: =COUNTIF(M10:M147,"Fail") -> 0 | P6: =COUNTIF(P10:P147,"Fail") -> 7 | T6: =COUNTIF(T10:T147,"Fail") -> 51 | X6: =COUNTIF(X10:X147,"Fail") -> 126
F7: Completeness | J7: Uniqueness | L7: Timeliness | N7: Validity | R7: Consistency | V7: Accuracy
A9: Sprint | B9: Table Name | C9: Table ID | D9: CDE Count | E9: Total Rules | F9: # of CDEs covered by rules | G9: Coverage | H9: Meet DDA requirement? | I9: CDE not covered by rule | J9: Uniqueness Rules | K9: Uniqueness Status | L9: Timeliness Rules | M9: Timeliness Status | N9: # of CDEs covered by rules | O9: Coverage | P9: Meet DDA requirement? | Q9: CDE not covered by rule | R9: # of CDEs covered by rules | S9: Coverage | T9: Meet DDA requirement? | U9: CDE need to cover with rule to meet goal | V9: # of CDEs covered by rules | W9: Coverage | X9: Meet DDA requirement? | Y9: CDE need to cover with rule to meet goal | Z9: Dimensions that need justification for coverage | AA9: Justification for Consistency WIP
A10: Sprint 1 | B10: Allocated_Quota | C10: DED_Data_Table_057 | D10: =COUNTIFS('In-scope Attributes'!H:H,$A10,'In-scope Attributes'!D:D,$C10,'In-scope Attributes'!G:G,"Y") -> 2 | E10: =COUNTIFS('Golden Rulebook-CDErule level'!$A$4:$A$3698,$A10,'Golden Rulebook-CDErule level'!$R$4:$R$3698,$C10,'Golden Rulebook-CDErule level'!$I$4:$I$3698,"<>") -> 3 | F10: =COUNTIFS('CDE Coverage Report'!$E$28:$E$1227,C10,'CDE Coverage Report'!$G$28:$G$1227,">0") -> 2 | G10: =IF($D10=0,"N/A",F10/$D10) -> 1 | H10: =IF($D10=0,"Review",IF(G10>=$B$3,"Pass","Fail")) -> Pass | I10: =$D10-F10 -> 0 | J10: =COUNTIFS('CDE Coverage Report'!$M$28:$M$1227,C10,'CDE Coverage Report'!$O$28:$O$1227,">0") -> 1 | K10: =IF(J10>=$C$3,"Pass","Fail") -> Pass | L10: =COUNTIFS('CDE Coverage Report'!$M$28:$M$1227,C10,'CDE Coverage Report'!$P$28:$P$1227,">0") -> 1 | M10: =IF(L10>=$D$3,"Pass","Fail") -> Pass | N10: =COUNTIFS('CDE Coverage Report'!$E$28:$E$1227,C10,'CDE Coverage Report'!$J$28:$J$1227,">0") -> 2 | O10: =IF($D10=0,"N/A",N10/$D10) -> 1 | P10: =IF($D10=0,"Review",IF(O10>=$E$3,"Pass","Fail")) -> Pass | Q10: =$D10-N10 -> 0 | R10: =COUNTIFS('CDE Coverage Report'!$E$28:$E$1227,C10,'CDE Coverage Report'!$H$28:$H$1227,">0") -> 2 | S10: =IF($D10=0,"N/A",R10/$D10) -> 1 | T10: =IF($D10=0,"Review",IF(S10>=$F$3,"Pass","Fail")) -> Pass | U10: =(0.5-S10)*D10 -> -1 | V10: =COUNTIFS('CDE Coverage Report'!$E$28:$E$1227,C10,'CDE Coverage Report'!$I$28:$I$1227,">0") -> 0 | W10: =IF($D10=0,"N/A",V10/$D10) -> 0 | X10: =IF($D10=0,"Review",IF(W10>=$G$3,"Pass","Fail")) -> Fail | Y10: =(0.5-W10)*D10 -> 1 | Z10: =_xlfn.TEXTJOIN(", ",TRUE,IF(H10="Fail",$F$7,""),IF(K10="Fail",$J$7,""),IF(M10="Fail",$L$7,""),IF(P10="Fail",$N$7,""),IF(T10="Fail",$R$7,""),IF(X10="Fail",$V$7,"")) -> Accuracy | AA10: Business Quota team doesn't use and know anything about this table
A11: Sprint 1 | B11: Application_Address | C11: DED_Data_Table_006 | D11: =COUNTIFS('In-scope Attributes'!H:H,$A11,'In-scope Attributes'!D:D,$C11,'In-scope Attributes'!G:G,"Y") -> 8 | E11: =COUNTIFS('Golden Rulebook-CDErule level'!$A$4:$A$3698,$A11,'Golden Rulebook-CDErule level'!$R$4:$R$3698,$C11,'Golden Rulebook-CDErule level'!$I$4:$I$3698,"<>") -> 11 | F11: =COUNTIFS('CDE Coverage Report'!$E$28:$E$1227,C11,'CDE Coverage Report'!$G$28:$G$1227,">0") -> 8 | G11: =IF($D11=0,"N/A",F11/$D11) -> 1 | H11: =IF($D11=0,"Review",IF(G11>=$B$3,"Pass","Fail")) -> Pass | I11: =$D11-F11 -> 0 | J11: =COUNTIFS('CDE Coverage Report'!$M$28:$M$1227,C11,'CDE Coverage Report'!$O$28:$O$1227,">0") -> 1 | K11: =IF(J11>=$C$3,"Pass","Fail") -> Pass | L11: =COUNTIFS('CDE Coverage Report'!$M$28:$M$1227,C11,'CDE Coverage Report'!$P$28:$P$1227,">0") -> 1 | M11: =IF(L11>=$D$3,"Pass","Fail") -> Pass | N11: =COUNTIFS('CDE Coverage Report'!$E$28:$E$1227,C11,'CDE Coverage Report'!$J$28:$J$1227,">0") -> 8 | O11: =IF($D11=0,"N/A",N11/$D11) -> 1 | P11: =IF($D11=0,"Review",IF(O11>=$E$3,"Pass","Fail")) -> Pass | Q11: =$D11-N11 -> 0 | R11: =COUNTIFS('CDE Coverage Report'!$E$28:$E$1227,C11,'CDE Coverage Report'!$H$28:$H$1227,">0") -> 6 | S11: =IF($D11=0,"N/A",R11/$D11) -> 0.75 | T11: =IF($D11=0,"Review",IF(S11>=$F$3,"Pass","Fail")) -> Pass | U11: =(0.5-S11)*D11 -> -2 | V11: =COUNTIFS('CDE Coverage Report'!$E$28:$E$1227,C11,'CDE Coverage Report'!$I$28:$I$1227,">0") -> 1 | W11: =IF($D11=0,"N/A",V11/$D11) -> 0.125 | X11: =IF($D11=0,"Review",IF(W11>=$G$3,"Pass","Fail")) -> Fail | Y11: =(0.5-W11)*D11 -> 3 | Z11: =_xlfn.TEXTJOIN(", ",TRUE,IF(H11="Fail",$F$7,""),IF(K11="Fail",$J$7,""),IF(M11="Fail",$L$7,""),IF(P11="Fail",$N$7,""),IF(T11="Fail",$R$7,""),IF(X11="Fail",$V$7,"")) -> Accuracy
A12: Sprint 1 | B12: Application_Address_Reference | C12: DED_Data_Table_034 | D12: =COUNTIFS('In-scope Attributes'!H:H,$A12,'In-scope Attributes'!D:D,$C12,'In-scope Attributes'!G:G,"Y") -> 3 | E12: =COUNTIFS('Golden Rulebook-CDErule level'!$A$4:$A$3698,$A12,'Golden Rulebook-CDErule level'!$R$4:$R$3698,$C12,'Golden Rulebook-CDErule level'!$I$4:$I$3698,"<>") -> 9 | F12: =COUNTIFS('CDE Coverage Report'!$E$28:$E$1227,C12,'CDE Coverage Report'!$G$28:$G$1227,">0") -> 3 | G12: =IF($D12=0,"N/A",F12/$D12) -> 1 | H12: =IF($D12=0,"Review",IF(G12>=$B$3,"Pass","Fail")) -> Pass | I12: =$D12-F12 -> 0 | J12: =COUNTIFS('CDE Coverage Report'!$M$28:$M$1227,C12,'CDE Coverage Report'!$O$28:$O$1227,">0") -> 1 | K12: =IF(J12>=$C$3,"Pass","Fail") -> Pass | L12: =COUNTIFS('CDE Coverage Report'!$M$28:$M$1227,C12,'CDE Coverage Report'!$P$28:$P$1227,">0") -> 1 | M12: =IF(L12>=$D$3,"Pass","Fail") -> Pass | N12: =COUNTIFS('CDE Coverage Report'!$E$28:$E$1227,C12,'CDE Coverage Report'!$J$28:$J$1227,">0") -> 3 | O12: =IF($D12=0,"N/A",N12/$D12) -> 1 | P12: =IF($D12=0,"Review",IF(O12>=$E$3,"Pass","Fail")) -> Pass | Q12: =$D12-N12 -> 0 | R12: =COUNTIFS('CDE Coverage Report'!$E$28:$E$1227,C12,'CDE Coverage Report'!$H$28:$H$1227,">0") -> 1 | S12: =IF($D12=0,"N/A",R12/$D12) -> 0.33333333 | T12: =IF($D12=0,"Review",IF(S12>=$F$3,"Pass","Fail")) -> Fail | U12: =ROUNDUP((0.5-S12)*D12,0) -> 1 | V12: =COUNTIFS('CDE Coverage Report'!$E$28:$E$1227,C12,'CDE Coverage Report'!$I$28:$I$1227,">0") -> 1 | W12: =IF($D12=0,"N/A",V12/$D12) -> 0.33333333 | X12: =IF($D12=0,"Review",IF(W12>=$G$3,"Pass","Fail")) -> Fail | Y12: =(0.5-W12)*D12 -> 0.5 | Z12: =_xlfn.TEXTJOIN(", ",TRUE,IF(H12="Fail",$F$7,""),IF(K12="Fail",$J$7,""),IF(M12="Fail",$L$7,""),IF(P12="Fail",$N$7,""),IF(T12="Fail",$R$7,""),IF(X12="Fail",$V$7,"")) -> Consistency, Accuracy
A13: Sprint 1 | B13: Application_District | C13: DED_Data_Table_007 | D13: =COUNTIFS('In-scope Attributes'!H:H,$A13,'In-scope Attributes'!D:D,$C13,'In-scope Attributes'!G:G,"Y") -> 2 | E13: =COUNTIFS('Golden Rulebook-CDErule level'!$A$4:$A$3698,$A13,'Golden Rulebook-CDErule level'!$R$4:$R$3698,$C13,'Golden Rulebook-CDErule level'!$I$4:$I$3698,"<>") -> 7 | F13: =COUNTIFS('CDE Coverage Report'!$E$28:$E$1227,C13,'CDE Coverage Report'!$G$28:$G$1227,">0") -> 2 | G13: =IF($D13=0,"N/A",F13/$D13) -> 1 | H13: =IF($D13=0,"Review",IF(G13>=$B$3,"Pass","Fail")) -> Pass | I13: =$D13-F13 -> 0 | J13: =COUNTIFS('CDE Coverage Report'!$M$28:$M$1227,C13,'CDE Coverage Report'!$O$28:$O$1227,">0") -> 1 | K13: =IF(J13>=$C$3,"Pass","Fail") -> Pass | L13: =COUNTIFS('CDE Coverage Report'!$M$28:$M$1227,C13,'CDE Coverage Report'!$P$28:$P$1227,">0") -> 1 | M13: =IF(L13>=$D$3,"Pass","Fail") -> Pass | N13: =COUNTIFS('CDE Coverage Report'!$E$28:$E$1227,C13,'CDE Coverage Report'!$J$28:$J$1227,">0") -> 2 | O13: =IF($D13=0,"N/A",N13/$D13) -> 1 | P13: =IF($D13=0,"Review",IF(O13>=$E$3,"Pass","Fail")) -> Pass | Q13: =$D13-N13 -> 0 | R13: =COUNTIFS('CDE Coverage Report'!$E$28:$E$1227,C13,'CDE Coverage Report'!$H$28:$H$1227,">0") -> 1 | S13: =IF($D13=0,"N/A",R13/$D13) -> 0.5 | T13: =IF($D13=0,"Review",IF(S13>=$F$3,"Pass","Fail")) -> Pass | U13: =ROUNDUP((0.5-S13)*D13,0) -> 0 | V13: =COUNTIFS('CDE Coverage Report'!$E$28:$E$1227,C13,'CDE Coverage Report'!$I$28:$I$1227,">0") -> 1 | W13: =IF($D13=0,"N/A",V13/$D13) -> 0.5 | X13: =IF($D13=0,"Review",IF(W13>=$G$3,"Pass","Fail")) -> Pass | Y13: =(0.5-W13)*D13 -> 0 | Z13: =_xlfn.TEXTJOIN(", ",TRUE,IF(H13="Fail",$F$7,""),IF(K13="Fail",$J$7,""),IF(M13="Fail",$L$7,""),IF(P13="Fail",$N$7,""),IF(T13="Fail",$R$7,""),IF(X13="Fail",$V$7,""))
A14: Sprint 1 | B14: Application_District_Reference | C14: DED_Data_Table_035 | D14: =COUNTIFS('In-scope Attributes'!H:H,$A14,'In-scope Attributes'!D:D,$C14,'In-scope Attributes'!G:G,"Y") -> 2 | E14: =COUNTIFS('Golden Rulebook-CDErule level'!$A$4:$A$3698,$A14,'Golden Rulebook-CDErule level'!$R$4:$R$3698,$C14,'Golden Rulebook-CDErule level'!$I$4:$I$3698,"<>") -> 8 | F14: =COUNTIFS('CDE Coverage Report'!$E$28:$E$1227,C14,'CDE Coverage Report'!$G$28:$G$1227,">0") -> 2 | G14: =IF($D14=0,"N/A",F14/$D14) -> 1 | H14: =IF($D14=0,"Review",IF(G14>=$B$3,"Pass","Fail")) -> Pass | I14: =$D14-F14 -> 0 | J14: =COUNTIFS('CDE Coverage Report'!$M$28:$M$1227,C14,'CDE Coverage Report'!$O$28:$O$1227,">0") -> 1 | K14: =IF(J14>=$C$3,"Pass","Fail") -> Pass | L14: =COUNTIFS('CDE Coverage Report'!$M$28:$M$1227,C14,'CDE Coverage Report'!$P$28:$P$1227,">0") -> 1 | M14: =IF(L14>=$D$3,"Pass","Fail") -> Pass | N14: =COUNTIFS('CDE Coverage Report'!$E$28:$E$1227,C14,'CDE Coverage Report'!$J$28:$J$1227,">0") -> 2 | O14: =IF($D14=0,"N/A",N14/$D14) -> 1 | P14: =IF($D14=0,"Review",IF(O14>=$E$3,"Pass","Fail")) -> Pass | Q14: =$D14-N14 -> 0 | R14: =COUNTIFS('CDE Coverage Report'!$E$28:$E$1227,C14,'CDE Coverage Report'!$H$28:$H$1227,">0") -> 2 | S14: =IF($D14=0,"N/A",R14/$D14) -> 1 | T14: =IF($D14=0,"Review",IF(S14>=$F$3,"Pass","Fail")) -> Pass | U14: =(0.5-S14)*D14 -> -1 | V14: =COUNTIFS('CDE Coverage Report'!$E$28:$E$1227,C14,'CDE Coverage Report'!$I$28:$I$1227,">0") -> 1 | W14: =IF($D14=0,"N/A",V14/$D14) -> 0.5 | X14: =IF($D14=0,"Review",IF(W14>=$G$3,"Pass","Fail")) -> Pass | Y14: =(0.5-W14)*D14 -> 0 | Z14: =_xlfn.TEXTJOIN(", ",TRUE,IF(H14="Fail",$F$7,""),IF(K14="Fail",$J$7,""),IF(M14="Fail",$L$7,""),IF(P14="Fail",$N$7,""),IF(T14="Fail",$R$7,""),IF(X14="Fail",$V$7,""))
A15: Sprint 1 | B15: Application_Fee | C15: DED_Data_Table_019 | D15: =COUNTIFS('In-scope Attributes'!H:H,$A15,'In-scope Attributes'!D:D,$C15,'In-scope Attributes'!G:G,"Y") -> 2 | E15: =COUNTIFS('Golden Rulebook-CDErule level'!$A$4:$A$3698,$A15,'Golden Rulebook-CDErule level'!$R$4:$R$3698,$C15,'Golden Rulebook-CDErule level'!$I$4:$I$3698,"<>") -> 10 | F15: =COUNTIFS('CDE Coverage Report'!$E$28:$E$1227,C15,'CDE Coverage Report'!$G$28:$G$1227,">0") -> 2 | G15: =IF($D15=0,"N/A",F15/$D15) -> 1 | H15: =IF($D15=0,"Review",IF(G15>=$B$3,"Pass","Fail")) -> Pass | I15: =$D15-F15 -> 0 | J15: =COUNTIFS('CDE Coverage Report'!$M$28:$M$1227,C15,'CDE Coverage Report'!$O$28:$O$1227,">0") -> 1 | K15: =IF(J15>=$C$3,"Pass","Fail") -> Pass | L15: =COUNTIFS('CDE Coverage Report'!$M$28:$M$1227,C15,'CDE Coverage Report'!$P$28:$P$1227,">0") -> 1 | M15: =IF(L15>=$D$3,"Pass","Fail") -> Pass | N15: =COUNTIFS('CDE Coverage Report'!$E$28:$E$1227,C15,'CDE Coverage Report'!$J$28:$J$1227,">0") -> 2 | O15: =IF($D15=0,"N/A",N15/$D15) -> 1 | P15: =IF($D15=0,"Review",IF(O15>=$E$3,"Pass","Fail")) -> Pass | Q15: =$D15-N15 -> 0 | R15: =COUNTIFS('CDE Coverage Report'!$E$28:$E$1227,C15,'CDE Coverage Report'!$H$28:$H$1227,">0") -> 2 | S15: =IF($D15=0,"N/A",R15/$D15) -> 1 | T15: =IF($D15=0,"Review",IF(S15>=$F$3,"Pass","Fail")) -> Pass | U15: =(0.5-S15)*D15 -> -1 | V15: =COUNTIFS('CDE Coverage Report'!$E$28:$E$1227,C15,'CDE Coverage Report'!$I$28:$I$1227,">0") -> 2 | W15: =IF($D15=0,"N/A",V15/$D15) -> 1 | X15: =IF($D15=0,"Review",IF(W15>=$G$3,"Pass","Fail")) -> Pass | Y15: =(0.5-W15)*D15 -> -1 | Z15: =_xlfn.TEXTJOIN(", ",TRUE,IF(H15="Fail",$F$7,""),IF(K15="Fail",$J$7,""),IF(M15="Fail",$L$7,""),IF(P15="Fail",$N$7,""),IF(T15="Fail",$R$7,""),IF(X15="Fail",$V$7,""))
A16: Sprint 1 | B16: Application_Fee_Audit | C16: DED_Data_Table_020 | D16: =COUNTIFS('In-scope Attributes'!H:H,$A16,'In-scope Attributes'!D:D,$C16,'In-scope Attributes'!G:G,"Y") -> 3 | E16: =COUNTIFS('Golden Rulebook-CDErule level'!$A$4:$A$3698,$A16,'Golden Rulebook-CDErule level'!$R$4:$R$3698,$C16,'Golden Rulebook-CDErule level'!$I$4:$I$3698,"<>") -> 11 | F16: =COUNTIFS('CDE Coverage Report'!$E$28:$E$1227,C16,'CDE Coverage Report'!$G$28:$G$1227,">0") -> 3 | G16: =IF($D16=0,"N/A",F16/$D16) -> 1 | H16: =IF($D16=0,"Review",IF(G16>=$B$3,"Pass","Fail")) -> Pass | I16: =$D16-F16 -> 0 | J16: =COUNTIFS('CDE Coverage Report'!$M$28:$M$1227,C16,'CDE Coverage Report'!$O$28:$O$1227,">0") -> 1 | K16: =IF(J16>=$C$3,"Pass","Fail") -> Pass | L16: =COUNTIFS('CDE Coverage Report'!$M$28:$M$1227,C16,'CDE Coverage Report'!$P$28:$P$1227,">0") -> 1 | M16: =IF(L16>=$D$3,"Pass","Fail") -> Pass | N16: =COUNTIFS('CDE Coverage Report'!$E$28:$E$1227,C16,'CDE Coverage Report'!$J$28:$J$1227,">0") -> 3 | O16: =IF($D16=0,"N/A",N16/$D16) -> 1 | P16: =IF($D16=0,"Review",IF(O16>=$E$3,"Pass","Fail")) -> Pass | Q16: =$D16-N16 -> 0 | R16: =COUNTIFS('CDE Coverage Report'!$E$28:$E$1227,C16,'CDE Coverage Report'!$H$28:$H$1227,">0") -> 2 | S16: =IF($D16=0,"N/A",R16/$D16) -> 0.66666667 | T16: =IF($D16=0,"Review",IF(S16>=$F$3,"Pass","Fail")) -> Pass | U16: =(0.5-S16)*D16 -> -0.5 | V16: =COUNTIFS('CDE Coverage Report'!$E$28:$E$1227,C16,'CDE Coverage Report'!$I$28:$I$1227,">0") -> 0 | W16: =IF($D16=0,"N/A",V16/$D16) -> 0 | X16: =IF($D16=0,"Review",IF(W16>=$G$3,"Pass","Fail")) -> Fail | Y16: =(0.5-W16)*D16 -> 1.5 | Z16: =_xlfn.TEXTJOIN(", ",TRUE,IF(H16="Fail",$F$7,""),IF(K16="Fail",$J$7,""),IF(M16="Fail",$L$7,""),IF(P16="Fail",$N$7,""),IF(T16="Fail",$R$7,""),IF(X16="Fail",$V$7,"")) -> Accuracy
A17: Sprint 1 | B17: Application_Fee_Reference | C17: DED_Data_Table_041 | D17: =COUNTIFS('In-scope Attributes'!H:H,$A17,'In-scope Attributes'!D:D,$C17,'In-scope Attributes'!G:G,"Y") -> 2 | E17: =COUNTIFS('Golden Rulebook-CDErule level'!$A$4:$A$3698,$A17,'Golden Rulebook-CDErule level'!$R$4:$R$3698,$C17,'Golden Rulebook-CDErule level'!$I$4:$I$3698,"<>") -> 11 | F17: =COUNTIFS('CDE Coverage Report'!$E$28:$E$1227,C17,'CDE Coverage Report'!$G$28:$G$1227,">0") -> 2 | G17: =IF($D17=0,"N/A",F17/$D17) -> 1 | H17: =IF($D17=0,"Review",IF(G17>=$B$3,"Pass","Fail")) -> Pass | I17: =$D17-F17 -> 0 | J17: =COUNTIFS('CDE Coverage Report'!$M$28:$M$1227,C17,'CDE Coverage Report'!$O$28:$O$1227,">0") -> 1 | K17: =IF(J17>=$C$3,"Pass","Fail") -> Pass | L17: =COUNTIFS('CDE Coverage Report'!$M$28:$M$1227,C17,'CDE Coverage Report'!$P$28:$P$1227,">0") -> 1 | M17: =IF(L17>=$D$3,"Pass","Fail") -> Pass | N17: =COUNTIFS('CDE Coverage Report'!$E$28:$E$1227,C17,'CDE Coverage Report'!$J$28:$J$1227,">0") -> 2 | O17: =IF($D17=0,"N/A",N17/$D17) -> 1 | P17: =IF($D17=0,"Review",IF(O17>=$E$3,"Pass","Fail")) -> Pass | Q17: =$D17-N17 -> 0 | R17: =COUNTIFS('CDE Coverage Report'!$E$28:$E$1227,C17,'CDE Coverage Report'!$H$28:$H$1227,">0") -> 2 | S17: =IF($D17=0,"N/A",R17/$D17) -> 1 | T17: =IF($D17=0,"Review",IF(S17>=$F$3,"Pass","Fail")) -> Pass | U17: =(0.5-S17)*D17 -> -1 | V17: =COUNTIFS('CDE Coverage Report'!$E$28:$E$1227,C17,'CDE Coverage Report'!$I$28:$I$1227,">0") -> 0 | W17: =IF($D17=0,"N/A",V17/$D17) -> 0 | X17: =IF($D17=0,"Review",IF(W17>=$G$3,"Pass","Fail")) -> Fail | Y17: =(0.5-W17)*D17 -> 1 | Z17: =_xlfn.TEXTJOIN(", ",TRUE,IF(H17="Fail",$F$7,""),IF(K17="Fail",$J$7,""),IF(M17="Fail",$L$7,""),IF(P17="Fail",$N$7,""),IF(T17="Fail",$R$7,""),IF(X17="Fail",$V$7,"")) -> Accuracy
A18: Sprint 1 | B18: Application_Invoice | C18: DED_Data_Table_021 | D18: =COUNTIFS('In-scope Attributes'!H:H,$A18,'In-scope Attributes'!D:D,$C18,'In-scope Attributes'!G:G,"Y") -> 3 | E18: =COUNTIFS('Golden Rulebook-CDErule level'!$A$4:$A$3698,$A18,'Golden Rulebook-CDErule level'!$R$4:$R$3698,$C18,'Golden Rulebook-CDErule level'!$I$4:$I$3698,"<>") -> 11 | F18: =COUNTIFS('CDE Coverage Report'!$E$28:$E$1227,C18,'CDE Coverage Report'!$G$28:$G$1227,">0") -> 3 | G18: =IF($D18=0,"N/A",F18/$D18) -> 1 | H18: =IF($D18=0,"Review",IF(G18>=$B$3,"Pass","Fail")) -> Pass | I18: =$D18-F18 -> 0 | J18: =COUNTIFS('CDE Coverage Report'!$M$28:$M$1227,C18,'CDE Coverage Report'!$O$28:$O$1227,">0") -> 1 | K18: =IF(J18>=$C$3,"Pass","Fail") -> Pass | L18: =COUNTIFS('CDE Coverage Report'!$M$28:$M$1227,C18,'CDE Coverage Report'!$P$28:$P$1227,">0") -> 1 | M18: =IF(L18>=$D$3,"Pass","Fail") -> Pass | N18: =COUNTIFS('CDE Coverage Report'!$E$28:$E$1227,C18,'CDE Coverage Report'!$J$28:$J$1227,">0") -> 3 | O18: =IF($D18=0,"N/A",N18/$D18) -> 1 | P18: =IF($D18=0,"Review",IF(O18>=$E$3,"Pass","Fail")) -> Pass | Q18: =$D18-N18 -> 0 | R18: =COUNTIFS('CDE Coverage Report'!$E$28:$E$1227,C18,'CDE Coverage Report'!$H$28:$H$1227,">0") -> 3 | S18: =IF($D18=0,"N/A",R18/$D18) -> 1 | T18: =IF($D18=0,"Review",IF(S18>=$F$3,"Pass","Fail")) -> Pass | U18: =(0.5-S18)*D18 -> -1.5 | V18: =COUNTIFS('CDE Coverage Report'!$E$28:$E$1227,C18,'CDE Coverage Report'!$I$28:$I$1227,">0") -> 0 | W18: =IF($D18=0,"N/A",V18/$D18) -> 0 | X18: =IF($D18=0,"Review",IF(W18>=$G$3,"Pass","Fail")) -> Fail | Y18: =(0.5-W18)*D18 -> 1.5 | Z18: =_xlfn.TEXTJOIN(", ",TRUE,IF(H18="Fail",$F$7,""),IF(K18="Fail",$J$7,""),IF(M18="Fail",$L$7,""),IF(P18="Fail",$N$7,""),IF(T18="Fail",$R$7,""),IF(X18="Fail",$V$7,"")) -> Accuracy
