Workbook
Name \0: #REF!
Name \66: '[8](2)'!#REF!
Name \A: #REF!
Name \B: #REF!
Name \C: #REF!
Name \E: #REF!
Name \F: #REF!
Name \G: #REF!
Name \J: #REF!
Name \K: #REF!
Name \L: #REF!
Name \M: '[9]EXH4A '!#REF!
Name \N: '[9]EXH4A '!#REF!
Name \P: #REF!
Name \R: #REF!
Name \RL: #REF!
Name \S: #REF!
Name \T: '[9]EXH4A '!#REF!
Name \U: #REF!
Name \v: #REF!
Name \W: '[9]EXH4A '!#REF!
Name \X: #REF!
Name \Y: #REF!
Name _: #REF!
Name __: #REF!
Name ___: #REF!
Name ____: #REF!
Name _____: #REF!
Name _____gas87: #REF!
Name _____gas91: #REF!
Name _____gas93: #REF!
Name _____gas95: #REF!
Name ____gas87: #REF!
Name ____gas91: #REF!
Name ____gas93: #REF!
Name ____gas95: #REF!
Name ___gas87: #REF!
Name ___gas91: #REF!
Name ___gas93: #REF!
Name ___gas95: #REF!
Name __gas87: #REF!
Name __gas91: #REF!
Name __gas93: #REF!
Name __gas95: #REF!
Name _01_Oct_08: '[3]Time(SA)'!#REF!
Name _1: #REF!
Name _1_: #REF!
Name _10: #REF!
Name _10t__WT: #REF!
Name _11: #REF!
Name _12: #REF!
Name _12WSOL: #REF!
Name _13: #REF!
Name _14: #REF!
Name _14W__WS: #REF!
Name _15: #REF!
Name _16: #REF!
Name _17: #REF!
Name _18: #REF!
Name _19: #REF!

Sheet Mapping-Table
A1: Column | B1: Requirement | C1: Explanation / Description from Manual | D1: Input | E1: Purview Mapping | F1: Column Name | G1: Comments
A2: Data Asset ID (English) | B2: Mandatory | C2: A unique identifier for the data table within the ADGE, provided in English (for example, Employee_Records). | D2: SSOT | E2: Existing | F2: Data Asset ID English
A3: Data Asset ID (Arabic) | B3: Optional | C3: A unique identifier for the Data Table, provided in Arabic (in digits). | D3: N/A | E3: Existing | F3: Data Asset ID Arabic
A4: Bronze Table | B4: Not for Submission | C4: N/A | D4: SSOT | E4: Not for Purview | F4: N/A
A5: Data Asset Name (English) | B5: Mandatory | C5: The data table name in English. | D5: SSOT | E5: Existing | F5: Data Asset Name English
A6: Data Asset Name (Arabic) | B6: Mandatory | C6: The data table name in Arabic. | D6: Inventory / DED | E6: Existing | F6: Data Asset Name Arabic
A7: Data Asset Description (English) | B7: Mandatory | C7: A brief description of the Data Table's contents and purpose, in English (for example, "This contains all records of government employees for the year 2024"). | D7: Inventory / DED | E7: Existing | F7: Data Asset Description English
A8: Data Asset Description (Arabic) | B8: Mandatory | C8: A brief description of the Data Table's contents and purpose, in Arabic. | D8: Inventory / DED | E8: Existing | F8: Data Asset Description Arabic
A9: Data Owner | B9: Mandatory | C9: Email address of the individual or group accountable for the data asset (for example, firstname.lastname@dge.ae). | D9: SSOT / DED Email | E9: Existing | F9: Owners
A10: Data Steward | B10: Mandatory | C10: Email address of the individual or group responsible for managing and overseeing the data, if designated. | D10: SSOT / DED Email | E10: Existing | F10: Experts
A11: Source System | B11: Mandatory | C11: The business-friendly name or type of the application system where the data originates (for example, "HR Management System"). | D11: Accela | E11: Existing | F11: Source System
A12: Domain ID | B12: Mandatory | C12: The unique identifier for the data domain or subject area aligned to the canonical list of Domains governed under the Government Information Model (GIM) and is defined in Section 7 | D12: SSOT / DED Email | E12: New | F12: Domain ID
A13: Domain Name | B13: Mandatory | C13: The business name of the data domain in English. | D13: SSOT / DED Email | E13: New | F13: Domain Name
... A32: Scope | B32: Mandatory | C32: Sprint 1/2/3 | D32: SSOT | E32: Not for Purview | F32: N/A

Sheet Mapping-Attribute
A1: Attribute Level | D1: Inputs From | E1: Comments
A2: Attribute ID (English) | B2: Mandatory | C2: A unique identifier for the attribute within the Data Table, provided in English (for example, Employee_ID).
A3: Attribute ID (Arabic) | B3: Optional | C3: A unique identifier for the attribute, provided in Arabic (if available).
A5: Attribute Description (English) | B5: Mandatory | C5: A detailed explanation or definition of the attribute in English (for example, "Unique identifier for each government employee").
A6: Attribute Description (Arabic) | B6: Optional | C6: A detailed explanation or definition of the attribute in Arabic, if available.
A7: Data Asset ID | B7: Mandatory | C7: The Data Asset ID of the Data Table to which the attribute belongs. The value must match an entry in Data Catalog - Data Table.
A8: Created Date | B8: Mandatory | C8: The date when the attribute was originally created (MM/DD/YYYY).
A9: Last Update Date | B9: Mandatory | C9: The most recent date when the attribute was updated (MM/DD/YYYY).
A10: Nullable (Y/N) | B10: Mandatory | C10: Indicates whether the attribute can accept null values (Y or N).
A11: Data Type | B11: Mandatory | C11: The type of data stored in the attribute (for example, integer, string, date).
A12: Data Length | B12: Mandatory | C12: The maximum length of data that can be stored in the attribute (for example, 10).
A13: Primary Key (Y/N) | B13: Mandatory | C13: Indicates whether the attribute serves as a primary key for the Data Table (Y or N).
A14: Foreign Key Data Asset | B14: Optional | C14: The Data Asset ID to which this attribute is linked as a foreign key, if applicable.
... A30: Data Steward | B30: Mandatory | C30: Email address of the individual or team responsible for managing and overseeing the attribute, if designated.

Sheet Purview-Catalogue
A1: TABLE LEVEL | F1: ATTRIBUTE LEVEL
A2: Document Column Name | B2: Purview Column Name | C2: New or Existing? | D2: New Column Name | F2: Document Column Name | G2: Purview Column Name | H2: New or Existing? | I2: New Column Name
A3: Data Asset ID (English) | B3: Data Asset ID English | C3: Existing | F3: Attribute ID (English) | G3: Attribute ID English | H3: Existing
A4: Data Asset ID (Arabic) | B4: Data Asset ID Arabic | C4: Existing | F4: Attribute ID (Arabic)
A5: Data Asset Name (English) | B5: Data Asset Name English | C5: Existing | F5: Attribute Description (English) | G5: Attribute Description English | H5: Existing
A6: Data Asset Name (Arabic) | B6: Data Asset Name Arabic | C6: Existing | F6: Attribute Description (Arabic) | G6: Attribute Description Arabic | H6: Existing
A7: Data Asset Description (English) | B7: Data Asset Description English | C7: Existing | F7: Data Asset ID | G7: Data Asset ID | H7: Existing
A8: Data Asset Description (Arabic) | B8: Data Asset Description Arabic | C8: Existing | F8: Created Date | G8: Created Date | H8: Existing
A9: Data Owner | B9: Owners | C9: Existing | F9: Last Update Date | H9: New | I9: Last Update Date
A10: Data Steward | B10: Experts | C10: Existing | F10: Nullable (Y/N) | G10: Is Nullable | H10: New | I10: Nullable Y_N
A11: Source System | B11: Source System | C11: Existing | F11: Data Type | G11: Data Type | H11: Existing
A12: Domain ID | C12: New | D12: Domain ID | F12: Data Length | G12: Data Length | H12: Existing
A13: Domain Name | C13: New | D13: Domain Name | F13: Primary Key (Y/N) | G13: Is Primary Key | H13: New | I13: Primary Key Y_N
A14: Created Date | B14: Created Date | C14: Existing | F14: Foreign Key Data Asset
A15: Last Update Date | C15: New | D15: Last Update Date | F15: Data Classification | G15: Data Classification | H15: Existing
A16: Retention Policy (Y/N) | B16: Retention Policy | C16: Existing | F16: Is Calculated? (Y/N) | G16: Is Calculated | H16: New | I16: Is Calculated Y_N
A17: Security Controls | B17: Security Controls | C17: Existing | F17: Calculation Logic | G17: Calculation Logic | H17: Existing
A18: Backup Interval | B18: Backup Interval | C18: Existing | F18: Business Validation Logic | G18: Business Validation Logic | H18: Existing
A19: Recovery | B19: Recovery | C19: Existing | F19: Data Completeness | H19: New | I19: Data Completeness
A20: Audit Logs | B20: Audit Logs | C20: Existing | F20: Data Completeness Target | H20: New | I20: Data Completeness Target
A21: Data Consumption (Direct) | B21: Data Consumption Direct | C21: Existing | F21: Missing Data Handling (Y/N) | G21: Missing Data Handling Y_N | H21: Existing
A22: Data Consumption (Indirect) | B22: Data Consumption Indirect | C22: Existing | F22: Missing Data Handling Process | G22: Missing Data Handling Process | H22: Existing
A23: Data Refresh Frequency | B23: Data Refresh Frequency | C23: Existing | F23: Duplicate Data Handling (Y/N) | G23: Duplicate Data Handling Y_N | H23: Existing
A24: Function / Business Unit | B24: Function or Business Unit | C24: Existing | F24: Duplicate Data Handling Process | G24: Duplicate Data Handling Process | H24: Existing
A25: ADGOV Data Classification | B25: ADGOV Data Classification | C25: Existing | F25: Duplicate (Y/N) | H25: New | I25: Duplicate Y_N
A26: Data Glossary | B26: Data Glossary/Glossary terms | C26: Existing | F26: Data Quality Issues | G26: Data Quality Issues | H26: Existing
A27: Publish to Platform (Y/N) | B27: Publish to Exchange Platform Y_N | C27: Existing | F27: Uniqueness Target | G27: Uniqueness Target | H27: Existing
A28: Integrate To WofG (Y/N) | C28: New | D28: Integrate To WofG (Y/N) | F28: Data Glossary | G28: Data Glossary | H28: Existing
A29: Data Source Name | B29: Data Source Name | C29: Existing | F29: Data Owner | G29: Data Owner | H29: Existing
A30: Data Asset Source Path | B30: Data Asset Source Path | C30: Existing | F30: Data Steward | G30: Data Steward | H30: Existing
A31: Data Asset Type | B31: Data Asset Type | C31: Existing

Sheet B1.2 Catalogue Table
A1: mandatory | B1: optional | C1: Not for Submission | D1: mandatory | E1: mandatory | F1: mandatory | G1: mandatory | H1: mandatory | I1: mandatory | J1: mandatory | K1: mandatory | L1: mandatory | M1: mandatory | N1: mandatory | O1: mandatory | P1: optional | Q1: optional | R1: optional | S1: optional | T1: optional | U1: optional | V1: mandatory | W1: mandatory | X1: mandatory | Y1: mandatory | Z1: Not for submission | AA1: mandatory | AB1: mandatory | AC1: mandatory | AD1: mandatory | AE1: mandatory | AF1: Not for purview
A2: Data Asset ID (English) | B2: Data Asset ID (Arabic) | C2: Bronze Table | D2: Data Asset Name (English) | E2: Data Asset Name (Arabic) | F2: Data Asset Description (English) | G2: Data Asset Description (Arabic) | H2: Data Owner | I2: Data Steward | J2: Source System | K2: Domain ID | L2: Domain Name | M2: Created Date | N2: Last Update Date | O2: Retention Policy (Y/N) | P2: Security Controls | Q2: Backup Interval | R2: Recovery | S2: Audit Logs | T2: Data Consumption (Direct) | U2: Data Consumption (Indirect) | V2: Data Refresh Frequency | W2: Function / Business Unit | X2: ADGOV Data Classification | Y2: Data Glossary | Z2: Formula for Data Glossary | AA2: Publish to Platform (Y/N) | AB2: Integrate To WofG (Y/N) | AC2: Data Source Name | AD2: Data Asset Source Path | AE2: Data Asset Type | AF2: Scope
A3: DED_Data_Table_001 | C3: ACCOUNTING_AUDIT_TRAIL | D3: Financial_Audit_Trail | E3: مسار_التدقيق_المالي | F3: Information of Accounting audit trail. | G3: معلومات سجل تدقيق المحاسبة. | H3: aiaalsheebani@ded.abudhabi.ae, rfmdaas@adra.gov.ae | I3: sraalbadi@ded.abudhabi.ae, rfmdaas@adra.gov.ae | J3: Accela | K3: DED_Domain_05 | L3: Financial Information | M3: 46175 | N3: 46273 | O3: Y | V3: Weekly | W3: =Table1[[#This Row],[Domain Name]] -> Financial Information | X3: Sensitive | Y3: Record Service Provider Code, Application ID, Financial Audit Sequence Number, Invoice ID, Receipt ID, Payment ID, Receipt Amount, Action, Application Fee ID, Payment Method Type Code, Payment Reference Number, Register Number, Record Status, Insert Timestamp, Update Timestamp, Row Hash, Business Key Hash, Processing Run ID, System Record Date | Z3: {=_xlfn.TEXTJOIN(", ",TRUE,_xlfn.UNIQUE(_xlfn._xlws.FILTER('B1.3 Catalogue Attribute'!AJ:AJ,'B1.3 Catalogue Attribute'!L:L=A3,"")))} -> Record Service Provider Code, Application ID, Financial Audit Sequence Number, Invoice ID, Receipt ID, Payment ID, Receipt Amount, Action, Application Fee ID, Payment Method Type Code, Payment Reference Number, Register Number, Record Status, Insert Timestamp, Update Timestamp, Row Hash, Business Key Hash, Processing Run ID, System Record Date | AA3: Y | AB3: Y | AC3: Oracle DB | AD3: =_xlfn.CONCAT("accelapr/",Table1[[#This Row],[Bronze Table]]) -> accelapr/ACCOUNTING_AUDIT_TRAIL | AE3: Table | AF3: Sprint 1
A4: DED_Data_Table_019 | C4: F4FEEITEM | D4: Application_Fee | E4: رسوم_الطلب | F4: Information of finance module application fee item. | G4: يحتوي على بيانات بنود الرسوم المرتبطة بالطلبات والمعاملات ضمن النظام المالي. | H4: aiaalsheebani@ded.abudhabi.ae, rfmdaas@adra.gov.ae | I4: sraalbadi@ded.abudhabi.ae, rfmdaas@adra.gov.ae | J4: Accela | K4: DED_Domain_05 | L4: Financial Information | M4: 46175 | N4: 46273 | O4: Y | V4: Weekly | W4: =Table1[[#This Row],[Domain Name]] -> Financial Information | X4: Sensitive | Y4: Record Service Provider Code, Application ID, Application Fee ID, Fee Formula Value, Unit Count, Unit Description, Fee Amount, Fee Apply Date, Fee Sub Group Type Code, Is Fee Calculated Indicator, Application Fee Item Status Description, Record Status, Application Fee Group Code, Pos Transaction Sequence Number, Fee Note Text, Parent Fee Item Sequence Number, Insert Timestamp, Update Timestamp, Processing Run ID, Row Hash, Business Key Hash, Fee Period, Fee Item Code, Version Code, System Record Date | Z4: {=_xlfn.TEXTJOIN(", ",TRUE,_xlfn.UNIQUE(_xlfn._xlws.FILTER('B1.3 Catalogue Attribute'!AJ:AJ,'B1.3 Catalogue Attribute'!L:L=A4,"")))} -> Record Service Provider Code, Application ID, Application Fee ID, Fee Formula Value, Unit Count, Unit Description, Fee Amount, Fee Apply Date, Fee Sub Group Type Code, Is Fee Calculated Indicator, Application Fee Item Status Description, Record Status, Application Fee Group Code, Pos Transaction Sequence Number, Fee Note Text, Parent Fee Item Sequence Number, Insert Timestamp, Update Timestamp, Processing Run ID, Row Hash, Business Key Hash, Fee Period, Fee Item Code, Version Code, System Record Date | AA4: Y | AB4: Y | AC4: Oracle DB | AD4: =_xlfn.CONCAT("accelapr/",Table1[[#This Row],[Bronze Table]]) -> accelapr/F4FEEITEM | AE4: Table | AF4: Sprint 1
A5: DED_Data_Table_020 | C5: F4FEEITEM_AUDIT_TRAIL | D5: Application_Fee_Audit | E5: تدقيق_رسوم_الطلب | F5: Information of finance module fee item audit trail which is before invoicing. | G5: يحتوي على السجل التدقيقي للتغييرات التي تطرأ على بنود الرسوم قبل إصدار الفواتير. | H5: aiaalsheebani@ded.abudhabi.ae, rfmdaas@adra.gov.ae | I5: sraalbadi@ded.abudhabi.ae, rfmdaas@adra.gov.ae | J5: Accela | K5: DED_Domain_05 | L5: Financial Information | M5: 46175 | N5: 46273 | O5: Y | V5: Weekly | W5: =Table1[[#This Row],[Domain Name]] -> Financial Information | X5: Sensitive | Y5: Record Service Provider Code, Fee Audit Trail Sequence Number, Application ID, Application Fee ID, Fee Period, Fee Item Code, Account Code, Account Code Level 3, Unit Count, Fee Amount, Fee Apply Date, Fee Sub Group Type Code, Application Fee Item Status Description, Record Status, Application Fee Group Code, Version Code, Fee Note Text, Insert Timestamp, Update Timestamp, Processing Run ID, Row Hash, Business Key Hash, System Record Date | Z5: {=_xlfn.TEXTJOIN(", ",TRUE,_xlfn.UNIQUE(_xlfn._xlws.FILTER('B1.3 Catalogue Attribute'!AJ:AJ,'B1.3 Catalogue Attribute'!L:L=A5,"")))} -> Record Service Provider Code, Fee Audit Trail Sequence Number, Application ID, Application Fee ID, Fee Period, Fee Item Code, Account Code, Account Code Level 3, Unit Count, Fee Amount, Fee Apply Date, Fee Sub Group Type Code, Application Fee Item Status Description, Record Status, Application Fee Group Code, Version Code, Fee Note Text, Insert Timestamp, Update Timestamp, Processing Run ID, Row Hash, Business Key Hash, System Record Date | AA5: Y | AB5: Y | AC5: Oracle DB | AD5: =_xlfn.CONCAT("accelapr/",Table1[[#This Row],[Bronze Table]]) -> accelapr/F4FEEITEM_AUDIT_TRAIL | AE5: Table | AF5: Sprint 1
A6: DED_Data_Table_021 | C6: F4INVOICE | D6: Application_Invoice | E6: فاتورة_الطلب | F6: Information of finance module invoice. It includes invoice number, amount, date, and so on. | G6: يحتوي على بيانات الفواتير، بما في ذلك رقم الفاتورة والمبلغ وتاريخ الإصدار وغيرها من التفاصيل المالية ذات الصلة. | H6: aiaalsheebani@ded.abudhabi.ae, rfmdaas@adra.gov.ae | I6: sraalbadi@ded.abudhabi.ae, rfmdaas@adra.gov.ae | J6: Accela | K6: DED_Domain_05 | L6: Financial Information | M6: 46175 | N6: 46273 | O6: Y | V6: Weekly | W6: =Table1[[#This Row],[Domain Name]] -> Financial Information | X6: Sensitive | Y6: Record Service Provider Code, Invoice ID, Invoice Status Description, Invoice Due Amount, Invoice Amount, Invoice Date, Invoice Batch Number, Printed Invoice Code, Record Status, Customized Invoice Code, Insert Timestamp, Update Timestamp, Processing Run ID, Business Key Hash, Row Hash | Z6: {=_xlfn.TEXTJOIN(", ",TRUE,_xlfn.UNIQUE(_xlfn._xlws.FILTER('B1.3 Catalogue Attribute'!AJ:AJ,'B1.3 Catalogue Attribute'!L:L=A6,"")))} -> Record Service Provider Code, Invoice ID, Invoice Status Description, Invoice Due Amount, Invoice Amount, Invoice Date, Invoice Batch Number, Printed Invoice Code, Record Status, Customized Invoice Code, Insert Timestamp, Update Timestamp, Processing Run ID, Business Key Hash, Row Hash | AA6: Y | AB6: Y | AC6: Oracle DB | AD6: =_xlfn.CONCAT("accelapr/",Table1[[#This Row],[Bronze Table]]) -> accelapr/F4INVOICE | AE6: Table | AF6: Sprint 1
A7: DED_Data_Table_022 | C7: F4PAYMENT | D7: Application_Payment | E7: دفعة_الطلب | F7: Information of finance module application payment. | G7: معلومات الفاتورة ضمن وحدة المالية، وتشمل رقم الفاتورة، المبلغ، التاريخ، وغيرها. | H7: aiaalsheebani@ded.abudhabi.ae, rfmdaas@adra.gov.ae | I7: sraalbadi@ded.abudhabi.ae, rfmdaas@adra.gov.ae | J7: Accela | K7: DED_Domain_05 | L7: Financial Information | M7: 46175 | N7: 46273 | O7: Y | V7: Weekly | W7: =Table1[[#This Row],[Domain Name]] -> Financial Information | X7: Sensitive | Y7: Record Service Provider Code, Application ID, Payment ID, Receipt ID, Payment Method Type Code, Payment Date & Time, Payment Amount, Not Allocated Amount, Payment Status Code, Record Status, Pos Transaction Sequence Number, Total Invoice Amount, Total Payment Amount, Batch Transaction Number, Payment Group Number, Insert Timestamp, Update Timestamp, Processing Run ID, Row Hash, Business Key Hash | Z7: {=_xlfn.TEXTJOIN(", ",TRUE,_xlfn.UNIQUE(_xlfn._xlws.FILTER('B1.3 Catalogue Attribute'!AJ:AJ,'B1.3 Catalogue Attribute'!L:L=A7,"")))} -> Record Service Provider Code, Application ID, Payment ID, Receipt ID, Payment Method Type Code, Payment Date & Time, Payment Amount, Not Allocated Amount, Payment Status Code, Record Status, Pos Transaction Sequence Number, Total Invoice Amount, Total Payment Amount, Batch Transaction Number, Payment Group Number, Insert Timestamp, Update Timestamp, Processing Run ID, Row Hash, Business Key Hash | AA7: Y | AB7: Y | AC7: Oracle DB | AD7: =_xlfn.CONCAT("accelapr/",Table1[[#This Row],[Bronze Table]]) -> accelapr/F4PAYMENT | AE7: Table | AF7: Sprint 1
A8: DED_Data_Table_023 | C8: F4RECEIPT | D8: Application_Receipt | E8: إيصال_الطلب | F8: Information of finance module receipt. | G8: يحتوي على بيانات الإيصالات المالية المرتبطة بالطلبات والمعاملات، | H8: aiaalsheebani@ded.abudhabi.ae, rfmdaas@adra.gov.ae | I8: sraalbadi@ded.abudhabi.ae, rfmdaas@adra.gov.ae | J8: Accela | K8: DED_Domain_05 | L8: Financial Information | M8: 46175 | N8: 46273 | O8: Y | V8: Weekly | W8: =Table1[[#This Row],[Domain Name]] -> Financial Information | X8: Sensitive | Y8: Record Service Provider Code, Receipt ID, Receipt Date, Register Number, Receipt Amount, Receipt Batch Number, Receipt Batch Date, Receipt Status Code, Receipt Customized Number, Total Invoice Amount, Total Payment Amount, Insert Timestamp, Update Timestamp, Processing Run ID, Row Hash, Business Key Hash | Z8: {=_xlfn.TEXTJOIN(", ",TRUE,_xlfn.UNIQUE(_xlfn._xlws.FILTER('B1.3 Catalogue Attribute'!AJ:AJ,'B1.3 Catalogue Attribute'!L:L=A8,"")))} -> Record Service Provider Code, Receipt ID, Receipt Date, Register Number, Receipt Amount, Receipt Batch Number, Receipt Batch Date, Receipt Status Code, Receipt Customized Number, Total Invoice Amount, Total Payment Amount, Insert Timestamp, Update Timestamp, Processing Run ID, Row Hash, Business Key Hash | AA8: Y | AB8: Y | AC8: Oracle DB | AD8: =_xlfn.CONCAT("accelapr/",Table1[[#This Row],[Bronze Table]]) -> accelapr/F4RECEIPT | AE8: Table | AF8: Sprint 1
A9: DED_Data_Table_041 | C9: RFEEITEM | D9: Application_Fee_Reference | E9: مرجع_رسوم_الطلب | F9: Information of reference fee item. | G9: معلومات بند الرسوم المرجعي. | H9: aiaalsheebani@ded.abudhabi.ae, rfmdaas@adra.gov.ae | I9: sraalbadi@ded.abudhabi.ae, rfmdaas@adra.gov.ae | J9: Accela | K9: DED_Domain_05 | L9: Financial Information | M9: 46175 | N9: 46273 | O9: Y | V9: Weekly | W9: =Table1[[#This Row],[Domain Name]] -> Financial Information | X9: Confidential | Y9: Record Service Provider Code, Application Fee Group Code, Fee Period, Fee Item Code, Account Code, Account Code Level 3, Record Status, Fee Note Text, Version Code, Resource ID, Insert Timestamp, Update Timestamp, Processing Run ID, Row Hash, Business Key Hash | Z9: {=_xlfn.TEXTJOIN(", ",TRUE,_xlfn.UNIQUE(_xlfn._xlws.FILTER('B1.3 Catalogue Attribute'!AJ:AJ,'B1.3 Catalogue Attribute'!L:L=A9,"")))} -> Record Service Provider Code, Application Fee Group Code, Fee Period, Fee Item Code, Account Code, Account Code Level 3, Record Status, Fee Note Text, Version Code, Resource ID, Insert Timestamp, Update Timestamp, Processing Run ID, Row Hash, Business Key Hash | AA9: Y | AB9: Y | AC9: Oracle DB | AD9: =_xlfn.CONCAT("accelapr/",Table1[[#This Row],[Bronze Table]]) -> accelapr/RFEEITEM | AE9: Table | AF9: Sprint 1
A10: DED_Data_Table_087 | C10: VIRTUAL_OUTSTANDING_FEES | D10: Outstanding_Fees | E10: الرسوم_المستحقة | F10: Stores outstanding fee items, approving-entity references, amounts, and payment status. | G10: يحتوي على تفاصيل الرسوم المستحقة، بما في ذلك مراجع جهات الاعتماد والمبالغ وحالة السداد. | H10: aiaalsheebani@ded.abudhabi.ae, rfmdaas@adra.gov.ae | I10: sraalbadi@ded.abudhabi.ae, rfmdaas@adra.gov.ae | J10: Accela | K10: DED_Domain_05 | L10: Financial Information | M10: 46175 | N10: 46273 | O10: Y | V10: Weekly | W10: =Table1[[#This Row],[Domain Name]] -> Financial Information | X10: Sensitive | Y10: Record Service Provider Code, Application ID, Record Group, Approving Entity Reference Date, Approving Entity Reference Number, Approving Entity, Outstanding Fees Comments, Fee Item Code, Fee Entry By, Fee Entry Date, Fee Entry Time, Fee Schedule, Fees, Status, Transaction Number, Record Type, System Record Date, Record Status, Row Index, Insert Timestamp, Update Timestamp, Business Key Hash, Row Hash, Processing Run ID | Z10: {=_xlfn.TEXTJOIN(", ",TRUE,_xlfn.UNIQUE(_xlfn._xlws.FILTER('B1.3 Catalogue Attribute'!AJ:AJ,'B1.3 Catalogue Attribute'!L:L=A10,"")))} -> Record Service Provider Code, Application ID, Record Group, Approving Entity Reference Date, Approving Entity Reference Number, Approving Entity, Outstanding Fees Comments, Fee Item Code, Fee Entry By, Fee Entry Date, Fee Entry Time, Fee Schedule, Fees, Status, Transaction Number, Record Type, System Record Date, Record Status, Row Index, Insert Timestamp, Update Timestamp, Business Key Hash, Row Hash, Processing Run ID | AA10: Y | AB10: N | AC10: Oracle DB | AD10: =_xlfn.CONCAT("accelapr/",Table1[[#This Row],[Bronze Table]]) -> accelapr/VIRTUAL_OUTSTANDING_FEES | AE10: Table | AF10: Sprint 2
A11: DED_Data_Table_109 | C11: VIRTUAL_VIOLATIONS_RECORD | D11: Violations_Record | E11: سجل_المخالفات | F11: Stores violation details, categories, amounts, inspectors, and update history. | G11: يخزن تفاصيل المخالفات، الفئات، المبالغ، المفتش، وتاريخ التحديثات. | H11: aiaalsheebani@ded.abudhabi.ae, rfmdaas@adra.gov.ae | I11: sraalbadi@ded.abudhabi.ae, rfmdaas@adra.gov.ae | J11: Accela | K11: DED_Domain_06 | L11: Fines & Violations | M11: 46175 | N11: 46273 | O11: Y | V11: Weekly | W11: =Table1[[#This Row],[Domain Name]] -> Fines & Violations | X11: Sensitive | Y11: Record Service Provider Code, Application ID, Record Group, Inspector, Update Date, Updated Record ID, Violation Amount, Violation Category, Violation Code, Violation Date, Violation Description, Violation Fee Sequence Number, Violation Level, Violation Status, Violation Type, System Record Date, Record Status, Row Index, Insert Timestamp, Update Timestamp, Business Key Hash, Row Hash, Processing Run ID | Z11: {=_xlfn.TEXTJOIN(", ",TRUE,_xlfn.UNIQUE(_xlfn._xlws.FILTER('B1.3 Catalogue Attribute'!AJ:AJ,'B1.3 Catalogue Attribute'!L:L=A11,"")))} -> Record Service Provider Code, Application ID, Record Group, Inspector, Update Date, Updated Record ID, Violation Amount, Violation Category, Violation Code, Violation Date, Violation Description, Violation Fee Sequence Number, Violation Level, Violation Status, Violation Type, System Record Date, Record Status, Row Index, Insert Timestamp, Update Timestamp, Business Key Hash, Row Hash, Processing Run ID | AA11: Y | AB11: N | AC11: Oracle DB | AD11: =_xlfn.CONCAT("accelapr/",Table1[[#This Row],[Bronze Table]]) -> accelapr/VIRTUAL_VIOLATIONS_RECORD | AE11: Table | AF11: Sprint 2
A12: DED_Data_Table_185 | C12: br_capital_type | D12: capital_type | E12: نوع_رأس_المال | F12: Provides capital information, including capital value, capital payable, recorded capital, total number of shares, bank name, and issuance place. | G12: يتضمن معلومات رأس المال، مثل قيمة رأس المال، والمبلغ الواجب دفعه، ورأس المال المسجل، وإجمالي عدد الأسهم، واسم البنك، ومكان الإصدار. | H12: aiaalsheebani@ded.abudhabi.ae, rfmdaas@adra.gov.ae | I12: sraalbadi@ded.abudhabi.ae, rfmdaas@adra.gov.ae | J12: Accela | K12: DED_Domain_05 | L12: Financial Information | M12: 46175 | N12: 46273 | O12: Y | V12: Weekly | W12: =Table1[[#This Row],[Domain Name]] -> Financial Information | X12: Confidential | Y12: Record Service Provider Code, Application ID, Application Service Type Code, Application Request Type Code, Capital Value, Capital to Be Paid, Capital, Total Number of Shares, Bank Name, Issuance Place, Issuance Date, Issuance Number, Capital Deposit Date, Record Status, Insert Timestamp, Update Timestamp, Processing Run ID, Business Key Hash, Row Hash | Z12: {=_xlfn.TEXTJOIN(", ",TRUE,_xlfn.UNIQUE(_xlfn._xlws.FILTER('B1.3 Catalogue Attribute'!AJ:AJ,'B1.3 Catalogue Attribute'!L:L=A12,"")))} -> Record Service Provider Code, Application ID, Application Service Type Code, Application Request Type Code, Capital Value, Capital to Be Paid, Capital, Total Number of Shares, Bank Name, Issuance Place, Issuance Date, Issuance Number, Capital Deposit Date, Record Status, Insert Timestamp, Update Timestamp, Processing Run ID, Business Key Hash, Row Hash | AA12: Y | AB12: Y | AC12: Oracle DB | AD12: accelapr/bchckbox | AE12: Table | AF12: Sprint 3
A13: DED_Data_Table_190 | C13: br_creditor_information | D13: creditor_information | E13: معلومات_الدائن | F13: Provides creditor information, including licence number, phone number, name, English and Arabic trade names, and email address. | G13: يتضمن معلومات الدائن، مثل رقم الرخصة، ورقم الهاتف، والاسم، والاسم التجاري بالإنجليزية والعربية، والبريد الإلكتروني. | H13: aiaalsheebani@ded.abudhabi.ae, rfmdaas@adra.gov.ae | I13: sraalbadi@ded.abudhabi.ae, rfmdaas@adra.gov.ae | J13: Accela | K13: DED_Domain_05 | L13: Financial Information | M13: 46175 | N13: 46273 | O13: Y | V13: Weekly | W13: =Table1[[#This Row],[Domain Name]] -> Financial Information | X13: Confidential | Y13: Record Service Provider Code, Application ID, Application Service Type Code, Application Request Type Code, Economic License Number, Phone Number, Name, Trade Name (English), Trade Name (Arabic), Email Address, Record Status, Insert Timestamp, Update Timestamp, Processing Run ID, Business Key Hash, Row Hash | Z13: {=_xlfn.TEXTJOIN(", ",TRUE,_xlfn.UNIQUE(_xlfn._xlws.FILTER('B1.3 Catalogue Attribute'!AJ:AJ,'B1.3 Catalogue Attribute'!L:L=A13,"")))} -> Record Service Provider Code, Application ID, Application Service Type Code, Application Request Type Code, Economic License Number, Phone Number, Name, Trade Name (English), Trade Name (Arabic), Email Address, Record Status, Insert Timestamp, Update Timestamp, Processing Run ID, Business Key Hash, Row Hash | AA13: Y | AB13: Y | AC13: Oracle DB | AD13: accelapr/bchckbox | AE13: Table | AF13: Sprint 3
A14: DED_Data_Table_025 | C14: G6ACTION | D14: Inspection_Suspension | E14: تعليق_التفتيش | F14: Information of Application inspections - Inspector, Department, and other attributes. | G14: معلومات تركيبة المستويات السبعة للغات المتعددة، وهي: الجهة، الإدارة، القسم، الوحدة، المجموعة، المجموعة الفرعية، والمكتب. | H14: amnalharthi@ded.abudhabi.ae, rfmdaas@adra.gov.ae | I14: ajmalhammadi@adra.gov.ae, fbakerbi@adra.gov.ae, rfmdaas@adra.gov.ae | J14: Accela | K14: DED_Domain_03 | L14: Inspection | M14: 46175 | N14: 46273 | O14: Y | V14: Weekly | W14: =Table1[[#This Row],[Domain Name]] -> Inspection | X14: Confidential | Y14: Record Service Provider Code, Application ID, Ispection Suspention ID, Inspection Bureau Code, Inspection Division Code, Inspection Branch Office Code, Inspection Section Code, Inspection Group Code, Inspection Scheduled Date, Inspection Type Description, Inspection Completion Date, Inspection Status, Inspection Submited Date, Record Status, Inspection Type Code, Insert Timestamp, Update Timestamp, Processing Run ID, Business Key Hash, Row Hash | Z14: {=_xlfn.TEXTJOIN(", ",TRUE,_xlfn.UNIQUE(_xlfn._xlws.FILTER('B1.3 Catalogue Attribute'!AJ:AJ,'B1.3 Catalogue Attribute'!L:L=A14,"")))} -> Record Service Provider Code, Application ID, Ispection Suspention ID, Inspection Bureau Code, Inspection Division Code, Inspection Branch Office Code, Inspection Section Code, Inspection Group Code, Inspection Scheduled Date, Inspection Type Description, Inspection Completion Date, Inspection Status, Inspection Submited Date, Record Status, Inspection Type Code, Insert Timestamp, Update Timestamp, Processing Run ID, Business Key Hash, Row Hash | AA14: Y | AB14: Y | AC14: Oracle DB | AD14: =_xlfn.CONCAT("accelapr/",Table1[[#This Row],[Bronze Table]]) -> accelapr/G6ACTION | AE14: Table | AF14: Sprint 1
A15: DED_Data_Table_043 | C15: RINSPTYP | D15: Inspection_Types | E15: أنواع_التفتيش | F15: Information of inspection types. | G15: معلومات بنود ورقة إرشادات التفتيش المرجعية للغات المتعددة. | H15: amnalharthi@ded.abudhabi.ae, rfmdaas@adra.gov.ae | I15: ajmalhammadi@adra.gov.ae, fbakerbi@adra.gov.ae, rfmdaas@adra.gov.ae | J15: Accela | K15: DED_Domain_03 | L15: Inspection | M15: 46175 | N15: 46273 | O15: Y | V15: Weekly | W15: =Table1[[#This Row],[Domain Name]] -> Inspection | X15: Sensitive | Y15: Record Service Provider Code, Inspection Type Code, Inspection Type Description, Record Status, Inspection Result Group, Resource ID, Insert Timestamp, Update Timestamp, Processing Run ID, Business Key Hash, Row Hash | Z15: {=_xlfn.TEXTJOIN(", ",TRUE,_xlfn.UNIQUE(_xlfn._xlws.FILTER('B1.3 Catalogue Attribute'!AJ:AJ,'B1.3 Catalogue Attribute'!L:L=A15,"")))} -> Record Service Provider Code, Inspection Type Code, Inspection Type Description, Record Status, Inspection Result Group, Resource ID, Insert Timestamp, Update Timestamp, Processing Run ID, Business Key Hash, Row Hash | AA15: Y | AB15: Y | AC15: Oracle DB | AD15: =_xlfn.CONCAT("accelapr/",Table1[[#This Row],[Bronze Table]]) -> accelapr/RINSPTYP | AE15: Table | AF15: Sprint 1
A16: DED_Data_Table_044 | C16: RINSPTYP_I18N | D16: Inspection_Types_Language | E16: لغات_أنواع_التفتيش | F16: Stores multilingual names and descriptions of inspection types used in the system. | G16: يحتوي على تفاصيل وأوصاف شروط المتطلبات المرتبطة بالطلبات بمختلف اللغات المعتمدة في النظام. | H16: amnalharthi@ded.abudhabi.ae, rfmdaas@adra.gov.ae | I16: ajmalhammadi@adra.gov.ae, fbakerbi@adra.gov.ae, rfmdaas@adra.gov.ae | J16: Accela | K16: DED_Domain_03 | L16: Inspection | M16: 46175 | N16: 46273 | O16: Y | V16: Weekly | W16: =Table1[[#This Row],[Domain Name]] -> Inspection | X16: Sensitive | Y16: Record Service Provider Code, Resource ID, Language ID, Inspection Type Description (Arabic), Inspection Group Type Code, Record Status, Inspection Group Type Name, Insert Timestamp, Update Timestamp, Processing Run ID, Business Key Hash, Row Hash | Z16: {=_xlfn.TEXTJOIN(", ",TRUE,_xlfn.UNIQUE(_xlfn._xlws.FILTER('B1.3 Catalogue Attribute'!AJ:AJ,'B1.3 Catalogue Attribute'!L:L=A16,"")))} -> Record Service Provider Code, Resource ID, Language ID, Inspection Type Description (Arabic), Inspection Group Type Code, Record Status, Inspection Group Type Name, Insert Timestamp, Update Timestamp, Processing Run ID, Business Key Hash, Row Hash | AA16: Y | AB16: Y | AC16: Oracle DB | AD16: =_xlfn.CONCAT("accelapr/",Table1[[#This Row],[Bronze Table]]) -> accelapr/RINSPTYP_I18N | AE16: Table | AF16: Sprint 1
A17: DED_Data_Table_045 | C17: RINSP_RESULT_GROUP | D17: Inspection_Relationship | E17: علاقة_التفتيش | F17: Information of the definition of the inspection group and the relationship between the inspection result and the inspection status. | G17: معلومات أنواع التفتيش للغات المتعددة. | H17: amnalharthi@ded.abudhabi.ae, rfmdaas@adra.gov.ae | I17: ajmalhammadi@adra.gov.ae, fbakerbi@adra.gov.ae, rfmdaas@adra.gov.ae | J17: Accela | K17: DED_Domain_03 | L17: Inspection | M17: 46175 | N17: 46273 | O17: Y | V17: Weekly | W17: =Table1[[#This Row],[Domain Name]] -> Inspection | X17: Sensitive | Y17: Record Service Provider Code, Inspection Result Group, Inspection Result, Record Status, Resource ID, Inspection Result Category, Insert Timestamp, Update Timestamp, Business Key Hash, Row Hash, Processing Run ID | Z17: {=_xlfn.TEXTJOIN(", ",TRUE,_xlfn.UNIQUE(_xlfn._xlws.FILTER('B1.3 Catalogue Attribute'!AJ:AJ,'B1.3 Catalogue Attribute'!L:L=A17,"")))} -> Record Service Provider Code, Inspection Result Group, Inspection Result, Record Status, Resource ID, Inspection Result Category, Insert Timestamp, Update Timestamp, Business Key Hash, Row Hash, Processing Run ID | AA17: Y | AB17: Y | AC17: Oracle DB | AD17: =_xlfn.CONCAT("accelapr/",Table1[[#This Row],[Bronze Table]]) -> accelapr/RINSP_RESULT_GROUP | AE17: Table | AF17: Sprint 2
A18: DED_Data_Table_046 | C18: RINSP_RESULT_GROUP_I18N | D18: Inspection_Relationship_Language | E18: لغات_علاقة_التفتيش | F18: Stores multilingual definitions of inspection groups and the relationships between inspection results and inspection statuses. | G18: يحتوي على أسماء وأوصاف شروط الطلبات بمختلف اللغات، بما في ذلك شروط القفل والتعليق والتنبيه. | H18: amnalharthi@ded.abudhabi.ae, rfmdaas@adra.gov.ae | I18: ajmalhammadi@adra.gov.ae, fbakerbi@adra.gov.ae, rfmdaas@adra.gov.ae | J18: Accela | K18: DED_Domain_03 | L18: Inspection | M18: 46175 | N18: 46273 | O18: Y | V18: Weekly | W18: =Table1[[#This Row],[Domain Name]] -> Inspection | X18: Sensitive | Y18: Record Service Provider Code, Resource ID, Language ID, Record Status, Inspection Result, Insert Timestamp, Update Timestamp, Business Key Hash, Row Hash, Processing Run ID | Z18: {=_xlfn.TEXTJOIN(", ",TRUE,_xlfn.UNIQUE(_xlfn._xlws.FILTER('B1.3 Catalogue Attribute'!AJ:AJ,'B1.3 Catalogue Attribute'!L:L=A18,"")))} -> Record Service Provider Code, Resource ID, Language ID, Record Status, Inspection Result, Insert Timestamp, Update Timestamp, Business Key Hash, Row Hash, Processing Run ID | AA18: Y | AB18: Y | AC18: Oracle DB | AD18: =_xlfn.CONCAT("accelapr/",Table1[[#This Row],[Bronze Table]]) -> accelapr/RINSP_RESULT_GROUP_I18N | AE18: Table | AF18: Sprint 2
A19: DED_Data_Table_074 | C19: VIRTUAL_INSPECTORCOORDINATES | D19: Inspector_Coordinates | E19: إحداثيات_المفتش | F19: Stores inspector geolocation coordinates captured during inspection activities. | G19: يحتوي على إحداثيات الموقع الجغرافي التي يتم تسجيلها أثناء تنفيذ أنشطة التفتيش. | H19: amnalharthi@ded.abudhabi.ae, rfmdaas@adra.gov.ae | I19: ajmalhammadi@adra.gov.ae, fbakerbi@adra.gov.ae, rfmdaas@adra.gov.ae | J19: Accela | K19: DED_Domain_03 | L19: Inspection | M19: 46175 | N19: 46273 | O19: Y | V19: Weekly | W19: =Table1[[#This Row],[Domain Name]] -> Inspection | X19: Confidential | Y19: Record Service Provider Code, Application ID, Record Group, Inspector Date & Time, Inspection ID, Inspector X Coordinate, Inspector Y Coordinate, Inspector Record Date, Record Status, Row Index, Insert Timestamp, Update Timestamp, Processing Run ID, Inspector Coordinates ID, Effective From Timestamp, Effective Till Timestamp, Active Flag, Business Key Hash, Row Hash | Z19: {=_xlfn.TEXTJOIN(", ",TRUE,_xlfn.UNIQUE(_xlfn._xlws.FILTER('B1.3 Catalogue Attribute'!AJ:AJ,'B1.3 Catalogue Attribute'!L:L=A19,"")))} -> Record Service Provider Code, Application ID, Record Group, Inspector Date & Time, Inspection ID, Inspector X Coordinate, Inspector Y Coordinate, Inspector Record Date, Record Status, Row Index, Insert Timestamp, Update Timestamp, Processing Run ID, Inspector Coordinates ID, Effective From Timestamp, Effective Till Timestamp, Active Flag, Business Key Hash, Row Hash | AA19: Y | AB19: N | AC19: Oracle DB | AD19: =_xlfn.CONCAT("accelapr/",Table1[[#This Row],[Bronze Table]]) -> accelapr/VIRTUAL_INSPECTORCOORDINATES | AE19: Table | AF19: Sprint 1
A20: DED_Data_Table_110 | C20: VIRTUAL_VIRTUAL_INSPECTION | D20: Virtual_Inspection | E20: التفتيش_الافتراضي | F20: Stores virtual-inspection identifiers, status, users, and update dates. | G20: يخزن معرفات الفحص الافتراضي، الحالة، المستخدمين، وتواريخ التحديث. | H20: amnalharthi@ded.abudhabi.ae, rfmdaas@adra.gov.ae | I20: ajmalhammadi@adra.gov.ae, fbakerbi@adra.gov.ae, rfmdaas@adra.gov.ae | J20: Accela | K20: DED_Domain_03 | L20: Inspection | M20: 46175 | N20: 46273 | O20: Y | V20: Weekly | W20: =Table1[[#This Row],[Domain Name]] -> Inspection | X20: Confidential | Y20: Record Service Provider Code, Application ID, Record Group, Inspection ID, Inspection Status, Update Date, User ID, System Record Date, Record Status, Row Index, Insert Timestamp, Update Timestamp, Business Key Hash, Row Hash, Processing Run ID | Z20: {=_xlfn.TEXTJOIN(", ",TRUE,_xlfn.UNIQUE(_xlfn._xlws.FILTER('B1.3 Catalogue Attribute'!AJ:AJ,'B1.3 Catalogue Attribute'!L:L=A20,"")))} -> Record Service Provider Code, Application ID, Record Group, Inspection ID, Inspection Status, Update Date, User ID, System Record Date, Record Status, Row Index, Insert Timestamp, Update Timestamp, Business Key Hash, Row Hash, Processing Run ID | AA20: Y | AB20: N | AC20: Oracle DB | AD20: =_xlfn.CONCAT("accelapr/",Table1[[#This Row],[Bronze Table]]) -> accelapr/VIRTUAL_VIRTUAL_INSPECTION | AE20: Table | AF20: Sprint 2
A21: DED_Data_Table_235 | C21: br_virtual_inspection_confirmation | D21: virtual_inspection_confirmation | E21: تأكيد_التفتيش_الافتراضي | F21: Provides virtual-inspection information. | G21: يتضمن معلومات التفتيش الافتراضي. | H21: amnalharthi@ded.abudhabi.ae, rfmdaas@adra.gov.ae | I21: ajmalhammadi@adra.gov.ae, fbakerbi@adra.gov.ae, rfmdaas@adra.gov.ae | J21: Accela | K21: DED_Domain_03 | L21: Inspection | M21: 46175 | N21: 46273 | O21: Y | V21: Weekly | W21: =Table1[[#This Row],[Domain Name]] -> Inspection | X21: Confidential | Y21: Record Service Provider Code, Application ID, Application Service Type Code, Application Request Type Code, Virtual, Record Status, Insert Timestamp, Update Timestamp, Processing Run ID, Business Key Hash, Row Hash | Z21: {=_xlfn.TEXTJOIN(", ",TRUE,_xlfn.UNIQUE(_xlfn._xlws.FILTER('B1.3 Catalogue Attribute'!AJ:AJ,'B1.3 Catalogue Attribute'!L:L=A21,"")))} -> Record Service Provider Code, Application ID, Application Service Type Code, Application Request Type Code, Virtual, Record Status, Insert Timestamp, Update Timestamp, Processing Run ID, Business Key Hash, Row Hash | AA21: Y | AB21: Y | AC21: Oracle DB | AD21: accelapr/bchckbox | AE21: Table | AF21: Sprint 3
A22: DED_Data_Table_002 | C22: APP_STATUS_GROUP | D22: Status_Lookup | E22: مرجع_الحالات | F22: Information of application status group name. | G22: معلومات سجل تدقيق المحاسبة. | H22: bmalkindi@adra.gov.ae, rfmdaas@adra.gov.ae | I22: asalmehiry@adra.gov.ae, rfmdaas@adra.gov.ae | J22: Accela | K22: DED_Domain_01 | L22: Economic Licenses | M22: 46175 | N22: 46273 | O22: Y | V22: Weekly | W22: =Table1[[#This Row],[Domain Name]] -> Economic Licenses | X22: Sensitive | Y22: Application Status Code, Application Status Description, Record Status, Record Service Provider Code, Resource ID, Insert Timestamp, Update Timestamp, Processing Run ID, Row Hash, Business Key Hash | Z22: {=_xlfn.TEXTJOIN(", ",TRUE,_xlfn.UNIQUE(_xlfn._xlws.FILTER('B1.3 Catalogue Attribute'!AJ:AJ,'B1.3 Catalogue Attribute'!L:L=A22,"")))} -> Application Status Code, Application Status Description, Record Status, Record Service Provider Code, Resource ID, Insert Timestamp, Update Timestamp, Processing Run ID, Row Hash, Business Key Hash | AA22: Y | AB22: Y | AC22: Oracle DB | AD22: =_xlfn.CONCAT("accelapr/",Table1[[#This Row],[Bronze Table]]) -> accelapr/APP_STATUS_GROUP | AE22: Table | AF22: Sprint 1
A23: DED_Data_Table_003 | C23: APP_STATUS_GROUP_I18N | D23: Status_Lookup_Language | E23: لغات_مرجع_الحالات | F23: Stores multilingual names and descriptions of application status groups used in the system. | G23: يحتوي على أسماء وأوصاف مجموعات حالات الطلبات بمختلف اللغات المعتمدة في النظام. | H23: bmalkindi@adra.gov.ae, rfmdaas@adra.gov.ae | I23: asalmehiry@adra.gov.ae, rfmdaas@adra.gov.ae | J23: Accela | K23: DED_Domain_01 | L23: Economic Licenses | M23: 46175 | N23: 46273 | O23: Y | V23: Weekly | W23: =Table1[[#This Row],[Domain Name]] -> Economic Licenses | X23: Sensitive | Y23: Record Service Provider Code, Resource ID, Language ID, Application Status Description (Arabic), Record Status, Insert Timestamp, Update Timestamp, Processing Run ID, Row Hash, Business Key Hash | Z23: {=_xlfn.TEXTJOIN(", ",TRUE,_xlfn.UNIQUE(_xlfn._xlws.FILTER('B1.3 Catalogue Attribute'!AJ:AJ,'B1.3 Catalogue Attribute'!L:L=A23,"")))} -> Record Service Provider Code, Resource ID, Language ID, Application Status Description (Arabic), Record Status, Insert Timestamp, Update Timestamp, Processing Run ID, Row Hash, Business Key Hash | AA23: Y | AB23: Y | AC23: Oracle DB | AD23: =_xlfn.CONCAT("accelapr/",Table1[[#This Row],[Bronze Table]]) -> accelapr/APP_STATUS_GROUP_I18N | AE23: Table | AF23: Sprint 1
A24: DED_Data_Table_004 | C24: B1PERMIT | D24: Application_Master | E24: الطلب_الرئيسي | F24: Stores the core information of applications and records, including application number, classification, type, category, creation date, and other key attributes. | G24: يحتوي على البيانات الأساسية للطلبات والسجلات، بما في ذلك رقم الطلب وتصنيفاته ونوعه وفئته وتاريخ إنشائه وغيرها من الخصائص الرئيسية. | H24: bmalkindi@adra.gov.ae, rfmdaas@adra.gov.ae | I24: asalmehiry@adra.gov.ae, rfmdaas@adra.gov.ae | J24: Accela | K24: DED_Domain_01 | L24: Economic Licenses | M24: 46175 | N24: 46273 | O24: Y | V24: Weekly | W24: =Table1[[#This Row],[Domain Name]] -> Economic Licenses | X24: Sensitive | Y24: Record Service Provider Code, Application ID, Application Service Group Code, Application Service Type Code, Application Request Type Code, Application Category Code, Application Submitted Date & Time, Record Status, Economic License Number, Insert Timestamp, Update Timestamp, Processing Run ID, Row Hash, Business Key Hash, Application Status Description, Application Status Code | Z24: {=_xlfn.TEXTJOIN(", ",TRUE,_xlfn.UNIQUE(_xlfn._xlws.FILTER('B1.3 Catalogue Attribute'!AJ:AJ,'B1.3 Catalogue Attribute'!L:L=A24,"")))} -> Record Service Provider Code, Application ID, Application Service Group Code, Application Service Type Code, Application Request Type Code, Application Category Code, Application Submitted Date & Time, Record Status, Economic License Number, Insert Timestamp, Update Timestamp, Processing Run ID, Row Hash, Business Key Hash, Application Status Description, Application Status Code | AA24: Y | AB24: Y | AC24: Oracle DB | AD24: =_xlfn.CONCAT("accelapr/",Table1[[#This Row],[Bronze Table]]) -> accelapr/B1PERMIT | AE24: Table | AF24: Sprint 1
A25: DED_Data_Table_005 | C25: B1_EXPIRATION | D25: License_Expiration | E25: انتهاء_صلاحية_الرخصة | F25: Information of tracing the license life cycle. It is used by license module. | G25: يحتوي على بيانات تتبع دورة حياة الترخيص ومراحله المختلفة، ويُستخدم لإدارة ومتابعة حالة الترخيص ضمن نظام التراخيص. | H25: bmalkindi@adra.gov.ae, rfmdaas@adra.gov.ae | I25: asalmehiry@adra.gov.ae, rfmdaas@adra.gov.ae | J25: Accela | K25: DED_Domain_01 | L25: Economic Licenses | M25: 46175 | N25: 46273 | O25: Y | V25: Weekly | W25: =Table1[[#This Row],[Domain Name]] -> Economic Licenses | X25: Sensitive | Y25: Record Service Provider Code, Application ID, License Expiration Rule Code, License Expiry Date, Record Status, Insert Timestamp, Update Timestamp, Processing Run ID, Row Hash, Business Key Hash | Z25: {=_xlfn.TEXTJOIN(", ",TRUE,_xlfn.UNIQUE(_xlfn._xlws.FILTER('B1.3 Catalogue Attribute'!AJ:AJ,'B1.3 Catalogue Attribute'!L:L=A25,"")))} -> Record Service Provider Code, Application ID, License Expiration Rule Code, License Expiry Date, Record Status, Insert Timestamp, Update Timestamp, Processing Run ID, Row Hash, Business Key Hash | AA25: Y | AB25: Y | AC25: Oracle DB | AD25: =_xlfn.CONCAT("accelapr/",Table1[[#This Row],[Bronze Table]]) -> accelapr/B1_EXPIRATION | AE25: Table | AF25: Sprint 1
A26: DED_Data_Table_006 | C26: B3ADDRES | D26: Application_Address | E26: عنوان_الطلب | F26: Stores address information associated with applications, including building or house number, street name, area, city, postal code, and other location details. | G26: يحتوي على بيانات العناوين المرتبطة بالطلبات، بما في ذلك رقم المبنى أو المنزل واسم الشارع والمنطقة والمدينة والرمز البريدي وغيرها من تفاصيل الموقع | H26: bmalkindi@adra.gov.ae, rfmdaas@adra.gov.ae | I26: asalmehiry@adra.gov.ae, rfmdaas@adra.gov.ae | J26: Accela | K26: DED_Domain_01 | L26: Economic Licenses | M26: 46175 | N26: 46273 | O26: Y | V26: Weekly | W26: =Table1[[#This Row],[Domain Name]] -> Economic Licenses | X26: Confidential | Y26: Record Service Provider Code, Application ID, Application Address ID, Longitude, Y Coordinate, Record Status, Master Application Address ID, Insert Timestamp, Update Timestamp, Processing Run ID, Row Hash, Business Key Hash | Z26: {=_xlfn.TEXTJOIN(", ",TRUE,_xlfn.UNIQUE(_xlfn._xlws.FILTER('B1.3 Catalogue Attribute'!AJ:AJ,'B1.3 Catalogue Attribute'!L:L=A26,"")))} -> Record Service Provider Code, Application ID, Application Address ID, Longitude, Y Coordinate, Record Status, Master Application Address ID, Insert Timestamp, Update Timestamp, Processing Run ID, Row Hash, Business Key Hash | AA26: Y | AB26: Y | AC26: Oracle DB | AD26: =_xlfn.CONCAT("accelapr/",Table1[[#This Row],[Bronze Table]]) -> accelapr/B3ADDRES | AE26: Table | AF26: Sprint 1
A27: DED_Data_Table_007 | C27: B3ADDRES_DISTRICT | D27: Application_District | E27: منطقة_الطلب | F27: Stores district information associated with application addresses, including the district or geographic area linked to the application location. | G27: يحتوي على بيانات المنطقة المرتبطة بعنوان الطلب، بما في ذلك اسم المنطقة أو النطاق الجغرافي المرتبط بموقع الطلب. | H27: bmalkindi@adra.gov.ae, rfmdaas@adra.gov.ae | I27: asalmehiry@adra.gov.ae, rfmdaas@adra.gov.ae | J27: Accela | K27: DED_Domain_01 | L27: Economic Licenses | M27: 46175 | N27: 46273 | O27: Y | V27: Weekly | W27: =Table1[[#This Row],[Domain Name]] -> Economic Licenses | X27: Confidential | Y27: Record Service Provider Code, Application ID, Address ID, District ID, Record Status, Insert Timestamp, Update Timestamp, Processing Run ID, Row Hash, Business Key Hash | Z27: {=_xlfn.TEXTJOIN(", ",TRUE,_xlfn.UNIQUE(_xlfn._xlws.FILTER('B1.3 Catalogue Attribute'!AJ:AJ,'B1.3 Catalogue Attribute'!L:L=A27,"")))} -> Record Service Provider Code, Application ID, Address ID, District ID, Record Status, Insert Timestamp, Update Timestamp, Processing Run ID, Row Hash, Business Key Hash | AA27: Y | AB27: Y | AC27: Oracle DB | AD27: =_xlfn.CONCAT("accelapr/",Table1[[#This Row],[Bronze Table]]) -> accelapr/B3ADDRES_DISTRICT | AE27: Table | AF27: Sprint 1
A28: DED_Data_Table_008 | C28: B3CONTACT | D28: Investor | E28: المستثمر | F28: Stores investor-related information associated with applications, licenses, or business activities. | G28: يحتوي على بيانات المستثمرين المرتبطة بالطلبات أو التراخيص أو الأنشطة التجارية. | H28: bmalkindi@adra.gov.ae, rfmdaas@adra.gov.ae | I28: asalmehiry@adra.gov.ae, rfmdaas@adra.gov.ae | J28: Accela | K28: DED_Domain_01 | L28: Economic Licenses | M28: 46175 | N28: 46273 | O28: Y | V28: Weekly | W28: =Table1[[#This Row],[Domain Name]] -> Economic Licenses | X28: Confidential | Y28: Record Service Provider Code, Application ID, Party ID, Investor Contact Type, Name, Investor Business Name (Arabic), Investor Address Line 1, Name (En), Country Dialing Code, Mobile Phone, Alternative 1 Mobile Number, Fax Number, E-mail, Record Status, Investor Contact ID, Insert Timestamp, Update Timestamp, Processing Run ID, Row Hash, Business Key Hash | Z28: {=_xlfn.TEXTJOIN(", ",TRUE,_xlfn.UNIQUE(_xlfn._xlws.FILTER('B1.3 Catalogue Attribute'!AJ:AJ,'B1.3 Catalogue Attribute'!L:L=A28,"")))} -> Record Service Provider Code, Application ID, Party ID, Investor Contact Type, Name, Investor Business Name (Arabic), Investor Address Line 1, Name (En), Country Dialing Code, Mobile Phone, Alternative 1 Mobile Number, Fax Number, E-mail, Record Status, Investor Contact ID, Insert Timestamp, Update Timestamp, Processing Run ID, Row Hash, Business Key Hash | AA28: Y | AB28: Y | AC28: Oracle DB | AD28: =_xlfn.CONCAT("accelapr/",Table1[[#This Row],[Bronze Table]]) -> accelapr/B3CONTACT | AE28: Table | AF28: Sprint 1
A29: DED_Data_Table_009 | C29: B3CONTRA | D29: Company_Name | E29: اسم_الشركة | F29: Stores company names associated with applications, licenses, or business records. | G29: يحتوي على أسماء الشركات المرتبطة بالطلبات أو التراخيص أو السجلات التجارية | H29: bmalkindi@adra.gov.ae, rfmdaas@adra.gov.ae | I29: asalmehiry@adra.gov.ae, rfmdaas@adra.gov.ae | J29: Accela | K29: DED_Domain_01 | L29: Economic Licenses | M29: 46175 | N29: 46273 | O29: Y | V29: Weekly | W29: =Table1[[#This Row],[Domain Name]] -> Economic Licenses | X29: Confidential | Y29: Record Service Provider Code, Application ID, Economic License Number, Service Description, Licence Type, Business Name, Licence Sequence Number, Business Name (Arabic), Insert Timestamp, Update Timestamp, Processing Run ID, Row Hash, Business Key Hash | Z29: {=_xlfn.TEXTJOIN(", ",TRUE,_xlfn.UNIQUE(_xlfn._xlws.FILTER('B1.3 Catalogue Attribute'!AJ:AJ,'B1.3 Catalogue Attribute'!L:L=A29,"")))} -> Record Service Provider Code, Application ID, Economic License Number, Service Description, Licence Type, Business Name, Licence Sequence Number, Business Name (Arabic), Insert Timestamp, Update Timestamp, Processing Run ID, Row Hash, Business Key Hash | AA29: Y | AB29: Y | AC29: Oracle DB | AD29: =_xlfn.CONCAT("accelapr/",Table1[[#This Row],[Bronze Table]]) -> accelapr/B3CONTRA | AE29: Table | AF29: Sprint 1
A30: DED_Data_Table_010 | C30: B6CONDIT | D30: Requirement_Condition | E30: شرط_المتطلب | F30: Information of application conditions. The conditions include Lock, Hold, Notice and so on. | G30: يحتوي على بيانات شروط الطلبات، بما في ذلك شروط القفل والتعليق والتنبيه وغيرها من الشروط المرتبطة بالطلبات. | H30: bmalkindi@adra.gov.ae, rfmdaas@adra.gov.ae | I30: asalmehiry@adra.gov.ae, rfmdaas@adra.gov.ae | J30: Accela | K30: DED_Domain_01 | L30: Economic Licenses | M30: 46175 | N30: 46273 | O30: Y | V30: Weekly | W30: =Table1[[#This Row],[Domain Name]] -> Economic Licenses | X30: Confidential | Y30: Record Service Provider Code, Application ID, Condition ID, Condition Description, Condition Issued Date, Condition Status Date, Condition Status Code, Condition Type Description, Record Status, Inspection ID, Source Condition ID, Insert Timestamp, Update Timestamp, Processing Run ID, Row Hash, Business Key Hash | Z30: {=_xlfn.TEXTJOIN(", ",TRUE,_xlfn.UNIQUE(_xlfn._xlws.FILTER('B1.3 Catalogue Attribute'!AJ:AJ,'B1.3 Catalogue Attribute'!L:L=A30,"")))} -> Record Service Provider Code, Application ID, Condition ID, Condition Description, Condition Issued Date, Condition Status Date, Condition Status Code, Condition Type Description, Record Status, Inspection ID, Source Condition ID, Insert Timestamp, Update Timestamp, Processing Run ID, Row Hash, Business Key Hash | AA30: Y | AB30: Y | AC30: Oracle DB | AD30: =_xlfn.CONCAT("accelapr/",Table1[[#This Row],[Bronze Table]]) -> accelapr/B6CONDIT | AE30: Table | AF30: Sprint 1
A31: DED_Data_Table_011 | C31: B6CONDIT_DETAIL | D31: Requirement_Condition_Dtl | E31: تفاصيل_شرط_المتطلب | F31: Stores detailed information about requirements, conditions, restrictions, and notices associated with applications and licenses. | G31: يحتوي على معلومات تفصيلية حول المتطلبات والشروط والقيود والتنبيهات المرتبطة بالطلبات والتراخيص. | H31: bmalkindi@adra.gov.ae, rfmdaas@adra.gov.ae | I31: asalmehiry@adra.gov.ae, rfmdaas@adra.gov.ae | J31: Accela | K31: DED_Domain_01 | L31: Economic Licenses | M31: 46175 | N31: 46273 | O31: Y | V31: Weekly | W31: =Table1[[#This Row],[Domain Name]] -> Economic Licenses | X31: Confidential | Y31: Record Service Provider Code, Condition ID, Application ID, Record Status, Resource ID, Insert Timestamp, Update Timestamp, Processing Run ID, Row Hash, Business Key Hash | Z31: {=_xlfn.TEXTJOIN(", ",TRUE,_xlfn.UNIQUE(_xlfn._xlws.FILTER('B1.3 Catalogue Attribute'!AJ:AJ,'B1.3 Catalogue Attribute'!L:L=A31,"")))} -> Record Service Provider Code, Condition ID, Application ID, Record Status, Resource ID, Insert Timestamp, Update Timestamp, Processing Run ID, Row Hash, Business Key Hash | AA31: Y | AB31: Y | AC31: Oracle DB | AD31: =_xlfn.CONCAT("accelapr/",Table1[[#This Row],[Bronze Table]]) -> accelapr/B6CONDIT_DETAIL | AE31: Table | AF31: Sprint 1
A32: DED_Data_Table_012 | C32: B6CONDIT_DETAIL_I18N | D32: Requirement_Condition_Dtl_Language | E32: لغات_تفاصيل_شرط_المتطلب | F32: Stores multilingual details and descriptions of requirement conditions associated with applications. | G32: يحتوي على تفاصيل وأوصاف شروط المتطلبات المرتبطة بالطلبات بمختلف اللغات المعتمدة في النظام. | H32: bmalkindi@adra.gov.ae, rfmdaas@adra.gov.ae | I32: asalmehiry@adra.gov.ae, rfmdaas@adra.gov.ae | J32: Accela | K32: DED_Domain_01 | L32: Economic Licenses | M32: 46175 | N32: 46273 | O32: Y | V32: Weekly | W32: =Table1[[#This Row],[Domain Name]] -> Economic Licenses | X32: Confidential | Y32: Record Service Provider Code, Resource ID, Language ID, Condition Resolution Action, Record Status, Insert Timestamp, Update Timestamp, Processing Run ID, Row Hash, Business Key Hash | Z32: {=_xlfn.TEXTJOIN(", ",TRUE,_xlfn.UNIQUE(_xlfn._xlws.FILTER('B1.3 Catalogue Attribute'!AJ:AJ,'B1.3 Catalogue Attribute'!L:L=A32,"")))} -> Record Service Provider Code, Resource ID, Language ID, Condition Resolution Action, Record Status, Insert Timestamp, Update Timestamp, Processing Run ID, Row Hash, Business Key Hash | AA32: Y | AB32: Y | AC32: Oracle DB | AD32: =_xlfn.CONCAT("accelapr/",Table1[[#This Row],[Bronze Table]]) -> accelapr/B6CONDIT_DETAIL_I18N | AE32: Table | AF32: Sprint 1
A33: DED_Data_Table_013 | C33: B6CONDIT_HISTORY | D33: Requirement_Condition_History | E33: سجل_شرط_المتطلب | F33: Information of record application condition history. | G33: يحتوي على السجل التاريخي للتغييرات التي تطرأ على شروط الطلبات والمتطلبات المرتبطة بها. | H33: bmalkindi@adra.gov.ae, rfmdaas@adra.gov.ae | I33: asalmehiry@adra.gov.ae, rfmdaas@adra.gov.ae | J33: Accela | K33: DED_Domain_01 | L33: Economic Licenses | M33: 46175 | N33: 46273 | O33: Y | V33: Weekly | W33: =Table1[[#This Row],[Domain Name]] -> Economic Licenses | X33: Confidential | Y33: Record Service Provider Code, Application Condition ID, Condition History ID, Condition History Description, Condition History Issued Date, Condition History Status Date, Condition History Status Code, Condition Type Description, Condition History Manipulation Date, Condition ID, Inspection ID, Language ID, Insert Timestamp, Update Timestamp, Processing Run ID, Row Hash, Business Key Hash | Z33: {=_xlfn.TEXTJOIN(", ",TRUE,_xlfn.UNIQUE(_xlfn._xlws.FILTER('B1.3 Catalogue Attribute'!AJ:AJ,'B1.3 Catalogue Attribute'!L:L=A33,"")))} -> Record Service Provider Code, Application Condition ID, Condition History ID, Condition History Description, Condition History Issued Date, Condition History Status Date, Condition History Status Code, Condition Type Description, Condition History Manipulation Date, Condition ID, Inspection ID, Language ID, Insert Timestamp, Update Timestamp, Processing Run ID, Row Hash, Business Key Hash | AA33: Y | AB33: Y | AC33: Oracle DB | AD33: =_xlfn.CONCAT("accelapr/",Table1[[#This Row],[Bronze Table]]) -> accelapr/B6CONDIT_HISTORY | AE33: Table | AF33: Sprint 1
... A79: DED_Data_Table_086 | C79: VIRTUAL_OFFICIAL_INFORMATION_L | D79: Official_Information_Logs | E79: سجلات_المعلومات_الرسمية | F79: Stores the change history of official information, including old and new values. | G79: يحتوي على معلومات العناية الواجبة ومؤشرات التحقق والفحص الخاصة بالأشخاص المعرضين سياسياً. | H79: bmalkindi@adra.gov.ae, rfmdaas@adra.gov.ae | I79: asalmehiry@adra.gov.ae, rfmdaas@adra.gov.ae | J79: Accela | K79: DED_Domain_01 | L79: Economic Licenses | M79: 46175 | N79: 46273 | O79: Y | V79: Weekly | W79: =Table1[[#This Row],[Domain Name]] -> Economic Licenses | X79: Sensitive | Y79: Record Service Provider Code, Application ID, Record Group, Change Type, Changed By, Change Date, New Value, Old Value, System Record Date, Record Status, Row Index, Insert Timestamp, Update Timestamp, Business Key Hash, Row Hash, Processing Run ID | Z79: {=_xlfn.TEXTJOIN(", ",TRUE,_xlfn.UNIQUE(_xlfn._xlws.FILTER('B1.3 Catalogue Attribute'!AJ:AJ,'B1.3 Catalogue Attribute'!L:L=A79,"")))} -> Record Service Provider Code, Application ID, Record Group, Change Type, Changed By, Change Date, New Value, Old Value, System Record Date, Record Status, Row Index, Insert Timestamp, Update Timestamp, Business Key Hash, Row Hash, Processing Run ID | AA79: Y | AB79: N | AC79: Oracle DB | AD79: =_xlfn.CONCAT("accelapr/",Table1[[#This Row],[Bronze Table]]) -> accelapr/VIRTUAL_OFFICIAL_INFORMATION_L | AE79: Table | AF79: Sprint 2
A80: DED_Data_Table_177 | C80: br_activity_detail | D80: activity_detail | E80: تفاصيل_النشاط | F80: Provides activity details for KIZAD 1, ICAD II, KIZAD 2, Abu Dhabi Municipality, Al Markaz, and the allowed-use classification. | G80: يحتوي على تفاصيل الأنشطة الاقتصادية المرتبطة بمناطق كيزاد 1، وآيكاد 2، وكيزاد 2، وبلدية أبوظبي، والمركز، بما في ذلك تصنيفات الاستخدامات المسموح بها. | H80: bmalkindi@adra.gov.ae, rfmdaas@adra.gov.ae | I80: asalmehiry@adra.gov.ae, rfmdaas@adra.gov.ae | J80: Accela | K80: DED_Domain_01 | L80: Economic Licenses | M80: 46175 | N80: 46273 | O80: Y | V80: Weekly | W80: =Table1[[#This Row],[Domain Name]] -> Economic Licenses | X80: Confidential | Y80: Tawazon, Economic Activity Code, Land Registration Incentive, ICAD III, ICAD V, ICAD I, AAIC II, Municipality Al Ain, Sub Group, Nebras, Industrial Activity, Farm Only, Arabic Description, Deleted Activity, Strategic Activities, License Notes, Activity Sector, Economic Activity Nature, Restricted for KF, Lease Optional, Suspended, Professional Activity, Inspection Needed, Suspended for License Issue, Creativity Activity, English Description, Not Allowed for GCC, Lease Optional for Normal License, General Notes, Suspended for License Renew, Ranch, Suspended for License Amendment, Farm Activity Applicability, Freelance Activity, Instant License, Activity Groups, Record Status, Record Service Provider Code, Application ID, Application Service Type Code, Application Request Type Code, KIZAD Zone 1, ICAD II, KIZAD Zone 2, Municipality - Abu Dhabi, Al Markaz, Allowed for Union Chamber (UC), Capital Minimum, Allowed for Public Relations (PR), Rowad Individual, Opportunity Activity, Rowad Company, Municipality - Al Dhafra, Name (Arabic), Ownership, Name (English), Foreign Investor, Product not required, ICAD IV, AAIC I, Rowad, DED Fee, Insert Timestamp, Update Timestamp, Processing Run ID, Business Key Hash, Row Hash | Z80: {=_xlfn.TEXTJOIN(", ",TRUE,_xlfn.UNIQUE(_xlfn._xlws.FILTER('B1.3 Catalogue Attribute'!AJ:AJ,'B1.3 Catalogue Attribute'!L:L=A80,"")))} -> Tawazon, Economic Activity Code, Land Registration Incentive, ICAD III, ICAD V, ICAD I, AAIC II, Municipality Al Ain, Sub Group, Nebras, Industrial Activity, Farm Only, Arabic Description, Deleted Activity, Strategic Activities, License Notes, Activity Sector, Economic Activity Nature, Restricted for KF, Lease Optional, Suspended, Professional Activity, Inspection Needed, Suspended for License Issue, Creativity Activity, English Description, Not Allowed for GCC, Lease Optional for Normal License, General Notes, Suspended for License Renew, Ranch, Suspended for License Amendment, Farm Activity Applicability, Freelance Activity, Instant License, Activity Groups, Record Status, Record Service Provider Code, Application ID, Application Service Type Code, Application Request Type Code, KIZAD Zone 1, ICAD II, KIZAD Zone 2, Municipality - Abu Dhabi, Al Markaz, Allowed for Union Chamber (UC), Capital Minimum, Allowed for Public Relations (PR), Rowad Individual, Opportunity Activity, Rowad Company, Municipality - Al Dhafra, Name (Arabic), Ownership, Name (English), Foreign Investor, Product not required, ICAD IV, AAIC I, Rowad, DED Fee, Insert Timestamp, Update Timestamp, Processing Run ID, Business Key Hash, Row Hash | AA80: Y | AB80: Y | AC80: Oracle DB | AD80: accelapr/bchckbox | AE80: Table | AF80: Sprint 3
A81: DED_Data_Table_178 | C81: br_address | D81: address | E81: العنوان | F81: Provides address information, including land area in square metres, sector, land location, tenant name, zone, and city. | G81: يوفر معلومات العنوان، بما في ذلك مساحة الأرض بالمتر المربع، والقطاع، وموقع الأرض، واسم المستأجر، والمنطقة، والمدينة. | H81: bmalkindi@adra.gov.ae, rfmdaas@adra.gov.ae | I81: asalmehiry@adra.gov.ae, rfmdaas@adra.gov.ae | J81: Accela | K81: DED_Domain_01 | L81: Economic Licenses | M81: 46175 | N81: 46273 | O81: Y | V81: Weekly | W81: =Table1[[#This Row],[Domain Name]] -> Economic Licenses | X81: Confidential | Y81: City, License Activity Sector, Zone, Record Service Provider Code, Application ID, Application Service Type Code, Application Request Type Code, Land Area (Square Metres), License Land Location, Tenant Name, License Specific Location, Record Status, Insert Timestamp, Update Timestamp, Processing Run ID, Business Key Hash, Row Hash | Z81: {=_xlfn.TEXTJOIN(", ",TRUE,_xlfn.UNIQUE(_xlfn._xlws.FILTER('B1.3 Catalogue Attribute'!AJ:AJ,'B1.3 Catalogue Attribute'!L:L=A81,"")))} -> City, License Activity Sector, Zone, Record Service Provider Code, Application ID, Application Service Type Code, Application Request Type Code, Land Area (Square Metres), License Land Location, Tenant Name, License Specific Location, Record Status, Insert Timestamp, Update Timestamp, Processing Run ID, Business Key Hash, Row Hash | AA81: Y | AB81: Y | AC81: Oracle DB | AD81: accelapr/bchckbox | AE81: Table | AF81: Sprint 3
A82: DED_Data_Table_179 | C82: br_amendment_type | D82: amendment_type | E82: نوع_التعديل | F82: Provides amendment types, including changes to the trade name, company address, partners, raw materials, activities, and services. | G82: يوفر معلومات أنواع التعديلات، بما في ذلك التغييرات على الاسم التجاري، وعنوان الشركة، والشركاء، والمواد الخام، والأنشطة، والخدمات. | H82: bmalkindi@adra.gov.ae, rfmdaas@adra.gov.ae | I82: asalmehiry@adra.gov.ae, rfmdaas@adra.gov.ae | J82: Accela | K82: DED_Domain_01 | L82: Economic Licenses | M82: 46175 | N82: 46273 | O82: Y | V82: Weekly | W82: =Table1[[#This Row],[Domain Name]] -> Economic Licenses | X82: Confidential | Y82: Record Service Provider Code, Application ID, Application Service Type Code, Application Request Type Code, License Name, Company Address Amendment, Partners Amendment, Raw Material Amendment, Activity Amendment, Service Amendment, Investment Amendment, Normal License to Foreign Investor Amendment, Legal Form Amendment, HSE Details Amendment, Partners Shares Amendment, Sales Amendment, Capital Amendment, Resolution Authentication Amendment, Product Amendment, Production Line Amendment, Lease Contract Attestation Amendment, Expected Labour Amendment, Under Construction to Production Amendment, Preliminary to Permanent Amendment, Quota Amendment, Industrial Leader to Under Construction Amendment, Spare Part Amendment, Machine Amendment, Inheritors Replacement Amendment, Land Amendment, Partners Nationality Amendment (c), Manager Amendment, Signboard Amendment, Amend Beneficiaries, Remarks, Country Amendment (Foreign Company), Heirs Amendment, Sponsor Amendment, Location Amendment (c), Activity Replacement, Location Amendment, Notarisation Contracts Amendment, Amend Board of Directors, VIP Customer Indicator, License Type Amendment, Partners Shares Amendment (c), Country Amendment (Foreign Company) (c), Capital Amendment (c), Activity Replacement (c), Authorized Signatories Amendment, Signboard Amendment (c), Trade Name Amendment, Manager Amendment (c), Technical Amendment, Heirs Amendment (c), License Type Amendment (c), Sponsor Amendment (c), Partners Amendment (c), Partners Nationality Amendment, Legal Form Amendment (c), Amend Companies, Notarisation Contracts Amendment (c), Record Status, Insert Timestamp, Update Timestamp, Processing Run ID, Business Key Hash, Row Hash | Z82: {=_xlfn.TEXTJOIN(", ",TRUE,_xlfn.UNIQUE(_xlfn._xlws.FILTER('B1.3 Catalogue Attribute'!AJ:AJ,'B1.3 Catalogue Attribute'!L:L=A82,"")))} -> Record Service Provider Code, Application ID, Application Service Type Code, Application Request Type Code, License Name, Company Address Amendment, Partners Amendment, Raw Material Amendment, Activity Amendment, Service Amendment, Investment Amendment, Normal License to Foreign Investor Amendment, Legal Form Amendment, HSE Details Amendment, Partners Shares Amendment, Sales Amendment, Capital Amendment, Resolution Authentication Amendment, Product Amendment, Production Line Amendment, Lease Contract Attestation Amendment, Expected Labour Amendment, Under Construction to Production Amendment, Preliminary to Permanent Amendment, Quota Amendment, Industrial Leader to Under Construction Amendment, Spare Part Amendment, Machine Amendment, Inheritors Replacement Amendment, Land Amendment, Partners Nationality Amendment (c), Manager Amendment, Signboard Amendment, Amend Beneficiaries, Remarks, Country Amendment (Foreign Company), Heirs Amendment, Sponsor Amendment, Location Amendment (c), Activity Replacement, Location Amendment, Notarisation Contracts Amendment, Amend Board of Directors, VIP Customer Indicator, License Type Amendment, Partners Shares Amendment (c), Country Amendment (Foreign Company) (c), Capital Amendment (c), Activity Replacement (c), Authorized Signatories Amendment, Signboard Amendment (c), Trade Name Amendment, Manager Amendment (c), Technical Amendment, Heirs Amendment (c), License Type Amendment (c), Sponsor Amendment (c), Partners Amendment (c), Partners Nationality Amendment, Legal Form Amendment (c), Amend Companies, Notarisation Contracts Amendment (c), Record Status, Insert Timestamp, Update Timestamp, Processing Run ID, Business Key Hash, Row Hash | AA82: Y | AB82: Y | AC82: Oracle DB | AD82: accelapr/bchckbox | AE82: Table | AF82: Sprint 3
A83: DED_Data_Table_180 | C83: br_ap_common | D83: ap_common | E83: التصريح_الإعلاني_العام | F83: Provides common advertisement-permit information, including customer and employee comments, advertisement details and location, Y coordinate, and advertisement end date. | G83: يوفر معلومات تصاريح الإعلانات العامة، بما في ذلك ملاحظات المتعاملين والموظفين، وتفاصيل الإعلان وموقعه، والإحداثيات الجغرافية، وتاريخ انتهاء عرض الإعلان. | H83: bmalkindi@adra.gov.ae, rfmdaas@adra.gov.ae | I83: asalmehiry@adra.gov.ae, rfmdaas@adra.gov.ae | J83: Accela | K83: DED_Domain_04 | L83: Permit | M83: 46175 | N83: 46273 | O83: Y | V83: Weekly | W83: =Table1[[#This Row],[Domain Name]] -> Permit | X83: Confidential | Y83: Record Service Provider Code, Application ID, Application Service Type Code, Application Request Type Code, Customer's Comments, Advertisement Details, Test, Y Coordinate, Advertisement End Date, Employee's Comments, Advertisement Location, Secondary Area, Primary Area, Advertisement Display Type, Advertisement Start Date, Permit Type, Category, City, Comments, Permit Number, Quantity, X Coordinate, Emirate ID, Food Activities, Non Food Activities, Record Status, Insert Timestamp, Update Timestamp, Processing Run ID, Business Key Hash, Row Hash | Z83: {=_xlfn.TEXTJOIN(", ",TRUE,_xlfn.UNIQUE(_xlfn._xlws.FILTER('B1.3 Catalogue Attribute'!AJ:AJ,'B1.3 Catalogue Attribute'!L:L=A83,"")))} -> Record Service Provider Code, Application ID, Application Service Type Code, Application Request Type Code, Customer's Comments, Advertisement Details, Test, Y Coordinate, Advertisement End Date, Employee's Comments, Advertisement Location, Secondary Area, Primary Area, Advertisement Display Type, Advertisement Start Date, Permit Type, Category, City, Comments, Permit Number, Quantity, X Coordinate, Emirate ID, Food Activities, Non Food Activities, Record Status, Insert Timestamp, Update Timestamp, Processing Run ID, Business Key Hash, Row Hash | AA83: Y | AB83: Y | AC83: Oracle DB | AD83: accelapr/bchckbox | AE83: Table | AF83: Sprint 3
A84: DED_Data_Table_182 | C84: br_branches_list | D84: branches_list | E84: قائمة_الفروع | F84: Provides a list of available branches. | G84: يحتوي على تفاصيل تصاريح المظلات، بما في ذلك النوع والكمية والملاحظات المرتبطة بها. | H84: bmalkindi@adra.gov.ae, rfmdaas@adra.gov.ae | I84: asalmehiry@adra.gov.ae, rfmdaas@adra.gov.ae | J84: Accela | K84: DED_Domain_01 | L84: Economic Licenses | M84: 46175 | N84: 46273 | O84: Y | V84: Weekly | W84: =Table1[[#This Row],[Domain Name]] -> Economic Licenses | X84: Confidential | Y84: Record Service Provider Code, Application ID, Application Service Type Code, Application Request Type Code, Available Branches, Record Status, Insert Timestamp, Update Timestamp, Processing Run ID, Business Key Hash, Row Hash | Z84: {=_xlfn.TEXTJOIN(", ",TRUE,_xlfn.UNIQUE(_xlfn._xlws.FILTER('B1.3 Catalogue Attribute'!AJ:AJ,'B1.3 Catalogue Attribute'!L:L=A84,"")))} -> Record Service Provider Code, Application ID, Application Service Type Code, Application Request Type Code, Available Branches, Record Status, Insert Timestamp, Update Timestamp, Processing Run ID, Business Key Hash, Row Hash | AA84: Y | AB84: Y | AC84: Oracle DB | AD84: accelapr/bchckbox | AE84: Table | AF84: Sprint 3
A85: DED_Data_Table_183 | C85: br_branches | D85: branches | E85: الفروع | F85: Provides branch information, including branches selected for cancellation. | G85: يتضمن معلومات الفروع، بما فيها الفروع المحددة للإلغاء. | H85: bmalkindi@adra.gov.ae, rfmdaas@adra.gov.ae | I85: asalmehiry@adra.gov.ae, rfmdaas@adra.gov.ae | J85: Accela | K85: DED_Domain_01 | L85: Economic Licenses | M85: 46175 | N85: 46273 | O85: Y | V85: Weekly | W85: =Table1[[#This Row],[Domain Name]] -> Economic Licenses | X85: Confidential | Y85: Record Service Provider Code, Application ID, Application Service Type Code, Application Request Type Code, Branches to Cancel, Record Status, Insert Timestamp, Update Timestamp, Processing Run ID, Business Key Hash, Row Hash | Z85: {=_xlfn.TEXTJOIN(", ",TRUE,_xlfn.UNIQUE(_xlfn._xlws.FILTER('B1.3 Catalogue Attribute'!AJ:AJ,'B1.3 Catalogue Attribute'!L:L=A85,"")))} -> Record Service Provider Code, Application ID, Application Service Type Code, Application Request Type Code, Branches to Cancel, Record Status, Insert Timestamp, Update Timestamp, Processing Run ID, Business Key Hash, Row Hash | AA85: Y | AB85: Y | AC85: Oracle DB | AD85: accelapr/bchckbox | AE85: Table | AF85: Sprint 3
A86: DED_Data_Table_184 | C86: br_cancellation_information | D86: cancellation_information | E86: معلومات_الإلغاء | F86: Provides cancellation information, including whether the request was submitted online, mobile number, mortgage certificate number, and email address. | G86: يتضمن معلومات الإلغاء، مثل ما إذا تم تقديم الطلب إلكترونيا، ورقم الهاتف المحمول، ورقم شهادة الرهن، والبريد الإلكتروني. | H86: bmalkindi@adra.gov.ae, rfmdaas@adra.gov.ae | I86: asalmehiry@adra.gov.ae, rfmdaas@adra.gov.ae | J86: Accela | K86: DED_Domain_01 | L86: Economic Licenses | M86: 46175 | N86: 46273 | O86: Y | V86: Weekly | W86: =Table1[[#This Row],[Domain Name]] -> Economic Licenses | X86: Confidential | Y86: Record Service Provider Code, Application ID, Application Service Type Code, Application Request Type Code, From Online, Mobile Number, Mortgage Certificate Number, Email Address, Record Status, Insert Timestamp, Update Timestamp, Processing Run ID, Business Key Hash, Row Hash | Z86: {=_xlfn.TEXTJOIN(", ",TRUE,_xlfn.UNIQUE(_xlfn._xlws.FILTER('B1.3 Catalogue Attribute'!AJ:AJ,'B1.3 Catalogue Attribute'!L:L=A86,"")))} -> Record Service Provider Code, Application ID, Application Service Type Code, Application Request Type Code, From Online, Mobile Number, Mortgage Certificate Number, Email Address, Record Status, Insert Timestamp, Update Timestamp, Processing Run ID, Business Key Hash, Row Hash | AA86: Y | AB86: Y | AC86: Oracle DB | AD86: accelapr/bchckbox | AE86: Table | AF86: Sprint 3
A87: DED_Data_Table_186 | C87: br_commercial_feature | D87: commercial_feature | E87: السمة_التجارية | F87: Provides commercial-feature information, including the abbreviated business name and the date commercial activities began in Abu Dhabi. | G87: يتضمن معلومات الصفة التجارية، مثل الاسم المختصر وتاريخ بدء الأنشطة التجارية في أبوظبي. | H87: bmalkindi@adra.gov.ae, rfmdaas@adra.gov.ae | I87: asalmehiry@adra.gov.ae, rfmdaas@adra.gov.ae | J87: Accela | K87: DED_Domain_01 | L87: Economic Licenses | M87: 46175 | N87: 46273 | O87: Y | V87: Weekly | W87: =Table1[[#This Row],[Domain Name]] -> Economic Licenses | X87: Confidential | Y87: Record Service Provider Code, Application ID, Application Service Type Code, Application Request Type Code, Abbreviated Name, Start date of the commercial activities in Abu Dhabi, Record Status, Insert Timestamp, Update Timestamp, Processing Run ID, Business Key Hash, Row Hash | Z87: {=_xlfn.TEXTJOIN(", ",TRUE,_xlfn.UNIQUE(_xlfn._xlws.FILTER('B1.3 Catalogue Attribute'!AJ:AJ,'B1.3 Catalogue Attribute'!L:L=A87,"")))} -> Record Service Provider Code, Application ID, Application Service Type Code, Application Request Type Code, Abbreviated Name, Start date of the commercial activities in Abu Dhabi, Record Status, Insert Timestamp, Update Timestamp, Processing Run ID, Business Key Hash, Row Hash | AA87: Y | AB87: Y | AC87: Oracle DB | AD87: accelapr/bchckbox | AE87: Table | AF87: Sprint 3
A88: DED_Data_Table_187 | C88: br_communication_information | D88: communication_information | E88: معلومات_الاتصال | F88: Provides communication information, including the enterprise mobile number, email address, and authorised signatory mobile number. | G88: يتضمن معلومات الاتصال، مثل رقم هاتف المنشأة، والبريد الإلكتروني، ورقم هاتف المفوض بالتوقيع. | H88: bmalkindi@adra.gov.ae, rfmdaas@adra.gov.ae | I88: asalmehiry@adra.gov.ae, rfmdaas@adra.gov.ae | J88: Accela | K88: DED_Domain_01 | L88: Economic Licenses | M88: 46175 | N88: 46273 | O88: Y | V88: Weekly | W88: =Table1[[#This Row],[Domain Name]] -> Economic Licenses | X88: Confidential | Y88: Record Service Provider Code, Application ID, Application Service Type Code, Application Request Type Code, Enterprise Mobile Number, Email Address, Authorized Signatory Mobile Number, Record Status, Insert Timestamp, Update Timestamp, Processing Run ID, Business Key Hash, Row Hash | Z88: {=_xlfn.TEXTJOIN(", ",TRUE,_xlfn.UNIQUE(_xlfn._xlws.FILTER('B1.3 Catalogue Attribute'!AJ:AJ,'B1.3 Catalogue Attribute'!L:L=A88,"")))} -> Record Service Provider Code, Application ID, Application Service Type Code, Application Request Type Code, Enterprise Mobile Number, Email Address, Authorized Signatory Mobile Number, Record Status, Insert Timestamp, Update Timestamp, Processing Run ID, Business Key Hash, Row Hash | AA88: Y | AB88: Y | AC88: Oracle DB | AD88: accelapr/bchckbox | AE88: Table | AF88: Sprint 3
A89: DED_Data_Table_188 | C89: br_company_contact | D89: company_contact | E89: جهة_اتصال_الشركة | F89: Provides company contact information, including landline number, P.O. box, email address and verification status, city, and mobile verification status. | G89: يتضمن بيانات اتصال الشركة، مثل الهاتف الأرضي، وصندوق البريد، والبريد الإلكتروني وحالة التحقق منه، والمدينة، وحالة التحقق من الهاتف المحمول. | H89: bmalkindi@adra.gov.ae, rfmdaas@adra.gov.ae | I89: asalmehiry@adra.gov.ae, rfmdaas@adra.gov.ae | J89: Accela | K89: DED_Domain_01 | L89: Economic Licenses | M89: 46175 | N89: 46273 | O89: Y | V89: Weekly | W89: =Table1[[#This Row],[Domain Name]] -> Economic Licenses | X89: Confidential | Y89: Record Service Provider Code, Application ID, Application Service Type Code, Application Request Type Code, Company Phone Number, Company PO Box, Email Verified, Company Email Address, Company City, Mobile Verified, Company Fax Number, Company Contact Name, Record Status, Insert Timestamp, Update Timestamp, Processing Run ID, Business Key Hash, Row Hash | Z89: {=_xlfn.TEXTJOIN(", ",TRUE,_xlfn.UNIQUE(_xlfn._xlws.FILTER('B1.3 Catalogue Attribute'!AJ:AJ,'B1.3 Catalogue Attribute'!L:L=A89,"")))} -> Record Service Provider Code, Application ID, Application Service Type Code, Application Request Type Code, Company Phone Number, Company PO Box, Email Verified, Company Email Address, Company City, Mobile Verified, Company Fax Number, Company Contact Name, Record Status, Insert Timestamp, Update Timestamp, Processing Run ID, Business Key Hash, Row Hash | AA89: Y | AB89: Y | AC89: Oracle DB | AD89: accelapr/bchckbox | AE89: Table | AF89: Sprint 3
A90: DED_Data_Table_189 | C90: br_company_service | D90: company_service | E90: خدمة_الشركة | F90: Provides company utility-consumption details for electricity, water, gas, and fuel, including private, public, and total values with their measurement units. | G90: يتضمن تفاصيل استهلاك الشركة للكهرباء والمياه والغاز والوقود، بما في ذلك القيم الخاصة والعامة والإجمالية ووحدات القياس. | H90: bmalkindi@adra.gov.ae, rfmdaas@adra.gov.ae | I90: asalmehiry@adra.gov.ae, rfmdaas@adra.gov.ae | J90: Accela | K90: DED_Domain_01 | L90: Economic Licenses | M90: 46175 | N90: 46273 | O90: Y | V90: Weekly | W90: =Table1[[#This Row],[Domain Name]] -> Economic Licenses | X90: Confidential | Y90: Record Service Provider Code, Application ID, Application Service Type Code, Application Request Type Code, Total Electricity Load (kW), Private Water Consumption (gal/day), Total Gas Consumption (m3/day), Private Gas Consumption (m3/day), Public Electricity Load (kW), Private Electricity Load (kW), Public Gas Consumption (m3/day), Total Fuel Consumption (l/day), Private Fuel Consumption (l/day), Public Water Consumption (gal/day), Total Water Consumption (gal/day), Public Fuel Consumption (l/day), Record Status, Insert Timestamp, Update Timestamp, Processing Run ID, Business Key Hash, Row Hash | Z90: {=_xlfn.TEXTJOIN(", ",TRUE,_xlfn.UNIQUE(_xlfn._xlws.FILTER('B1.3 Catalogue Attribute'!AJ:AJ,'B1.3 Catalogue Attribute'!L:L=A90,"")))} -> Record Service Provider Code, Application ID, Application Service Type Code, Application Request Type Code, Total Electricity Load (kW), Private Water Consumption (gal/day), Total Gas Consumption (m3/day), Private Gas Consumption (m3/day), Public Electricity Load (kW), Private Electricity Load (kW), Public Gas Consumption (m3/day), Total Fuel Consumption (l/day), Private Fuel Consumption (l/day), Public Water Consumption (gal/day), Total Water Consumption (gal/day), Public Fuel Consumption (l/day), Record Status, Insert Timestamp, Update Timestamp, Processing Run ID, Business Key Hash, Row Hash | AA90: Y | AB90: Y | AC90: Oracle DB | AD90: accelapr/bchckbox | AE90: Table | AF90: Sprint 3
A91: DED_Data_Table_191 | C91: br_general | D91: general | E91: معلومات_عامة | F91: Provides general application information, including document pages, Abu Dhabi Chamber Unified ID (ADC ), updated real-beneficiary status, establishment-card issuance, unified registration number, and revocation status. | G91: يتضمن معلومات عامة عن الطلب، مثل صفحات المستند، ومعرف الرقم الموحد لغرفة أبوظبي ، وحالة تحديث المستفيد الحقيقي، وإصدار بطاقة المنشأة، ورقم التسجيل الموحد، وحالة الإلغاء. | H91: bmalkindi@adra.gov.ae, rfmdaas@adra.gov.ae | I91: asalmehiry@adra.gov.ae, rfmdaas@adra.gov.ae | J91: Accela | K91: DED_Domain_01 | L91: Economic Licenses | M91: 46175 | N91: 46273 | O91: Y | V91: Weekly | W91: =Table1[[#This Row],[Domain Name]] -> Economic Licenses | X91: Confidential | Y91: Revoked, DocPages, Remarks, SPAC, Record Service Provider Code, Application ID, Application Service Type Code, Application Request Type Code, ADC Unified ID, Has an Updated Real Beneficiary, Est Card Issue, Unified Registration Number, Revoked Start Date, Revoked End Date, Non Default Authorized Signatory, License Duration, MOA Signature Link, Cancel Advertisement Consent, Lease Agreement End Date, Advertisement Period, Identification Number, Lease Agreement Start Date, Lease Optional and Unprovided, RBA Number, Lease Agreement Number, Labor Sector, First Real Beneficiary, Est Card Eligible, Labor Recruitment, Contains Tourism Activity, Duration of the Contract, Licence Original Issue Date, Sponsor Amount, Unit Is Office Indicator, Create Civil Works, Local Fee Free, Country of Origin, Private Sector Full Time Disclaimer, Test, All Activity Lease Optional, ADNOC Undertaking Indicator, Security Reference Number, Duration of the Company in Years, GDRFA Auto Close CC, License Old Expiration Date, Lease Agreement Duration, NotarisationContracts, Main License RB Number, Unified License Number, Incompatible with Real Beneficiary, Requires Newspaper, Investment Start Date, Required RB Amendment, Economic Registry Number (ERN), Investment End Date, Manager Appointment Duration in Years, Create Foreign Investor, Number of Attempts, Aramex Delivery, License Membership Number, License Classification, Record Status, Insert Timestamp, Update Timestamp, Processing Run ID, Business Key Hash, Row Hash | Z91: {=_xlfn.TEXTJOIN(", ",TRUE,_xlfn.UNIQUE(_xlfn._xlws.FILTER('B1.3 Catalogue Attribute'!AJ:AJ,'B1.3 Catalogue Attribute'!L:L=A91,"")))} -> Revoked, DocPages, Remarks, SPAC, Record Service Provider Code, Application ID, Application Service Type Code, Application Request Type Code, ADC Unified ID, Has an Updated Real Beneficiary, Est Card Issue, Unified Registration Number, Revoked Start Date, Revoked End Date, Non Default Authorized Signatory, License Duration, MOA Signature Link, Cancel Advertisement Consent, Lease Agreement End Date, Advertisement Period, Identification Number, Lease Agreement Start Date, Lease Optional and Unprovided, RBA Number, Lease Agreement Number, Labor Sector, First Real Beneficiary, Est Card Eligible, Labor Recruitment, Contains Tourism Activity, Duration of the Contract, Licence Original Issue Date, Sponsor Amount, Unit Is Office Indicator, Create Civil Works, Local Fee Free, Country of Origin, Private Sector Full Time Disclaimer, Test, All Activity Lease Optional, ADNOC Undertaking Indicator, Security Reference Number, Duration of the Company in Years, GDRFA Auto Close CC, License Old Expiration Date, Lease Agreement Duration, NotarisationContracts, Main License RB Number, Unified License Number, Incompatible with Real Beneficiary, Requires Newspaper, Investment Start Date, Required RB Amendment, Economic Registry Number (ERN), Investment End Date, Manager Appointment Duration in Years, Create Foreign Investor, Number of Attempts, Aramex Delivery, License Membership Number, License Classification, Record Status, Insert Timestamp, Update Timestamp, Processing Run ID, Business Key Hash, Row Hash | AA91: Y | AB91: Y | AC91: Oracle DB | AD91: accelapr/bchckbox | AE91: Table | AF91: Sprint 3
... A119: DED_Data_Table_181 | C119: br_basic_information | D119: basic_information | E119: المعلومات_الأساسية | F119: Provides core business information, including duration, Memorandum of Association Number, service agent contract, identification number, Industrial Rowad status, and unified licence number. | G119: يوفر المعلومات الأساسية للمنشأة، بما في ذلك مدة الترخيص، ورقم عقد التأسيس، وعقد وكيل الخدمات، ورقم الهوية، وحالة برنامج رواد الصناعة، ورقم الرخصة الموحد. | H119: bmalkindi@adra.gov.ae, rfmdaas@adra.gov.ae, aiaalsheebani@ded.abudhabi.ae | I119: asalmehiry@adra.gov.ae, rfmdaas@adra.gov.ae, sraalbadi@ded.abudhabi.ae | J119: Accela | K119: DED_Domain_01, DED_Domain_06 | L119: Economic Licenses, Fines & Violations | M119: 46175 | N119: 46273 | O119: Y | V119: Weekly | W119: =Table1[[#This Row],[Domain Name]] -> Economic Licenses, Fines & Violations | X119: Sensitive | Y119: Record Service Provider Code, Application ID, Application Service Type Code, Application Request Type Code, License Duration, MOA Number, Service Agent Contract, Identification Number, Industrial Rowad, Unified License Number, Economic Registry Number (ERN), Local Fee Free, Lease Agreement End Date, Industry Type, License Effective Date, Lease Amount, In Type, EMS Number, Incompatible with Real Beneficiary, Issue Date, Lease Agreement Number, Branch Type, Final Version Indicator, Trade Name Number, Security Reference Number, FCR Number, Permanent, Main License Number, Duration of the Company in Years, Company Legal Form, Quick License Subtype, Lease Agreement Start Date, Total Number of Shares, Required RB Amendment, Quick License, Manager Appointment Duration in Years, RBA Number, ADC Unified ID, Legal Type Change Required, License Classification, Service Description, Has an Updated Real Beneficiary, Number of Years, Service Name, Attendee Name, Proposed Action, Inspection Report Number, Fine Type, Comment, Follow Up Date, Attendee EID, Summary of Findings, Economic License Number, Job Title, Fine Level, Record Status, Insert Timestamp, Update Timestamp, Processing Run ID, Business Key Hash, Row Hash | Z119: {=_xlfn.TEXTJOIN(", ",TRUE,_xlfn.UNIQUE(_xlfn._xlws.FILTER('B1.3 Catalogue Attribute'!AJ:AJ,'B1.3 Catalogue Attribute'!L:L=A119,"")))} -> Record Service Provider Code, Application ID, Application Service Type Code, Application Request Type Code, License Duration, MOA Number, Service Agent Contract, Identification Number, Industrial Rowad, Unified License Number, Economic Registry Number (ERN), Local Fee Free, Lease Agreement End Date, Industry Type, License Effective Date, Lease Amount, In Type, EMS Number, Incompatible with Real Beneficiary, Issue Date, Lease Agreement Number, Branch Type, Final Version Indicator, Trade Name Number, Security Reference Number, FCR Number, Permanent, Main License Number, Duration of the Company in Years, Company Legal Form, Quick License Subtype, Lease Agreement Start Date, Total Number of Shares, Required RB Amendment, Quick License, Manager Appointment Duration in Years, RBA Number, ADC Unified ID, Legal Type Change Required, License Classification, Service Description, Has an Updated Real Beneficiary, Number of Years, Service Name, Attendee Name, Proposed Action, Inspection Report Number, Fine Type, Comment, Follow Up Date, Attendee EID, Summary of Findings, Economic License Number, Job Title, Fine Level, Record Status, Insert Timestamp, Update Timestamp, Processing Run ID, Business Key Hash, Row Hash | AA119: Y | AB119: Y | AC119: Oracle DB | AD119: accelapr/bchckbox | AE119: Table | AF119: Sprint 3
A120: DED_Data_Table_059 | C120: VIRTUAL_ASSOCIATIONS_WITH_PEPS | D120: RB_PEP_Association | E120: ارتباط_المستفيد_الحقيقي_بالشخص_المعرض_سياسياً | F120: Stores relationships and associations between beneficiaries and politically exposed persons. | G120: يحتوي على بيانات العلاقات والارتباطات بين المستفيدين الحقيقيين والأشخاص المعرضين سياسياً. | H120: oeaalali@adra.gov.ae, rfmdaas@adra.gov.ae | I120: aamalseiari@adra.gov.ae, rfmdaas@adra.gov.ae | J120: Accela | K120: DED_Domain_02 | L120: Real Beneficiary (RB) | M120: 46175 | N120: 46273 | O120: Y | V120: Weekly | W120: =Table1[[#This Row],[Domain Name]] -> Real Beneficiary (RB) | X120: Sensitive | Y120: Record Service Provider Code, Application ID, Record Group, PEP Screening Indentifier, PEP Association Category, Full Name, Job Description, Source Meta Data Text, Official Title, Show Detail Indicator, PEP Information Source, System PEP Screening Indentifier, System Record Date, Record Status, Row Index, Insert Timestamp, Update Timestamp, Business Key Hash, Row Hash, Processing Run ID | Z120: {=_xlfn.TEXTJOIN(", ",TRUE,_xlfn.UNIQUE(_xlfn._xlws.FILTER('B1.3 Catalogue Attribute'!AJ:AJ,'B1.3 Catalogue Attribute'!L:L=A120,"")))} -> Record Service Provider Code, Application ID, Record Group, PEP Screening Indentifier, PEP Association Category, Full Name, Job Description, Source Meta Data Text, Official Title, Show Detail Indicator, PEP Information Source, System PEP Screening Indentifier, System Record Date, Record Status, Row Index, Insert Timestamp, Update Timestamp, Business Key Hash, Row Hash, Processing Run ID | AA120: Y | AB120: N | AC120: Oracle DB | AD120: =_xlfn.CONCAT("accelapr/",Table1[[#This Row],[Bronze Table]]) -> accelapr/VIRTUAL_ASSOCIATIONS_WITH_PEPS | AE120: Table | AF120: Sprint 2
A121: DED_Data_Table_061 | C121: VIRTUAL_BASIC_INFORMATION_PEPS | D121: RB_Basic_Information_PEP | E121: المعلومات_الأساسية_للشخص_المعرض_سياسياً_للمستفيد_الحقيقي | F121: Stores core due-diligence information and screening indicators for politically exposed persons. | G121: يحتوي على معلومات العناية الواجبة ومؤشرات التحقق والفحص الخاصة بالأشخاص المعرضين سياسياً. | H121: oeaalali@adra.gov.ae, rfmdaas@adra.gov.ae | I121: aamalseiari@adra.gov.ae, rfmdaas@adra.gov.ae | J121: Accela | K121: DED_Domain_02 | L121: Real Beneficiary (RB) | M121: 46175 | N121: 46273 | O121: Y | V121: Weekly | W121: =Table1[[#This Row],[Domain Name]] -> Real Beneficiary (RB) | X121: Sensitive | Y121: Record Service Provider Code, Application ID, Record Group, Adverse Media Screening Indicator, PEP Position Conflict Indicator, PEP Screening Indentifier, Closely Associated To PEP Indicator, Closely Related To PEP Indicator, Ability to Move Indicator, Has Number Business Interests Indicator, Has Number PEP Associations Indicator, Has Number Roles Of Authority Indicator, Has Number Source Of Fund Indicator, Jurisdiction Risk Details Text, Source Meta Data Text, Is PEP Indicator, PEP Screening Result Text, Sanctions Screening Result Text, PEP Additional Details Text, PEP Information Source, System PEP Screening Indentifier, PEP Screening Record Date, Record Status, Row Index, Insert Timestamp, Update Timestamp, Processing Run ID, Business Key Hash, Row Hash | Z121: {=_xlfn.TEXTJOIN(", ",TRUE,_xlfn.UNIQUE(_xlfn._xlws.FILTER('B1.3 Catalogue Attribute'!AJ:AJ,'B1.3 Catalogue Attribute'!L:L=A121,"")))} -> Record Service Provider Code, Application ID, Record Group, Adverse Media Screening Indicator, PEP Position Conflict Indicator, PEP Screening Indentifier, Closely Associated To PEP Indicator, Closely Related To PEP Indicator, Ability to Move Indicator, Has Number Business Interests Indicator, Has Number PEP Associations Indicator, Has Number Roles Of Authority Indicator, Has Number Source Of Fund Indicator, Jurisdiction Risk Details Text, Source Meta Data Text, Is PEP Indicator, PEP Screening Result Text, Sanctions Screening Result Text, PEP Additional Details Text, PEP Information Source, System PEP Screening Indentifier, PEP Screening Record Date, Record Status, Row Index, Insert Timestamp, Update Timestamp, Processing Run ID, Business Key Hash, Row Hash | AA121: Y | AB121: N | AC121: Oracle DB | AD121: =_xlfn.CONCAT("accelapr/",Table1[[#This Row],[Bronze Table]]) -> accelapr/VIRTUAL_BASIC_INFORMATION_PEPS | AE121: Table | AF121: Sprint 1
A122: DED_Data_Table_062 | C122: VIRTUAL_BENEFICIAL_OWNER | D122: RB_Beneficial_Owner | E122: المستفيد_الحقيقي | F122: Stores detailed beneficial-owner identity, address, ownership, control, and disclosure information. | G122: يحتوي على معلومات تفصيلية عن هوية المستفيد الحقيقي وعنوانه ونسب الملكية وحقوق السيطرة وبيانات الإفصاح. | H122: oeaalali@adra.gov.ae, rfmdaas@adra.gov.ae | I122: aamalseiari@adra.gov.ae, rfmdaas@adra.gov.ae | J122: Accela | K122: DED_Domain_02 | L122: Real Beneficiary (RB) | M122: 46175 | N122: 46273 | O122: Y | V122: Weekly | W122: =Table1[[#This Row],[Domain Name]] -> Real Beneficiary (RB) | X122: Sensitive | Y122: Record Service Provider Code, Application ID, Record Group, Address of Employer Entity, Alternative Nationality, Beneficial Owner Street Area, Beneficial Owner Disclosure Letter, Beneficial Owner Disclosure 002, Beneficiary Owner Email, Beneficiary Owner Emirates ID, Beneficiary Owner Home Country, Beneficiary Owner ID Issuance, Beneficiary Owner Mobile Number, Beneficiary Owner Number of Shares, Beneficiary Owner Passport Number, Beneficiary Owner Phone Number, Beneficiary Owner Representative, Beneficiary Owner Share Percentage, Beneficiary Owner Unified Number, Beneficiary Owner Value of Shares, Beneficiary Owner Voting Right, Beneficiary Parent ID, Beneficiary Reference ID, Beneficial Owner City, Country of Residence, Date became a Beneficial Owner, Date of Birth, Economic Development Beneficiary Owner ID, Beneficial Owner Emirate, Emirates ID Expiry Date, Error Message, Establishment Country, Beneficial Owner Free Zone, Gender, Home Country ID Expiry Date, Home Country ID Issuance Date, House Name, House Number, Investor Location, Is Beneficiary Nominee, Is Beneficiary Owner Resident of UAE, Is Beneficiary Owner Trustee, Is Beneficiary PEP, Is Employee, Is Power User, Economic License Number, Source Meta Data Text, Name (Arabic), Name (English), Name of Employer Entity, Nationality, Onwani Address, Countries of Operation (Arabic), Countries of Operation (English), Passport Expiry Date, Passport Issuance Country, Passport Issuance Date, Place of Birth, Investor PO Box, Profile Type, Residence Address, Settlor Full Name, Settlor ID, Share Percentage on Main Licence, Special Persona, TAMM System ID, Trustee Full Name, Trustee ID, VIP Politically Exposed Person (PEP), Verified with ICA, WC Unique Identifier, System Record Date, Record Status, Row Index, Party Document Expiration Date, Insert Timestamp, Update Timestamp, Business Key Hash, Row Hash, Processing Run ID | Z122: {=_xlfn.TEXTJOIN(", ",TRUE,_xlfn.UNIQUE(_xlfn._xlws.FILTER('B1.3 Catalogue Attribute'!AJ:AJ,'B1.3 Catalogue Attribute'!L:L=A122,"")))} -> Record Service Provider Code, Application ID, Record Group, Address of Employer Entity, Alternative Nationality, Beneficial Owner Street Area, Beneficial Owner Disclosure Letter, Beneficial Owner Disclosure 002, Beneficiary Owner Email, Beneficiary Owner Emirates ID, Beneficiary Owner Home Country, Beneficiary Owner ID Issuance, Beneficiary Owner Mobile Number, Beneficiary Owner Number of Shares, Beneficiary Owner Passport Number, Beneficiary Owner Phone Number, Beneficiary Owner Representative, Beneficiary Owner Share Percentage, Beneficiary Owner Unified Number, Beneficiary Owner Value of Shares, Beneficiary Owner Voting Right, Beneficiary Parent ID, Beneficiary Reference ID, Beneficial Owner City, Country of Residence, Date became a Beneficial Owner, Date of Birth, Economic Development Beneficiary Owner ID, Beneficial Owner Emirate, Emirates ID Expiry Date, Error Message, Establishment Country, Beneficial Owner Free Zone, Gender, Home Country ID Expiry Date, Home Country ID Issuance Date, House Name, House Number, Investor Location, Is Beneficiary Nominee, Is Beneficiary Owner Resident of UAE, Is Beneficiary Owner Trustee, Is Beneficiary PEP, Is Employee, Is Power User, Economic License Number, Source Meta Data Text, Name (Arabic), Name (English), Name of Employer Entity, Nationality, Onwani Address, Countries of Operation (Arabic), Countries of Operation (English), Passport Expiry Date, Passport Issuance Country, Passport Issuance Date, Place of Birth, Investor PO Box, Profile Type, Residence Address, Settlor Full Name, Settlor ID, Share Percentage on Main Licence, Special Persona, TAMM System ID, Trustee Full Name, Trustee ID, VIP Politically Exposed Person (PEP), Verified with ICA, WC Unique Identifier, System Record Date, Record Status, Row Index, Party Document Expiration Date, Insert Timestamp, Update Timestamp, Business Key Hash, Row Hash, Processing Run ID | AA122: Y | AB122: N | AC122: Oracle DB | AD122: =_xlfn.CONCAT("accelapr/",Table1[[#This Row],[Bronze Table]]) -> accelapr/VIRTUAL_BENEFICIAL_OWNER | AE122: Table | AF122: Sprint 2
A123: DED_Data_Table_063 | C123: VIRTUAL_BUSINESS_INTERESTS_OF_ | D123: RB_Business_Interests | E123: المصالح_التجارية_للمستفيد_الحقيقي | F123: Stores business interests, roles, and entity relationships associated with politically exposed persons. | G123: يحتوي على بيانات المصالح التجارية والأدوار والعلاقات مع الجهات المرتبطة بالأشخاص المعرضين سياسياً. | H123: oeaalali@adra.gov.ae, rfmdaas@adra.gov.ae | I123: aamalseiari@adra.gov.ae, rfmdaas@adra.gov.ae | J123: Accela | K123: DED_Domain_02 | L123: Real Beneficiary (RB) | M123: 46175 | N123: 46273 | O123: Y | V123: Weekly | W123: =Table1[[#This Row],[Domain Name]] -> Real Beneficiary (RB) | X123: Sensitive | Y123: Record Service Provider Code, Application ID, Record Group, PEP Screening Indentifier, Date of Join, Entity Name, Source Meta Data Text, Roles, Share Percentage, Show Detail Indicator, PEP Information Source, Status, System PEP Screening Indentifier, System Record Date, Record Status, Row Index, Insert Timestamp, Update Timestamp, Business Key Hash, Row Hash, Processing Run ID | Z123: {=_xlfn.TEXTJOIN(", ",TRUE,_xlfn.UNIQUE(_xlfn._xlws.FILTER('B1.3 Catalogue Attribute'!AJ:AJ,'B1.3 Catalogue Attribute'!L:L=A123,"")))} -> Record Service Provider Code, Application ID, Record Group, PEP Screening Indentifier, Date of Join, Entity Name, Source Meta Data Text, Roles, Share Percentage, Show Detail Indicator, PEP Information Source, Status, System PEP Screening Indentifier, System Record Date, Record Status, Row Index, Insert Timestamp, Update Timestamp, Business Key Hash, Row Hash, Processing Run ID | AA123: Y | AB123: N | AC123: Oracle DB | AD123: =_xlfn.CONCAT("accelapr/",Table1[[#This Row],[Bronze Table]]) -> accelapr/VIRTUAL_BUSINESS_INTERESTS_OF_ | AE123: Table | AF123: Sprint 2
A124: DED_Data_Table_068 | C124: VIRTUAL_DIRECTORS_MEMBERS | D124: RB_Directors | E124: مديرو_المستفيد_الحقيقي | F124: Stores identity, contact, and appointment details for directors and board members. | G124: يحتوي على بيانات الهوية ووسائل التواصل وتفاصيل التعيين الخاصة بأعضاء مجلس الإدارة والمديرين. | H124: oeaalali@adra.gov.ae, rfmdaas@adra.gov.ae | I124: aamalseiari@adra.gov.ae, rfmdaas@adra.gov.ae | J124: Accela | K124: DED_Domain_02 | L124: Real Beneficiary (RB) | M124: 46175 | N124: 46273 | O124: Y | V124: Weekly | W124: =Table1[[#This Row],[Domain Name]] -> Real Beneficiary (RB) | X124: Sensitive | Y124: Record Service Provider Code, Application ID, Record Group, Street Area, Board Member Home Country ID, Board Member ID Issuance Country, Board Member Passport Number, Board Member Unified Number, Directors City, Country of Residence, Emirates Identification Number, Directors Emirate, Error Message, House Name, House Number, Investor Location, Board Member Nominee Indicator, Is Board Member PEP, Is Board Member Resident of UAE, Source Meta Data Text, Name (Arabic), Name (English), Nationality, Onwani Address, Investor PO Box, System PEP Screening Indentifier, TAMM System ID, VIP Politically Exposed Person (PEP), Verified with ICA, WC Unique Identifier, System Record Date, Record Status, Row Index, Party Document Expiration Date, Insert Timestamp, Update Timestamp, Business Key Hash, Row Hash, Processing Run ID | Z124: {=_xlfn.TEXTJOIN(", ",TRUE,_xlfn.UNIQUE(_xlfn._xlws.FILTER('B1.3 Catalogue Attribute'!AJ:AJ,'B1.3 Catalogue Attribute'!L:L=A124,"")))} -> Record Service Provider Code, Application ID, Record Group, Street Area, Board Member Home Country ID, Board Member ID Issuance Country, Board Member Passport Number, Board Member Unified Number, Directors City, Country of Residence, Emirates Identification Number, Directors Emirate, Error Message, House Name, House Number, Investor Location, Board Member Nominee Indicator, Is Board Member PEP, Is Board Member Resident of UAE, Source Meta Data Text, Name (Arabic), Name (English), Nationality, Onwani Address, Investor PO Box, System PEP Screening Indentifier, TAMM System ID, VIP Politically Exposed Person (PEP), Verified with ICA, WC Unique Identifier, System Record Date, Record Status, Row Index, Party Document Expiration Date, Insert Timestamp, Update Timestamp, Business Key Hash, Row Hash, Processing Run ID | AA124: Y | AB124: N | AC124: Oracle DB | AD124: =_xlfn.CONCAT("accelapr/",Table1[[#This Row],[Bronze Table]]) -> accelapr/VIRTUAL_DIRECTORS_MEMBERS | AE124: Table | AF124: Sprint 2
A125: DED_Data_Table_080 | C125: VIRTUAL_MANAGER_INFOMATION | D125: Manager_Information | E125: معلومات_المدير | F125: Stores manager identity, contact, address, nationality, and residency information. | G125: يحتوي على بيانات هوية المدير ووسائل التواصل والعنوان والجنسية ومعلومات الإقامة. | H125: oeaalali@adra.gov.ae, rfmdaas@adra.gov.ae | I125: aamalseiari@adra.gov.ae, rfmdaas@adra.gov.ae | J125: Accela | K125: DED_Domain_02 | L125: Real Beneficiary (RB) | M125: 46175 | N125: 46273 | O125: Y | V125: Weekly | W125: =Table1[[#This Row],[Domain Name]] -> Real Beneficiary (RB) | X125: Sensitive | Y125: Record Service Provider Code, Application ID, Record Group, Street Area, Manager City, Country of Residence, Manager Email Address, Manager Emirate, Error Message, House Name, House Number, Investor Location, Manager Nominee Indicator, Is Manager PEP, Manager UAE Residency Indicator, Manager EID, Manager Home Country ID, Manager Issuance Country, Manager Name Ar, Manager Name En, Manager Nationality, Manager Passport Number, Manager Unified Number, Source Meta Data Text, Onwani Address, Manager Phone Number, Investor PO Box, Residence Address, System PEP Screening Indentifier, TAMM System ID, VIP Politically Exposed Person (PEP), Verified with ICA, WC Unique Identifier, System Record Date, Record Status, Row Index, Insert Timestamp, Update Timestamp, Business Key Hash, Row Hash, Processing Run ID | Z125: {=_xlfn.TEXTJOIN(", ",TRUE,_xlfn.UNIQUE(_xlfn._xlws.FILTER('B1.3 Catalogue Attribute'!AJ:AJ,'B1.3 Catalogue Attribute'!L:L=A125,"")))} -> Record Service Provider Code, Application ID, Record Group, Street Area, Manager City, Country of Residence, Manager Email Address, Manager Emirate, Error Message, House Name, House Number, Investor Location, Manager Nominee Indicator, Is Manager PEP, Manager UAE Residency Indicator, Manager EID, Manager Home Country ID, Manager Issuance Country, Manager Name Ar, Manager Name En, Manager Nationality, Manager Passport Number, Manager Unified Number, Source Meta Data Text, Onwani Address, Manager Phone Number, Investor PO Box, Residence Address, System PEP Screening Indentifier, TAMM System ID, VIP Politically Exposed Person (PEP), Verified with ICA, WC Unique Identifier, System Record Date, Record Status, Row Index, Insert Timestamp, Update Timestamp, Business Key Hash, Row Hash, Processing Run ID | AA125: Y | AB125: N | AC125: Oracle DB | AD125: =_xlfn.CONCAT("accelapr/",Table1[[#This Row],[Bronze Table]]) -> accelapr/VIRTUAL_MANAGER_INFOMATION | AE125: Table | AF125: Sprint 2
A126: DED_Data_Table_088 | C126: VIRTUAL_POLITICALLY_EXPOSED_PE | D126: RB_PEP | E126: الشخص_المعرض_سياسياً_للمستفيد_الحقيقي | F126: Stores positions, entities, dates, and status information for politically exposed persons. | G126: يحتوي على بيانات المناصب والجهات والتواريخ والحالة الخاصة بالأشخاص المعرضين سياسياً. | H126: oeaalali@adra.gov.ae, rfmdaas@adra.gov.ae | I126: aamalseiari@adra.gov.ae, rfmdaas@adra.gov.ae | J126: Accela | K126: DED_Domain_02 | L126: Real Beneficiary (RB) | M126: 46175 | N126: 46273 | O126: Y | V126: Weekly | W126: =Table1[[#This Row],[Domain Name]] -> Real Beneficiary (RB) | X126: Confidential | Y126: Record Service Provider Code, Application ID, Record Group, PEP Screening Indentifier, End Date, Entity Name, Source Meta Data Text, Current PEP Role Indicator, Roles, Show Detail Indicator, PEP Information Source, Start Date, System PEP Screening Indentifier, System Record Date, Record Status, Row Index, Insert Timestamp, Update Timestamp, Business Key Hash, Row Hash, Processing Run ID | Z126: {=_xlfn.TEXTJOIN(", ",TRUE,_xlfn.UNIQUE(_xlfn._xlws.FILTER('B1.3 Catalogue Attribute'!AJ:AJ,'B1.3 Catalogue Attribute'!L:L=A126,"")))} -> Record Service Provider Code, Application ID, Record Group, PEP Screening Indentifier, End Date, Entity Name, Source Meta Data Text, Current PEP Role Indicator, Roles, Show Detail Indicator, PEP Information Source, Start Date, System PEP Screening Indentifier, System Record Date, Record Status, Row Index, Insert Timestamp, Update Timestamp, Business Key Hash, Row Hash, Processing Run ID | AA126: Y | AB126: N | AC126: Oracle DB | AD126: =_xlfn.CONCAT("accelapr/",Table1[[#This Row],[Bronze Table]]) -> accelapr/VIRTUAL_POLITICALLY_EXPOSED_PE | AE126: Table | AF126: Sprint 2
A127: DED_Data_Table_093 | C127: VIRTUAL_RBF_COMPANIES | D127: RB_Companies | E127: شركات_المستفيد_الحقيقي | F127: Stores company relationships captured in the real-beneficiary form. | G127: يحتوي على بيانات العلاقات بين الشركات المسجلة ضمن نموذج المستفيد الحقيقي. | H127: oeaalali@adra.gov.ae, rfmdaas@adra.gov.ae | I127: aamalseiari@adra.gov.ae, rfmdaas@adra.gov.ae | J127: Accela | K127: DED_Domain_02 | L127: Real Beneficiary (RB) | M127: 46175 | N127: 46273 | O127: Y | V127: Weekly | W127: =Table1[[#This Row],[Domain Name]] -> Real Beneficiary (RB) | X127: Sensitive | Y127: Record Service Provider Code, Application ID, Record Group, Contact ID, Establishment Country, Economic License Number, Name (Arabic), Name (English), Countries of Operation (Arabic), Countries of Operation (English), System PEP Screening Indentifier, System Record Date, Record Status, Row Index, Insert Timestamp, Update Timestamp, Business Key Hash, Row Hash, Processing Run ID | Z127: {=_xlfn.TEXTJOIN(", ",TRUE,_xlfn.UNIQUE(_xlfn._xlws.FILTER('B1.3 Catalogue Attribute'!AJ:AJ,'B1.3 Catalogue Attribute'!L:L=A127,"")))} -> Record Service Provider Code, Application ID, Record Group, Contact ID, Establishment Country, Economic License Number, Name (Arabic), Name (English), Countries of Operation (Arabic), Countries of Operation (English), System PEP Screening Indentifier, System Record Date, Record Status, Row Index, Insert Timestamp, Update Timestamp, Business Key Hash, Row Hash, Processing Run ID | AA127: Y | AB127: N | AC127: Oracle DB | AD127: =_xlfn.CONCAT("accelapr/",Table1[[#This Row],[Bronze Table]]) -> accelapr/VIRTUAL_RBF_COMPANIES | AE127: Table | AF127: Sprint 2
A128: DED_Data_Table_096 | C128: VIRTUAL_RISK_SCORE_LOGS | D128: RB_Risk_Score_Logs | E128: سجلات_درجات_مخاطر_المستفيد_الحقيقي | F128: Stores historical changes to transaction or license risk classifications. | G128: يحتوي على السجل التاريخي للتغييرات التي تطرأ على تصنيفات المخاطر الخاصة بالمعاملات أو التراخيص. | H128: oeaalali@adra.gov.ae, rfmdaas@adra.gov.ae | I128: aamalseiari@adra.gov.ae, rfmdaas@adra.gov.ae | J128: Accela | K128: DED_Domain_02 | L128: Real Beneficiary (RB) | M128: 46175 | N128: 46273 | O128: Y | V128: Weekly | W128: =Table1[[#This Row],[Domain Name]] -> Real Beneficiary (RB) | X128: Sensitive | Y128: Record Service Provider Code, Application ID, Record Group, Licence Classification (New Value), Licence Classification (Previous Value), Transaction Number, Update Date, System Record Date, Record Status, Row Index, Insert Timestamp, Update Timestamp, Business Key Hash, Row Hash, Processing Run ID | Z128: {=_xlfn.TEXTJOIN(", ",TRUE,_xlfn.UNIQUE(_xlfn._xlws.FILTER('B1.3 Catalogue Attribute'!AJ:AJ,'B1.3 Catalogue Attribute'!L:L=A128,"")))} -> Record Service Provider Code, Application ID, Record Group, Licence Classification (New Value), Licence Classification (Previous Value), Transaction Number, Update Date, System Record Date, Record Status, Row Index, Insert Timestamp, Update Timestamp, Business Key Hash, Row Hash, Processing Run ID | AA128: Y | AB128: N | AC128: Oracle DB | AD128: =_xlfn.CONCAT("accelapr/",Table1[[#This Row],[Bronze Table]]) -> accelapr/VIRTUAL_RISK_SCORE_LOGS | AE128: Table | AF128: Sprint 2
A129: DED_Data_Table_099 | C129: VIRTUAL_SOURCE_OF_FUNDS_PEPS | D129: RB_PEP_Source_Of_Funds | E129: مصدر_أموال_الشخص_المعرض_سياسياً_للمستفيد_الحقيقي | F129: Stores declared sources and amounts of funds associated with politically exposed persons. | G129: يحتوي على مصادر الأموال المصرح بها والمبالغ المرتبطة بالأشخاص المعرضين سياسياً. | H129: oeaalali@adra.gov.ae, rfmdaas@adra.gov.ae | I129: aamalseiari@adra.gov.ae, rfmdaas@adra.gov.ae | J129: Accela | K129: DED_Domain_02 | L129: Real Beneficiary (RB) | M129: 46175 | N129: 46273 | O129: Y | V129: Weekly | W129: =Table1[[#This Row],[Domain Name]] -> Real Beneficiary (RB) | X129: Sensitive | Y129: Record Service Provider Code, Application ID, Record Group, Amount, PEP Screening Indentifier, Source Meta Data Text, Show Detail Indicator, PEP Information Source, Specify Source of Fund, System PEP Screening Indentifier, Wealth Type, System Record Date, Record Status, Row Index, Insert Timestamp, Update Timestamp, Business Key Hash, Row Hash, Processing Run ID | Z129: {=_xlfn.TEXTJOIN(", ",TRUE,_xlfn.UNIQUE(_xlfn._xlws.FILTER('B1.3 Catalogue Attribute'!AJ:AJ,'B1.3 Catalogue Attribute'!L:L=A129,"")))} -> Record Service Provider Code, Application ID, Record Group, Amount, PEP Screening Indentifier, Source Meta Data Text, Show Detail Indicator, PEP Information Source, Specify Source of Fund, System PEP Screening Indentifier, Wealth Type, System Record Date, Record Status, Row Index, Insert Timestamp, Update Timestamp, Business Key Hash, Row Hash, Processing Run ID | AA129: Y | AB129: N | AC129: Oracle DB | AD129: =_xlfn.CONCAT("accelapr/",Table1[[#This Row],[Bronze Table]]) -> accelapr/VIRTUAL_SOURCE_OF_FUNDS_PEPS | AE129: Table | AF129: Sprint 2
A130: DED_Data_Table_100 | C130: VIRTUAL_SOURCE_OF_FUND_AND_WEA | D130: RB_Source_Of_Fund_Wealth | E130: مصدر_أموال_وثروة_المستفيد_الحقيقي | F130: Stores detailed declarations supporting the source of funds and source of wealth. | G130: يحتوي على الإفصاحات والتفاصيل الداعمة لمصادر الأموال ومصادر الثروة. | H130: oeaalali@adra.gov.ae, rfmdaas@adra.gov.ae | I130: aamalseiari@adra.gov.ae, rfmdaas@adra.gov.ae | J130: Accela | K130: DED_Domain_02 | L130: Real Beneficiary (RB) | M130: 46175 | N130: 46273 | O130: Y | V130: Weekly | W130: =Table1[[#This Row],[Domain Name]] -> Real Beneficiary (RB) | X130: Sensitive | Y130: Record Service Provider Code, Application ID, Record Group, Address of Sold Property, Amount in AED, Applicant Share, Broker Address, Broker Name, Company Address, Source of Fund wealth Company Name , Date of Sell, Date of Loan Approval, Date of Receiving Amount, Description of Stocks or Money, Donor Information, Donor Name, Duration of Holding Amount, Duration of Investment Holding, Duration of Property Holding, Employer Address, Employer Name, From Which Company, Loan Provider Address, Loan Provider Name, Source Meta Data Text, Method of Sale, Nature of Business, Nature of Employer Business, Nature of Income, Reason for Gift, Reason for Requesting Loan, Relationship with Donor, Source of Granted Funds, Specify Source of Fund, System PEP Screening Indentifier, TAMM System ID, Wealth Type, System Record Date, Record Status, Row Index, Insert Timestamp, Update Timestamp, Business Key Hash, Row Hash, Processing Run ID | Z130: {=_xlfn.TEXTJOIN(", ",TRUE,_xlfn.UNIQUE(_xlfn._xlws.FILTER('B1.3 Catalogue Attribute'!AJ:AJ,'B1.3 Catalogue Attribute'!L:L=A130,"")))} -> Record Service Provider Code, Application ID, Record Group, Address of Sold Property, Amount in AED, Applicant Share, Broker Address, Broker Name, Company Address, Source of Fund wealth Company Name , Date of Sell, Date of Loan Approval, Date of Receiving Amount, Description of Stocks or Money, Donor Information, Donor Name, Duration of Holding Amount, Duration of Investment Holding, Duration of Property Holding, Employer Address, Employer Name, From Which Company, Loan Provider Address, Loan Provider Name, Source Meta Data Text, Method of Sale, Nature of Business, Nature of Employer Business, Nature of Income, Reason for Gift, Reason for Requesting Loan, Relationship with Donor, Source of Granted Funds, Specify Source of Fund, System PEP Screening Indentifier, TAMM System ID, Wealth Type, System Record Date, Record Status, Row Index, Insert Timestamp, Update Timestamp, Business Key Hash, Row Hash, Processing Run ID | AA130: Y | AB130: N | AC130: Oracle DB | AD130: =_xlfn.CONCAT("accelapr/",Table1[[#This Row],[Bronze Table]]) -> accelapr/VIRTUAL_SOURCE_OF_FUND_AND_WEA | AE130: Table | AF130: Sprint 2
A131: DED_Data_Table_105 | C131: VIRTUAL_ULTIMATE_BENEFICIAL_OW | D131: RB_Ultimate_Owner | E131: المالك_النهائي_للمستفيد_الحقيقي | F131: Stores ultimate beneficial-owner identifiers, names, locations, shares, and user indicators. | G131: يحتوي على معرفات المستفيدين الحقيقيين النهائيين وأسمائهم ومواقعهم ونسب الملكية والمؤشرات المرتبطة بهم. | H131: oeaalali@adra.gov.ae, rfmdaas@adra.gov.ae | I131: aamalseiari@adra.gov.ae, rfmdaas@adra.gov.ae | J131: Accela | K131: DED_Domain_02 | L131: Real Beneficiary (RB) | M131: 46175 | N131: 46273 | O131: Y | V131: Weekly | W131: =Table1[[#This Row],[Domain Name]] -> Real Beneficiary (RB) | X131: Sensitive | Y131: Record Service Provider Code, Application ID, Record Group, Economic Development Beneficiary Owner ID, Ultimate Owner Identification Number, Investor Location, Is Power User, Name (Arabic), Name (English), Show Detail Indicator, Total Share Percentage on Main Licence, System Record Date, Record Status, Row Index, Insert Timestamp, Update Timestamp, Business Key Hash, Row Hash, Processing Run ID | Z131: {=_xlfn.TEXTJOIN(", ",TRUE,_xlfn.UNIQUE(_xlfn._xlws.FILTER('B1.3 Catalogue Attribute'!AJ:AJ,'B1.3 Catalogue Attribute'!L:L=A131,"")))} -> Record Service Provider Code, Application ID, Record Group, Economic Development Beneficiary Owner ID, Ultimate Owner Identification Number, Investor Location, Is Power User, Name (Arabic), Name (English), Show Detail Indicator, Total Share Percentage on Main Licence, System Record Date, Record Status, Row Index, Insert Timestamp, Update Timestamp, Business Key Hash, Row Hash, Processing Run ID | AA131: Y | AB131: N | AC131: Oracle DB | AD131: =_xlfn.CONCAT("accelapr/",Table1[[#This Row],[Bronze Table]]) -> accelapr/VIRTUAL_ULTIMATE_BENEFICIAL_OW | AE131: Table | AF131: Sprint 2
A132: DED_Data_Table_202 | C132: br_manager_additional_infomation | D132: manager_additional_infomation | E132: معلومات_إضافية_للمدير | F132: Provides manager information, including draft resubmission, licence-amendment requirements, English trade name, no-nominal-member declaration, applicant unified ID, and applicant name. | G132: يتضمن معلومات المدير، مثل إعادة تقديم المسودة، ومتطلبات تعديل الرخصة، والاسم التجاري بالإنجليزية، وإقرار عدم وجود عضو اسمي، ومعرف مقدم الطلب الموحد، واسم مقدم الطلب. | H132: oeaalali@adra.gov.ae, rfmdaas@adra.gov.ae | I132: aamalseiari@adra.gov.ae, rfmdaas@adra.gov.ae | J132: Accela | K132: DED_Domain_02 | L132: Real Beneficiary (RB) | M132: 46175 | N132: 46273 | O132: Y | V132: Weekly | W132: =Table1[[#This Row],[Domain Name]] -> Real Beneficiary (RB) | X132: Sensitive | Y132: Record Service Provider Code, Application ID, Application Service Type Code, Application Request Type Code, Re Request Draft, License Amendment Required, Trade Name (English), Number Nominal Member Declaration, Applicant UnifiedID, Applicant Name, Previous RB Number, E-mail, System PEP Screening Indentifier, Manager Name Ar, System-Created Record Indicator, Print Flag, Trade Name (Arabic), Official Mobile, Official Email, Phone Number, Manager Issuance Country, Manager Passport Number, Link Local Branch, Trade Name Number, License Amendment Number, Manager Name En, Manager EID, License Amendment Issued, Manager Home Country ID, Capital Amount, Auto-Create Indicator, Manager Nationality, Manager Unified Number, Applicant EID, Manager UAE Residency Indicator, Manager Address, First Load, Record Status, Insert Timestamp, Update Timestamp, Processing Run ID, Business Key Hash, Row Hash | Z132: {=_xlfn.TEXTJOIN(", ",TRUE,_xlfn.UNIQUE(_xlfn._xlws.FILTER('B1.3 Catalogue Attribute'!AJ:AJ,'B1.3 Catalogue Attribute'!L:L=A132,"")))} -> Record Service Provider Code, Application ID, Application Service Type Code, Application Request Type Code, Re Request Draft, License Amendment Required, Trade Name (English), Number Nominal Member Declaration, Applicant UnifiedID, Applicant Name, Previous RB Number, E-mail, System PEP Screening Indentifier, Manager Name Ar, System-Created Record Indicator, Print Flag, Trade Name (Arabic), Official Mobile, Official Email, Phone Number, Manager Issuance Country, Manager Passport Number, Link Local Branch, Trade Name Number, License Amendment Number, Manager Name En, Manager EID, License Amendment Issued, Manager Home Country ID, Capital Amount, Auto-Create Indicator, Manager Nationality, Manager Unified Number, Applicant EID, Manager UAE Residency Indicator, Manager Address, First Load, Record Status, Insert Timestamp, Update Timestamp, Processing Run ID, Business Key Hash, Row Hash | AA132: Y | AB132: Y | AC132: Oracle DB | AD132: accelapr/bchckbox | AE132: Table | AF132: Sprint 3
A133: DED_Data_Table_213 | C133: br_rb_record | D133: rb_record | E133: سجل_المستفيد_الحقيقي | F133: Provides the real-beneficiary record, including unified registration number, security reference number, RB record, and real-beneficiary number. | G133: يتضمن سجل المستفيد الحقيقي، مثل رقم التسجيل الموحد، والمرجع الأمني، وسجل المستفيد الحقيقي، ورقم المستفيد الحقيقي. | H133: oeaalali@adra.gov.ae, rfmdaas@adra.gov.ae | I133: aamalseiari@adra.gov.ae, rfmdaas@adra.gov.ae | J133: Accela | K133: DED_Domain_02 | L133: Real Beneficiary (RB) | M133: 46175 | N133: 46273 | O133: Y | V133: Weekly | W133: =Table1[[#This Row],[Domain Name]] -> Real Beneficiary (RB) | X133: Confidential | Y133: Record Service Provider Code, Application ID, Application Service Type Code, Application Request Type Code, Unified Registration Number, Security Reference Number, RB Record, Real Beneficiary Number, Record Status, Insert Timestamp, Update Timestamp, Processing Run ID, Business Key Hash, Row Hash | Z133: {=_xlfn.TEXTJOIN(", ",TRUE,_xlfn.UNIQUE(_xlfn._xlws.FILTER('B1.3 Catalogue Attribute'!AJ:AJ,'B1.3 Catalogue Attribute'!L:L=A133,"")))} -> Record Service Provider Code, Application ID, Application Service Type Code, Application Request Type Code, Unified Registration Number, Security Reference Number, RB Record, Real Beneficiary Number, Record Status, Insert Timestamp, Update Timestamp, Processing Run ID, Business Key Hash, Row Hash | AA133: Y | AB133: Y | AC133: Oracle DB | AD133: accelapr/bchckbox | AE133: Table | AF133: Sprint 3
A134: DED_Data_Table_214 | C134: br_rbf_activity_risk | D134: rbf_activity_risk | E134: مخاطر_النشاط_في_التقييم_القائم_على_المخاطر | F134: Provides activity-risk factors, including compliance-investigation findings, discrepancies involving connected parties, annual amendment volume, warnings under Cabinet Resolution 53, and material adverse-news indicators. | G134: يتضمن عوامل مخاطر النشاط، مثل نتائج تحقيق الامتثال، والاختلافات المتعلقة بالأطراف المرتبطة، وعدد التعديلات السنوية، والتحذيرات بموجب قرار مجلس الوزراء رقم 53، ومؤشرات الأخبار السلبية الجوهرية. | H134: oeaalali@adra.gov.ae, rfmdaas@adra.gov.ae | I134: aamalseiari@adra.gov.ae, rfmdaas@adra.gov.ae | J134: Accela | K134: DED_Domain_02 | L134: Real Beneficiary (RB) | M134: 46175 | N134: 46273 | O134: Y | V134: Weekly | W134: =Table1[[#This Row],[Domain Name]] -> Real Beneficiary (RB) | X134: Confidential | Y134: Record Service Provider Code, Application ID, Application Service Type Code, Application Request Type Code, Issues Identified During Compliance Investigation, Any Discrepancy Identified on Connected Parties in NER, Number of Amendments Made in a Year, Warnings Issued in Respect to Cabinet Resolution 53, Material Adverse News Indicator, Record Status, Insert Timestamp, Update Timestamp, Processing Run ID, Business Key Hash, Row Hash | Z134: {=_xlfn.TEXTJOIN(", ",TRUE,_xlfn.UNIQUE(_xlfn._xlws.FILTER('B1.3 Catalogue Attribute'!AJ:AJ,'B1.3 Catalogue Attribute'!L:L=A134,"")))} -> Record Service Provider Code, Application ID, Application Service Type Code, Application Request Type Code, Issues Identified During Compliance Investigation, Any Discrepancy Identified on Connected Parties in NER, Number of Amendments Made in a Year, Warnings Issued in Respect to Cabinet Resolution 53, Material Adverse News Indicator, Record Status, Insert Timestamp, Update Timestamp, Processing Run ID, Business Key Hash, Row Hash | AA134: Y | AB134: Y | AC134: Oracle DB | AD134: accelapr/bchckbox | AE134: Table | AF134: Sprint 3
A135: DED_Data_Table_215 | C135: br_rbf_company_risk | D135: rbf_company_risk | E135: مخاطر_الشركة_في_التقييم_القائم_على_المخاطر | F135: Provides company-risk factors, including entity type, ownership type, CID or other clearance, and length of the company relationship. | G135: يتضمن عوامل مخاطر الشركة، مثل نوع الكيان، ونوع الملكية، وتصريح CID أو أي تصريح آخر، ومدة علاقة الشركة. | H135: oeaalali@adra.gov.ae, rfmdaas@adra.gov.ae | I135: aamalseiari@adra.gov.ae, rfmdaas@adra.gov.ae | J135: Accela | K135: DED_Domain_02 | L135: Real Beneficiary (RB) | M135: 46175 | N135: 46273 | O135: Y | V135: Weekly | W135: =Table1[[#This Row],[Domain Name]] -> Real Beneficiary (RB) | X135: Confidential | Y135: Record Service Provider Code, Application ID, Application Service Type Code, Application Request Type Code, Entity Type, Ownership Type, CID or Other Clearance, Length of Company Relationship, Record Status, Insert Timestamp, Update Timestamp, Processing Run ID, Business Key Hash, Row Hash | Z135: {=_xlfn.TEXTJOIN(", ",TRUE,_xlfn.UNIQUE(_xlfn._xlws.FILTER('B1.3 Catalogue Attribute'!AJ:AJ,'B1.3 Catalogue Attribute'!L:L=A135,"")))} -> Record Service Provider Code, Application ID, Application Service Type Code, Application Request Type Code, Entity Type, Ownership Type, CID or Other Clearance, Length of Company Relationship, Record Status, Insert Timestamp, Update Timestamp, Processing Run ID, Business Key Hash, Row Hash | AA135: Y | AB135: Y | AC135: Oracle DB | AD135: accelapr/bchckbox | AE135: Table | AF135: Sprint 3
A136: DED_Data_Table_216 | C136: br_rbf_initiation_risk | D136: rbf_initiation_risk | E136: مخاطر_طريقة_البدء_في_التقييم_القائم_على_المخاطر | F136: Provides initiation-method risk information used in the risk-based assessment. | G136: يتضمن معلومات مخاطر طريقة بدء المعاملة المستخدمة في التقييم القائم على المخاطر. | H136: oeaalali@adra.gov.ae, rfmdaas@adra.gov.ae | I136: aamalseiari@adra.gov.ae, rfmdaas@adra.gov.ae | J136: Accela | K136: DED_Domain_02 | L136: Real Beneficiary (RB) | M136: 46175 | N136: 46273 | O136: Y | V136: Weekly | W136: =Table1[[#This Row],[Domain Name]] -> Real Beneficiary (RB) | X136: Confidential | Y136: Record Service Provider Code, Application ID, Application Service Type Code, Application Request Type Code, Initiation Method Risk, Record Status, Insert Timestamp, Update Timestamp, Processing Run ID, Business Key Hash, Row Hash | Z136: {=_xlfn.TEXTJOIN(", ",TRUE,_xlfn.UNIQUE(_xlfn._xlws.FILTER('B1.3 Catalogue Attribute'!AJ:AJ,'B1.3 Catalogue Attribute'!L:L=A136,"")))} -> Record Service Provider Code, Application ID, Application Service Type Code, Application Request Type Code, Initiation Method Risk, Record Status, Insert Timestamp, Update Timestamp, Processing Run ID, Business Key Hash, Row Hash | AA136: Y | AB136: Y | AC136: Oracle DB | AD136: accelapr/bchckbox | AE136: Table | AF136: Sprint 3
A137: DED_Data_Table_217 | C137: br_rbf_main_inputs | D137: rbf_main_inputs | E137: المدخلات_الرئيسية_للتقييم_القائم_على_المخاطر | F137: Provides the main inputs for the risk-based assessment, including number of directors, new or existing company status, risk-rating date, unique reference, and company name. | G137: يتضمن المدخلات الرئيسية للتقييم القائم على المخاطر، مثل عدد المديرين، وحالة الشركة الجديدة أو القائمة، وتاريخ تصنيف المخاطر، والمرجع الفريد، واسم الشركة. | H137: oeaalali@adra.gov.ae, rfmdaas@adra.gov.ae | I137: aamalseiari@adra.gov.ae, rfmdaas@adra.gov.ae | J137: Accela | K137: DED_Domain_02 | L137: Real Beneficiary (RB) | M137: 46175 | N137: 46273 | O137: Y | V137: Weekly | W137: =Table1[[#This Row],[Domain Name]] -> Real Beneficiary (RB) | X137: Confidential | Y137: Record Service Provider Code, Application ID, Application Service Type Code, Application Request Type Code, Instance, Number of Directors, New or Existing, Date of Risk Rating, Unique Reference, Company Name, Number of Shareholders, Number of Managers, Business Establishment Date, License Expiry Date, Record Status, Insert Timestamp, Update Timestamp, Processing Run ID, Business Key Hash, Row Hash | Z137: {=_xlfn.TEXTJOIN(", ",TRUE,_xlfn.UNIQUE(_xlfn._xlws.FILTER('B1.3 Catalogue Attribute'!AJ:AJ,'B1.3 Catalogue Attribute'!L:L=A137,"")))} -> Record Service Provider Code, Application ID, Application Service Type Code, Application Request Type Code, Instance, Number of Directors, New or Existing, Date of Risk Rating, Unique Reference, Company Name, Number of Shareholders, Number of Managers, Business Establishment Date, License Expiry Date, Record Status, Insert Timestamp, Update Timestamp, Processing Run ID, Business Key Hash, Row Hash | AA137: Y | AB137: Y | AC137: Oracle DB | AD137: accelapr/bchckbox | AE137: Table | AF137: Sprint 3
A138: DED_Data_Table_218 | C138: br_rbf_overriding_factors | D138: rbf_overriding_factors | E138: عوامل_تعديل_المخاطر_في_التقييم_القائم_على_المخاطر | F138: Provides risk-overriding factors, including suspicious activity reports, politically exposed person (PEP) status and details, DNFBP classification, repeated ownership or control changes, and primary nationalities of individual and corporate partners. | G138: يتضمن عوامل تعديل المخاطر، مثل تقارير الأنشطة المشبوهة، وحالة الشخص المعرض سياسيا (PEP) وتفاصيله، وتصنيف DNFBP، وتكرار تغييرات الملكية أو السيطرة، والجنسيات الرئيسية للشركاء الأفراد والشركات. | H138: oeaalali@adra.gov.ae, rfmdaas@adra.gov.ae | I138: aamalseiari@adra.gov.ae, rfmdaas@adra.gov.ae | J138: Accela | K138: DED_Domain_02 | L138: Real Beneficiary (RB) | M138: 46175 | N138: 46273 | O138: Y | V138: Weekly | W138: =Table1[[#This Row],[Domain Name]] -> Real Beneficiary (RB) | X138: Confidential | Y138: Record Service Provider Code, Application ID, Application Service Type Code, Application Request Type Code, Suspicious Activity Report Indicator, PEP Customer Indicator, DNFBP (Designated Non Financial Business or Profession), Has the Entity Made Changes in ownership/control Structure More Than 3 Times in a year?, Partners (Individual & Companies) Primary Nationalities, Is the Entity Customer Identified as PEP - Information?, Licensing Activity Change Frequency, Record Status, Insert Timestamp, Update Timestamp, Processing Run ID, Business Key Hash, Row Hash | Z138: {=_xlfn.TEXTJOIN(", ",TRUE,_xlfn.UNIQUE(_xlfn._xlws.FILTER('B1.3 Catalogue Attribute'!AJ:AJ,'B1.3 Catalogue Attribute'!L:L=A138,"")))} -> Record Service Provider Code, Application ID, Application Service Type Code, Application Request Type Code, Suspicious Activity Report Indicator, PEP Customer Indicator, DNFBP (Designated Non Financial Business or Profession), Has the Entity Made Changes in ownership/control Structure More Than 3 Times in a year?, Partners (Individual & Companies) Primary Nationalities, Is the Entity Customer Identified as PEP - Information?, Licensing Activity Change Frequency, Record Status, Insert Timestamp, Update Timestamp, Processing Run ID, Business Key Hash, Row Hash | AA138: Y | AB138: Y | AC138: Oracle DB | AD138: accelapr/bchckbox | AE138: Table | AF138: Sprint 3
A139: DED_Data_Table_219 | C139: br_rbf_property_risk | D139: rbf_property_risk | E139: مخاطر_العقار_في_التقييم_القائم_على_المخاطر | F139: Provides property-risk information used in the risk-based assessment. | G139: يتضمن معلومات مخاطر العقار المستخدمة في التقييم القائم على المخاطر. | H139: oeaalali@adra.gov.ae, rfmdaas@adra.gov.ae | I139: aamalseiari@adra.gov.ae, rfmdaas@adra.gov.ae | J139: Accela | K139: DED_Domain_02 | L139: Real Beneficiary (RB) | M139: 46175 | N139: 46273 | O139: Y | V139: Weekly | W139: =Table1[[#This Row],[Domain Name]] -> Real Beneficiary (RB) | X139: Confidential | Y139: Record Service Provider Code, Application ID, Application Service Type Code, Application Request Type Code, Property Risk, Record Status, Insert Timestamp, Update Timestamp, Processing Run ID, Business Key Hash, Row Hash | Z139: {=_xlfn.TEXTJOIN(", ",TRUE,_xlfn.UNIQUE(_xlfn._xlws.FILTER('B1.3 Catalogue Attribute'!AJ:AJ,'B1.3 Catalogue Attribute'!L:L=A139,"")))} -> Record Service Provider Code, Application ID, Application Service Type Code, Application Request Type Code, Property Risk, Record Status, Insert Timestamp, Update Timestamp, Processing Run ID, Business Key Hash, Row Hash | AA139: Y | AB139: Y | AC139: Oracle DB | AD139: accelapr/bchckbox | AE139: Table | AF139: Sprint 3
A140: DED_Data_Table_220 | C140: br_rbf_scoring_and_risk_rating | D140: rbf_scoring_and_risk_rating | E140: درجات_وتصنيف_المخاطر_في_التقييم_القائم_على_المخاطر | F140: Provides risk scores and ratings, including override status, overriding risk score, company risk, property risk, activity risk, and jurisdiction risk. | G140: يتضمن درجات وتصنيفات المخاطر، مثل حالة التجاوز، ودرجة المخاطر المعدلة، ومخاطر الشركة والعقار والنشاط والاختصاص القضائي. | H140: oeaalali@adra.gov.ae, rfmdaas@adra.gov.ae | I140: aamalseiari@adra.gov.ae, rfmdaas@adra.gov.ae | J140: Accela | K140: DED_Domain_02 | L140: Real Beneficiary (RB) | M140: 46175 | N140: 46273 | O140: Y | V140: Weekly | W140: =Table1[[#This Row],[Domain Name]] -> Real Beneficiary (RB) | X140: Confidential | Y140: Record Service Provider Code, Application ID, Application Service Type Code, Application Request Type Code, Any Override, Overriding Risk Score, Company Risk Score, Property Risk Score, Activity Risk Score, Jurisdiction Risk Score, Initiation Method Risk Score, Final Risk Rating, Total Score, Initial Risk Rating, Record Status, Insert Timestamp, Update Timestamp, Processing Run ID, Business Key Hash, Row Hash | Z140: {=_xlfn.TEXTJOIN(", ",TRUE,_xlfn.UNIQUE(_xlfn._xlws.FILTER('B1.3 Catalogue Attribute'!AJ:AJ,'B1.3 Catalogue Attribute'!L:L=A140,"")))} -> Record Service Provider Code, Application ID, Application Service Type Code, Application Request Type Code, Any Override, Overriding Risk Score, Company Risk Score, Property Risk Score, Activity Risk Score, Jurisdiction Risk Score, Initiation Method Risk Score, Final Risk Rating, Total Score, Initial Risk Rating, Record Status, Insert Timestamp, Update Timestamp, Processing Run ID, Business Key Hash, Row Hash | AA140: Y | AB140: Y | AC140: Oracle DB | AD140: accelapr/bchckbox | AE140: Table | AF140: Sprint 3

Sheet B1.3 Catalogue Attribute
B1: Not for Submission | C1: Not for Submission | D1: Not for Submission | E1: mandatory | F1: optional | G1: Not for Submission | H1: Not for Submission | I1: mandatory | J1: Not for Submission | K1: optional | L1: mandatory | M1: Not for Submission | N1: mandatory | O1: mandatory | P1: mandatory | Q1: mandatory | R1: mandatory | S1: Not for Submission | T1: mandatory | U1: optional | V1: mandatory | W1: Not for Submission | X1: mandatory | Y1: optional | Z1: optional | AA1: mandatory | AB1: mandatory | AC1: optional | AD1: optional | AE1: optional | AF1: optional | AG1: mandatory | AH1: optional | AI1: mandatory | AJ1: mandatory | AK1: mandatory | AL1: mandatory | AM1: Not for purview | AN1: Not for Submission
A2: Type | B2: Accela Table | C2: Accela Variable | D2: Accela Label | E2: Attribute ID (English) | F2: Attribute ID (Arabic) | G2: Attribute Name | H2: Attribute Description (E-Old) | I2: Attribute Description (English) | J2: Attribute Description (A-Old) | K2: Attribute Description (Arabic) | L2: Data Asset ID | M2: Data Table Name (S) | N2: Created Date | O2: Last Update Date | P2: Nullable (Y/N) | Q2: Data Type | R2: Data Length | S2: CDE Flag (Y/N) | T2: Primary Key (Y/N) | U2: Foreign Key Data Asset | V2: Data Classification | W2: Data Classification Justification - 23Sep | X2: Is Calculated? (Y/N) | Y2: Calculation Logic | Z2: Business Validation Logic | AA2: Data Completeness | AB2: Data Completeness Target | AC2: Missing Data Handling (Y/N) | AD2: Missing Data Handling Process | AE2: Duplicate Data Handling (Y/N) | AF2: Duplicate Data Handling Process | AG2: Duplicate (Y/N) | AH2: Data Quality Issues | AI2: Uniqueness Target | AJ2: Data Glossary | AK2: Data Owner | AL2: Data Steward | AM2: Scope | AN2: Accela Disabled
A3: old | B3: N/A | C3: N/A | D3: N/A | E3: DED_Attribute_0001 | G3: SERV_PROV_CODE | H3: Unique code identifying the service provider (agency or jurisdiction) within the Accela system | I3: Unique code identifying the service provider (agency or jurisdiction) within the Accela system. | J3: رمز فريد يحدد مقدم الخدمة (الوكالة أو الجهة القضائية) داخل نظام أكسيلا. | K3: رمز فريد يحدد مقدم الخدمة (الجهة أو الولاية القضائية) داخل نظام أكسيلا. | L3: DED_Data_Table_001 | M3: Financial_Audit_Trail | N3: 46202 | O3: 46267 | P3: Y | Q3: varchar | R3: 60 | S3: N | T3: N | V3: Sensitive | W3: Uniquely identifies or cross-references Financial Audit Trail records and supports traceability, auditability, and record linkage. Classified as Sensitive, consistent with the parent data asset 'Financial Audit Trail' (Financial Information), whose unauthorised access or disclosure could have a significant impact on the privacy of licence holders and on ADRA's operations, as per the ADDED Data Classification Policy (CH-ISBCO-POL 10) and the Abu Dhabi Whole of Government Data Classification Framework. | X3: N | AA3: N/A | AB3: 0.95 | AG3: =IF(T3="Y","N","Y") -> Y | AI3: 1 | AJ3: Record Service Provider Code | AK3: aiaalsheebani@ded.abudhabi.ae, rfmdaas@adra.gov.ae | AL3: sraalbadi@ded.abudhabi.ae, rfmdaas@adra.gov.ae | AM3: Sprint 1
A4: old | B4: N/A | C4: N/A | D4: N/A | E4: DED_Attribute_0002 | G4: B1_PER_ID1 | H4: First part of the permit/record identifier used to uniquely identify a business record in Accela | I4: First part of the permit/record identifier used to uniquely identify a business record in Accela. | J4: الجزء الأول من معرف التصريح أو السجل يستخدم لتحديد السجل التجاري بشكل فريد في أكسيلا. | K4: الجزء الأول من معرف التصريح أو السجل، يُستخدم لتحديد سجل الأعمال بشكل فريد في نظام أكسيلا. | L4: DED_Data_Table_001 | M4: Financial_Audit_Trail | N4: 46202 | O4: 46267 | P4: Y | Q4: varchar | R4: 20 | S4: N | T4: N | V4: Sensitive | W4: Business content of the Financial Audit Trail record used in day-to-day licensing, permitting, and compliance operations. Classified as Sensitive, consistent with the parent data asset 'Financial Audit Trail' (Financial Information), whose unauthorised access or disclosure could have a significant impact on the privacy of licence holders and on ADRA's operations, as per the ADDED Data Classification Policy (CH-ISBCO-POL 10) and the Abu Dhabi Whole of Government Data Classification Framework. | X4: N | AA4: N/A | AB4: 0.95 | AG4: =IF(T4="Y","N","Y") -> Y | AI4: 1 | AJ4: Application ID | AK4: aiaalsheebani@ded.abudhabi.ae, rfmdaas@adra.gov.ae | AL4: sraalbadi@ded.abudhabi.ae, rfmdaas@adra.gov.ae | AM4: Sprint 1
A5: old | B5: N/A | C5: N/A | D5: N/A | E5: DED_Attribute_0003 | G5: ACC_AUDIT_SEQ_NBR | H5: Unique sequence number identifying a specific accounting audit trail record Primary key for the audit transaction | I5: Unique sequence number identifying a specific accounting audit trail record Primary key for the audit transaction. | J5: رقم تسلسلي فريد يحدد سجلاً معيناً لمسار تدقيق محاسبي، وهو المفتاح الأساسي لمعاملة التدقيق | K5: الرقم التسلسلي الفريد الذي يحدد سجلاً معيناً في مسار تدقيق المحاسبة، وهو المفتاح الأساسي لمعاملة التدقيق. | L5: DED_Data_Table_001 | M5: Financial_Audit_Trail | N5: 46202 | O5: 46267 | P5: Y | Q5: int | R5: N/A | S5: N | T5: N | V5: Sensitive | W5: Uniquely identifies or cross-references Financial Audit Trail records and supports traceability, auditability, and record linkage. Classified as Sensitive, consistent with the parent data asset 'Financial Audit Trail' (Financial Information), whose unauthorised access or disclosure could have a significant impact on the privacy of licence holders and on ADRA's operations, as per the ADDED Data Classification Policy (CH-ISBCO-POL 10) and the Abu Dhabi Whole of Government Data Classification Framework. | X5: N | AA5: N/A | AB5: 0.95 | AG5: =IF(T5="Y","N","Y") -> Y | AI5: 1 | AJ5: Financial Audit Sequence Number | AK5: aiaalsheebani@ded.abudhabi.ae, rfmdaas@adra.gov.ae | AL5: sraalbadi@ded.abudhabi.ae, rfmdaas@adra.gov.ae | AM5: Sprint 1
A6: old | B6: N/A | C6: N/A | D6: N/A | E6: DED_Attribute_0004 | G6: B1_PER_ID2 | H6: Second part of the permit/record identifier used together with other ID parts to uniquely identify the record | I6: Second part of the permit/record identifier used together with other ID parts to uniquely identify the record. | J6: الجزء الثاني من معرف التصريح أو السجل يستخدم مع أجزاء أخرى للتعريف بالسجل بشكل فريد. | K6: الجزء الثاني من معرف التصريح أو السجل، يُستخدم مع الأجزاء الأخرى لتحديد السجل بشكل فريد. | L6: DED_Data_Table_001 | M6: Financial_Audit_Trail | N6: 46202 | O6: 46267 | P6: Y | Q6: varchar | R6: 20 | S6: N | T6: N | V6: Sensitive | W6: Business content of the Financial Audit Trail record used in day-to-day licensing, permitting, and compliance operations. Classified as Sensitive, consistent with the parent data asset 'Financial Audit Trail' (Financial Information), whose unauthorised access or disclosure could have a significant impact on the privacy of licence holders and on ADRA's operations, as per the ADDED Data Classification Policy (CH-ISBCO-POL 10) and the Abu Dhabi Whole of Government Data Classification Framework. | X6: N | AA6: N/A | AB6: 0.95 | AG6: =IF(T6="Y","N","Y") -> Y | AI6: 1 | AJ6: Application ID | AK6: aiaalsheebani@ded.abudhabi.ae, rfmdaas@adra.gov.ae | AL6: sraalbadi@ded.abudhabi.ae, rfmdaas@adra.gov.ae | AM6: Sprint 1
A7: old | B7: N/A | C7: N/A | D7: N/A | E7: DED_Attribute_0005 | G7: B1_PER_ID3 | H7: Third part of the permit/record identifier used together with other ID parts to uniquely identify the record | I7: Third part of the permit/record identifier used together with other ID parts to uniquely identify the record. | J7: الجزء الثالث من معرف التصريح أو السجل يستخدم مع أجزاء أخرى من التعريف لتحديد السجل بشكل فريد. | K7: الجزء الثالث من معرف التصريح أو السجل، يُستخدم مع الأجزاء الأخرى لتحديد السجل بشكل فريد. | L7: DED_Data_Table_001 | M7: Financial_Audit_Trail | N7: 46202 | O7: 46267 | P7: Y | Q7: varchar | R7: 20 | S7: N | T7: N | V7: Sensitive | W7: Business content of the Financial Audit Trail record used in day-to-day licensing, permitting, and compliance operations. Classified as Sensitive, consistent with the parent data asset 'Financial Audit Trail' (Financial Information), whose unauthorised access or disclosure could have a significant impact on the privacy of licence holders and on ADRA's operations, as per the ADDED Data Classification Policy (CH-ISBCO-POL 10) and the Abu Dhabi Whole of Government Data Classification Framework. | X7: N | AA7: N/A | AB7: 0.95 | AG7: =IF(T7="Y","N","Y") -> Y | AI7: 1 | AJ7: Application ID | AK7: aiaalsheebani@ded.abudhabi.ae, rfmdaas@adra.gov.ae | AL7: sraalbadi@ded.abudhabi.ae, rfmdaas@adra.gov.ae | AM7: Sprint 1
A8: old | B8: N/A | C8: N/A | D8: N/A | E8: DED_Attribute_0006 | G8: INVOICE_NBR | H8: Invoice number associated with the financial transaction recorded in the audit trail | I8: Invoice number associated with the financial transaction recorded in the audit trail. | J8: رقم الفاتورة المرتبط بالمعاملة المالية المسجلة في مسار التدقيق | K8: رقم الفاتورة المرتبط بالمعاملة المالية المسجلة في مسار التدقيق. | L8: DED_Data_Table_001 | M8: Financial_Audit_Trail | N8: 46202 | O8: 46267 | P8: Y | Q8: decimal | R8: decimal(12,0) | S8: Y | T8: N | V8: Sensitive | W8: Contains financial transaction or obligation details (INVOICE_NBR) used for reconciliation, compliance, and decision-making. Classified as Sensitive, consistent with the parent data asset 'Financial Audit Trail' (Financial Information), whose unauthorised access or disclosure could have a significant impact on the privacy of licence holders and on ADRA's operations, as per the ADDED Data Classification Policy (CH-ISBCO-POL 10) and the Abu Dhabi Whole of Government Data Classification Framework. | X8: N | AA8: 100 | AB8: 0.95 | AG8: =IF(T8="Y","N","Y") -> Y | AI8: 1 | AJ8: Invoice ID | AK8: aiaalsheebani@ded.abudhabi.ae, rfmdaas@adra.gov.ae | AL8: sraalbadi@ded.abudhabi.ae, rfmdaas@adra.gov.ae | AM8: Sprint 1
A9: old | B9: N/A | C9: N/A | D9: N/A | E9: DED_Attribute_0007 | G9: RECEIPT_NBR | H9: Receipt number issued for the payment related to the transaction | I9: Receipt number issued for the payment related to the transaction. | J9: رقم الإيصال الصادر للدفعة المرتبطة بالمعاملة | K9: رقم الإيصال الصادر عن الدفعة المرتبطة بالمعاملة. | L9: DED_Data_Table_001 | M9: Financial_Audit_Trail | N9: 46202 | O9: 46267 | P9: Y | Q9: decimal | R9: decimal(12,0) | S9: Y | T9: N | V9: Sensitive | W9: Contains financial transaction or obligation details (RECEIPT_NBR) used for reconciliation, compliance, and decision-making. Classified as Sensitive, consistent with the parent data asset 'Financial Audit Trail' (Financial Information), whose unauthorised access or disclosure could have a significant impact on the privacy of licence holders and on ADRA's operations, as per the ADDED Data Classification Policy (CH-ISBCO-POL 10) and the Abu Dhabi Whole of Government Data Classification Framework. | X9: N | AA9: 100 | AB9: 0.95 | AG9: =IF(T9="Y","N","Y") -> Y | AI9: 1 | AJ9: Receipt ID | AK9: aiaalsheebani@ded.abudhabi.ae, rfmdaas@adra.gov.ae | AL9: sraalbadi@ded.abudhabi.ae, rfmdaas@adra.gov.ae | AM9: Sprint 1
A10: old | B10: N/A | C10: N/A | D10: N/A | E10: DED_Attribute_0008 | G10: PAYMENT_SEQ_NBR | H10: Sequence number identifying the specific payment applied to the transaction | I10: Sequence number identifying the specific payment applied to the transaction. | J10: رقم تسلسلي يحدد الدفعة المحددة المطبقة على المعاملة | K10: الرقم التسلسلي الذي يحدد الدفعة المطبقة على المعاملة. | L10: DED_Data_Table_001 | M10: Financial_Audit_Trail | N10: 46202 | O10: 46267 | P10: Y | Q10: decimal | R10: decimal(12,0) | S10: Y | T10: N | V10: Sensitive | W10: Contains financial transaction or obligation details (PAYMENT_SEQ_NBR) used for reconciliation, compliance, and decision-making. Classified as Sensitive, consistent with the parent data asset 'Financial Audit Trail' (Financial Information), whose unauthorised access or disclosure could have a significant impact on the privacy of licence holders and on ADRA's operations, as per the ADDED Data Classification Policy (CH-ISBCO-POL 10) and the Abu Dhabi Whole of Government Data Classification Framework. | X10: N | AA10: 100 | AB10: 0.95 | AG10: =IF(T10="Y","N","Y") -> Y | AI10: 1 | AJ10: Payment ID | AK10: aiaalsheebani@ded.abudhabi.ae, rfmdaas@adra.gov.ae | AL10: sraalbadi@ded.abudhabi.ae, rfmdaas@adra.gov.ae | AM10: Sprint 1
A11: old | B11: All Module | C11: Payments | D11: Amount | E11: DED_Attribute_0009 | G11: RECEIPT_AMOUNT | H11: Amount of money associated with the financial item (fee, payment, refund, or adjustment) recorded for this transaction | I11: Amount of money associated with the financial item (fee, payment, refund, or adjustment) recorded for this transaction. | J11: المبلغ المالي المرتبط بالبند المالي (رسم أو دفعة أو استرداد أو تسوية) المسجل لهذه المعاملة | K11: المبلغ المالي المرتبط بـالبند المالي (رسوم، دفعة، استرداد، أو تسوية) المسجل لهذه المعاملة. | L11: DED_Data_Table_001 | M11: Financial_Audit_Trail | N11: 46202 | O11: 46267 | P11: Y | Q11: decimal | R11: decimal(15,2) | S11: N | T11: N | V11: Sensitive | W11: Contains financial transaction or obligation details (RECEIPT_AMOUNT) used for reconciliation, compliance, and decision-making. Classified as Sensitive, consistent with the parent data asset 'Financial Audit Trail' (Financial Information), whose unauthorised access or disclosure could have a significant impact on the privacy of licence holders and on ADRA's operations, as per the ADDED Data Classification Policy (CH-ISBCO-POL 10) and the Abu Dhabi Whole of Government Data Classification Framework. | X11: N | AA11: N/A | AB11: 0.95 | AG11: =IF(T11="Y","N","Y") -> Y | AI11: 1 | AJ11: Receipt Amount | AK11: aiaalsheebani@ded.abudhabi.ae, rfmdaas@adra.gov.ae | AL11: sraalbadi@ded.abudhabi.ae, rfmdaas@adra.gov.ae | AM11: Sprint 1
A12: old | B12: N/A | C12: N/A | D12: N/A | E12: DED_Attribute_0010 | G12: ACTION | H12: Business data element 'action' captured in the ACCELAACCOUNTING_AUDIT_TRAIL dataset to support operational processing, compliance tracking, and reporting | I12: Holds the 'action' business data element captured in the ACCELAACCOUNTING_AUDIT_TRAIL dataset to support operational processing, compliance tracking, and reporting. | J12: عنصر بيانات الأعمال 'الإجراء' المسجل في مجموعة بيانات ACCELAACCOUNTING_AUDIT_TRAIL لدعم المعالجة التشغيلية وتتبع الامتثال وإعداد التقارير | K12: يحتوي على عنصر بيانات الأعمال 'action' المسجل في مجموعة بيانات تدقيق المحاسبة لدعم المعالجة التشغيلية وتتبع الامتثال وإعداد التقارير. | L12: DED_Data_Table_001 | M12: Financial_Audit_Trail | N12: 46202 | O12: 46267 | P12: Y | Q12: varchar | R12: 120 | S12: N | T12: N | V12: Sensitive | W12: Business content of the Financial Audit Trail record used in day-to-day licensing, permitting, and compliance operations. Classified as Sensitive, consistent with the parent data asset 'Financial Audit Trail' (Financial Information), whose unauthorised access or disclosure could have a significant impact on the privacy of licence holders and on ADRA's operations, as per the ADDED Data Classification Policy (CH-ISBCO-POL 10) and the Abu Dhabi Whole of Government Data Classification Framework. | X12: N | AA12: N/A | AB12: 0.95 | AG12: =IF(T12="Y","N","Y") -> Y | AI12: 1 | AJ12: Action | AK12: aiaalsheebani@ded.abudhabi.ae, rfmdaas@adra.gov.ae | AL12: sraalbadi@ded.abudhabi.ae, rfmdaas@adra.gov.ae | AM12: Sprint 1
A13: old | B13: N/A | C13: N/A | D13: N/A | E13: DED_Attribute_0011 | G13: FEEITEM_SEQ_NBR | H13: System-generated sequence value used to uniquely identify the row and maintain relationships between related transactions/records | I13: System-generated sequence value used to uniquely identify the row and maintain relationships between related transactions/records. | J13: قيمة تسلسلية ينشئها النظام لتحديد الصف بشكل فريد والحفاظ على العلاقات بين المعاملات أو السجلات ذات الصلة | K13: قيمة تسلسلية يولّدها النظام لتحديد الصف بشكل فريد والحفاظ على العلاقات بين المعاملات أو السجلات المرتبطة. | L13: DED_Data_Table_001 | M13: Financial_Audit_Trail | N13: 46202 | O13: 46267 | P13: Y | Q13: int | R13: N/A | S13: Y | T13: N | V13: Sensitive | W13: Contains financial transaction or obligation details (FEEITEM_SEQ_NBR) used for reconciliation, compliance, and decision-making. Classified as Sensitive, consistent with the parent data asset 'Financial Audit Trail' (Financial Information), whose unauthorised access or disclosure could have a significant impact on the privacy of licence holders and on ADRA's operations, as per the ADDED Data Classification Policy (CH-ISBCO-POL 10) and the Abu Dhabi Whole of Government Data Classification Framework. | X13: N | AA13: 100 | AB13: 0.95 | AG13: =IF(T13="Y","N","Y") -> Y | AI13: 1 | AJ13: Application Fee ID | AK13: aiaalsheebani@ded.abudhabi.ae, rfmdaas@adra.gov.ae | AL13: sraalbadi@ded.abudhabi.ae, rfmdaas@adra.gov.ae | AM13: Sprint 1
A14: old | B14: All Module | C14: Payments | D14: Method | E14: DED_Attribute_0012 | G14: PAYMENT_METHOD | H14: Business data element 'payment method' captured in the ACCELAACCOUNTING_AUDIT_TRAIL dataset to support operational processing, compliance tracking, and reporting | I14: Holds the 'payment method' business data element captured in the ACCELAACCOUNTING_AUDIT_TRAIL dataset to support operational processing, compliance tracking, and reporting. | J14: عنصر بيانات الأعمال 'طريقة الدفع' المسجل في مجموعة بيانات ACCELAACCOUNTING_AUDIT_TRAIL لدعم المعالجة التشغيلية وتتبع الامتثال وإعداد التقارير | K14: يحتوي على عنصر بيانات الأعمال 'دفعة method' المسجل في مجموعة بيانات تدقيق المحاسبة لدعم المعالجة التشغيلية وتتبع الامتثال وإعداد التقارير. | L14: DED_Data_Table_001 | M14: Financial_Audit_Trail | N14: 46202 | O14: 46267 | P14: Y | Q14: varchar | R14: 120 | S14: N | T14: N | V14: Sensitive | W14: Contains financial transaction or obligation details (PAYMENT_METHOD) used for reconciliation, compliance, and decision-making. Classified as Sensitive, consistent with the parent data asset 'Financial Audit Trail' (Financial Information), whose unauthorised access or disclosure could have a significant impact on the privacy of licence holders and on ADRA's operations, as per the ADDED Data Classification Policy (CH-ISBCO-POL 10) and the Abu Dhabi Whole of Government Data Classification Framework. | X14: N | AA14: N/A | AB14: 0.95 | AG14: =IF(T14="Y","N","Y") -> Y | AI14: 1 | AJ14: Payment Method Type Code | AK14: aiaalsheebani@ded.abudhabi.ae, rfmdaas@adra.gov.ae | AL14: sraalbadi@ded.abudhabi.ae, rfmdaas@adra.gov.ae | AM14: Sprint 1
A15: old | B15: All Module | C15: Payments | D15: Receipt# | E15: DED_Attribute_0013 | G15: PAYMENT_REF_NBR | H15: System sequence identifying the specific payment entry (eg, cash/cheque/card) applied to an invoice or fee item | I15: System sequence identifying the specific payment entry (eg, cash/cheque/card) applied to an invoice or fee item. | J15: تسلسل نظامي يحدد قيد الدفع المحدد (مثل النقد أو الشيك أو البطاقة) المطبق على فاتورة أو بند رسوم | K15: التسلسل النظامي الذي يحدد قيد الدفعة المحددة (مثل: نقداً/شيك/بطاقة) المطبقة على فاتورة أو بند رسوم. | L15: DED_Data_Table_001 | M15: Financial_Audit_Trail | N15: 46202 | O15: 46267 | P15: Y | Q15: varchar | R15: 280 | S15: N | T15: N | V15: Sensitive | W15: Contains financial transaction or obligation details (PAYMENT_REF_NBR) used for reconciliation, compliance, and decision-making. Classified as Sensitive, consistent with the parent data asset 'Financial Audit Trail' (Financial Information), whose unauthorised access or disclosure could have a significant impact on the privacy of licence holders and on ADRA's operations, as per the ADDED Data Classification Policy (CH-ISBCO-POL 10) and the Abu Dhabi Whole of Government Data Classification Framework. | X15: N | AA15: N/A | AB15: 0.95 | AG15: =IF(T15="Y","N","Y") -> Y | AI15: 1 | AJ15: Payment Reference Number | AK15: aiaalsheebani@ded.abudhabi.ae, rfmdaas@adra.gov.ae | AL15: sraalbadi@ded.abudhabi.ae, rfmdaas@adra.gov.ae | AM15: Sprint 1
A16: old | B16: N/A | C16: N/A | D16: N/A | E16: DED_Attribute_0014 | G16: REGISTER_NBR | H16: Reference number for register used by business users to search, reconcile, and audit transactions | I16: Reference number for register used by business users to search, reconcile, and audit transactions. | J16: الرقم المرجعي للسجل الذي يستخدمه مستخدمو الأعمال للبحث عن المعاملات وتسويتها وتدقيقها | K16: الرقم المرجعي لـالسجل الذي يستخدمه مستخدمو الأعمال للبحث في المعاملات ومطابقتها وتدقيقها. | L16: DED_Data_Table_001 | M16: Financial_Audit_Trail | N16: 46202 | O16: 46267 | P16: Y | Q16: varchar | R16: 32 | S16: N | T16: N | V16: Sensitive | W16: Uniquely identifies or cross-references Financial Audit Trail records and supports traceability, auditability, and record linkage. Classified as Sensitive, consistent with the parent data asset 'Financial Audit Trail' (Financial Information), whose unauthorised access or disclosure could have a significant impact on the privacy of licence holders and on ADRA's operations, as per the ADDED Data Classification Policy (CH-ISBCO-POL 10) and the Abu Dhabi Whole of Government Data Classification Framework. | X16: N | AA16: N/A | AB16: 0.95 | AG16: =IF(T16="Y","N","Y") -> Y | AI16: 1 | AJ16: Register Number | AK16: aiaalsheebani@ded.abudhabi.ae, rfmdaas@adra.gov.ae | AL16: sraalbadi@ded.abudhabi.ae, rfmdaas@adra.gov.ae | AM16: Sprint 1
A17: old | B17: N/A | C17: N/A | D17: N/A | E17: DED_Attribute_0015 | G17: REC_STATUS | H17: Financial status of the transaction (eg, invoiced, paid, voided, refunded) used for reconciliation and reporting | I17: Financial status of the transaction (eg, invoiced, paid, voided, refunded) used for reconciliation and reporting. | J17: الجزء الثالث من معرف التصريح أو السجل يستخدم مع أجزاء أخرى من التعريف لتحديد السجل بشكل فريد. | K17: الحالة المالية للمعاملة (مثل: مفوتر، مدفوع، ملغى، مسترد)؛ تُستخدم للتسوية وإعداد التقارير. | L17: DED_Data_Table_001 | M17: Financial_Audit_Trail | N17: 46202 | O17: 46267 | P17: Y | Q17: varchar | R17: 4 | S17: N | T17: N | V17: Sensitive | W17: System-generated technical metadata (REC_STATUS) used for data-lineage tracking and record-integrity checks, without direct business or personal content. Classified as Sensitive, consistent with the parent data asset 'Financial Audit Trail' (Financial Information), whose unauthorised access or disclosure could have a significant impact on the privacy of licence holders and on ADRA's operations, as per the ADDED Data Classification Policy (CH-ISBCO-POL 10) and the Abu Dhabi Whole of Government Data Classification Framework. | X17: N | AA17: N/A | AB17: 0.95 | AG17: =IF(T17="Y","N","Y") -> Y | AI17: 1 | AJ17: Record Status | AK17: aiaalsheebani@ded.abudhabi.ae, rfmdaas@adra.gov.ae | AL17: sraalbadi@ded.abudhabi.ae, rfmdaas@adra.gov.ae | AM17: Sprint 1
A18: old | B18: N/A | C18: N/A | D18: N/A | E18: DED_Attribute_0016 | G18: APP_STATUS_GROUP_CODE | H18: Identifier/code for app status group used to uniquely reference the related entity in Accela and support joins, auditing, and reporting | I18: Identifier/code for app status group used to uniquely reference the related entity in Accela and support joins, auditing, and reporting. | J18: معرّف أو رمز مجموعة حالة الطلب المستخدم للإشارة بشكل فريد إلى الكيان ذي الصلة في Accela ودعم عمليات الربط والتدقيق وإعداد التقارير | K18: معرف أو رمز لـمجموعة حالة الطلب؛ يُستخدم للإحالة الفريدة إلى الجهة المرتبطة في نظام أكسيلا ودعم الربط والتدقيق وإعداد التقارير. | L18: DED_Data_Table_002 | M18: Status_Lookup | N18: 46202 | O18: 46267 | P18: N | Q18: varchar | R18: 120 | S18: Y | T18: Y | V18: Sensitive | W18: Uniquely identifies or cross-references Status Lookup records and supports traceability, auditability, and record linkage. Classified as Sensitive, consistent with the parent data asset 'Status Lookup' (Economic Licenses), whose unauthorised access or disclosure could have a significant impact on the privacy of licence holders and on ADRA's operations, as per the ADDED Data Classification Policy (CH-ISBCO-POL 10) and the Abu Dhabi Whole of Government Data Classification Framework. | X18: N | AA18: 100 | AB18: 0.95 | AG18: =IF(T18="Y","N","Y") -> N | AI18: 1 | AJ18: Application Status Code | AK18: bmalkindi@adra.gov.ae, rfmdaas@adra.gov.ae | AL18: asalmehiry@adra.gov.ae, rfmdaas@adra.gov.ae | AM18: Sprint 1
A19: old | B19: N/A | C19: N/A | D19: N/A | E19: DED_Attribute_0017 | G19: STATUS | H19: Business data element 'status' captured in the ACCELAAPP_STATUS_GROUP dataset to support operational processing, compliance tracking, and reporting | I19: Holds the 'status' business data element captured in the ACCELAAPP_STATUS_GROUP dataset to support operational processing, compliance tracking, and reporting. | J19: عنصر بيانات الأعمال 'الحالة' المسجل في مجموعة بيانات ACCELAAPP_STATUS_GROUP لدعم المعالجة التشغيلية وتتبع الامتثال وإعداد التقارير | K19: يحتوي على عنصر بيانات الأعمال 'status' المسجل في مجموعة بيانات مجموعة حالة الطلب لدعم المعالجة التشغيلية وتتبع الامتثال وإعداد التقارير. | L19: DED_Data_Table_002 | M19: Status_Lookup | N19: 46202 | O19: 46267 | P19: N | Q19: varchar | R19: 120 | S19: Y | T19: Y | V19: Sensitive | W19: Reference and lookup content supporting the consistent classification and processing of Status Lookup records. Classified as Sensitive, consistent with the parent data asset 'Status Lookup' (Economic Licenses), whose unauthorised access or disclosure could have a significant impact on the privacy of licence holders and on ADRA's operations, as per the ADDED Data Classification Policy (CH-ISBCO-POL 10) and the Abu Dhabi Whole of Government Data Classification Framework. | X19: N | AA19: 100 | AB19: 0.95 | AG19: =IF(T19="Y","N","Y") -> N | AI19: 1 | AJ19: Application Status Description | AK19: bmalkindi@adra.gov.ae, rfmdaas@adra.gov.ae | AL19: asalmehiry@adra.gov.ae, rfmdaas@adra.gov.ae | AM19: Sprint 1
A20: old | B20: N/A | C20: N/A | D20: N/A | E20: DED_Attribute_0018 | G20: REC_STATUS | H20: Financial status of the transaction (eg, invoiced, paid, voided, refunded) used for reconciliation and reporting | I20: Financial status of the transaction (eg, invoiced, paid, voided, refunded) used for reconciliation and reporting. | J20: الجزء الثالث من معرف التصريح أو السجل يستخدم مع أجزاء أخرى من التعريف لتحديد السجل بشكل فريد. | K20: الحالة المالية للمعاملة (مثل: مفوتر، مدفوع، ملغى، مسترد)؛ تُستخدم للتسوية وإعداد التقارير. | L20: DED_Data_Table_002 | M20: Status_Lookup | N20: 46202 | O20: 46267 | P20: Y | Q20: varchar | R20: 4 | S20: N | T20: N | V20: Sensitive | W20: System-generated technical metadata (REC_STATUS) used for data-lineage tracking and record-integrity checks, without direct business or personal content. Classified as Sensitive, consistent with the parent data asset 'Status Lookup' (Economic Licenses), whose unauthorised access or disclosure could have a significant impact on the privacy of licence holders and on ADRA's operations, as per the ADDED Data Classification Policy (CH-ISBCO-POL 10) and the Abu Dhabi Whole of Government Data Classification Framework. | X20: N | AA20: N/A | AB20: 0.95 | AG20: =IF(T20="Y","N","Y") -> Y | AI20: 1 | AJ20: Record Status | AK20: bmalkindi@adra.gov.ae, rfmdaas@adra.gov.ae | AL20: asalmehiry@adra.gov.ae, rfmdaas@adra.gov.ae | AM20: Sprint 1
A21: old | B21: N/A | C21: N/A | D21: N/A | E21: DED_Attribute_0019 | G21: SERV_PROV_CODE | H21: Unique code identifying the service provider (agency or jurisdiction) within the Accela system | I21: Unique code identifying the service provider (agency or jurisdiction) within the Accela system. | J21: رمز فريد يحدد مقدم الخدمة (الوكالة أو الجهة القضائية) داخل نظام أكسيلا. | K21: رمز فريد يحدد مقدم الخدمة (الجهة أو الولاية القضائية) داخل نظام أكسيلا. | L21: DED_Data_Table_002 | M21: Status_Lookup | N21: 46202 | O21: 46267 | P21: N | Q21: varchar | R21: 60 | S21: Y | T21: Y | V21: Sensitive | W21: Uniquely identifies or cross-references Status Lookup records and supports traceability, auditability, and record linkage. Classified as Sensitive, consistent with the parent data asset 'Status Lookup' (Economic Licenses), whose unauthorised access or disclosure could have a significant impact on the privacy of licence holders and on ADRA's operations, as per the ADDED Data Classification Policy (CH-ISBCO-POL 10) and the Abu Dhabi Whole of Government Data Classification Framework. | X21: N | AA21: 100 | AB21: 0.95 | AG21: =IF(T21="Y","N","Y") -> N | AI21: 1 | AJ21: Record Service Provider Code | AK21: bmalkindi@adra.gov.ae, rfmdaas@adra.gov.ae | AL21: asalmehiry@adra.gov.ae, rfmdaas@adra.gov.ae | AM21: Sprint 1
A22: old | B22: N/A | C22: N/A | D22: N/A | E22: DED_Attribute_0020 | G22: RES_ID | H22: Identifier/code for res identifier used to uniquely reference the related entity in Accela and support joins, auditing, and reporting | I22: Identifier/code for res identifier used to uniquely reference the related entity in Accela and support joins, auditing, and reporting. | J22: الجزء الأول من معرف التصريح أو السجل يستخدم لتحديد السجل التجاري بشكل فريد في أكسيلا. | K22: معرف أو رمز للمعرف السكني؛ يُستخدم للإحالة الفريدة إلى الجهة المرتبطة في نظام أكسيلا ودعم الربط والتدقيق وإعداد التقارير. | L22: DED_Data_Table_002 | M22: Status_Lookup | N22: 46202 | O22: 46267 | P22: Y | Q22: decimal | R22: decimal(10,0) | S22: N | T22: N | V22: Sensitive | W22: Uniquely identifies or cross-references Status Lookup records and supports traceability, auditability, and record linkage. Classified as Sensitive, consistent with the parent data asset 'Status Lookup' (Economic Licenses), whose unauthorised access or disclosure could have a significant impact on the privacy of licence holders and on ADRA's operations, as per the ADDED Data Classification Policy (CH-ISBCO-POL 10) and the Abu Dhabi Whole of Government Data Classification Framework. | X22: N | AA22: N/A | AB22: 0.95 | AG22: =IF(T22="Y","N","Y") -> Y | AI22: 1 | AJ22: Resource ID | AK22: bmalkindi@adra.gov.ae, rfmdaas@adra.gov.ae | AL22: asalmehiry@adra.gov.ae, rfmdaas@adra.gov.ae | AM22: Sprint 1
A23: old | B23: N/A | C23: N/A | D23: N/A | E23: DED_Attribute_0021 | G23: SERV_PROV_CODE | H23: Unique code identifying the service provider (agency or jurisdiction) within the Accela system | I23: Unique code identifying the service provider (agency or jurisdiction) within the Accela system. | J23: رمز فريد يحدد مقدم الخدمة (الوكالة أو الجهة القضائية) داخل نظام أكسيلا. | K23: رمز فريد يحدد مقدم الخدمة (الجهة أو الولاية القضائية) داخل نظام أكسيلا. | L23: DED_Data_Table_003 | M23: Status_Lookup_Language | N23: 46202 | O23: 46267 | P23: N | Q23: varchar | R23: 60 | S23: N | T23: Y | V23: Sensitive | W23: Uniquely identifies or cross-references Status Lookup Language records and supports traceability, auditability, and record linkage. Classified as Sensitive, consistent with the parent data asset 'Status Lookup Language' (Economic Licenses), whose unauthorised access or disclosure could have a significant impact on the privacy of licence holders and on ADRA's operations, as per the ADDED Data Classification Policy (CH-ISBCO-POL 10) and the Abu Dhabi Whole of Government Data Classification Framework. | X23: N | AA23: N/A | AB23: 0.95 | AG23: =IF(T23="Y","N","Y") -> N | AI23: 1 | AJ23: Record Service Provider Code | AK23: bmalkindi@adra.gov.ae, rfmdaas@adra.gov.ae | AL23: asalmehiry@adra.gov.ae, rfmdaas@adra.gov.ae | AM23: Sprint 1
A24: old | B24: N/A | C24: N/A | D24: N/A | E24: DED_Attribute_0022 | G24: RES_ID | H24: Identifier/code for res identifier used to uniquely reference the related entity in Accela and support joins, auditing, and reporting | I24: Identifier/code for res identifier used to uniquely reference the related entity in Accela and support joins, auditing, and reporting. | J24: الجزء الأول من معرف التصريح أو السجل يستخدم لتحديد السجل التجاري بشكل فريد في أكسيلا. | K24: معرف أو رمز للمعرف السكني؛ يُستخدم للإحالة الفريدة إلى الجهة المرتبطة في نظام أكسيلا ودعم الربط والتدقيق وإعداد التقارير. | L24: DED_Data_Table_003 | M24: Status_Lookup_Language | N24: 46202 | O24: 46267 | P24: N | Q24: decimal | R24: decimal(10,0) | S24: Y | T24: Y | V24: Sensitive | W24: Uniquely identifies or cross-references Status Lookup Language records and supports traceability, auditability, and record linkage. Classified as Sensitive, consistent with the parent data asset 'Status Lookup Language' (Economic Licenses), whose unauthorised access or disclosure could have a significant impact on the privacy of licence holders and on ADRA's operations, as per the ADDED Data Classification Policy (CH-ISBCO-POL 10) and the Abu Dhabi Whole of Government Data Classification Framework. | X24: N | AA24: 100 | AB24: 0.95 | AG24: =IF(T24="Y","N","Y") -> N | AI24: 1 | AJ24: Resource ID | AK24: bmalkindi@adra.gov.ae, rfmdaas@adra.gov.ae | AL24: asalmehiry@adra.gov.ae, rfmdaas@adra.gov.ae | AM24: Sprint 1
A25: old | B25: N/A | C25: N/A | D25: N/A | E25: DED_Attribute_0023 | G25: LANG_ID | H25: Identifier/code for lang identifier used to uniquely reference the related entity in Accela and support joins, auditing, and reporting | I25: Identifier/code for lang identifier used to uniquely reference the related entity in Accela and support joins, auditing, and reporting. | J25: الجزء الثاني من معرف التصريح أو السجل يستخدم مع أجزاء أخرى للتعريف بالسجل بشكل فريد. | K25: معرف أو رمز للمعرف اللغوي؛ يُستخدم للإحالة الفريدة إلى الجهة المرتبطة في نظام أكسيلا ودعم الربط والتدقيق وإعداد التقارير. | L25: DED_Data_Table_003 | M25: Status_Lookup_Language | N25: 46202 | O25: 46267 | P25: N | Q25: varchar | R25: 40 | S25: Y | T25: Y | V25: Sensitive | W25: Uniquely identifies or cross-references Status Lookup Language records and supports traceability, auditability, and record linkage. Classified as Sensitive, consistent with the parent data asset 'Status Lookup Language' (Economic Licenses), whose unauthorised access or disclosure could have a significant impact on the privacy of licence holders and on ADRA's operations, as per the ADDED Data Classification Policy (CH-ISBCO-POL 10) and the Abu Dhabi Whole of Government Data Classification Framework. | X25: N | AA25: 100 | AB25: 0.95 | AG25: =IF(T25="Y","N","Y") -> N | AI25: 1 | AJ25: Language ID | AK25: bmalkindi@adra.gov.ae, rfmdaas@adra.gov.ae | AL25: asalmehiry@adra.gov.ae, rfmdaas@adra.gov.ae | AM25: Sprint 1
A26: old | B26: N/A | C26: N/A | D26: N/A | E26: DED_Attribute_0024 | G26: STATUS | H26: Business data element 'status' captured in the ACCELAAPP_STATUS_GROUP dataset to support operational processing, compliance tracking, and reporting | I26: Holds the 'status' business data element captured in the ACCELAAPP_STATUS_GROUP dataset to support operational processing, compliance tracking, and reporting. | J26: عنصر بيانات الأعمال 'الحالة' المسجل في مجموعة بيانات ACCELAAPP_STATUS_GROUP لدعم المعالجة التشغيلية وتتبع الامتثال وإعداد التقارير | K26: يحتوي على عنصر بيانات الأعمال 'status' المسجل في مجموعة بيانات مجموعة حالة الطلب لدعم المعالجة التشغيلية وتتبع الامتثال وإعداد التقارير. | L26: DED_Data_Table_003 | M26: Status_Lookup_Language | N26: 46202 | O26: 46267 | P26: Y | Q26: varchar | R26: 120 | S26: Y | T26: N | V26: Sensitive | W26: Reference and lookup content supporting the consistent classification and processing of Status Lookup Language records. Classified as Sensitive, consistent with the parent data asset 'Status Lookup Language' (Economic Licenses), whose unauthorised access or disclosure could have a significant impact on the privacy of licence holders and on ADRA's operations, as per the ADDED Data Classification Policy (CH-ISBCO-POL 10) and the Abu Dhabi Whole of Government Data Classification Framework. | X26: N | AA26: 100 | AB26: 0.95 | AG26: =IF(T26="Y","N","Y") -> Y | AI26: 1 | AJ26: Application Status Description (Arabic) | AK26: bmalkindi@adra.gov.ae, rfmdaas@adra.gov.ae | AL26: asalmehiry@adra.gov.ae, rfmdaas@adra.gov.ae | AM26: Sprint 1
A27: old | B27: N/A | C27: N/A | D27: N/A | E27: DED_Attribute_0025 | G27: REC_STATUS | H27: Financial status of the transaction (eg, invoiced, paid, voided, refunded) used for reconciliation and reporting | I27: Financial status of the transaction (eg, invoiced, paid, voided, refunded) used for reconciliation and reporting. | J27: الجزء الثالث من معرف التصريح أو السجل يستخدم مع أجزاء أخرى من التعريف لتحديد السجل بشكل فريد. | K27: الحالة المالية للمعاملة (مثل: مفوتر، مدفوع، ملغى، مسترد)؛ تُستخدم للتسوية وإعداد التقارير. | L27: DED_Data_Table_003 | M27: Status_Lookup_Language | N27: 46202 | O27: 46267 | P27: Y | Q27: varchar | R27: 4 | S27: N | T27: N | V27: Sensitive | W27: System-generated technical metadata (REC_STATUS) used for data-lineage tracking and record-integrity checks, without direct business or personal content. Classified as Sensitive, consistent with the parent data asset 'Status Lookup Language' (Economic Licenses), whose unauthorised access or disclosure could have a significant impact on the privacy of licence holders and on ADRA's operations, as per the ADDED Data Classification Policy (CH-ISBCO-POL 10) and the Abu Dhabi Whole of Government Data Classification Framework. | X27: N | AA27: N/A | AB27: 0.95 | AG27: =IF(T27="Y","N","Y") -> Y | AI27: 1 | AJ27: Record Status | AK27: bmalkindi@adra.gov.ae, rfmdaas@adra.gov.ae | AL27: asalmehiry@adra.gov.ae, rfmdaas@adra.gov.ae | AM27: Sprint 1
A28: old | B28: N/A | C28: N/A | D28: N/A | E28: DED_Attribute_0026 | G28: SERV_PROV_CODE | H28: Unique code identifying the service provider (agency or jurisdiction) within the Accela system | I28: Unique code identifying the service provider (agency or jurisdiction) within the Accela system. | J28: رمز فريد يحدد مقدم الخدمة (الوكالة أو الجهة القضائية) داخل نظام أكسيلا. | K28: رمز فريد يحدد مقدم الخدمة (الجهة أو الولاية القضائية) داخل نظام أكسيلا. | L28: DED_Data_Table_004 | M28: Application_Master | N28: 46202 | O28: 46267 | P28: Y | Q28: varchar | R28: 60 | S28: Y | T28: N | V28: Sensitive | W28: Uniquely identifies or cross-references Application Master records and supports traceability, auditability, and record linkage. Classified as Sensitive, consistent with the parent data asset 'Application Master' (Economic Licenses), whose unauthorised access or disclosure could have a significant impact on the privacy of licence holders and on ADRA's operations, as per the ADDED Data Classification Policy (CH-ISBCO-POL 10) and the Abu Dhabi Whole of Government Data Classification Framework. | X28: N | AA28: 100 | AB28: 0.95 | AG28: =IF(T28="Y","N","Y") -> Y | AI28: 1 | AJ28: Record Service Provider Code | AK28: bmalkindi@adra.gov.ae, rfmdaas@adra.gov.ae | AL28: asalmehiry@adra.gov.ae, rfmdaas@adra.gov.ae | AM28: Sprint 1
A29: old | B29: N/A | C29: N/A | D29: N/A | E29: DED_Attribute_0027 | G29: B1_PER_ID1 | H29: First part of the permit/record identifier used to uniquely identify a business record in Accela | I29: First part of the permit/record identifier used to uniquely identify a business record in Accela. | J29: الجزء الأول من معرف التصريح أو السجل يستخدم لتحديد السجل التجاري بشكل فريد في أكسيلا. | K29: الجزء الأول من معرف التصريح أو السجل، يُستخدم لتحديد سجل الأعمال بشكل فريد في نظام أكسيلا. | L29: DED_Data_Table_004 | M29: Application_Master | N29: 46202 | O29: 46267 | P29: N | Q29: varchar | R29: 20 | S29: Y | T29: Y | V29: Sensitive | W29: Business content of the Application Master record used in day-to-day licensing, permitting, and compliance operations. Classified as Sensitive, consistent with the parent data asset 'Application Master' (Economic Licenses), whose unauthorised access or disclosure could have a significant impact on the privacy of licence holders and on ADRA's operations, as per the ADDED Data Classification Policy (CH-ISBCO-POL 10) and the Abu Dhabi Whole of Government Data Classification Framework. | X29: N | AA29: 100 | AB29: 0.95 | AG29: =IF(T29="Y","N","Y") -> N | AI29: 1 | AJ29: Application ID | AK29: bmalkindi@adra.gov.ae, rfmdaas@adra.gov.ae | AL29: asalmehiry@adra.gov.ae, rfmdaas@adra.gov.ae | AM29: Sprint 1
A30: old | B30: N/A | C30: N/A | D30: N/A | E30: DED_Attribute_0028 | G30: B1_PER_ID2 | H30: Second part of the permit/record identifier used together with other ID parts to uniquely identify the record | I30: Second part of the permit/record identifier used together with other ID parts to uniquely identify the record. | J30: الجزء الثاني من معرف التصريح أو السجل يستخدم مع أجزاء أخرى للتعريف بالسجل بشكل فريد. | K30: الجزء الثاني من معرف التصريح أو السجل، يُستخدم مع الأجزاء الأخرى لتحديد السجل بشكل فريد. | L30: DED_Data_Table_004 | M30: Application_Master | N30: 46202 | O30: 46267 | P30: N | Q30: varchar | R30: 20 | S30: Y | T30: Y | V30: Sensitive | W30: Business content of the Application Master record used in day-to-day licensing, permitting, and compliance operations. Classified as Sensitive, consistent with the parent data asset 'Application Master' (Economic Licenses), whose unauthorised access or disclosure could have a significant impact on the privacy of licence holders and on ADRA's operations, as per the ADDED Data Classification Policy (CH-ISBCO-POL 10) and the Abu Dhabi Whole of Government Data Classification Framework. | X30: N | AA30: 100 | AB30: 0.95 | AG30: =IF(T30="Y","N","Y") -> N | AI30: 1 | AJ30: Application ID | AK30: bmalkindi@adra.gov.ae, rfmdaas@adra.gov.ae | AL30: asalmehiry@adra.gov.ae, rfmdaas@adra.gov.ae | AM30: Sprint 1
A31: old | B31: N/A | C31: N/A | D31: N/A | E31: DED_Attribute_0029 | G31: B1_PER_ID3 | H31: Third part of the permit/record identifier used together with other ID parts to uniquely identify the record | I31: Third part of the permit/record identifier used together with other ID parts to uniquely identify the record. | J31: الجزء الثالث من معرف التصريح أو السجل يستخدم مع أجزاء أخرى من التعريف لتحديد السجل بشكل فريد. | K31: الجزء الثالث من معرف التصريح أو السجل، يُستخدم مع الأجزاء الأخرى لتحديد السجل بشكل فريد. | L31: DED_Data_Table_004 | M31: Application_Master | N31: 46202 | O31: 46267 | P31: Y | Q31: varchar | R31: 20 | S31: Y | T31: N | V31: Sensitive | W31: Business content of the Application Master record used in day-to-day licensing, permitting, and compliance operations. Classified as Sensitive, consistent with the parent data asset 'Application Master' (Economic Licenses), whose unauthorised access or disclosure could have a significant impact on the privacy of licence holders and on ADRA's operations, as per the ADDED Data Classification Policy (CH-ISBCO-POL 10) and the Abu Dhabi Whole of Government Data Classification Framework. | X31: N | AA31: 100 | AB31: 0.95 | AG31: =IF(T31="Y","N","Y") -> Y | AI31: 1 | AJ31: Application ID | AK31: bmalkindi@adra.gov.ae, rfmdaas@adra.gov.ae | AL31: asalmehiry@adra.gov.ae, rfmdaas@adra.gov.ae | AM31: Sprint 1
A32: old | B32: All Module | C32: Record | D32: Group | E32: DED_Attribute_0030 | G32: B1_PER_GROUP | H32: Business data element 'record permit group' captured in the ACCELAB1PERMIT dataset to support operational processing, compliance tracking, and reporting | I32: Holds the 'record permit group' business data element captured in the ACCELAB1PERMIT dataset to support operational processing, compliance tracking, and reporting. | J32: عنصر بيانات الأعمال 'مجموعة تصريح السجل' المسجل في مجموعة بيانات ACCELAB1PERMIT لدعم المعالجة التشغيلية وتتبع الامتثال وإعداد التقارير | K32: يحتوي على عنصر بيانات الأعمال 'سجل permit group' المسجل في مجموعة بيانات تصريح B1 لدعم المعالجة التشغيلية وتتبع الامتثال وإعداد التقارير. | L32: DED_Data_Table_004 | M32: Application_Master | N32: 46202 | O32: 46267 | P32: Y | Q32: varchar | R32: 120 | S32: Y | T32: N | V32: Sensitive | W32: Business content of the Application Master record used in day-to-day licensing, permitting, and compliance operations. Classified as Sensitive, consistent with the parent data asset 'Application Master' (Economic Licenses), whose unauthorised access or disclosure could have a significant impact on the privacy of licence holders and on ADRA's operations, as per the ADDED Data Classification Policy (CH-ISBCO-POL 10) and the Abu Dhabi Whole of Government Data Classification Framework. | X32: N | AA32: 100 | AB32: 0.95 | AG32: =IF(T32="Y","N","Y") -> Y | AI32: 1 | AJ32: Application Service Group Code | AK32: bmalkindi@adra.gov.ae, rfmdaas@adra.gov.ae | AL32: asalmehiry@adra.gov.ae, rfmdaas@adra.gov.ae | AM32: Sprint 1
A33: old | B33: All Module | C33: Record | D33: Type | E33: DED_Attribute_0031 | G33: B1_PER_TYPE | H33: Business classification of the record or transaction used for routing, reporting, and applying configured business rules | I33: Business classification of the record or transaction used for routing, reporting, and applying configured business rules. | J33: تصنيف الأعمال للسجل أو المعاملة المستخدمة في التوجيه، والتقارير، وتطبيق قواعد الأعمال المكونة. | K33: تصنيف الأعمال للسجل أو المعاملة؛ يُستخدم للتوجيه وإعداد التقارير وتطبيق قواعد الأعمال المكونة. | L33: DED_Data_Table_004 | M33: Application_Master | N33: 46202 | O33: 46267 | P33: Y | Q33: varchar | R33: 120 | S33: N | T33: N | V33: Sensitive | W33: Reference and lookup content supporting the consistent classification and processing of Application Master records. Classified as Sensitive, consistent with the parent data asset 'Application Master' (Economic Licenses), whose unauthorised access or disclosure could have a significant impact on the privacy of licence holders and on ADRA's operations, as per the ADDED Data Classification Policy (CH-ISBCO-POL 10) and the Abu Dhabi Whole of Government Data Classification Framework. | X33: N | AA33: N/A | AB33: 0.95 | AG33: =IF(T33="Y","N","Y") -> Y | AI33: 1 | AJ33: Application Service Type Code | AK33: bmalkindi@adra.gov.ae, rfmdaas@adra.gov.ae | AL33: asalmehiry@adra.gov.ae, rfmdaas@adra.gov.ae | AM33: Sprint 1
A34: old | B34: All Module | C34: Record | D34: Sub type | E34: DED_Attribute_0032 | G34: B1_PER_SUB_TYPE | H34: Business classification of the record or transaction used for routing, reporting, and applying configured business rules | I34: Business classification of the record or transaction used for routing, reporting, and applying configured business rules. | J34: تصنيف الأعمال للسجل أو المعاملة المستخدمة في التوجيه، والتقارير، وتطبيق قواعد الأعمال المكونة. | K34: تصنيف الأعمال للسجل أو المعاملة؛ يُستخدم للتوجيه وإعداد التقارير وتطبيق قواعد الأعمال المكونة. | L34: DED_Data_Table_004 | M34: Application_Master | N34: 46202 | O34: 46267 | P34: Y | Q34: varchar | R34: 120 | S34: N | T34: N | V34: Sensitive | W34: Reference and lookup content supporting the consistent classification and processing of Application Master records. Classified as Sensitive, consistent with the parent data asset 'Application Master' (Economic Licenses), whose unauthorised access or disclosure could have a significant impact on the privacy of licence holders and on ADRA's operations, as per the ADDED Data Classification Policy (CH-ISBCO-POL 10) and the Abu Dhabi Whole of Government Data Classification Framework. | X34: N | AA34: N/A | AB34: 0.95 | AG34: =IF(T34="Y","N","Y") -> Y | AI34: 1 | AJ34: Application Request Type Code | AK34: bmalkindi@adra.gov.ae, rfmdaas@adra.gov.ae | AL34: asalmehiry@adra.gov.ae, rfmdaas@adra.gov.ae | AM34: Sprint 1
A35: old | B35: All Module | C35: Record | D35: Category | E35: DED_Attribute_0033 | G35: B1_PER_CATEGORY | H35: Business data element 'record permit category' captured in the ACCELAB1PERMIT dataset to support operational processing, compliance tracking, and reporting | I35: Holds the 'record permit category' business data element captured in the ACCELAB1PERMIT dataset to support operational processing, compliance tracking, and reporting. | J35: عنصر بيانات الأعمال 'فئة تصريح السجل' المسجل في مجموعة بيانات ACCELAB1PERMIT لدعم المعالجة التشغيلية وتتبع الامتثال وإعداد التقارير | K35: يحتوي على عنصر بيانات الأعمال 'سجل permit category' المسجل في مجموعة بيانات تصريح B1 لدعم المعالجة التشغيلية وتتبع الامتثال وإعداد التقارير. | L35: DED_Data_Table_004 | M35: Application_Master | N35: 46202 | O35: 46267 | P35: Y | Q35: varchar | R35: 120 | S35: Y | T35: N | V35: Sensitive | W35: Reference and lookup content supporting the consistent classification and processing of Application Master records. Classified as Sensitive, consistent with the parent data asset 'Application Master' (Economic Licenses), whose unauthorised access or disclosure could have a significant impact on the privacy of licence holders and on ADRA's operations, as per the ADDED Data Classification Policy (CH-ISBCO-POL 10) and the Abu Dhabi Whole of Government Data Classification Framework. | X35: N | AA35: 100 | AB35: 0.95 | AG35: =IF(T35="Y","N","Y") -> Y | AI35: 1 | AJ35: Application Category Code | AK35: bmalkindi@adra.gov.ae, rfmdaas@adra.gov.ae | AL35: asalmehiry@adra.gov.ae, rfmdaas@adra.gov.ae | AM35: Sprint 1
A36: old | B36: All Module | C36: Record | D36: Application Date | E36: DED_Attribute_0034 | G36: B1_FILE_DD | H36: Business data element 'record file dd' captured in the ACCELAB1PERMIT dataset to support operational processing, compliance tracking, and reporting | I36: Holds the 'record file dd' business data element captured in the ACCELAB1PERMIT dataset to support operational processing, compliance tracking, and reporting. | J36: عنصر بيانات الأعمال 'record file dd' المسجل في مجموعة بيانات ACCELAB1PERMIT لدعم المعالجة التشغيلية وتتبع الامتثال وإعداد التقارير | K36: يحتوي على عنصر بيانات الأعمال 'سجل file dd' المسجل في مجموعة بيانات تصريح B1 لدعم المعالجة التشغيلية وتتبع الامتثال وإعداد التقارير. | L36: DED_Data_Table_004 | M36: Application_Master | N36: 46202 | O36: 46267 | P36: Y | Q36: date | R36: 10 | S36: Y | T36: N | V36: Sensitive | W36: Business content of the Application Master record used in day-to-day licensing, permitting, and compliance operations. Classified as Sensitive, consistent with the parent data asset 'Application Master' (Economic Licenses), whose unauthorised access or disclosure could have a significant impact on the privacy of licence holders and on ADRA's operations, as per the ADDED Data Classification Policy (CH-ISBCO-POL 10) and the Abu Dhabi Whole of Government Data Classification Framework. | X36: N | AA36: 100 | AB36: 0.95 | AG36: =IF(T36="Y","N","Y") -> Y | AI36: 1 | AJ36: Application Submitted Date & Time | AK36: bmalkindi@adra.gov.ae, rfmdaas@adra.gov.ae | AL36: asalmehiry@adra.gov.ae, rfmdaas@adra.gov.ae | AM36: Sprint 1
A37: old | B37: N/A | C37: N/A | D37: N/A | E37: DED_Attribute_0035 | G37: REC_STATUS | H37: Financial status of the transaction (eg, invoiced, paid, voided, refunded) used for reconciliation and reporting | I37: Financial status of the transaction (eg, invoiced, paid, voided, refunded) used for reconciliation and reporting. | J37: الجزء الثالث من معرف التصريح أو السجل يستخدم مع أجزاء أخرى من التعريف لتحديد السجل بشكل فريد. | K37: الحالة المالية للمعاملة (مثل: مفوتر، مدفوع، ملغى، مسترد)؛ تُستخدم للتسوية وإعداد التقارير. | L37: DED_Data_Table_004 | M37: Application_Master | N37: 46202 | O37: 46267 | P37: Y | Q37: varchar | R37: 4 | S37: N | T37: N | V37: Sensitive | W37: System-generated technical metadata (REC_STATUS) used for data-lineage tracking and record-integrity checks, without direct business or personal content. Classified as Sensitive, consistent with the parent data asset 'Application Master' (Economic Licenses), whose unauthorised access or disclosure could have a significant impact on the privacy of licence holders and on ADRA's operations, as per the ADDED Data Classification Policy (CH-ISBCO-POL 10) and the Abu Dhabi Whole of Government Data Classification Framework. | X37: N | AA37: N/A | AB37: 0.95 | AG37: =IF(T37="Y","N","Y") -> Y | AI37: 1 | AJ37: Record Status | AK37: bmalkindi@adra.gov.ae, rfmdaas@adra.gov.ae | AL37: asalmehiry@adra.gov.ae, rfmdaas@adra.gov.ae | AM37: Sprint 1
A38: old | B38: N/A | C38: N/A | D38: N/A | E38: DED_Attribute_0036 | G38: B1_ALT_ID | H38: Alternate ID or user-friendly record number associated with the permit or business record | I38: Alternate ID or user-friendly record number associated with the permit or business record. | J38: معرّف بديل أو رقم سجل سهل الاستخدام مرتبط بالتصريح أو سجل الأعمال | K38: معرف بديل أو رقم سجل سهل القراءة المرتبط بالتصريح أو سجل الأعمال. | L38: DED_Data_Table_004 | M38: Application_Master | N38: 46202 | O38: 46267 | P38: Y | Q38: varchar | R38: 120 | S38: Y | T38: N | V38: Sensitive | W38: Uniquely identifies or cross-references Application Master records and supports traceability, auditability, and record linkage. Classified as Sensitive, consistent with the parent data asset 'Application Master' (Economic Licenses), whose unauthorised access or disclosure could have a significant impact on the privacy of licence holders and on ADRA's operations, as per the ADDED Data Classification Policy (CH-ISBCO-POL 10) and the Abu Dhabi Whole of Government Data Classification Framework. | X38: N | AA38: 100 | AB38: 0.95 | AG38: =IF(T38="Y","N","Y") -> Y | AI38: 1 | AJ38: Economic License Number | AK38: bmalkindi@adra.gov.ae, rfmdaas@adra.gov.ae | AL38: asalmehiry@adra.gov.ae, rfmdaas@adra.gov.ae | AM38: Sprint 1
A39: old | B39: N/A | C39: N/A | D39: N/A | E39: DED_Attribute_0037 | G39: SERV_PROV_CODE | H39: Unique code identifying the service provider (agency or jurisdiction) within the Accela system | I39: Unique code identifying the service provider (agency or jurisdiction) within the Accela system. | J39: رمز فريد يحدد مقدم الخدمة (الوكالة أو الجهة القضائية) داخل نظام أكسيلا. | K39: رمز فريد يحدد مقدم الخدمة (الجهة أو الولاية القضائية) داخل نظام أكسيلا. | L39: DED_Data_Table_005 | M39: License_Expiration | N39: 46202 | O39: 46267 | P39: Y | Q39: varchar | R39: 60 | S39: N | T39: N | V39: Sensitive | W39: Uniquely identifies or cross-references License Expiration records and supports traceability, auditability, and record linkage. Classified as Sensitive, consistent with the parent data asset 'License Expiration' (Economic Licenses), whose unauthorised access or disclosure could have a significant impact on the privacy of licence holders and on ADRA's operations, as per the ADDED Data Classification Policy (CH-ISBCO-POL 10) and the Abu Dhabi Whole of Government Data Classification Framework. | X39: N | AA39: N/A | AB39: 0.95 | AG39: =IF(T39="Y","N","Y") -> Y | AI39: 1 | AJ39: Record Service Provider Code | AK39: bmalkindi@adra.gov.ae, rfmdaas@adra.gov.ae | AL39: asalmehiry@adra.gov.ae, rfmdaas@adra.gov.ae | AM39: Sprint 1
A40: old | B40: N/A | C40: N/A | D40: N/A | E40: DED_Attribute_0038 | G40: B1_PER_ID1 | H40: First part of the permit/record identifier used to uniquely identify a business record in Accela | I40: First part of the permit/record identifier used to uniquely identify a business record in Accela. | J40: الجزء الأول من معرف التصريح أو السجل يستخدم لتحديد السجل التجاري بشكل فريد في أكسيلا. | K40: الجزء الأول من معرف التصريح أو السجل، يُستخدم لتحديد سجل الأعمال بشكل فريد في نظام أكسيلا. | L40: DED_Data_Table_005 | M40: License_Expiration | N40: 46202 | O40: 46267 | P40: Y | Q40: varchar | R40: 20 | S40: N | T40: N | V40: Sensitive | W40: Business content of the License Expiration record used in day-to-day licensing, permitting, and compliance operations. Classified as Sensitive, consistent with the parent data asset 'License Expiration' (Economic Licenses), whose unauthorised access or disclosure could have a significant impact on the privacy of licence holders and on ADRA's operations, as per the ADDED Data Classification Policy (CH-ISBCO-POL 10) and the Abu Dhabi Whole of Government Data Classification Framework. | X40: N | AA40: N/A | AB40: 0.95 | AG40: =IF(T40="Y","N","Y") -> Y | AI40: 1 | AJ40: Application ID | AK40: bmalkindi@adra.gov.ae, rfmdaas@adra.gov.ae | AL40: asalmehiry@adra.gov.ae, rfmdaas@adra.gov.ae | AM40: Sprint 1
A41: old | B41: N/A | C41: N/A | D41: N/A | E41: DED_Attribute_0039 | G41: B1_PER_ID2 | H41: Second part of the permit/record identifier used together with other ID parts to uniquely identify the record | I41: Second part of the permit/record identifier used together with other ID parts to uniquely identify the record. | J41: الجزء الثاني من معرف التصريح أو السجل يستخدم مع أجزاء أخرى للتعريف بالسجل بشكل فريد. | K41: الجزء الثاني من معرف التصريح أو السجل، يُستخدم مع الأجزاء الأخرى لتحديد السجل بشكل فريد. | L41: DED_Data_Table_005 | M41: License_Expiration | N41: 46202 | O41: 46267 | P41: Y | Q41: varchar | R41: 20 | S41: N | T41: N | V41: Sensitive | W41: Business content of the License Expiration record used in day-to-day licensing, permitting, and compliance operations. Classified as Sensitive, consistent with the parent data asset 'License Expiration' (Economic Licenses), whose unauthorised access or disclosure could have a significant impact on the privacy of licence holders and on ADRA's operations, as per the ADDED Data Classification Policy (CH-ISBCO-POL 10) and the Abu Dhabi Whole of Government Data Classification Framework. | X41: N | AA41: N/A | AB41: 0.95 | AG41: =IF(T41="Y","N","Y") -> Y | AI41: 1 | AJ41: Application ID | AK41: bmalkindi@adra.gov.ae, rfmdaas@adra.gov.ae | AL41: asalmehiry@adra.gov.ae, rfmdaas@adra.gov.ae | AM41: Sprint 1
A42: old | B42: N/A | C42: N/A | D42: N/A | E42: DED_Attribute_0040 | G42: B1_PER_ID3 | H42: Third part of the permit/record identifier used together with other ID parts to uniquely identify the record | I42: Third part of the permit/record identifier used together with other ID parts to uniquely identify the record. | J42: الجزء الثالث من معرف التصريح أو السجل يستخدم مع أجزاء أخرى من التعريف لتحديد السجل بشكل فريد. | K42: الجزء الثالث من معرف التصريح أو السجل، يُستخدم مع الأجزاء الأخرى لتحديد السجل بشكل فريد. | L42: DED_Data_Table_005 | M42: License_Expiration | N42: 46202 | O42: 46267 | P42: Y | Q42: varchar | R42: 20 | S42: N | T42: N | V42: Sensitive | W42: Business content of the License Expiration record used in day-to-day licensing, permitting, and compliance operations. Classified as Sensitive, consistent with the parent data asset 'License Expiration' (Economic Licenses), whose unauthorised access or disclosure could have a significant impact on the privacy of licence holders and on ADRA's operations, as per the ADDED Data Classification Policy (CH-ISBCO-POL 10) and the Abu Dhabi Whole of Government Data Classification Framework. | X42: N | AA42: N/A | AB42: 0.95 | AG42: =IF(T42="Y","N","Y") -> Y | AI42: 1 | AJ42: Application ID | AK42: bmalkindi@adra.gov.ae, rfmdaas@adra.gov.ae | AL42: asalmehiry@adra.gov.ae, rfmdaas@adra.gov.ae | AM42: Sprint 1
A43: old | B43: N/A | C43: N/A | D43: N/A | E43: DED_Attribute_0041 | G43: EXPIRATION_CODE | H43: Identifier/code for expiration code used to uniquely reference the related entity in Accela and support joins, auditing, and reporting | I43: Identifier/code for expiration code used to uniquely reference the related entity in Accela and support joins, auditing, and reporting. | J43: معرّف أو رمز الانتهاء المستخدم للإشارة بشكل فريد إلى الكيان ذي الصلة في Accela ودعم عمليات الربط والتدقيق وإعداد التقارير | K43: معرف أو رمز لـرمز انتهاء الصلاحية؛ يُستخدم للإحالة الفريدة إلى الجهة المرتبطة في نظام أكسيلا ودعم الربط والتدقيق وإعداد التقارير. | L43: DED_Data_Table_005 | M43: License_Expiration | N43: 46202 | O43: 46267 | P43: Y | Q43: varchar | R43: 120 | S43: N | T43: N | V43: Sensitive | W43: Uniquely identifies or cross-references License Expiration records and supports traceability, auditability, and record linkage. Classified as Sensitive, consistent with the parent data asset 'License Expiration' (Economic Licenses), whose unauthorised access or disclosure could have a significant impact on the privacy of licence holders and on ADRA's operations, as per the ADDED Data Classification Policy (CH-ISBCO-POL 10) and the Abu Dhabi Whole of Government Data Classification Framework. | X43: N | AA43: N/A | AB43: 0.95 | AG43: =IF(T43="Y","N","Y") -> Y | AI43: 1 | AJ43: License Expiration Rule Code | AK43: bmalkindi@adra.gov.ae, rfmdaas@adra.gov.ae | AL43: asalmehiry@adra.gov.ae, rfmdaas@adra.gov.ae | AM43: Sprint 1
A44: old | B44: All Module | C44: Renewal info | D44: expiration date | E44: DED_Attribute_0042 | G44: EXPIRATION_DATE | H44: Business date associated with this record event (creation, update, status change, or processing), used for reporting and audit tracking | I44: Business date associated with this record event (creation, update, status change, or processing), used for reporting and audit tracking. | J44: تاريخ العمل المرتبط بحدث السجل هذا (الإنشاء أو التحديث أو تغيير الحالة أو المعالجة)، ويستخدم لإعداد التقارير وتتبع التدقيق | K44: تاريخ أعمال مرتبط بحدث السجل هذا (الإنشاء أو التحديث أو تغيير الحالة أو المعالجة)؛ يُستخدم لإعداد التقارير وتتبع التدقيق. | L44: DED_Data_Table_005 | M44: License_Expiration | N44: 46202 | O44: 46267 | P44: Y | Q44: date | R44: 10 | S44: Y | T44: N | V44: Sensitive | W44: Business content of the License Expiration record used in day-to-day licensing, permitting, and compliance operations. Classified as Sensitive, consistent with the parent data asset 'License Expiration' (Economic Licenses), whose unauthorised access or disclosure could have a significant impact on the privacy of licence holders and on ADRA's operations, as per the ADDED Data Classification Policy (CH-ISBCO-POL 10) and the Abu Dhabi Whole of Government Data Classification Framework. | X44: N | AA44: 100 | AB44: 0.95 | AG44: =IF(T44="Y","N","Y") -> Y | AI44: 1 | AJ44: License Expiry Date | AK44: bmalkindi@adra.gov.ae, rfmdaas@adra.gov.ae | AL44: asalmehiry@adra.gov.ae, rfmdaas@adra.gov.ae | AM44: Sprint 1
A45: old | B45: N/A | C45: N/A | D45: N/A | E45: DED_Attribute_0043 | G45: REC_STATUS | H45: Financial status of the transaction (eg, invoiced, paid, voided, refunded) used for reconciliation and reporting | I45: Financial status of the transaction (eg, invoiced, paid, voided, refunded) used for reconciliation and reporting. | J45: الجزء الثالث من معرف التصريح أو السجل يستخدم مع أجزاء أخرى من التعريف لتحديد السجل بشكل فريد. | K45: الحالة المالية للمعاملة (مثل: مفوتر، مدفوع، ملغى، مسترد)؛ تُستخدم للتسوية وإعداد التقارير. | L45: DED_Data_Table_005 | M45: License_Expiration | N45: 46202 | O45: 46267 | P45: Y | Q45: varchar | R45: 4 | S45: N | T45: N | V45: Sensitive | W45: System-generated technical metadata (REC_STATUS) used for data-lineage tracking and record-integrity checks, without direct business or personal content. Classified as Sensitive, consistent with the parent data asset 'License Expiration' (Economic Licenses), whose unauthorised access or disclosure could have a significant impact on the privacy of licence holders and on ADRA's operations, as per the ADDED Data Classification Policy (CH-ISBCO-POL 10) and the Abu Dhabi Whole of Government Data Classification Framework. | X45: N | AA45: N/A | AB45: 0.95 | AG45: =IF(T45="Y","N","Y") -> Y | AI45: 1 | AJ45: Record Status | AK45: bmalkindi@adra.gov.ae, rfmdaas@adra.gov.ae | AL45: asalmehiry@adra.gov.ae, rfmdaas@adra.gov.ae | AM45: Sprint 1
A46: old | B46: N/A | C46: N/A | D46: N/A | E46: DED_Attribute_0044 | G46: SERV_PROV_CODE | H46: Unique code identifying the service provider (agency or jurisdiction) within the Accela system | I46: Unique code identifying the service provider (agency or jurisdiction) within the Accela system. | J46: رمز فريد يحدد مقدم الخدمة (الوكالة أو الجهة القضائية) داخل نظام أكسيلا. | K46: رمز فريد يحدد مقدم الخدمة (الجهة أو الولاية القضائية) داخل نظام أكسيلا. | L46: DED_Data_Table_006 | M46: Application_Address | N46: 46202 | O46: 46267 | P46: N | Q46: varchar | R46: 60 | S46: N | T46: Y | V46: Confidential | W46: Uniquely identifies or cross-references Application Address records and supports traceability, auditability, and record linkage. Classified as Confidential, consistent with the parent data asset 'Application Address' (Economic Licenses): it requires limited confidentiality protection due to privacy and proprietary concerns, while personal and business information is classified as Confidential by default unless a higher level is warranted, as per the ADDED Data Classification Policy (CH-ISBCO-POL 10) and the Abu Dhabi Whole of Government Data Classification Framework. | X46: N | AA46: N/A | AB46: 0.95 | AG46: =IF(T46="Y","N","Y") -> N | AI46: 1 | AJ46: Record Service Provider Code | AK46: bmalkindi@adra.gov.ae, rfmdaas@adra.gov.ae | AL46: asalmehiry@adra.gov.ae, rfmdaas@adra.gov.ae | AM46: Sprint 1
A47: old | B47: N/A | C47: N/A | D47: N/A | E47: DED_Attribute_0045 | G47: B1_PER_ID1 | H47: First part of the permit/record identifier used to uniquely identify a business record in Accela | I47: First part of the permit/record identifier used to uniquely identify a business record in Accela. | J47: الجزء الأول من معرف التصريح أو السجل يستخدم لتحديد السجل التجاري بشكل فريد في أكسيلا. | K47: الجزء الأول من معرف التصريح أو السجل، يُستخدم لتحديد سجل الأعمال بشكل فريد في نظام أكسيلا. | L47: DED_Data_Table_006 | M47: Application_Address | N47: 46202 | O47: 46267 | P47: Y | Q47: varchar | R47: 20 | S47: N | T47: N | V47: Confidential | W47: Business content of the Application Address record used in day-to-day licensing, permitting, and compliance operations. Classified as Confidential, consistent with the parent data asset 'Application Address' (Economic Licenses): it requires limited confidentiality protection due to privacy and proprietary concerns, while personal and business information is classified as Confidential by default unless a higher level is warranted, as per the ADDED Data Classification Policy (CH-ISBCO-POL 10) and the Abu Dhabi Whole of Government Data Classification Framework. | X47: N | AA47: N/A | AB47: 0.95 | AG47: =IF(T47="Y","N","Y") -> Y | AI47: 1 | AJ47: Application ID | AK47: bmalkindi@adra.gov.ae, rfmdaas@adra.gov.ae | AL47: asalmehiry@adra.gov.ae, rfmdaas@adra.gov.ae | AM47: Sprint 1
A48: old | B48: N/A | C48: N/A | D48: N/A | E48: DED_Attribute_0046 | G48: B1_PER_ID2 | H48: Second part of the permit/record identifier used together with other ID parts to uniquely identify the record | I48: Second part of the permit/record identifier used together with other ID parts to uniquely identify the record. | J48: الجزء الثاني من معرف التصريح أو السجل يستخدم مع أجزاء أخرى للتعريف بالسجل بشكل فريد. | K48: الجزء الثاني من معرف التصريح أو السجل، يُستخدم مع الأجزاء الأخرى لتحديد السجل بشكل فريد. | L48: DED_Data_Table_006 | M48: Application_Address | N48: 46202 | O48: 46267 | P48: N | Q48: varchar | R48: 20 | S48: N | T48: Y | V48: Confidential | W48: Business content of the Application Address record used in day-to-day licensing, permitting, and compliance operations. Classified as Confidential, consistent with the parent data asset 'Application Address' (Economic Licenses): it requires limited confidentiality protection due to privacy and proprietary concerns, while personal and business information is classified as Confidential by default unless a higher level is warranted, as per the ADDED Data Classification Policy (CH-ISBCO-POL 10) and the Abu Dhabi Whole of Government Data Classification Framework. | X48: N | AA48: N/A | AB48: 0.95 | AG48: =IF(T48="Y","N","Y") -> N | AI48: 1 | AJ48: Application ID | AK48: bmalkindi@adra.gov.ae, rfmdaas@adra.gov.ae | AL48: asalmehiry@adra.gov.ae, rfmdaas@adra.gov.ae | AM48: Sprint 1
