Workbook

Sheet S1
A1: DQO | B1: Rule_Title_B | C1: Purview_B | D1: Rule_Title_S | E1: Purview_S | F1: Dimension | G1: Attribute_ID | H1: Attribute_Name | I1: Asset_ID | J1: Asset_Name_B | K1: Asset_Name_S | L1: Sprint | M1: Silver Active Flag
A2: DQO-475 | B2: Completeness_Ck-Virt_Umbrella-QUANT_OF_UMBRELLAS | C2: aa58b431-1fea-459d-83b3-98de26426fd0 | D2: Completeness_Ck-Permit_Umbrella-QUANT_OF_UMBRELLAS | E2: b5b2e534-8e1e-4619-83cb-b88c11a18c92 | F2: 0 | G2: DED_Attribute_1435 | H2: quantity_of_umbrellas | I2: DED_Data_Table_106 | J2: VIRTUAL_UMBRELLA | K2: permit_umbrella | L2: 1 | M2: =VLOOKUP(E2,'Sprint 1 Silver Dump'!$B$2:$K$602,10,0) -> Active
A3: DQO-476 | B3: DatTypMatch_Ck-Virtual_Umbrella-QUANT_OF_UMBRELLAS | C3: aad26c8e-2f64-4928-927a-9f6e1de6a702 | D3: DatTypMatch_Ck-Permit_Umbrella-QUANT_OF_UMBRELLAS | E3: 7f57727a-c000-442f-ad2e-fe17f21aa1bf | F3: 0 | G3: DED_Attribute_1435 | H3: quantity_of_umbrellas | I3: DED_Data_Table_106 | J3: VIRTUAL_UMBRELLA | K3: permit_umbrella | L3: 1 | M3: =VLOOKUP(E3,'Sprint 1 Silver Dump'!$B$2:$K$602,10,0) -> Active
A4: DQO-477 | B4: NumVal_Check-Virtual_Umbrella-QUANT_OF_UMBRELLAS | C4: e6a87e09-d426-4034-afd1-dd3ca15a2681 | D4: NumVal_Check-Permit_Umbrella-QUANT_OF_UMBRELLAS | E4: 0a171573-74e2-445a-8a23-7f44a3d9f3e1 | F4: Conformity | G4: N/A | H4: quantity_of_umbrellas,rec_status | I4: DED_Data_Table_106 | J4: VIRTUAL_UMBRELLA | K4: permit_umbrella | L4: 1 | M4: =VLOOKUP(E4,'Sprint 1 Silver Dump'!$B$2:$K$602,10,0) -> Active
A5: DQO-478 | B5: Timeliness-Virtual_Umbrella | C5: 76b26652-9b1b-4271-9027-2c4064bd5158 | D5: Timeliness_metadata_gap-PU-UMBRELLA_TYPE | E5: f1af842f-fde8-4ba6-b542-07b5b94f8d3b | F5: Timeliness | G5: N/A | H5: 0 | I5: DED_Data_Table_106 | J5: VIRTUAL_UMBRELLA | K5: permit_umbrella | L5: 1 | M5: =VLOOKUP(E5,'Sprint 1 Silver Dump'!$B$2:$K$602,10,0) -> Active
A6: DQO-479 | B6: Uniqueness_Check-Virtual_Umbrella | C6: c0bc4247-36f7-4a85-9702-0ecd872d1f7e | D6: Uniqueness_Check-Permit_Umbrella | E6: 5f6a172a-0471-4ab8-9ea5-571a86e85df5 | F6: Accuracy | G6: N/A | H6: b1_per_id1,b1_per_id2,b1_per_id3,serv_prov_code,row_index | I6: DED_Data_Table_106 | J6: VIRTUAL_UMBRELLA | K6: permit_umbrella | L6: 1 | M6: =VLOOKUP(E6,'Sprint 1 Silver Dump'!$B$2:$K$602,10,0) -> Active
A7: DQO-030 | B7: Completeness_Check-Virtu_Machines-machine_address | C7: 9db2ff9c-094c-45fe-8a79-86f1a200952d | D7: Completeness_Check-IDB_Machines-machine_address | E7: 4e475072-52d3-4977-87cd-de8fa8eadbb4 | F7: 0 | G7: DED_Attribute_0939 | H7: machine_address | I7: DED_Data_Table_078 | J7: VIRTUAL_MACHINES | K7: idb_machines | L7: 1 | M7: =VLOOKUP(E7,'Sprint 1 Silver Dump'!$B$2:$K$602,10,0) -> Active
A8: DQO-029 | B8: Lead_Trail_Space_Chk-Virt_Machines-MACHINE_ADDRESS | C8: d47a7e03-9736-4dcd-bef2-97d1e3ce0238 | D8: Lead_Trail_Space_Chk-IDB_Machines-MACHINE_ADDRESS | E8: 9fb55f94-911e-4970-ab9f-4ce236c49eb0 | F8: Conformity | G8: N/A | H8: machine_address,rec_status | I8: DED_Data_Table_078 | J8: VIRTUAL_MACHINES | K8: idb_machines | L8: 1 | M8: =VLOOKUP(E8,'Sprint 1 Silver Dump'!$B$2:$K$602,10,0) -> Active
A9: DQO-028 | B9: Cons_Space_Check-Virt_Machines-MACHINE_ADDRESS | C9: ec068720-d9f5-41ed-b79a-deff906674f6 | D9: Cons_Space_Check-IDB_Machines-MACHINE_ADDRESS | E9: 393046a9-4809-4174-b69d-031d58a7872c | F9: Conformity | G9: N/A | H9: machine_address,rec_status | I9: DED_Data_Table_078 | J9: VIRTUAL_MACHINES | K9: idb_machines | L9: 1 | M9: =VLOOKUP(E9,'Sprint 1 Silver Dump'!$B$2:$K$602,10,0) -> Active
A10: DQO-027 | B10: Timeliness_Check-Virtual_Machines | C10: 8bf8d252-d4e0-422c-8e1c-85186ad1f00a | D10: Timeliness_Check-IDB_Machines | E10: a28955c5-8af2-4b4c-a764-5b24deb2cc78 | F10: 0 | G10: N/A | H10: 0 | I10: DED_Data_Table_078 | J10: VIRTUAL_MACHINES | K10: idb_machines | L10: 1 | M10: =VLOOKUP(E10,'Sprint 1 Silver Dump'!$B$2:$K$602,10,0) -> Active
A11: DQO-026 | B11: Uniqueness_Check-Virtual_Machines | C11: aae13618-05aa-44f6-ace5-66eb18fcc255 | D11: Uniqueness_Check-IDB_Machines | E11: 5dbf1e98-ca3c-424c-a6b0-a0a01bfeb857 | F11: Accuracy | G11: N/A | H11: b1_per_id1,b1_per_id2,b1_per_id3,serv_prov_code,row_index | I11: DED_Data_Table_078 | J11: VIRTUAL_MACHINES | K11: idb_machines | L11: 1 | M11: =VLOOKUP(E11,'Sprint 1 Silver Dump'!$B$2:$K$602,10,0) -> Active
A12: DQO-9022 | B12: N/A | C12: N/A | D12: Consec_Chk-IDB_Machines-machine_type | E12: e5d85e67-9b3f-4ac9-904e-995aa9714e23 | F12: Conformity | G12: N/A | H12: machine_type,rec_status | I12: DED_Data_Table_078 | J12: VIRTUAL_MACHINES | K12: idb_machines | L12: 1 | M12: =VLOOKUP(E12,'Sprint 1 Silver Dump'!$B$2:$K$602,10,0) -> Active
A13: DQO-063 | B13: Completeness_Check-Virt_ISIC_4_ACT-activity_id | C13: 18eb9cfc-5cd6-48f6-8353-7e4b50b028ba | D13: Completeness_Check-Instant_Activities-activity_id | E13: f18f671c-ee78-4ac4-b72d-a941d1736576 | F13: 0 | G13: DED_Attribute_0907 | H13: activity_id | I13: DED_Data_Table_075 | J13: VIRTUAL_ISIC_4_ACTIVITIES | K13: instant_activities | L13: 1 | M13: =VLOOKUP(E13,'Sprint 1 Silver Dump'!$B$2:$K$602,10,0) -> Active
A14: DQO-064 | B14: Cons_Space_Check-Virt_ISIC_4_ACT-ACTIVITY_ID | C14: e6b42f20-30c9-4dd6-945a-dbb4c51bee16 | D14: Cons_Space_Check-Instant_Activities-ACTIVITY_ID | E14: 8edebd26-7894-49c8-b9a5-3b3b906cfb3a | F14: Conformity | G14: N/A | H14: activity_id,rec_status | I14: DED_Data_Table_075 | J14: VIRTUAL_ISIC_4_ACTIVITIES | K14: instant_activities | L14: 1 | M14: =VLOOKUP(E14,'Sprint 1 Silver Dump'!$B$2:$K$602,10,0) -> Active
A15: DQO-065 | B15: Lead_Trail_Spc_Chk-Virt_ISIC_4_ACT-ACTIVITY_ID | C15: 8b7cb4e9-82bf-4288-841a-067909186164 | D15: Lead_Trail_Spc_Chk-Instant_Activities-ACTIVITY_ID | E15: 0bbc88d9-5221-41b2-8450-8c6a5f6c3da8 | F15: Conformity | G15: N/A | H15: activity_id,rec_status | I15: DED_Data_Table_075 | J15: VIRTUAL_ISIC_4_ACTIVITIES | K15: instant_activities | L15: 1 | M15: =VLOOKUP(E15,'Sprint 1 Silver Dump'!$B$2:$K$602,10,0) -> Active
A16: DQO-066 | B16: Num_Format_Check-Virt_ISIC_4_ACT-ACTIVITY_ID | C16: c8385d7c-dcf8-44be-a414-7de6d95a47f8 | D16: Num_Format_Check-Instant_Activities-ACTIVITY_ID | E16: 045bdaf7-d766-4d98-a1ee-a0a057fd75c4 | F16: Conformity | G16: N/A | H16: activity_id,rec_status | I16: DED_Data_Table_075 | J16: VIRTUAL_ISIC_4_ACTIVITIES | K16: instant_activities | L16: 1 | M16: =VLOOKUP(E16,'Sprint 1 Silver Dump'!$B$2:$K$602,10,0) -> Active
A17: NA | B17: N/A | C17: N/A | D17: Completeness_Check-IA-ACTIVITY_NAME_AR | E17: ccbe48c0-a4db-4a19-8500-1b23f59b84fb | F17: 0 | G17: DED_Attribute_0908 | H17: activity_name_ar | I17: DED_Data_Table_075 | J17: VIRTUAL_ISIC_4_ACTIVITIES | K17: instant_activities | L17: 1 | M17: =VLOOKUP(E17,'Sprint 1 Silver Dump'!$B$2:$K$602,10,0) -> Active
A18: DQO-067 | B18: Lead_Trail_Spc_Chk-Virt_ISIC_4_ACT-ACTIVIT_NAME_AR | C18: 725df9ee-bf43-4ee1-9f3c-b41fa0519154 | D18: Lead_Trail_Spc_Chk-Instant_Act-ACTIVITY_NAME_AR | E18: 149d84a5-4128-455b-8a0e-784caded066f | F18: Conformity | G18: N/A | H18: activity_name_ar,rec_status | I18: DED_Data_Table_075 | J18: VIRTUAL_ISIC_4_ACTIVITIES | K18: instant_activities | L18: 1 | M18: =VLOOKUP(E18,'Sprint 1 Silver Dump'!$B$2:$K$602,10,0) -> Active
A19: DQO-068 | B19: Cons_Space_Chk-Virt_ISIC_4_ACT-ACTIVITY_NAME_AR | C19: 66fe371b-5f8d-4a71-8ac6-0c6624c8e6f0 | D19: Cons_Space_Chk-Instant_Activities-ACTIVITY_NAME_AR | E19: d9f00547-454d-458a-bcad-873cf5d91871 | F19: Conformity | G19: N/A | H19: activity_name_ar,rec_status | I19: DED_Data_Table_075 | J19: VIRTUAL_ISIC_4_ACTIVITIES | K19: instant_activities | L19: 1 | M19: =VLOOKUP(E19,'Sprint 1 Silver Dump'!$B$2:$K$602,10,0) -> Active
A20: DQO-069 | B20: Str_Format_Chk-Virt_ISIC_4_ACT-activity_name_ar | C20: 8ad9d3f0-38a8-4f02-93d1-89107430304a | D20: Str_Format_Chk-Instant_Activities_activity_name_ar | E20: dae4044a-1031-49c2-a9b8-4d21f3482e8b | F20: Conformity | G20: DED_Attribute_0908 | H20: activity_name_ar | I20: DED_Data_Table_075 | J20: VIRTUAL_ISIC_4_ACTIVITIES | K20: instant_activities | L20: 1 | M20: =VLOOKUP(E20,'Sprint 1 Silver Dump'!$B$2:$K$602,10,0) -> Active
A21: DQO-070 | B21: Comp_Check-Virt_ISIC_4_ACT-activity_name_en | C21: 63805840-ddeb-4321-8200-4f0d18308071 | D21: Comp_Check-Instant_Activities-activity_name_en | E21: a6ef914f-2dff-4aa9-8c64-bfff4db6b8e4 | F21: 0 | G21: DED_Attribute_0909 | H21: activity_name_en | I21: DED_Data_Table_075 | J21: VIRTUAL_ISIC_4_ACTIVITIES | K21: instant_activities | L21: 1 | M21: =VLOOKUP(E21,'Sprint 1 Silver Dump'!$B$2:$K$602,10,0) -> Active
A22: DQO-062 | B22: Lead_Trail_Spc_Chk-Virt_ISIC_4_ACT-ACTIVIT_NAME_EN | C22: 28da1e7e-b67a-469d-81bb-4a574c19c1b5 | D22: Lead_Trail_Spc_Chk-Instant_Act-ACTIVITY_NAME_EN | E22: 4b9ad871-0c4d-4dbf-af34-230ce87145f0 | F22: Conformity | G22: N/A | H22: activity_name_en,rec_status | I22: DED_Data_Table_075 | J22: VIRTUAL_ISIC_4_ACTIVITIES | K22: instant_activities | L22: 1 | M22: =VLOOKUP(E22,'Sprint 1 Silver Dump'!$B$2:$K$602,10,0) -> Active
A23: DQO-061 | B23: Cons_Space_Check-Virt_ISIC_4_ACT-ACTIVITY_NAME_EN | C23: cef4a39f-3ebf-41f2-9566-5a0b680da4bb | D23: Cons_Space_Check-Instant_Act-ACTIVITY_NAME_EN | E23: 35216e45-be3d-4731-9bf3-0f9db269963b | F23: Conformity | G23: N/A | H23: activity_name_en,rec_status | I23: DED_Data_Table_075 | J23: VIRTUAL_ISIC_4_ACTIVITIES | K23: instant_activities | L23: 1 | M23: =VLOOKUP(E23,'Sprint 1 Silver Dump'!$B$2:$K$602,10,0) -> Active
A24: DQO-060 | B24: Str_Format_Chk-Virt_ISIC_4_ACT-activity_name_en | C24: edb58996-518d-42e2-bc67-ccd0a1514f46 | D24: Str_Format_Chk-Instant_Activities_activity_name_en | E24: b1b92031-c41a-4d7b-9919-47018eb778a9 | F24: Conformity | G24: DED_Attribute_0909 | H24: activity_name_en | I24: DED_Data_Table_075 | J24: VIRTUAL_ISIC_4_ACTIVITIES | K24: instant_activities | L24: 1 | M24: =VLOOKUP(E24,'Sprint 1 Silver Dump'!$B$2:$K$602,10,0) -> Active
A25: DQO-059 | B25: Timeliness_Check-Virtual_ISIC_4_Activities | C25: 3e5e18d4-0706-4afc-848f-a73b5eda21e3 | D25: Timeliness_Check-Instant_Activities | E25: ea183c70-3465-45e4-9e30-8b8d394aa1e4 | F25: 0 | G25: N/A | H25: 0 | I25: DED_Data_Table_075 | J25: VIRTUAL_ISIC_4_ACTIVITIES | K25: instant_activities | L25: 1 | M25: =VLOOKUP(E25,'Sprint 1 Silver Dump'!$B$2:$K$602,10,0) -> Active
A26: DQO-058 | B26: Uniqueness_Check-Virtual_ISIC_4_Activities | C26: aae16bfc-74f7-4968-b7c9-294cdb71421c | D26: Uniqueness_Check-Instant_Activities | E26: c933d847-699c-4207-91f0-07354a972d71 | F26: Accuracy | G26: N/A | H26: activity_id,b1_per_id1,b1_per_id2,b1_per_id3,serv_prov_code,row_index | I26: DED_Data_Table_075 | J26: VIRTUAL_ISIC_4_ACTIVITIES | K26: instant_activities | L26: 1 | M26: =VLOOKUP(E26,'Sprint 1 Silver Dump'!$B$2:$K$602,10,0) -> Active
A27: DQO-071 | B27: Accuracy_Chk-VIRTUAL_ISIC_4_ACTIVITIES-activity_id | C27: 1dd68e1e-5e6a-4b16-87e3-1187aaa92f8a | D27: Accuracy_Chk-Instant_Activities-activity_id | E27: 249e7ebc-3057-427c-9ca1-09336187d281 | F27: 0 | G27: DED_Attribute_0907 | H27: activity_id | I27: DED_Data_Table_075 | J27: VIRTUAL_ISIC_4_ACTIVITIES | K27: instant_activities | L27: 1 | M27: =VLOOKUP(E27,'Sprint 1 Silver Dump'!$B$2:$K$602,10,0) -> Active
A28: DQO-466 | B28: Completeness_check-Virtual_Kiosk-KIOSK_ADDRESS | C28: a826b711-1386-4e3e-8df6-6a2fea9ec5c1 | D28: Completeness_check-Permit_Kiosk-KIOSK_ADDRESS | E28: 5c0cf737-071c-4025-9549-9ff85e123c70 | F28: 0 | G28: DED_Attribute_0919 | H28: kiosk_address | I28: DED_Data_Table_076 | J28: VIRTUAL_KIOSK | K28: permit_kiosk | L28: 1 | M28: =VLOOKUP(E28,'Sprint 1 Silver Dump'!$B$2:$K$602,10,0) -> Active
A29: DQO-467 | B29: Timeliness_Check-Virtual_Kiosk | C29: 179ab191-0115-4bfe-a76d-97c4c4f4e545 | D29: Timeliness_metadata_gap-Permit_Kiosk-KIOSK_ADDRESS | E29: e87e0e8a-0361-48fd-b4cd-3c52f6c942fb | F29: Timeliness | G29: N/A | H29: 0 | I29: DED_Data_Table_076 | J29: VIRTUAL_KIOSK | K29: permit_kiosk | L29: 1 | M29: =VLOOKUP(E29,'Sprint 1 Silver Dump'!$B$2:$K$602,10,0) -> Active
A30: DQO-468 | B30: Uniqueness_Check-Virtual_Kiosk | C30: 3caecea8-dd91-4568-8ccb-3c00f4d00042 | D30: Duplicate_rows_Permit_Kiosk | E30: 4d3ee107-3204-4a48-8b13-99f5eeab6a30 | F30: Accuracy | G30: N/A | H30: b1_per_id1,b1_per_id2,b1_per_id3,serv_prov_code,row_index | I30: DED_Data_Table_076 | J30: VIRTUAL_KIOSK | K30: permit_kiosk | L30: 1 | M30: =VLOOKUP(E30,'Sprint 1 Silver Dump'!$B$2:$K$602,10,0) -> Active
A31: DQO-9026 | B31: N/A | C31: N/A | D31: Consec_Chk-Permit_Kiosk-kiosk_address | E31: 290497c3-bf36-4808-a3fb-f6588eed8073 | F31: Conformity | G31: N/A | H31: kiosk_address,rec_status | I31: DED_Data_Table_076 | J31: VIRTUAL_KIOSK | K31: permit_kiosk | L31: 1 | M31: =VLOOKUP(E31,'Sprint 1 Silver Dump'!$B$2:$K$602,10,0) -> Active
A32: DQO-048 | B32: String_check-Virt_Exempt_Change_Log-CHANGE_TYPE | C32: c49792b8-f9dc-46e1-b5b6-1837c156998d | D32: String_check-Exemption_Change_Log-CHANGE_TYPE | E32: 5252f406-f0c2-4f7a-be7e-18f4cd8add74 | F32: Conformity | G32: DED_Attribute_0833 | H32: change_type | I32: DED_Data_Table_070 | J32: VIRTUAL_EXEMPTION_CHANGE_LOG | K32: exemption_change_log | L32: 1 | M32: =VLOOKUP(E32,'Sprint 1 Silver Dump'!$B$2:$K$602,10,0) -> Active
A33: DQO-049 | B33: Completeness_chck-Virt_Exempt_Change_Log-USER_NAME | C33: 41d2a319-e29d-413c-bfd5-a951118602f5 | D33: Completeness_check-Exemption_Change_Log-USER_NAME | E33: d7b003ba-a8bc-4aee-94e7-a62a2b2335cb | F33: 0 | G33: DED_Attribute_0835 | H33: user_name | I33: DED_Data_Table_070 | J33: VIRTUAL_EXEMPTION_CHANGE_LOG | K33: exemption_change_log | L33: 1 | M33: =VLOOKUP(E33,'Sprint 1 Silver Dump'!$B$2:$K$602,10,0) -> Active
A34: DQO-050 | B34: String_check-Virt_Exempt_Change_Log-USER_NAME | C34: 79ee3154-1c3e-4730-ba05-115aab7f9e58 | D34: String_check-Exemption_Change_Log-USER_NAME | E34: 3529144f-1712-4e48-a50e-9a96493ef812 | F34: 0 | G34: DED_Attribute_0835 | H34: user_name | I34: DED_Data_Table_070 | J34: VIRTUAL_EXEMPTION_CHANGE_LOG | K34: exemption_change_log | L34: 1 | M34: =VLOOKUP(E34,'Sprint 1 Silver Dump'!$B$2:$K$602,10,0) -> Active
A35: DQO-051 | B35: Timeliness_Check-Virtual_Exempt_Change_Log | C35: 13a36151-f147-4b3a-a1d6-2841813d67a4 | D35: Timeliness_Check-Exemption_Change_Log | E35: 8d8c2e4e-3d62-4309-bf09-89f39b3761fe | F35: 0 | G35: N/A | H35: 0 | I35: DED_Data_Table_070 | J35: VIRTUAL_EXEMPTION_CHANGE_LOG | K35: exemption_change_log | L35: 1 | M35: =VLOOKUP(E35,'Sprint 1 Silver Dump'!$B$2:$K$602,10,0) -> Active
A36: DQO-052 | B36: Uniqueness_Check-Virtual_Exemption_Change_Log | C36: 609bf82a-466b-4081-9c3d-ae29d5933588 | D36: Uniqueness_Check-Exemption_Change_Log | E36: 2c730e89-72d2-4e55-a078-fa34ad27614c | F36: Accuracy | G36: N/A | H36: b1_per_id1,b1_per_id2,b1_per_id3,serv_prov_code,row_index | I36: DED_Data_Table_070 | J36: VIRTUAL_EXEMPTION_CHANGE_LOG | K36: exemption_change_log | L36: 1 | M36: =VLOOKUP(E36,'Sprint 1 Silver Dump'!$B$2:$K$602,10,0) -> Active
A37: DQO-9008 | B37: N/A | C37: N/A | D37: Completeness_Chk-Exemption_Change_Log-change_type | E37: cc832c8f-8d2b-4df7-9361-659e67ac6450 | F37: 0 | G37: DED_Attribute_0833 | H37: change_type | I37: DED_Data_Table_070 | J37: VIRTUAL_EXEMPTION_CHANGE_LOG | K37: exemption_change_log | L37: 1 | M37: =VLOOKUP(E37,'Sprint 1 Silver Dump'!$B$2:$K$602,10,0) -> Active
A38: DQO-106 | B38: Completeness_Check-R3APPTYP_I18N-r1_per_grp | C38: 49c6998d-9c83-4d52-a60d-acec71505548 | D38: Comp_Chk-applctn_Config_Language-R1_PER_GROUP | E38: 3d05cdc2-72aa-4489-a2cb-4c1b3880bf6c | F38: 0 | G38: DED_Attribute_0397 | H38: r1_per_group | I38: DED_Data_Table_038 | J38: R3APPTYP_I18N | K38: application_configuration_language | L38: 1 | M38: =VLOOKUP(E38,'Sprint 1 Silver Dump'!$B$2:$K$602,10,0) -> Active
A39: DQO-107 | B39: Comp_Chk-r3apptyp_i18n-R1_PER_SUB_TYPE | C39: f3aa7426-9d58-4f4d-9f4d-d128da75243c | D39: Comp_Chk-applctn_Config_Language-R1_PER_SUB_TYPE | E39: 7a4f724b-182c-40f6-b943-0d1e4dd93217 | F39: 0 | G39: DED_Attribute_0398 | H39: r1_per_sub_type | I39: DED_Data_Table_038 | J39: R3APPTYP_I18N | K39: application_configuration_language | L39: 1 | M39: =VLOOKUP(E39,'Sprint 1 Silver Dump'!$B$2:$K$602,10,0) -> Active
A40: DQO-108 | B40: Comp_Chk-r3apptype_i18n-R1_PER_CATEGORY | C40: e2c29501-d17d-4cf9-b0b5-5f606b6e5871 | D40: Comp_Chk-applctn_Config_Language-R1_PER_CATEGORY | E40: 5e727671-7fe9-48d7-bdc0-ad0b67acdbc1 | F40: 0 | G40: DED_Attribute_0399 | H40: r1_per_category | I40: DED_Data_Table_038 | J40: R3APPTYP_I18N | K40: application_configuration_language | L40: 1 | M40: =VLOOKUP(E40,'Sprint 1 Silver Dump'!$B$2:$K$602,10,0) -> Active
A41: DQO-109 | B41: Freshness_Chk-r3apptyp_i18n | C41: 330390cb-8a8c-4a69-b964-e7f7f6590f63 | D41: Freshness_Chk-application_Configuration_Language | E41: 2f9a4cb0-f015-4022-9d62-8f7eff28e64c | F41: 0 | G41: N/A | H41: 0 | I41: DED_Data_Table_038 | J41: R3APPTYP_I18N | K41: application_configuration_language | L41: 1 | M41: =VLOOKUP(E41,'Sprint 1 Silver Dump'!$B$2:$K$602,10,0) -> Active
A42: DQO-110 | B42: Dup_Rows_Check-r3apptyp_i18n | C42: 7ae928fc-1e7d-4fbc-92d7-ab2241a779e0 | D42: Dup_Rows_Check-application_Configuration_Language | E42: c247dcd9-ea7f-4268-8a96-101131c92353 | F42: 0 | G42: N/A | H42: lang_id,res_id,serv_prov_code | I42: DED_Data_Table_038 | J42: R3APPTYP_I18N | K42: application_configuration_language | L42: 1 | M42: =VLOOKUP(E42,'Sprint 1 Silver Dump'!$B$2:$K$602,10,0) -> Active
A43: DQO-111 | B43: Data_Val_Check-r3apptyp_i18n-R1_PER_GROUP | C43: 033f7c98-bdc7-4b86-83ab-ebf58f740a09 | D43: Data_Val_Check-applctn_Config_Lang-R1_PER_GROUP | E43: 54910cb3-0981-45e6-9b25-f526e39acf35 | F43: 0 | G43: DED_Attribute_0397 | H43: r1_per_group | I43: DED_Data_Table_038 | J43: R3APPTYP_I18N | K43: application_configuration_language | L43: 1 | M43: =VLOOKUP(E43,'Sprint 1 Silver Dump'!$B$2:$K$602,10,0) -> Active
A44: DQO-112 | B44: Format_Val_Check-r3apptyp_i18n-R1_PER_GROUP | C44: ad222f4b-e87e-4f42-a77f-b69c615f79af | D44: Fmt_Val_Check-app_Config_Language-R1_PER_GROUP | E44: a1095ed0-1363-4102-86bd-721a6d5f9948 | F44: Conformity | G44: DED_Attribute_0397 | H44: r1_per_group | I44: DED_Data_Table_038 | J44: R3APPTYP_I18N | K44: application_configuration_language | L44: 1 | M44: =VLOOKUP(E44,'Sprint 1 Silver Dump'!$B$2:$K$602,10,0) -> Active
A45: DQO-113 | B45: Data_Val_Check-r3apptyp_i18n-R1_PER_SUB_TYPE | C45: 83b6c50b-7032-4287-bc63-2793f1b9477d | D45: Data_Val_Check-applctn_Config_Lang-R1_PER_SUB_TYPE | E45: 19ce5988-52cf-4011-a567-2980763a898d | F45: 0 | G45: DED_Attribute_0398 | H45: r1_per_sub_type | I45: DED_Data_Table_038 | J45: R3APPTYP_I18N | K45: application_configuration_language | L45: 1 | M45: =VLOOKUP(E45,'Sprint 1 Silver Dump'!$B$2:$K$602,10,0) -> Active
A46: DQO-114 | B46: Fmt_Val_Check-r3apptyp_18n-R1_PER_SUB_TYPE | C46: e2443a55-2767-46e2-a52a-e1aa8e951e44 | D46: Fmt_Val_Check-applctn_Config_Lang-R1_PER_SUB_TYPE | E46: bd8d6c30-0829-4ddb-b58f-e4766fad7297 | F46: Conformity | G46: DED_Attribute_0398 | H46: r1_per_sub_type | I46: DED_Data_Table_038 | J46: R3APPTYP_I18N | K46: application_configuration_language | L46: 1 | M46: =VLOOKUP(E46,'Sprint 1 Silver Dump'!$B$2:$K$602,10,0) -> Active
A47: DQO-115 | B47: Data_Val_Check-r3apptyp_i18n-R1_PER_CATEGORY | C47: 71be119a-9fb1-4be6-8792-a22acdeb1243 | D47: Data_Val_Check-applctn_Config_Lang-R1_PER_CATEGORY | E47: fbafcd16-5b61-4a5b-a307-67d7a174bbf5 | F47: 0 | G47: DED_Attribute_0399 | H47: r1_per_category | I47: DED_Data_Table_038 | J47: R3APPTYP_I18N | K47: application_configuration_language | L47: 1 | M47: =VLOOKUP(E47,'Sprint 1 Silver Dump'!$B$2:$K$602,10,0) -> Active
A48: DQO-116 | B48: Fmt_Val_Check-r3apptyp_i18n-R1_PER_CATEGORY | C48: b8eff137-d74f-40a0-87e8-679346f512df | D48: Fmt_Val_Check-applctn_Config_Lang-R1_PER_CATEGORY | E48: 1ffdec3d-5e47-4e49-8fce-f8d2aef79dd7 | F48: Conformity | G48: DED_Attribute_0399 | H48: r1_per_category | I48: DED_Data_Table_038 | J48: R3APPTYP_I18N | K48: application_configuration_language | L48: 1 | M48: =VLOOKUP(E48,'Sprint 1 Silver Dump'!$B$2:$K$602,10,0) -> Active
A49: DQO-120 | B49: Lead_Trail_Space_Chk-r3apptyp_18n-R1_PER_GROUP | C49: cbf906f4-4536-4e50-ac6d-e4ec25a73455 | D49: Lead_Trail_Space_Chk-app_Config_Lang-R1_PER_GROUP | E49: a09b2248-c3b8-4aff-80b6-cd11abfdf0e9 | F49: Conformity | G49: N/A | H49: r1_per_group,rec_status | I49: DED_Data_Table_038 | J49: R3APPTYP_I18N | K49: application_configuration_language | L49: 1 | M49: =VLOOKUP(E49,'Sprint 1 Silver Dump'!$B$2:$K$602,10,0) -> Active
A50: DQO-121 | B50: Cons_Space_Check-r3apptype_i18n-R1_PER_GROUP | C50: ea1575e2-a453-4c81-9f66-2ed5dccb22d6 | D50: Cons_Space_Check-app_Config_Lang-R1_PER_GROUP | E50: 3b2c83e0-2fe0-4e7e-8caa-78686fae8c1d | F50: Conformity | G50: N/A | H50: r1_per_group,rec_status | I50: DED_Data_Table_038 | J50: R3APPTYP_I18N | K50: application_configuration_language | L50: 1 | M50: =VLOOKUP(E50,'Sprint 1 Silver Dump'!$B$2:$K$602,10,0) -> Active
A51: DQO-122 | B51: Lead_Trail_Spc_Chk-r3apptyp_i18n-R1_PER_SUB_TYPE | C51: 5af4e89d-caa3-42bf-89be-ee524dcc72b2 | D51: Lead_Trail_Spc_Chk-app_Config_Lang-R1_PER_SUB_TYPE | E51: bbf6de88-e887-4d3a-aba8-a609e9601946 | F51: Conformity | G51: N/A | H51: r1_per_sub_type,rec_status | I51: DED_Data_Table_038 | J51: R3APPTYP_I18N | K51: application_configuration_language | L51: 1 | M51: =VLOOKUP(E51,'Sprint 1 Silver Dump'!$B$2:$K$602,10,0) -> Active
A52: DQO-117 | B52: Cons_Space_Check-r3apptyp_18n-R1_PER_SUB_TYPE | C52: a2b3d779-19f8-4a7f-8e41-c1b50b86a61a | D52: Cons_Space_Check-app_Config_Lang-R1_PER_SUB_TYPE | E52: 43b15822-3be9-4477-974e-a93740dda3b9 | F52: Conformity | G52: N/A | H52: r1_per_sub_type,rec_status | I52: DED_Data_Table_038 | J52: R3APPTYP_I18N | K52: application_configuration_language | L52: 1 | M52: =VLOOKUP(E52,'Sprint 1 Silver Dump'!$B$2:$K$602,10,0) -> Active
A53: DQO-118 | B53: Lead_Trail_Spc_Chk-r3apptyp_18n-R1_PER_CATEGORY | C53: 9a816702-8f02-4bec-8aec-e925c2765a2f | D53: Lead_Trail_Spc_Chk-app_Config_Lang-R1_PER_CATEGORY | E53: bb452ada-6218-4fa9-9ff5-7ab791887dfe | F53: Conformity | G53: N/A | H53: r1_per_category,rec_status | I53: DED_Data_Table_038 | J53: R3APPTYP_I18N | K53: application_configuration_language | L53: 1 | M53: =VLOOKUP(E53,'Sprint 1 Silver Dump'!$B$2:$K$602,10,0) -> Active
A54: DQO-119 | B54: Cons_Space_Check-r3apptyp_i18n-R1_PER_CATEGORY | C54: f736360e-4e3d-45fb-8301-7c3a0a3700d9 | D54: Cons_Space_Check-app_Config_Lang-R1_PER_CATEGORY | E54: 7582f5d2-92dd-459e-8692-78d3185b4c0a | F54: Conformity | G54: N/A | H54: r1_per_category,rec_status | I54: DED_Data_Table_038 | J54: R3APPTYP_I18N | K54: application_configuration_language | L54: 1 | M54: =VLOOKUP(E54,'Sprint 1 Silver Dump'!$B$2:$K$602,10,0) -> Active
A55: NA | B55: N/A | C55: N/A | D55: Accuracy_Chk-app_Config_Lang-R1_PER_SUB_TYPE | E55: 132d9364-fe6c-4450-8f8a-ca8d76c74f61 | F55: 0 | G55: DED_Attribute_0398 | H55: r1_per_sub_type | I55: DED_Data_Table_038 | J55: R3APPTYP_I18N | K55: application_configuration_language | L55: 1 | M55: =VLOOKUP(E55,'Sprint 1 Silver Dump'!$B$2:$K$602,10,0) -> Disabled
A56: DQO-175 | B56: Freshness_Check-Virtual_Balloons | C56: b22b50e7-a92b-4538-b8e0-93bf2597a87b | D56: Freshness_Check-Permit_Balloons | E56: 4736159d-40de-420f-aa0b-18582ed9176f | F56: 0 | G56: N/A | H56: 0 | I56: DED_Data_Table_060 | J56: VIRTUAL_BALLOONS | K56: permit_balloons | L56: 1 | M56: =VLOOKUP(E56,'Sprint 1 Silver Dump'!$B$2:$K$602,10,0) -> Active
A57: DQO-176 | B57: Duplicate_Rows_Check-Virtual_Balloons | C57: 4510871f-88af-4a5e-af18-262b189292f4 | D57: Duplicate_Rows_Check-Permit_Balloons | E57: 8eeb6105-5b44-490b-bb4f-5616ad0df01b | F57: Accuracy | G57: N/A | H57: b1_per_id1,b1_per_id2,b1_per_id3,serv_prov_code,show_dates,row_index | I57: DED_Data_Table_060 | J57: VIRTUAL_BALLOONS | K57: permit_balloons | L57: 1 | M57: =VLOOKUP(E57,'Sprint 1 Silver Dump'!$B$2:$K$602,10,0) -> Active
A58: NA | B58: N/A | C58: N/A | D58: Completeness_Check-balloons-balloons_address | E58: 326df206-68a9-478b-8dc1-73f485bd6d58 | F58: 0 | G58: DED_Attribute_0607 | H58: balloons_address | I58: DED_Data_Table_060 | J58: VIRTUAL_BALLOONS | K58: permit_balloons | L58: 1 | M58: =VLOOKUP(E58,'Sprint 1 Silver Dump'!$B$2:$K$602,10,0) -> Disabled
A59: DQO-483 | B59: Data_Type_Check-Virtual_Balloons-balloons_address | C59: 012eb193-82e4-4320-abc0-a9dad2cae7c2 | D59: Data_Type_Check-Permit_Balloons-balloons_address | E59: a3b1c221-ef50-4a58-887f-1306b81c1083 | F59: 0 | G59: DED_Attribute_0607 | H59: balloons_address | I59: DED_Data_Table_060 | J59: VIRTUAL_BALLOONS | K59: permit_balloons | L59: 1 | M59: =VLOOKUP(E59,'Sprint 1 Silver Dump'!$B$2:$K$602,10,0) -> Active
A60: DQO-177 | B60: Comp_Check-Virtual_Balloons-SHOW_DATES | C60: c449d461-cded-4fa9-87f8-af90db8880aa | D60: Comp_Check-Permit_Balloons-show_dates | E60: 0018d977-0acf-4cc9-9db0-80667c36d509 | F60: 0 | G60: DED_Attribute_0611 | H60: show_dates | I60: DED_Data_Table_060 | J60: VIRTUAL_BALLOONS | K60: permit_balloons | L60: 1 | M60: =VLOOKUP(E60,'Sprint 1 Silver Dump'!$B$2:$K$602,10,0) -> Active
A61: DQO-178 | B61: Data_Type_Check-Virtual_Balloons-SHOW_DATES | C61: 8db620ff-a183-4a83-8824-6ca9749d067f | D61: Data_Type_Check-Permit_Balloons-SHOW_DATES | E61: f6e7e557-c7c1-4a11-b2fa-9cc90f49dad6 | F61: 0 | G61: DED_Attribute_0611 | H61: show_dates | I61: DED_Data_Table_060 | J61: VIRTUAL_BALLOONS | K61: permit_balloons | L61: 1 | M61: =VLOOKUP(E61,'Sprint 1 Silver Dump'!$B$2:$K$602,10,0) -> Active
A62: DQO-9025 | B62: N/A | C62: N/A | D62: Consec_Chk-Permit_Balloons-balloons_address | E62: ce4022b4-16b6-465e-85ca-4477c66c53ab | F62: Conformity | G62: N/A | H62: balloons_address,rec_status | I62: DED_Data_Table_060 | J62: VIRTUAL_BALLOONS | K62: permit_balloons | L62: 1 | M62: =VLOOKUP(E62,'Sprint 1 Silver Dump'!$B$2:$K$602,10,0) -> Active
A63: DQO-157 | B63: Freshness_Check-Virtual_Air | C63: bcfaf63d-fd1a-478b-8fae-97d8f9e40b2c | D63: Freshness_Check-Permit_Air | E63: eceeb5a4-55c7-44d4-96bf-6fb50627febe | F63: 0 | G63: N/A | H63: 0 | I63: DED_Data_Table_056 | J63: VIRTUAL_AIR | K63: permit_air | L63: 1 | M63: =VLOOKUP(E63,'Sprint 1 Silver Dump'!$B$2:$K$602,10,0) -> Active
A64: DQO-158 | B64: Duplicate_Rows_Check-Virtual_Air | C64: 1bb9fd78-e1ca-4400-9c50-cf6781508cad | D64: Duplicate_Rows_Check-Permit_Air | E64: 4df07bf0-04fa-49a2-b371-d58291e70b13 | F64: Accuracy | G64: N/A | H64: b1_per_id1,b1_per_id2,b1_per_id3,serv_prov_code,row_index | I64: DED_Data_Table_056 | J64: VIRTUAL_AIR | K64: permit_air | L64: 1 | M64: =VLOOKUP(E64,'Sprint 1 Silver Dump'!$B$2:$K$602,10,0) -> Active
A65: DQO-159 | B65: Comp_Check-Virtual_Air-AIR_AD_TYPE | C65: 44b00ba4-e079-4209-b51a-7ea993f429c1 | D65: Comp_Check-Permit_Air-AIR_AD_TYPE | E65: 6fc625a6-d4a3-4533-bede-f2b0bd032bcc | F65: 0 | G65: DED_Attribute_0543 | H65: air_ad_type | I65: DED_Data_Table_056 | J65: VIRTUAL_AIR | K65: permit_air | L65: 1 | M65: =VLOOKUP(E65,'Sprint 1 Silver Dump'!$B$2:$K$602,10,0) -> Active
A66: DQO-160 | B66: Data_Type_Check-Virtual_Air-AIR_AD_TYPE | C66: 600b4881-2e5d-4e82-90b6-a4895a5b00bf | D66: Data_Type_Check-Permit_Air-AIR_AD_TYPE | E66: 5830b54d-a1fb-4d28-8f9b-ef12e64d6823 | F66: 0 | G66: DED_Attribute_0543 | H66: air_ad_type | I66: DED_Data_Table_056 | J66: VIRTUAL_AIR | K66: permit_air | L66: 1 | M66: =VLOOKUP(E66,'Sprint 1 Silver Dump'!$B$2:$K$602,10,0) -> Active
A67: DQO-161 | B67: Completeness_Check-Virtual_Air-SHOW_DATES | C67: 5071d203-065d-40cf-87f2-8597240f1bdd | D67: Completeness_Check-Permit_Air-SHOW_DATES | E67: 4e6a52f3-24df-4c9b-9dfc-7e08278bdd90 | F67: 0 | G67: DED_Attribute_0547 | H67: show_dates | I67: DED_Data_Table_056 | J67: VIRTUAL_AIR | K67: permit_air | L67: 1 | M67: =VLOOKUP(E67,'Sprint 1 Silver Dump'!$B$2:$K$602,10,0) -> Active
A68: DQO-162 | B68: Data_Type_Check-Virtual_Air-SHOW_DATES | C68: 6a977b55-d4c8-4121-ab01-41b9683b2fc0 | D68: Data_Type_Check-Permit_Air-SHOW_DATES | E68: 34ee9e87-3525-4a59-9171-1b10f6f5db6c | F68: 0 | G68: DED_Attribute_0547 | H68: show_dates | I68: DED_Data_Table_056 | J68: VIRTUAL_AIR | K68: permit_air | L68: 1 | M68: =VLOOKUP(E68,'Sprint 1 Silver Dump'!$B$2:$K$602,10,0) -> Active
A69: DQO-053 | B69: Completeness_chck-Virt_InspectCoordinates-DATETIME | C69: af6d8b90-7c92-48e4-9d6c-a673d6710033 | D69: Completeness_check-Inspector_Coordinates-DATETIME | E69: 60eebaf0-3fbc-4d07-bccc-b609fea27773 | F69: 0 | G69: DED_Attribute_0896 | H69: datetime | I69: DED_Data_Table_074 | J69: VIRTUAL_INSPECTORCOORDINATES | K69: inspector_coordinates | L69: 1 | M69: =VLOOKUP(E69,'Sprint 1 Silver Dump'!$B$2:$K$602,10,0) -> Active
A70: DQO-054 | B70: DataTypeValid_Chck-Virt_InspCoordinates-DATETIME | C70: c3623533-fce4-4fb6-921d-fc2c8d5255af | D70: DataTypeValid_Check-Inspector_Coordinates-DATETIME | E70: 09abb4cf-4305-4b5e-9ac6-16a079482a1c | F70: 0 | G70: DED_Attribute_0896 | H70: datetime | I70: DED_Data_Table_074 | J70: VIRTUAL_INSPECTORCOORDINATES | K70: inspector_coordinates | L70: 1 | M70: =VLOOKUP(E70,'Sprint 1 Silver Dump'!$B$2:$K$602,10,0) -> Active
A71: DQO-055 | B71: Timeliness_Check-Virtual_InspectorCoordinates | C71: bc0fbb7a-2532-4458-aaa6-6a3bf27ed275 | D71: Timeliness_Check-Inspector_Coordinates | E71: 3a6d419b-9e38-4efe-b7c8-7f3a64175792 | F71: Timeliness | G71: N/A | H71: 0 | I71: DED_Data_Table_074 | J71: VIRTUAL_INSPECTORCOORDINATES | K71: inspector_coordinates | L71: 1 | M71: =VLOOKUP(E71,'Sprint 1 Silver Dump'!$B$2:$K$602,10,0) -> Active
A72: DQO-056 | B72: Dup_rows_Uniqueness_Check-Virtual_InspCoordinates | C72: 26371c5c-3c16-4261-86bb-041aac90d065 | D72: Uniqueness_Check-Inspector_Coordinates | E72: b7124a1b-10e7-4a0d-b6a8-80f36eed657e | F72: Accuracy | G72: N/A | H72: b1_per_id1,b1_per_id2,b1_per_id3,serv_prov_code,row_index | I72: DED_Data_Table_074 | J72: VIRTUAL_INSPECTORCOORDINATES | K72: inspector_coordinates | L72: 1 | M72: =VLOOKUP(E72,'Sprint 1 Silver Dump'!$B$2:$K$602,10,0) -> Active
A73: DQO-057 | B73: DateValid_Check-Virt_InspectorCoordinates-DATETIME | C73: 1cb09815-2ac8-4576-9aea-9d1bccac9ecf | D73: DateValid_Check-Inspector_Coordinates-DATETIME | E73: 9fc0a3e5-e36c-45bb-a249-b0f43802b9e9 | F73: 0 | G73: DED_Attribute_0896 | H73: datetime | I73: DED_Data_Table_074 | J73: VIRTUAL_INSPECTORCOORDINATES | K73: inspector_coordinates | L73: 1 | M73: =VLOOKUP(E73,'Sprint 1 Silver Dump'!$B$2:$K$602,10,0) -> Active
A74: DQO-217 | B74: Cus_Allow_Val_Chk-APP_STATUS_GROUP-SERV_PROV_CODE | C74: 2fc3f137-a58d-45c1-8ff7-554d6c85222e | D74: Cus_Allow_Val_Chk-status_lookup-serv_prov_code | E74: fbebba0c-1dbe-4e32-9012-4397d0843136 | F74: Conformity | G74: N/A | H74: serv_prov_code,rec_status | I74: DED_Data_Table_002 | J74: APP_STATUS_GROUP | K74: status_lookup | L74: 1 | M74: =VLOOKUP(E74,'Sprint 1 Silver Dump'!$B$2:$K$602,10,0) -> Active
A75: DQO-218 | B75: Completeness_Check-APP_STATUS_GROUP-SERV_PROV_CODE | C75: 90536ccc-3a47-46b3-a82f-0b8c9f0c9da4 | D75: Completeness_Check-status_lookup-serv-prov-code | E75: eaf38526-585f-4382-9e68-84a321f3d459 | F75: 0 | G75: DED_Attribute_0019 | H75: serv_prov_code | I75: DED_Data_Table_002 | J75: APP_STATUS_GROUP | K75: status_lookup | L75: 1 | M75: =VLOOKUP(E75,'Sprint 1 Silver Dump'!$B$2:$K$602,10,0) -> Active
A76: DQO-219 | B76: Completeness_Check-APP_STATUS_GROUP-STATUS | C76: 490f82d6-f146-4f11-a8cb-2cc7d3f32a14 | D76: Completeness_Check-status-lookup-status | E76: 3f6e9cce-d832-4b48-84ec-fcd4e742e4f1 | F76: 0 | G76: DED_Attribute_0017 | H76: status | I76: DED_Data_Table_002 | J76: APP_STATUS_GROUP | K76: status_lookup | L76: 1 | M76: =VLOOKUP(E76,'Sprint 1 Silver Dump'!$B$2:$K$602,10,0) -> Active
A77: DQO-220 | B77: Data_Validity_Check-APP_STATUS_GROUP-STATUS | C77: fa8023d3-b018-45af-9dc0-96115f5aecfa | D77: Data_Validity_Check-status_lookup-status | E77: 78ab3718-da96-4bad-909b-aabc959ece70 | F77: Consistency | G77: DED_Attribute_0017 | H77: status | I77: DED_Data_Table_002 | J77: APP_STATUS_GROUP | K77: status_lookup | L77: 1 | M77: =VLOOKUP(E77,'Sprint 1 Silver Dump'!$B$2:$K$602,10,0) -> Active
A78: DQO-221 | B78: Duplicate_Rows_Check-APP_STATUS_GROUP | C78: ca7e7c24-2710-44d5-988b-5b4944f6b55f | D78: Duplicate_Rows_Check-status_lookup | E78: 96c10d6f-7f71-4852-993b-63bd08790dcb | F78: Accuracy | G78: N/A | H78: serv_prov_code,status,app_status_group_code | I78: DED_Data_Table_002 | J78: APP_STATUS_GROUP | K78: status_lookup | L78: 1 | M78: =VLOOKUP(E78,'Sprint 1 Silver Dump'!$B$2:$K$602,10,0) -> Active
A79: DQO-222 | B79: String_Format_Check-APP_STATUS_GROUP-STATUS | C79: 2fdee6f1-865f-411f-a684-5ab42bc5a2b6 | D79: String_Format_Check-status_lookup-status | E79: 384d3302-ef2e-4649-a880-5a68b29917ab | F79: Conformity | G79: DED_Attribute_0017 | H79: status | I79: DED_Data_Table_002 | J79: APP_STATUS_GROUP | K79: status_lookup | L79: 1 | M79: =VLOOKUP(E79,'Sprint 1 Silver Dump'!$B$2:$K$602,10,0) -> Active
A80: DQO-223 | B80: Data_Val_Chk-APP_STATUS_GROUP-SERV_PROV_CODE | C80: 00c65898-58e1-47f3-b605-0d078930188c | D80: Data_Val_Chk-status_lookup-serv_prov_code | E80: 2cfec829-7f5e-498b-a7f7-9e47677c6bc3 | F80: 0 | G80: DED_Attribute_0019 | H80: serv_prov_code | I80: DED_Data_Table_002 | J80: APP_STATUS_GROUP | K80: status_lookup | L80: 1 | M80: =VLOOKUP(E80,'Sprint 1 Silver Dump'!$B$2:$K$602,10,0) -> Active
A81: DQO-224 | B81: Str_Check-APP_STATUS_GROUP-SERV_PROV_CODE | C81: 80a46cf3-06c7-4a66-b4a8-d55bb0513d8f | D81: Str_Check-status_lookup-serv_prov_code | E81: 4e826247-6f90-442b-afa7-d316a3e1d9f7 | F81: Conformity | G81: N/A | H81: serv_prov_code,rec_status | I81: DED_Data_Table_002 | J81: APP_STATUS_GROUP | K81: status_lookup | L81: 1 | M81: =VLOOKUP(E81,'Sprint 1 Silver Dump'!$B$2:$K$602,10,0) -> Active
A82: DQO-225 | B82: Freshness_Check-APP_STATUS_GROUP | C82: c99aa7d3-ef82-4353-9377-dfed209c5f4d | D82: Freshness_Check-status_lookup | E82: 4adf104c-e210-40eb-86d4-f11a61aae761 | F82: Timeliness | G82: N/A | H82: 0 | I82: DED_Data_Table_002 | J82: APP_STATUS_GROUP | K82: status_lookup | L82: 1 | M82: =VLOOKUP(E82,'Sprint 1 Silver Dump'!$B$2:$K$602,10,0) -> Active
A83: DQO-227 | B83: Completeness_Chk-APP_STAT_GP-APP_STATUS_GROUP_CODE | C83: 177c164b-dff0-4bf9-9b6f-b4e1b0207a3a | D83: Completeness_Chk-Stat_Lookup-APP_STATUS_GROUP_CODE | E83: 698bb391-591a-417a-ab72-5338c7c265cd | F83: Completeness | G83: DED_Attribute_0016 | H83: app_status_group_code | I83: DED_Data_Table_002 | J83: APP_STATUS_GROUP | K83: status_lookup | L83: 1 | M83: =VLOOKUP(E83,'Sprint 1 Silver Dump'!$B$2:$K$602,10,0) -> Active
A84: DQO-226 | B84: Validity_Chk-APP_STAT_GP-APP_STATUS_GROUP_CODE | C84: 6e8a7aba-a065-4589-9803-58dbeb77e7c2 | D84: Validity_Chk-Status_Lookup-APP_STATUS_GROUP_CODE | E84: a2b86782-b81d-4eb6-bc6a-8fbb931b79a9 | F84: Conformity | G84: DED_Attribute_0016 | H84: app_status_group_code | I84: DED_Data_Table_002 | J84: APP_STATUS_GROUP | K84: status_lookup | L84: 1 | M84: =VLOOKUP(E84,'Sprint 1 Silver Dump'!$B$2:$K$602,10,0) -> Active
A85: DQO-493 | B85: N/A | C85: N/A | D85: Accuracy_Check-Status_Lookup-STATUS | E85: fcde947a-4b1b-4804-9a23-4f03e6a16904 | F85: 0 | G85: DED_Attribute_0017 | H85: status | I85: DED_Data_Table_002 | J85: APP_STATUS_GROUP | K85: status_lookup | L85: 1 | M85: =VLOOKUP(E85,'Sprint 1 Silver Dump'!$B$2:$K$602,10,0) -> Disabled
A86: DQO-238 | B86: Completeness_Check-APP_STATUS_GROUP_I18N-LANG_ID | C86: 097dc2a5-9022-4206-bc29-2a6891c7ef9f | D86: Completeness_Check-Status_Lookup_Language-lang_id | E86: 99fd2a81-44ef-4a01-9cfd-d092c0227ba7 | F86: 0 | G86: DED_Attribute_0023 | H86: lang_id | I86: DED_Data_Table_003 | J86: APP_STATUS_GROUP_I18N | K86: status_lookup_language | L86: 1 | M86: =VLOOKUP(E86,'Sprint 1 Silver Dump'!$B$2:$K$602,10,0) -> Active
A87: DQO-239 | B87: Completeness_Check-APP_STATUS_GROUP_I18N-RES_ID | C87: b7bf4305-14c7-4b60-aa84-b36e3c10ecdc | D87: Completeness_Check-Status_Lookup_Language-RES_ID | E87: a1bf6c71-f317-4159-a4fe-75d86f072de7 | F87: 0 | G87: DED_Attribute_0022 | H87: res_id | I87: DED_Data_Table_003 | J87: APP_STATUS_GROUP_I18N | K87: status_lookup_language | L87: 1 | M87: =VLOOKUP(E87,'Sprint 1 Silver Dump'!$B$2:$K$602,10,0) -> Active
A88: DQO-240 | B88: Data_Validity_Check-APP_STATUS_GROUP_I18N-RES_ID | C88: 0c5de629-a1ef-4b77-8074-c4997ad975ae | D88: Data_Validity_Check-Status_Lookup_Language-RES_ID | E88: 426305da-c4e0-4e37-93a2-66971640d212 | F88: 0 | G88: DED_Attribute_0022 | H88: res_id | I88: DED_Data_Table_003 | J88: APP_STATUS_GROUP_I18N | K88: status_lookup_language | L88: 1 | M88: =VLOOKUP(E88,'Sprint 1 Silver Dump'!$B$2:$K$602,10,0) -> Active
A89: DQO-241 | B89: Num_Val_Check-APP_STATUS_GROUP_I18N-RES_ID | C89: e35c0863-a460-4e46-ae1f-d1ad43df7a9a | D89: Num_Val_Check-Status_Lookup_Language-RES_ID | E89: ba6b58e3-4c09-4b68-bd92-ae3fc2591b96 | F89: Conformity | G89: N/A | H89: res_id,rec_status | I89: DED_Data_Table_003 | J89: APP_STATUS_GROUP_I18N | K89: status_lookup_language | L89: 1 | M89: =VLOOKUP(E89,'Sprint 1 Silver Dump'!$B$2:$K$602,10,0) -> Active
A90: DQO-242 | B90: APP_STATUS_GROUP_I18N-LANG_ID-AllowedValues | C90: afab7a45-454a-4d36-a41f-fad5492b9617 | D90: String_Format_Check-Status_Lookup_Language-LAN_ID | E90: 4defcb72-fc6f-4234-89e8-23135413d0bf | F90: Conformity | G90: N/A | H90: lang_id,rec_status | I90: DED_Data_Table_003 | J90: APP_STATUS_GROUP_I18N | K90: status_lookup_language | L90: 1 | M90: =VLOOKUP(E90,'Sprint 1 Silver Dump'!$B$2:$K$602,10,0) -> Active
A91: DQO-243 | B91: Completeness_Check-APP_STATUS_GROUP_I18N-STATUS | C91: 7ddd8841-3457-40d0-8ddb-b49b68f16fb0 | D91: Completeness_Check-Status_Lookup_Language-STATUS | E91: f2b601fa-6e66-419f-91ca-42480e542666 | F91: 0 | G91: DED_Attribute_0024 | H91: status | I91: DED_Data_Table_003 | J91: APP_STATUS_GROUP_I18N | K91: status_lookup_language | L91: 1 | M91: =VLOOKUP(E91,'Sprint 1 Silver Dump'!$B$2:$K$602,10,0) -> Active
A92: DQO-244 | B92: Data_Validity_Check-APP_STATUS_GROUP_I18N-STATUS | C92: 2d16c59b-da17-4d8a-acf6-4c641bebccb5 | D92: Data_Validity_Check-Status_Lookup_Language-STATUS | E92: 6c594b21-d671-4f87-bc46-ff353ec56657 | F92: 0 | G92: DED_Attribute_0024 | H92: status | I92: DED_Data_Table_003 | J92: APP_STATUS_GROUP_I18N | K92: status_lookup_language | L92: 1 | M92: =VLOOKUP(E92,'Sprint 1 Silver Dump'!$B$2:$K$602,10,0) -> Active
A93: DQO-245 | B93: String_Format_Check-APP_STATUS_GROUP_I18N-STATUS | C93: 968b0869-072f-4c05-a3d2-9ae1a7278694 | D93: String_Format_Check-Status_Lookup_Language-STATUS | E93: 41f2960d-3440-4926-ad1d-1d7d1999587a | F93: Conformity | G93: N/A | H93: status,rec_status | I93: DED_Data_Table_003 | J93: APP_STATUS_GROUP_I18N | K93: status_lookup_language | L93: 1 | M93: =VLOOKUP(E93,'Sprint 1 Silver Dump'!$B$2:$K$602,10,0) -> Active
A94: NA | B94: N/A | C94: N/A | D94: Ref_Lookup_Check-Status_Lookup_Language-STATUS | E94: f401766d-272c-46a6-bc4a-c9c5299b6576 | F94: 0 | G94: DED_Attribute_0024 | H94: status | I94: DED_Data_Table_003 | J94: APP_STATUS_GROUP_I18N | K94: status_lookup_language | L94: 1 | M94: =VLOOKUP(E94,'Sprint 1 Silver Dump'!$B$2:$K$602,10,0) -> Disabled
A95: DQO-246 | B95: APP_STATUS_GROUP_I18N-RES_ID&LANG_ID-Duplicate | C95: c876c3d2-e028-4395-9fcc-82a612d19b24 | D95: Duplicate_Check-Status_Lookup_Language | E95: 67aeb19c-c1c7-40da-abc2-2e4ab53c7fac | F95: 0 | G95: N/A | H95: res_id,lang_id | I95: DED_Data_Table_003 | J95: APP_STATUS_GROUP_I18N | K95: status_lookup_language | L95: 1 | M95: =VLOOKUP(E95,'Sprint 1 Silver Dump'!$B$2:$K$602,10,0) -> Active
A96: DQO-247 | B96: Freshness_Check-APP_STATUS_GROUP_I18N | C96: 1c48404c-9542-4cf9-9438-8dbb48e3db85 | D96: Freshness_Check-Status_Lookup_Language | E96: 466ab382-6ae3-4f8d-aa1e-06cad783f66c | F96: 0 | G96: N/A | H96: 0 | I96: DED_Data_Table_003 | J96: APP_STATUS_GROUP_I18N | K96: status_lookup_language | L96: 1 | M96: =VLOOKUP(E96,'Sprint 1 Silver Dump'!$B$2:$K$602,10,0) -> Active
A97: DQO-250 | B97: Table_lookup-APP_STATUS_GRP_I18-res_id | C97: abc58c13-5b29-4406-8509-f8143646fd2a | D97: Table_lookup_Check-Status_Lookup_Language-res_id | E97: 5c26b732-8b57-4eee-8b45-26038cd009f1 | F97: 0 | G97: DED_Attribute_0022 | H97: res_id | I97: DED_Data_Table_003 | J97: APP_STATUS_GROUP_I18N | K97: status_lookup_language | L97: 1 | M97: =VLOOKUP(E97,'Sprint 1 Silver Dump'!$B$2:$K$602,10,0) -> Active
A98: DQO-249 | B98: APP_STATUS_GROUP_I18N-STATUS-LangCheckAr | C98: b4f41f91-9e8a-4cff-bc54-3a05e204e9b3 | D98: CustomCheck-status_lkp_lang-status_lang | E98: bad2f0df-2b36-4fe5-9ad3-7ac22bc5609f | F98: Conformity | G98: N/A | H98: lang_id,status,rec_status | I98: DED_Data_Table_003 | J98: APP_STATUS_GROUP_I18N | K98: status_lookup_language | L98: 1 | M98: =VLOOKUP(E98,'Sprint 1 Silver Dump'!$B$2:$K$602,10,0) -> Active
A99: DQO-248 | B99: APP_STATUS_GROUP_I18N-STATUS-LangCheckEn | C99: 527d335c-6c5a-4e9d-8f67-30e9f7ba0e1e | D99: CustomCheck-status_lkp_lang-status_lang1 | E99: de1bfbfb-c914-40b7-aa68-d5f3d82c09a4 | F99: Conformity | G99: N/A | H99: lang_id,status,rec_status | I99: DED_Data_Table_003 | J99: APP_STATUS_GROUP_I18N | K99: status_lookup_language | L99: 1 | M99: =VLOOKUP(E99,'Sprint 1 Silver Dump'!$B$2:$K$602,10,0) -> Active
A100: DQO-415 | B100: Completeness-F4FEEITEM_AUDIT_TRAIL-FEEITEM_SEQ_NBR | C100: d9a95b03-5732-42f8-8b37-a3e2cb3b5ab1 | D100: Completeness-APPLICATION_FEE_AUDIT-FEEITEM_SEQ_NBR | E100: f2cc3953-404f-42ba-8934-023889ee494f | F100: Completeness | G100: DED_Attribute_0201 | H100: feeitem_seq_nbr | I100: DED_Data_Table_020 | J100: F4FEEITEM_AUDIT_TRAIL | K100: application_fee_audit | L100: 1 | M100: =VLOOKUP(E100,'Sprint 1 Silver Dump'!$B$2:$K$602,10,0) -> Active
...

Sheet S2
A1: DQO | B1: Rule_Title_B | C1: Purview_B | D1: Rule_Title_S | E1: Purview_S | F1: Dimension | G1: Attribute_ID | H1: Attribute_Name_From-Rule_Book | I1: Attribute_Name from file | J1: Asset_ID | K1: Asset_Name_B | L1: Asset_Name_S | M1: Sprint
A2: DQO-1060 | B2: Compl_Chk-V_BUSINESS_INTERESTS_OF_-source_of_pep | C2: 875b0bba-fcc6-4c39-9cc4-20103fd16258 | D2: Compl_Chk-RB_Business_Interests-source_of_pep | E2: cf9d3b0b-3b73-4c45-bc4e-7c312acad10b | F2: Completeness | G2: DED_Attribute_0726 | H2: source_of_pep | I2: source_of_pep,rec_status | J2: DED_Data_Table_063 | K2: VIRTUAL_BUSINESS_INTERESTS_OF_ | L2: rb_business_interests | M2: 2
A3: DQO-1146 | B3: Freshness_Chk-VIRTUAL_BUSINESS_INTERESTS_OF_ | C3: 6e665073-5207-47a9-a6aa-add03dff3f56 | D3: Freshness_Chk-RB_Business_Interests | E3: ed92f2a1-15ca-4d40-bab4-c6a74afcccd8 | F3: Timeliness | G3: N/A | H3: NA - Table level rule | I3: 0 | J3: DED_Data_Table_063 | K3: VIRTUAL_BUSINESS_INTERESTS_OF_ | L3: rb_business_interests | M3: 2
A4: DQO-1165 | B4: Uniqueness_Chk-VIRTUAL_BUSINESS_INTERESTS_OF_ | C4: 22bb90f7-81cb-4df5-a10d-76d8c6dd029d | D4: Uniqueness_Chk-RB_Business_Interests | E4: 367d5f9a-8e65-409e-a9df-772d98c0b427 | F4: Uniqueness | G4: N/A | H4: SERV_PROV_CODE, B1_PER_ID1, B1_PER_ID2, B1_PER_ID3, SYSTEM_ID | I4: serv_prov_code,b1_per_id1,b1_per_id2,b1_per_id3,system_id | J4: DED_Data_Table_063 | K4: VIRTUAL_BUSINESS_INTERESTS_OF_ | L4: rb_business_interests | M4: 2
A5: DQO-1249 | B5: Compl_Chk-V_BUSINESS_INTERESTS_OF_-date_of_join | C5: b739b54b-3c04-4a3c-8d32-42be6de9324d | D5: Compl_Chk-RB_Business_Interests-date_of_join | E5: 8c69c053-97e3-4736-ad30-a61a3c59c091 | F5: Completeness | G5: DED_Attribute_0720 | H5: date_of_join | I5: date_of_join,rec_status | J5: DED_Data_Table_063 | K5: VIRTUAL_BUSINESS_INTERESTS_OF_ | L5: rb_business_interests | M5: 2
A6: DQO-1526 | B6: Compl_Chk-V_BUSINESS_INTERESTS_OF_-entity_name | C6: 26596ec6-2fe0-48fd-82c1-ef9858ae5bcf | D6: Compl_Chk-RB_Business_Interests-entity_name | E6: f5736ffc-38c6-417e-893a-0ec6ff76f39c | F6: Completeness | G6: DED_Attribute_0721 | H6: entity_name | I6: entity_name,rec_status | J6: DED_Data_Table_063 | K6: VIRTUAL_BUSINESS_INTERESTS_OF_ | L6: rb_business_interests | M6: 2
A7: DQO-1527 | B7: Compl_Chk-V_BUSINESS_INT_OF_-share_percentage | C7: 5eebc957-4459-4f8b-a61c-7b7bb224f249 | D7: Compl_Chk-RB_Business_Interests-share_percentage | E7: e0cac0d1-39bb-4582-91f9-a38bda429e38 | F7: Completeness | G7: DED_Attribute_0724 | H7: share_percentage | I7: share_percentage,rec_status | J7: DED_Data_Table_063 | K7: VIRTUAL_BUSINESS_INTERESTS_OF_ | L7: rb_business_interests | M7: 2
A8: DQO-1528 | B8: Compl_Chk-VIRTUAL_BUSINESS_INTERESTS_OF_-status | C8: cfa04b82-287e-43e6-a029-12fa6bf9df2b | D8: Compl_Chk-RB_Business_Interests-status | E8: c1167a19-1e87-44e5-b7de-40b8b674f691 | F8: Completeness | G8: DED_Attribute_0727 | H8: status | I8: status,rec_status | J8: DED_Data_Table_063 | K8: VIRTUAL_BUSINESS_INTERESTS_OF_ | L8: rb_business_interests | M8: 2
A9: DQO-2345 | B9: EntityDep-RB_Business_Interests-share_percentage | C9: 65ef2327-e9d4-4def-98d7-67b79c8b6353 | D9: EntityDep-RB_Business_Interests-share_percentage | E9: 83abbb1d-98f4-4885-a57e-1fcecee8d5bd | F9: Consistency | G9: DED_Attribute_0724 | H9: share_percentage | I9: share_percentage,entity_name,rec_status | J9: DED_Data_Table_063 | K9: VIRTUAL_BUSINESS_INTERESTS_OF_ | L9: rb_business_interests | M9: 2
A10: DQO-2346 | B10: EntityDep-RB_Business_Interests-date_of_join | C10: 729a8d4a-f729-45f9-94ad-17420f865f2d | D10: EntityDep-RB_Business_Interests-date_of_join | E10: 7d296af3-0586-49fc-ba29-c0269e9a94f9 | F10: Consistency | G10: DED_Attribute_0720 | H10: date_of_join | I10: date_of_join,entity_name,rec_status | J10: DED_Data_Table_063 | K10: VIRTUAL_BUSINESS_INTERESTS_OF_ | L10: rb_business_interests | M10: 2
A11: DQO-2347 | B11: StatusDep-RB_Business_Interests-status | C11: cebc5332-eb83-4689-a48f-d07ef07672c4 | D11: StatusDep-RB_Business_Interests-status | E11: e8964086-611c-4f4b-94a2-b30d5601a82a | F11: Consistency | G11: DED_Attribute_0727 | H11: status | I11: status,entity_name,rec_status | J11: DED_Data_Table_063 | K11: VIRTUAL_BUSINESS_INTERESTS_OF_ | L11: rb_business_interests | M11: 2
A12: DQO-2405 | B12: Acc_Chk-VR_BUSINESS_INTERESTS_OF_-Source_of_PEP | C12: 93a79b11-2852-476f-8356-8fa416202127 | D12: Accuracy_Check-RB_Business_Interests-Source_of_PEP | E12: 400ba501-74e2-47a8-8a2a-f9a3ee6b5916 | F12: Accuracy | G12: DED_Attribute_0726 | H12: Source_of_PEP | I12: source_of_pep | J12: DED_Data_Table_063 | K12: VIRTUAL_BUSINESS_INTERESTS_OF_ | L12: rb_business_interests | M12: 2
A13: DQO-1758 | B13: DataTyp_Chk-rb_bus_intr-dt_of_join | C13: 2ab94d5e-b876-4a70-b70a-11a24b310bf0 | D13: DataTyp_Chk-RB_Business_Interests-dt_of_join | E13: c46a08e5-8bf7-4a78-ba8a-dd8bdc2463af | F13: Conformity | G13: DED_Attribute_0720 | H13: date_of_join | I13: date_of_join,rec_status | J13: DED_Data_Table_063 | K13: VIRTUAL_BUSINESS_INTERESTS_OF_ | L13: rb_business_interests | M13: 2
A14: DQO-1759 | B14: Consec_Spc_Chk-rb_bus_intr-dt_of_join | C14: 1f2a1677-94f9-40f2-a7ba-56b4c0baac6d | D14: Consec_Spc_Chk-RB_Business_Interests-dt_of_join | E14: 0bd51d1d-c3be-4648-9038-8dc8c095fff9 | F14: Conformity | G14: DED_Attribute_0720 | H14: date_of_join | I14: date_of_join,rec_status | J14: DED_Data_Table_063 | K14: VIRTUAL_BUSINESS_INTERESTS_OF_ | L14: rb_business_interests | M14: 2
A15: DQO-1794 | B15: DataTyp_Chk-rb_bus_intr-ent_name | C15: 12c8d249-ffab-4a6b-b8af-f833a24ff797 | D15: DataTyp_Chk-RB_Business_Interests-ent_name | E15: 8dcc3bc9-8cd9-43d6-bc09-47c31ed5159d | F15: Conformity | G15: DED_Attribute_0721 | H15: entity_name | I15: entity_name,rec_status | J15: DED_Data_Table_063 | K15: VIRTUAL_BUSINESS_INTERESTS_OF_ | L15: rb_business_interests | M15: 2
... A24: DQO-1125 | B24: Completeness_Chk-VIRTUAL_SPARE_PART_DETAILS-unit | C24: ff38bda0-ac19-489d-bed8-35858110a316 | D24: Completeness_Chk-IDB_Spare_Part-unit | E24: 42f7c3e8-2331-42ac-a35d-ffcfac5b590d | F24: Completeness | G24: DED_Attribute_1372 | H24: unit | I24: unit,rec_status | J24: DED_Data_Table_101 | K24: VIRTUAL_SPARE_PART_DETAILS | L24: idb_spare_part | M24: 2
A25: DQO-1133 | B25: Freshness_Chk-VIRTUAL_SPARE_PART_DETAILS | C25: 87db84c5-d43f-4078-b09c-161d67a0418f | D25: Freshness_Chk-IDB_Spare_Part | E25: 2ba05ad9-c111-43f0-ad37-f3b294fe5cfb | F25: Timeliness | G25: N/A | H25: NA - Table level rule | I25: 0 | J25: DED_Data_Table_101 | K25: VIRTUAL_SPARE_PART_DETAILS | L25: idb_spare_part | M25: 2
A26: DQO-1158 | B26: Uniqueness_Chk-VIRTUAL_SPARE_PART_DETAILS | C26: 3fa374d3-1e95-4d2f-a316-c58defca7a20 | D26: Uniqueness_Chk-IDB_Spare_Part | E26: 1f628b85-2756-471b-bf8b-8fbcd58b1b35 | F26: Uniqueness | G26: N/A | H26: SERV_PROV_CODE, B1_PER_ID1, B1_PER_ID2, B1_PER_ID3, SPARE_PART_ID | I26: serv_prov_code,b1_per_id1,b1_per_id2,b1_per_id3,spare_part_id | J26: DED_Data_Table_101 | K26: VIRTUAL_SPARE_PART_DETAILS | L26: idb_spare_part | M26: 2
A27: DQO-1350 | B27: Compl_Chk-VIRTUAL_SPARE_PART_DETAILS-chapter | C27: 56293579-2a1d-4ea3-932a-ef1352c72c04 | D27: Compl_Chk-IDB_Spare_Part-chapter | E27: ae6b4d39-fddd-46de-8fe7-936e7ec24252 | F27: Completeness | G27: DED_Attribute_1351 | H27: chapter | I27: chapter,rec_status | J27: DED_Data_Table_101 | K27: VIRTUAL_SPARE_PART_DETAILS | L27: idb_spare_part | M27: 2
A28: DQO-1351 | B28: Compl_Chk-V_SPARE_PAR-duration_to_replace_the_part | C28: fdc9e3a9-d493-4954-aa20-fe1ca8cba3a1 | D28: Compl_Chk-IDB_Spare_P-duration_to_replace_the_part | E28: 7d272a2d-4e9b-46ed-8259-dece8ed328af | F28: Completeness | G28: DED_Attribute_1352 | H28: duration_to_replace_the_part | I28: duration_to_replace_the_part,rec_status | J28: DED_Data_Table_101 | K28: VIRTUAL_SPARE_PART_DETAILS | L28: idb_spare_part | M28: 2
A29: DQO-1352 | B29: Compl_Chk-V_SPARE_PART-hs_code_description_arabic | C29: 7f1eae03-c42b-463d-b566-495c6e9b5a34 | D29: Compl_Chk-IDB_Spare_Par-hs_code_description_arabic | E29: 6866f6cf-1759-426a-9112-3d5ce4e09500 | F29: Completeness | G29: DED_Attribute_1354 | H29: hs_code_description_arabic | I29: hs_code_description_arabic,rec_status | J29: DED_Data_Table_101 | K29: VIRTUAL_SPARE_PART_DETAILS | L29: idb_spare_part | M29: 2
A30: DQO-1353 | B30: Compl_Chk-V_SPARE_PART-hs_code_description_english | C30: 756a4e7d-d5c2-4d10-9d17-50afb8ba56b7 | D30: Compl_Chk-IDB_Spare_Pa-hs_code_description_english | E30: 3f81032c-025d-4731-8f20-1d2dffef61f8 | F30: Completeness | G30: DED_Attribute_1355 | H30: hs_code_description_english | I30: hs_code_description_english,rec_status | J30: DED_Data_Table_101 | K30: VIRTUAL_SPARE_PART_DETAILS | L30: idb_spare_part | M30: 2
A31: DQO-1354 | B31: Compl_Chk-VIRTUAL_SPARE_PART_DETAILS-heading | C31: cdea03a4-3ae7-425a-992c-262dde800268 | D31: Compl_Chk-IDB_Spare_Part-heading | E31: c7174035-3657-40d0-8e7a-4498dcd74dea | F31: Completeness | G31: DED_Attribute_1356 | H31: heading | I31: heading,rec_status | J31: DED_Data_Table_101 | K31: VIRTUAL_SPARE_PART_DETAILS | L31: idb_spare_part | M31: 2
A32: DQO-1355 | B32: Compl_Chk-V_SPARE_P-machine_brand_and_year_of_manu | C32: 5732b5cd-2473-48e4-aa5f-f3528e936f48 | D32: Compl_Chk-IDB_Spare-machine_brand_and_year_of_manu | E32: 6f334409-d31f-45a7-8304-c4cf2785e15b | F32: Completeness | G32: DED_Attribute_1357 | H32: machine_brand_and_year_of_manu | I32: machine_brand_and_year_of_manu,rec_status | J32: DED_Data_Table_101 | K32: VIRTUAL_SPARE_PART_DETAILS | L32: idb_spare_part | M32: 2
A33: DQO-1356 | B33: Compl_Chk-V_SPARE_PART_DETAILS-machine_hs_code | C33: 584a2321-6d8b-437a-91fe-2d8335335e09 | D33: Compl_Chk-IDB_Spare_Part-machine_hs_code | E33: d273b91c-cd09-4ee5-8889-42e590429f1f | F33: Completeness | G33: DED_Attribute_1358 | H33: machine_hs_code | I33: machine_hs_code,rec_status | J33: DED_Data_Table_101 | K33: VIRTUAL_SPARE_PART_DETAILS | L33: idb_spare_part | M33: 2
A34: DQO-1357 | B34: Compl_Chk-V_SPARE_PART_DETAILS-machine_name_list | C34: b18263e9-e2d1-410e-abeb-de6f7406bbc7 | D34: Compl_Chk-IDB_Spare_Part-machine_name_list | E34: 2bf069db-a34d-433c-8f59-e5f95cbdaee8 | F34: Completeness | G34: DED_Attribute_1359 | H34: machine_name_list | I34: machine_name_list,rec_status | J34: DED_Data_Table_101 | K34: VIRTUAL_SPARE_PART_DETAILS | L34: idb_spare_part | M34: 2
A35: DQO-1358 | B35: Compl_Chk-V_SPARE_PAR-machine_name_and_description | C35: 3b9046e8-4c59-4d30-a95c-6795df1c1ae6 | D35: Compl_Chk-IDB_Spare_P-machine_name_and_description | E35: 828c45ad-89b2-4342-9f77-cc3e420f9227 | F35: Completeness | G35: DED_Attribute_1360 | H35: machine_name_and_description | I35: machine_name_and_description,rec_status | J35: DED_Data_Table_101 | K35: VIRTUAL_SPARE_PART_DETAILS | L35: idb_spare_part | M35: 2
A36: DQO-1359 | B36: Compl_Chk-V_SPARE_P-number_of_machines_using_this_ | C36: 7736eb97-41cb-45d8-bce9-6fd1c27dc5cd | D36: Compl_Chk-IDB_Spare-number_of_machines_using_this_ | E36: 292a8f71-89fe-4bf2-9cb5-b6e1ed779de4 | F36: Completeness | G36: DED_Attribute_1362 | H36: number_of_machines_using_this_ | I36: number_of_machines_using_this_,rec_status | J36: DED_Data_Table_101 | K36: VIRTUAL_SPARE_PART_DETAILS | L36: idb_spare_part | M36: 2
A37: DQO-1360 | B37: Compl_Chk-V_SPARE_P-number_of_parts_in_the_machine | C37: a9aa233e-293e-409b-9bae-4217c4d9b7da | D37: Compl_Chk-IDB_Spare-number_of_parts_in_the_machine | E37: 7ca5ad9e-965e-46ce-b234-40ad548bfd75 | F37: Completeness | G37: DED_Attribute_1363 | H37: number_of_parts_in_the_machine | I37: number_of_parts_in_the_machine,rec_status | J37: DED_Data_Table_101 | K37: VIRTUAL_SPARE_PART_DETAILS | L37: idb_spare_part | M37: 2
... A84: DQO-1118 | B84: Completeness_Chk-VIRTUAL_SIGN_BOARD-width | C84: 5ff02c25-1512-4e4a-a00c-5c86d7972649 | D84: Completeness_Chk-Permit_Sign_Board-width | E84: 17719cf5-509a-44e6-92e6-64a45eba985c | F84: Completeness | G84: DED_Attribute_1285 | H84: width | I84: width,rec_status | J84: DED_Data_Table_098 | K84: VIRTUAL_SIGN_BOARD | L84: permit_sign_board | M84: 2
A85: DQO-1144 | B85: Freshness_Chk-VIRTUAL_SIGN_BOARD | C85: c1f4998d-2c25-439e-a005-907b13427c0f | D85: Freshness_Chk-Permit_Sign_Board | E85: 1ab82fda-c629-4c74-9697-de0038328c6c | F85: Timeliness | G85: N/A | H85: NA - Table level rule | I85: 0 | J85: DED_Data_Table_098 | K85: VIRTUAL_SIGN_BOARD | L85: permit_sign_board | M85: 2
A86: DQO-1164 | B86: Uniqueness_Chk-VIRTUAL_SIGN_BOARD | C86: ad39653d-7bda-43af-82b1-68042c1e823a | D86: Uniqueness_Chk-Permit_Sign_Board | E86: c923a0e9-97af-4c78-b88a-941a9c64bdfd | F86: Uniqueness | G86: N/A | H86: SERV_PROV_CODE, B1_PER_ID1, B1_PER_ID2, B1_PER_ID3, ROW_INDEX | I86: serv_prov_code,b1_per_id1,b1_per_id2,b1_per_id3,row_index | J86: DED_Data_Table_098 | K86: VIRTUAL_SIGN_BOARD | L86: permit_sign_board | M86: 2
A87: DQO-1606 | B87: DataTyp_Chk-Virt_Sign_Board-length | C87: d16a6460-dd8d-4dfc-aa04-44b1f4c79e69 | D87: DataTyp_Chk-Permit_Sign_Board-length | E87: 214ff657-19c6-4380-bcb3-001b7bf29cdd | F87: Conformity | G87: DED_Attribute_1282 | H87: length | I87: length,rec_status | J87: DED_Data_Table_098 | K87: VIRTUAL_SIGN_BOARD | L87: permit_sign_board | M87: 2
A88: DQO-1607 | B88: Num_Range_Chk-Virt_Sign_Board-length | C88: 797b4ea4-a8c7-4548-a4b5-6379539da8d0 | D88: Num_Range_Chk-Permit_Sign_Board-length | E88: e07e9309-d5b5-4c6d-8112-37d297e7ff78 | F88: Conformity | G88: DED_Attribute_1282 | H88: length | I88: length,rec_status | J88: DED_Data_Table_098 | K88: VIRTUAL_SIGN_BOARD | L88: permit_sign_board | M88: 2
A89: DQO-1608 | B89: DataTyp_Chk-Virt_Sign_Board-total_area | C89: 0e8a015b-b9b0-459e-a624-5b5f96b2e358 | D89: DataTyp_Chk-Permit_Sign_Board-total_area | E89: df3a4aa8-3ad2-476b-87b7-d40c04414aca | F89: Conformity | G89: DED_Attribute_1284 | H89: total_area | I89: total_area,rec_status | J89: DED_Data_Table_098 | K89: VIRTUAL_SIGN_BOARD | L89: permit_sign_board | M89: 2
A90: DQO-1609 | B90: Num_Range_Chk-Virt_Sign_Board-total_area | C90: ac45d288-24bd-42fc-80a0-f31ba74ddaf4 | D90: Num_Range_Chk-Permit_Sign_Board-total_area | E90: 515ab08d-4a5a-4ae9-9b20-bc4df4fd82cc | F90: Conformity | G90: DED_Attribute_1284 | H90: total_area | I90: total_area,rec_status | J90: DED_Data_Table_098 | K90: VIRTUAL_SIGN_BOARD | L90: permit_sign_board | M90: 2
A91: DQO-1610 | B91: DataTyp_Chk-Virt_Sign_Board-width | C91: b2e6c2eb-2599-4864-abfd-4e1ee5d566b9 | D91: DataTyp_Chk-Permit_Sign_Board-width | E91: 957c57d3-1272-4ede-bfdb-c4de83f273c7 | F91: Conformity | G91: DED_Attribute_1285 | H91: width | I91: width,rec_status | J91: DED_Data_Table_098 | K91: VIRTUAL_SIGN_BOARD | L91: permit_sign_board | M91: 2
A92: DQO-1611 | B92: Num_Range_Chk-Virt_Sign_Board-width | C92: 134f7ee6-cd5f-41af-9b0a-2c65922797f5 | D92: Num_Range_Chk-Permit_Sign_Board-width | E92: 2e11655e-8541-4daa-9c2d-a13e0e15b47a | F92: Conformity | G92: DED_Attribute_1285 | H92: width | I92: width,rec_status | J92: DED_Data_Table_098 | K92: VIRTUAL_SIGN_BOARD | L92: permit_sign_board | M92: 2
A93: DQO-1637 | B93: Area_Calc_Cons_Chk-virtual_sign_board | C93: 9a60739c-f8a3-4415-9aa0-fefae65bda6f | D93: Area_Calc_Cons_Chk-Permit_Sign_Board | E93: baffb06d-3d8a-4824-80e5-4e7cead11765 | F93: Consistency | G93: DED_Attribute_1282 | H93: length | I93: total_area,length,width,rec_status | J93: DED_Data_Table_098 | K93: VIRTUAL_SIGN_BOARD | L93: permit_sign_board | M93: 2
A94: DQO-1138 | B94: Freshness_Chk-VIRTUAL_OFFER_TASTING_CAMPAIGN | C94: a6029e8e-d054-4e35-8e7e-602302daeb27 | D94: Freshness_Chk-Offer_Tasting_Campaign | E94: 0c19d5e3-cb72-4a6b-85da-59f62c70008b | F94: Timeliness | G94: N/A | H94: NA - Table level rule | I94: 0 | J94: DED_Data_Table_085 | K94: VIRTUAL_OFFER_TASTING_CAMPAIGN | L94: offer_tasting_campaign | M94: 2
A95: DQO-1189 | B95: Uniqueness_Chk-VIRTUAL_OFFER_TASTING_CAMPAIGN | C95: 4d37a0d8-4f6f-45b4-b857-42b3122b0c27 | D95: Uniqueness_Chk-Offer_Tasting_Campaign | E95: f4a8e0f5-55c9-4779-ba54-145e58d8ae6f | F95: Uniqueness | G95: N/A | H95: SERV_PROV_CODE, B1_PER_ID1, B1_PER_ID2, B1_PER_ID3, ROW_INDEX | I95: serv_prov_code,b1_per_id1,b1_per_id2,b1_per_id3,row_index | J95: DED_Data_Table_085 | K95: VIRTUAL_OFFER_TASTING_CAMPAIGN | L95: offer_tasting_campaign | M95: 2
A96: DQO-1295 | B96: Compl_Chk-V_OFFER_TASTING_CAMPAI-country_of_origin | C96: 2e7eda10-83e8-4ce9-a29d-1060b57a296b | D96: Compl_Chk-Offer_Tasting_Campaign-country_of_origin | E96: 932ce4b4-4dc4-41dc-a8f8-1afa997d4fe9 | F96: Completeness | G96: DED_Attribute_1093 | H96: country_of_origin | I96: country_of_origin,rec_status | J96: DED_Data_Table_085 | K96: VIRTUAL_OFFER_TASTING_CAMPAIGN | L96: offer_tasting_campaign | M96: 2
A97: DQO-1296 | B97: Compl_Chk-V_OFFER_TASTING_CAMPAIGN-expiry_date | C97: 387a9e69-51e2-4596-972f-88713a1076aa | D97: Compl_Chk-Offer_Tasting_Campaign-expiry_date | E97: 23b84521-8a69-4565-9d48-34f70a58d27e | F97: Completeness | G97: DED_Attribute_1094 | H97: expiry_date | I97: expiry_date,rec_status | J97: DED_Data_Table_085 | K97: VIRTUAL_OFFER_TASTING_CAMPAIGN | L97: offer_tasting_campaign | M97: 2
A98: DQO-1297 | B98: Compl_Chk-V_OFFER_TASTING_CAMPAIGN-package_type | C98: 01782aba-78db-44e9-a0a3-8e1090e83cc8 | D98: Compl_Chk-Offer_Tasting_Campaign-package_type | E98: 51845c18-5fc2-40d0-be90-c6e155c39931 | F98: Completeness | G98: DED_Attribute_1095 | H98: package_type | I98: package_type,rec_status | J98: DED_Data_Table_085 | K98: VIRTUAL_OFFER_TASTING_CAMPAIGN | L98: offer_tasting_campaign | M98: 2
A99: DQO-1298 | B99: Compl_Chk-V_OFFER_TASTING_CAMPAIGN-product_name | C99: e2a55157-4a05-460d-b0e6-56d64074a416 | D99: Compl_Chk-Offer_Tasting_Campaign-product_name | E99: df707fbd-cf8d-47a0-b583-add44895e956 | F99: Completeness | G99: DED_Attribute_1096 | H99: product_name | I99: product_name,rec_status | J99: DED_Data_Table_085 | K99: VIRTUAL_OFFER_TASTING_CAMPAIGN | L99: offer_tasting_campaign | M99: 2
A100: DQO-1299 | B100: Compl_Chk-V_OFFER_TASTING_CAMPAIGN-production_date | C100: 6760cb4a-8937-43fc-a024-fa55514de172 | D100: Compl_Chk-Offer_Tasting_Campaign-production_date | E100: f0acbd6f-ede4-4d20-959e-b5edf9c2dec4 | F100: Completeness | G100: DED_Attribute_1097 | H100: production_date | I100: production_date,rec_status | J100: DED_Data_Table_085 | K100: VIRTUAL_OFFER_TASTING_CAMPAIGN | L100: offer_tasting_campaign | M100: 2
A101: DQO-1748 | B101: DataTyp_Chk-offer_taste_camp-cntry_of_origin | C101: b9dc6fcc-79f4-446b-9677-db0b88e81ff2 | D101: DataTyp_Chk-Offer_Tasting_Campaign-cntry_of_origin | E101: 7f0e4d54-fb53-46f9-acb3-dcf5dc25efa3 | F101: Conformity | G101: DED_Attribute_1093 | H101: country_of_origin | I101: country_of_origin,rec_status | J101: DED_Data_Table_085 | K101: VIRTUAL_OFFER_TASTING_CAMPAIGN | L101: offer_tasting_campaign | M101: 2
A102: DQO-1749 | B102: Consec_Spc_Chk-offer_taste_camp-cntry_of_origin | C102: 8d7d283f-4519-49a0-a5d2-fb487b0ece1f | D102: Consec_Spc_Chk-Offer_Tasting_Campa-cntry_of_origin | E102: bd11c85d-19c1-45a4-936b-f268b280ed9a | F102: Conformity | G102: DED_Attribute_1093 | H102: country_of_origin | I102: country_of_origin,rec_status | J102: DED_Data_Table_085 | K102: VIRTUAL_OFFER_TASTING_CAMPAIGN | L102: offer_tasting_campaign | M102: 2
A103: DQO-1798 | B103: DataTyp_Chk-offer_taste_camp-exp_dt | C103: 373de133-1e7e-4457-bd6d-f677744bc7e6 | D103: DataTyp_Chk-Offer_Tasting_Campaign-exp_dt | E103: 8e214c7b-1512-4e87-bff7-a5a71fc8a314 | F103: Conformity | G103: DED_Attribute_1094 | H103: expiry_date | I103: expiry_date,rec_status | J103: DED_Data_Table_085 | K103: VIRTUAL_OFFER_TASTING_CAMPAIGN | L103: offer_tasting_campaign | M103: 2
A104: DQO-1799 | B104: Consec_Spc_Chk-offer_taste_camp-exp_dt | C104: 8e1f1650-ec17-4355-95bf-e966047ef64f | D104: Consec_Spc_Chk-Offer_Tasting_Campaign-exp_dt | E104: 6f705a1f-663d-481c-ae43-4d81a63692bc | F104: Conformity | G104: DED_Attribute_1094 | H104: expiry_date | I104: expiry_date,rec_status | J104: DED_Data_Table_085 | K104: VIRTUAL_OFFER_TASTING_CAMPAIGN | L104: offer_tasting_campaign | M104: 2
A105: DQO-1973 | B105: DataTyp_Chk-offer_taste_camp-package_type | C105: 50dcb733-859f-4b84-9fed-d5fab70db6fd | D105: DataTyp_Chk-Offer_Tasting_Campaign-package_type | E105: 980251c9-abe3-486a-a7ab-f4df6f4ebe25 | F105: Conformity | G105: DED_Attribute_1095 | H105: package_type | I105: package_type,rec_status | J105: DED_Data_Table_085 | K105: VIRTUAL_OFFER_TASTING_CAMPAIGN | L105: offer_tasting_campaign | M105: 2
A106: DQO-1974 | B106: Consec_Spc_Chk-offer_taste_camp-package_type | C106: 0dc546c4-c7fa-4730-9f78-b345756aa851 | D106: Consec_Spc_Chk-Offer_Tasting_Campaign-package_type | E106: 141bda99-c3bd-4eff-9ba6-f5e33d8f5a32 | F106: Conformity | G106: DED_Attribute_1095 | H106: package_type | I106: package_type,rec_status | J106: DED_Data_Table_085 | K106: VIRTUAL_OFFER_TASTING_CAMPAIGN | L106: offer_tasting_campaign | M106: 2
... A112: DQO-2392 | B112: Acc_Chk-VR_OFF_TASTING_CAMPAIGN-country_of_origin | C112: fa17315e-f8f5-4d95-991d-5e02eb93730b | D112: Accuracy_Check-Offer_Tasting_Campaign-country_of_origin | E112: 16958ee7-c0e0-4ec8-aa8e-70b0501e293b | F112: Accuracy | G112: DED_Attribute_1093 | H112: country_of_origin | I112: country_of_origin | J112: DED_Data_Table_085 | K112: VIRTUAL_OFFER_TASTING_CAMPAIGN | L112: offer_tasting_campaign | M112: 2
A113: DQO-1141 | B113: Freshness_Chk-VIRTUAL_PRIZES | C113: c91dabad-0d49-45cd-9e2d-8bda2de7c986 | D113: Freshness_Chk-Permit_Prizes | E113: cc31c3ff-fdad-4bf0-b4a1-147700137cc6 | F113: Timeliness | G113: N/A | H113: NA - Table level rule | I113: 0 | J113: DED_Data_Table_089 | K113: VIRTUAL_PRIZES | L113: permit_prizes | M113: 2
A114: DQO-1190 | B114: Uniqueness_Chk-VIRTUAL_PRIZES | C114: 032adc53-cfb3-4433-8b85-1d0f3ba84827 | D114: Uniqueness_Chk-Permit_Prizes | E114: e855e455-5b8e-415e-a72a-b6d0f62d04ed | F114: Uniqueness | G114: N/A | H114: SERV_PROV_CODE, B1_PER_ID1, B1_PER_ID2, B1_PER_ID3, ROW_INDEX | I114: serv_prov_code,b1_per_id1,b1_per_id2,b1_per_id3,row_index | J114: DED_Data_Table_089 | K114: VIRTUAL_PRIZES | L114: permit_prizes | M114: 2
A115: DQO-1315 | B115: Compl_Chk-VIRTUAL_PRIZES-prize_type | C115: c3719f5f-2230-4d53-b60c-662c9f06fbd3 | D115: Compl_Chk-Permit_Prizes-prize_type | E115: 637d5d10-1794-4ae5-9653-69ea449f3b3e | F115: Completeness | G115: DED_Attribute_1159 | H115: prize_type | I115: prize_type,rec_status | J115: DED_Data_Table_089 | K115: VIRTUAL_PRIZES | L115: permit_prizes | M115: 2
A116: DQO-1316 | B116: Compl_Chk-VIRTUAL_PRIZES-raffle_address | C116: 27a362f5-b8f4-4244-9fef-3aff41136fd5 | D116: Compl_Chk-Permit_Prizes-raffle_address | E116: d0205b0d-c98d-43de-a56c-c128f5825598 | F116: Completeness | G116: DED_Attribute_1160 | H116: raffle_address | I116: raffle_address,rec_status | J116: DED_Data_Table_089 | K116: VIRTUAL_PRIZES | L116: permit_prizes | M116: 2
A117: DQO-1317 | B117: Compl_Chk-VIRTUAL_PRIZES-raffle_date | C117: ed68c137-30f3-44c4-ae1b-5725323c4905 | D117: Compl_Chk-Permit_Prizes-raffle_date | E117: bbdca64c-9833-43ee-869b-8bd831be9393 | F117: Completeness | G117: DED_Attribute_1161 | H117: raffle_date | I117: raffle_date,rec_status | J117: DED_Data_Table_089 | K117: VIRTUAL_PRIZES | L117: permit_prizes | M117: 2
A118: DQO-1990 | B118: DataTyp_Chk-permit_prizes-prize_type | C118: b0672bee-75a7-4a6f-a467-5d5623c66b79 | D118: DataTyp_Chk-Permit_Prizes-prize_type | E118: 50f2fa81-17a0-4bf8-83b6-47c4feebe2b7 | F118: Conformity | G118: DED_Attribute_1159 | H118: prize_type | I118: prize_type,rec_status | J118: DED_Data_Table_089 | K118: VIRTUAL_PRIZES | L118: permit_prizes | M118: 2
A119: DQO-1991 | B119: Consec_Spc_Chk-permit_prizes-prize_type | C119: 2a130cf5-9f92-4137-a4c3-e99e0f95a0d7 | D119: Consec_Spc_Chk-Permit_Prizes-prize_type | E119: 751ffd13-a219-4641-be74-4b7462e7aa5b | F119: Conformity | G119: DED_Attribute_1159 | H119: prize_type | I119: prize_type,rec_status | J119: DED_Data_Table_089 | K119: VIRTUAL_PRIZES | L119: permit_prizes | M119: 2
A120: DQO-2010 | B120: DataTyp_Chk-permit_prizes-raffle_addr | C120: 0515ea71-300a-4708-8a02-dcf1e3c04f44 | D120: DataTyp_Chk-Permit_Prizes-raffle_addr | E120: cc01ea46-69f9-40e3-a1eb-df48f6accc28 | F120: Conformity | G120: DED_Attribute_1160 | H120: raffle_address | I120: raffle_address,rec_status | J120: DED_Data_Table_089 | K120: VIRTUAL_PRIZES | L120: permit_prizes | M120: 2
A121: DQO-2011 | B121: Consec_Spc_Chk-permit_prizes-raffle_addr | C121: a37f4831-2d3f-4006-a9e0-584c9418cd08 | D121: Consec_Spc_Chk-Permit_Prizes-raffle_addr | E121: 9e5682b4-4d54-4945-9d86-172f91f5e27d | F121: Conformity | G121: DED_Attribute_1160 | H121: raffle_address | I121: raffle_address,rec_status | J121: DED_Data_Table_089 | K121: VIRTUAL_PRIZES | L121: permit_prizes | M121: 2
A122: DQO-2012 | B122: DataTyp_Chk-permit_prizes-raffle_dt | C122: d3935cb6-cae5-441c-9142-1c1137ed1f2a | D122: DataTyp_Chk-Permit_Prizes-raffle_dt | E122: f2871130-8415-4875-884c-061d3b5ef87b | F122: Conformity | G122: DED_Attribute_1161 | H122: raffle_date | I122: raffle_date,rec_status | J122: DED_Data_Table_089 | K122: VIRTUAL_PRIZES | L122: permit_prizes | M122: 2
A123: DQO-2013 | B123: Consec_Spc_Chk-permit_prizes-raffle_dt | C123: 76124c00-7895-4549-9472-5f52414ac38b | D123: Consec_Spc_Chk-Permit_Prizes-raffle_dt | E123: f732fec5-67a8-4bac-acfc-c57f3f79b242 | F123: Conformity | G123: DED_Attribute_1161 | H123: raffle_date | I123: raffle_date,rec_status | J123: DED_Data_Table_089 | K123: VIRTUAL_PRIZES | L123: permit_prizes | M123: 2
A124: DQO-2326 | B124: RaffleDep_Check-VIRTUAL_PRIZES-PRIZE_TYPE | C124: 3d6d8a9b-f4e6-461b-a378-a7a3b51f8e8a | D124: RaffleDep_Check-Permit_Prizes-prize_type | E124: eec490a5-5ee7-4f87-8e3c-523637b999d4 | F124: Consistency | G124: DED_Attribute_1159 | H124: prize_type | I124: prize_type,raffle_date,rec_status | J124: DED_Data_Table_089 | K124: VIRTUAL_PRIZES | L124: permit_prizes | M124: 2
A125: DQO-1142 | B125: Freshness_Chk-VIRTUAL_PROPAGANDA_ADVERTISING | C125: 67de0b15-88d9-4a76-bd26-bdc65b3b6559 | D125: Freshness_Chk-Permit_Propaganda_Advertising | E125: 43bc234f-e7fe-450a-9a5c-b206b8047804 | F125: Timeliness | G125: N/A | H125: NA - Table level rule | I125: 0 | J125: DED_Data_Table_090 | K125: VIRTUAL_PROPAGANDA_ADVERTISING | L125: permit_propaganda_advertising | M125: 2
A126: DQO-1191 | B126: Uniqueness_Chk-VIRTUAL_PROPAGANDA_ADVERTISING | C126: a788d979-ec2b-4a37-8e96-845eb6e68cac | D126: Uniqueness_Chk-Permit_Propaganda_Advertising | E126: 0406b1cf-614c-4516-90db-46fb8de3bb30 | F126: Uniqueness | G126: N/A | H126: SERV_PROV_CODE, B1_PER_ID1, B1_PER_ID2, B1_PER_ID3, ROW_INDEX | I126: serv_prov_code,b1_per_id1,b1_per_id2,b1_per_id3,row_index | J126: DED_Data_Table_090 | K126: VIRTUAL_PROPAGANDA_ADVERTISING | L126: permit_propaganda_advertising | M126: 2
A127: DQO-1542 | B127: Compl_Chk-VIRTUAL_PROPAGANDA_ADVERTISING-length | C127: dae23866-6778-405b-bbf4-d1602785809b | D127: Compl_Chk-Permit_Propaganda_Advertising-length | E127: e494207c-b01e-41c2-962e-1c7af6d98467 | F127: Completeness | G127: DED_Attribute_1171 | H127: length | I127: length,rec_status | J127: DED_Data_Table_090 | K127: VIRTUAL_PROPAGANDA_ADVERTISING | L127: permit_propaganda_advertising | M127: 2
A128: DQO-1543 | B128: Compl_Chk-V_PROPAGANDA_ADVERTISING-total_area | C128: c00d5f37-20e1-484c-a202-2336fb7e4318 | D128: Compl_Chk-Permit_Propaganda_Advertising-total_area | E128: 28306dd8-67d1-4741-bfe8-34eb620a825a | F128: Completeness | G128: DED_Attribute_1172 | H128: total_area | I128: total_area,rec_status | J128: DED_Data_Table_090 | K128: VIRTUAL_PROPAGANDA_ADVERTISING | L128: permit_propaganda_advertising | M128: 2
A129: DQO-1544 | B129: Compl_Chk-VIRTUAL_PROPAGANDA_ADVERTISING-width | C129: e09ac583-e01e-4318-abe0-467ef503d69f | D129: Compl_Chk-Permit_Propaganda_Advertising-width | E129: 182435c3-19b7-4df6-b3ce-4410ccf04415 | F129: Completeness | G129: DED_Attribute_1173 | H129: width | I129: width,rec_status | J129: DED_Data_Table_090 | K129: VIRTUAL_PROPAGANDA_ADVERTISING | L129: permit_propaganda_advertising | M129: 2
A130: DQO-1883 | B130: DataTyp_Chk-permit_prop_adv-length | C130: 3cefbe12-fbc1-40d3-b7b7-6a91894edc01 | D130: DataTyp_Chk-Permit_Propaganda_Advertising-length | E130: b29d314c-be7a-4f66-a89d-ea7608ce1b22 | F130: Conformity | G130: DED_Attribute_1171 | H130: length | I130: length,rec_status | J130: DED_Data_Table_090 | K130: VIRTUAL_PROPAGANDA_ADVERTISING | L130: permit_propaganda_advertising | M130: 2
A131: DQO-1884 | B131: Consec_Spc_Chk-permit_prop_adv-length | C131: 3f3b36d9-5c48-4491-8d0f-b388019323aa | D131: Consec_Spc_Chk-Permit_Propaganda_Advertisin-length | E131: 7aac3f35-aa30-4110-b9eb-616adc86584d | F131: Conformity | G131: DED_Attribute_1171 | H131: length | I131: length,rec_status | J131: DED_Data_Table_090 | K131: VIRTUAL_PROPAGANDA_ADVERTISING | L131: permit_propaganda_advertising | M131: 2
A132: DQO-2048 | B132: DataTyp_Chk-permit_prop_adv-total_area | C132: 2a452e37-059e-4f31-8c8d-41f0807227ca | D132: DataTyp_Chk-Permit_Propaganda_Advertisi-total_area | E132: 085aa94b-d16d-4701-99a4-697c63402bef | F132: Conformity | G132: DED_Attribute_1172 | H132: total_area | I132: total_area,rec_status | J132: DED_Data_Table_090 | K132: VIRTUAL_PROPAGANDA_ADVERTISING | L132: permit_propaganda_advertising | M132: 2
A133: DQO-2049 | B133: Consec_Spc_Chk-permit_prop_adv-total_area | C133: 6c9c6974-d4f6-4461-8ca6-6fac7c93dae2 | D133: Consec_Spc_Chk-Permit_Propaganda_Advert-total_area | E133: 7a795939-b0bd-4d2f-af8f-282f7bfcc5bf | F133: Conformity | G133: DED_Attribute_1172 | H133: total_area | I133: total_area,rec_status | J133: DED_Data_Table_090 | K133: VIRTUAL_PROPAGANDA_ADVERTISING | L133: permit_propaganda_advertising | M133: 2
A134: DQO-2101 | B134: DataTyp_Chk-permit_prop_adv-width | C134: 045a9384-2254-4038-91c6-3255de04e17b | D134: DataTyp_Chk-Permit_Propaganda_Advertising-width | E134: 7fa1f2d2-df00-448f-ae8b-72d308f8d72d | F134: Conformity | G134: DED_Attribute_1173 | H134: width | I134: width,rec_status | J134: DED_Data_Table_090 | K134: VIRTUAL_PROPAGANDA_ADVERTISING | L134: permit_propaganda_advertising | M134: 2
A135: DQO-2102 | B135: Consec_Spc_Chk-permit_prop_adv-width | C135: 82e0ab71-ae56-441f-8631-6621a8a3a6c5 | D135: Consec_Spc_Chk-Permit_Propaganda_Advertising-width | E135: 84a1219b-3015-4e14-8ed5-b52a3f2b3cd6 | F135: Conformity | G135: DED_Attribute_1173 | H135: width | I135: width,rec_status | J135: DED_Data_Table_090 | K135: VIRTUAL_PROPAGANDA_ADVERTISING | L135: permit_propaganda_advertising | M135: 2
A136: DQO-2289 | B136: Area_Calc_Cons_Chk-VIRT_PROPAGANDA_ADVERTISING | C136: af9d5918-ecc5-491c-a3e8-24eec7049457 | D136: Area_Calc_Cons_Chk-Permit_Prop_Advertising | E136: 4c5c0230-2680-4a76-bd00-9fe8c7d9179c | F136: Consistency | G136: N/A | H136: total_area, length, width | I136: total_area,length,width,rec_status | J136: DED_Data_Table_090 | K136: VIRTUAL_PROPAGANDA_ADVERTISING | L136: permit_propaganda_advertising | M136: 2
A137: DQO-1074 | B137: Compl_Chk-V_LICENSE_LOCAL_BRANCH-license_number | C137: 589c03b3-daff-4590-8aa6-74003319b7f2 | D137: Compl_Chk-License_Local_Branch-license_number | E137: 57db1448-f6ce-4760-9054-baf3a2109e17 | F137: Completeness | G137: DED_Attribute_0929 | H137: license_number | I137: license_number,rec_status | J137: DED_Data_Table_077 | K137: VIRTUAL_LICENSE_LOCAL_BRANCH | L137: license_local_branch | M137: 2
A138: DQO-1134 | B138: Freshness_Chk-VIRTUAL_LICENSE_LOCAL_BRANCH | C138: e9d95cd0-41df-43e3-a323-bb205410c968 | D138: Freshness_Chk-License_Local_Branch | E138: cd9dbe82-98ef-4a6d-a812-79b980b00fb1 | F138: Timeliness | G138: N/A | H138: NA - Table level rule | I138: 0 | J138: DED_Data_Table_077 | K138: VIRTUAL_LICENSE_LOCAL_BRANCH | L138: license_local_branch | M138: 2
A139: DQO-1159 | B139: Uniqueness_Chk-VIRTUAL_LICENSE_LOCAL_BRANCH | C139: fee6e210-2dd9-4c74-be84-d1370647c141 | D139: Uniqueness_Chk-License_Local_Branch | E139: dffbd42b-ff80-42b1-b64f-efd1bcd600e0 | F139: Uniqueness | G139: N/A | H139: SERV_PROV_CODE, B1_PER_ID1, B1_PER_ID2, B1_PER_ID3, LICENSE_NUMBER | I139: serv_prov_code,b1_per_id1,b1_per_id2,b1_per_id3,license_number | J139: DED_Data_Table_077 | K139: VIRTUAL_LICENSE_LOCAL_BRANCH | L139: license_local_branch | M139: 2
A140: DQO-1533 | B140: Compl_Chk-V_LICENSE_LOCAL_BRANCH-trade_name_ar | C140: 7fdf4cf7-e115-41ca-a124-c9fe58fa807d | D140: Compl_Chk-License_Local_Branch-trade_name_ar | E140: 3d4cd2c1-a026-45cd-ae88-73673ca44c91 | F140: Completeness | G140: DED_Attribute_0930 | H140: trade_name_ar | I140: trade_name_ar,rec_status | J140: DED_Data_Table_077 | K140: VIRTUAL_LICENSE_LOCAL_BRANCH | L140: license_local_branch | M140: 2
A141: DQO-1534 | B141: Compl_Chk-V_LICENSE_LOCAL_BRANCH-trade_name_en | C141: 8708db9f-a828-4378-8cf0-63d9075f08b8 | D141: Compl_Chk-License_Local_Branch-trade_name_en | E141: 4059cc39-023a-4bb7-b6cd-a672435fcde1 | F141: Completeness | G141: DED_Attribute_0931 | H141: trade_name_en | I141: trade_name_en,rec_status | J141: DED_Data_Table_077 | K141: VIRTUAL_LICENSE_LOCAL_BRANCH | L141: license_local_branch | M141: 2
A142: DQO-1574 | B142: Code_Fmt_Chk-Virt_Lic_Local_Br-license_number | C142: 2d3e6cbc-ee83-4912-89ac-c3b810649b57 | D142: Code_Fmt_Chk-License_Local_Branch-license_number | E142: 6f11c4ea-e081-4624-a231-297cf0f14af9 | F142: Conformity | G142: DED_Attribute_0929 | H142: license_number | I142: license_number,rec_status | J142: DED_Data_Table_077 | K142: VIRTUAL_LICENSE_LOCAL_BRANCH | L142: license_local_branch | M142: 2
A143: DQO-2052 | B143: DataTyp_Chk-lic_local_br-trade_name_ar | C143: 8b8a71fb-eadd-4333-82c6-5f198527dd54 | D143: DataTyp_Chk-License_Local_Branch-trade_name_ar | E143: 6c40e208-f298-4af3-9518-a99a0a1c986e | F143: Conformity | G143: DED_Attribute_0930 | H143: trade_name_ar | I143: trade_name_ar,rec_status | J143: DED_Data_Table_077 | K143: VIRTUAL_LICENSE_LOCAL_BRANCH | L143: license_local_branch | M143: 2
A144: DQO-2053 | B144: Consec_Spc_Chk-lic_local_br-trade_name_ar | C144: 3ba5996d-1b4f-4b23-bcc0-db707fd344f0 | D144: Consec_Spc_Chk-License_Local_Branch-trade_name_ar | E144: 1359649a-e796-4f3d-88cc-917ced9c3ec2 | F144: Conformity | G144: DED_Attribute_0930 | H144: trade_name_ar | I144: trade_name_ar,rec_status | J144: DED_Data_Table_077 | K144: VIRTUAL_LICENSE_LOCAL_BRANCH | L144: license_local_branch | M144: 2
A145: DQO-2054 | B145: DataTyp_Chk-lic_local_br-trade_name_en | C145: 0909aee6-9b83-446d-ad43-72011de8af15 | D145: DataTyp_Chk-License_Local_Branch-trade_name_en | E145: 3135673f-00dd-48c0-b8a1-3c8b872f911f | F145: Conformity | G145: DED_Attribute_0931 | H145: trade_name_en | I145: trade_name_en,rec_status | J145: DED_Data_Table_077 | K145: VIRTUAL_LICENSE_LOCAL_BRANCH | L145: license_local_branch | M145: 2
A146: DQO-2055 | B146: Consec_Spc_Chk-lic_local_br-trade_name_en | C146: 64942df1-a17d-4986-9c3c-3c3b994ab80f | D146: Consec_Spc_Chk-License_Local_Branch-trade_name_en | E146: 9b81fe91-cedd-486f-b083-b07b10940f47 | F146: Conformity | G146: DED_Attribute_0931 | H146: trade_name_en | I146: trade_name_en,rec_status | J146: DED_Data_Table_077 | K146: VIRTUAL_LICENSE_LOCAL_BRANCH | L146: license_local_branch | M146: 2
A147: DQO-2294 | B147: Bilingual_Cons_Chk-VIR_LIC_LCL_BRNCH-tr_name_ar-en | C147: 18f0a365-551e-4059-8da1-795a829d017c | D147: Bilingual_Cons_Chk-Lice_Local_Bch-tr_name_ar-en | E147: fe3ebea6-dd08-44eb-b388-9b7ededa71d7 | F147: Consistency | G147: N/A | H147: trade_name_ar, trade_name_en | I147: trade_name_ar,trade_name_en,rec_status | J147: DED_Data_Table_077 | K147: VIRTUAL_LICENSE_LOCAL_BRANCH | L147: license_local_branch | M147: 2
A148: DQO-1090 | B148: Completeness_Chk-VIRTUAL_MORTGAGE_RECORDS-status | C148: 4e8d71af-bfb1-48af-8ddc-5590e0507237 | D148: Completeness_Chk-Mortgage_Records-status | E148: 54dfc024-ac49-4fa0-a50b-e5233f3ef02e | F148: Completeness | G148: DED_Attribute_1070 | H148: status | I148: status,rec_status | J148: DED_Data_Table_083 | K148: VIRTUAL_MORTGAGE_RECORDS | L148: mortgage_records | M148: 2
A149: DQO-1136 | B149: Freshness_Chk-VIRTUAL_MORTGAGE_RECORDS | C149: 432a8dcd-548e-4f3e-be31-f35ddd909c1c | D149: Freshness_Chk-Mortgage_Records | E149: de6064de-9b65-40c8-b7a5-c14281f063ba | F149: Timeliness | G149: N/A | H149: NA - Table level rule | I149: 0 | J149: DED_Data_Table_083 | K149: VIRTUAL_MORTGAGE_RECORDS | L149: mortgage_records | M149: 2
A150: DQO-1188 | B150: Uniqueness_Chk-VIRTUAL_MORTGAGE_RECORDS | C150: b0e573ec-4949-4aec-8d26-c084199bba91 | D150: Uniqueness_Chk-Mortgage_Records | E150: 7ccf943b-f46b-409b-ba0c-464dc934ebbc | F150: Uniqueness | G150: N/A | H150: SERV_PROV_CODE, B1_PER_ID1, B1_PER_ID2, B1_PER_ID3, TRANSACTION_ID | I150: serv_prov_code,b1_per_id1,b1_per_id2,b1_per_id3,transaction_id | J150: DED_Data_Table_083 | K150: VIRTUAL_MORTGAGE_RECORDS | L150: mortgage_records | M150: 2
A151: DQO-1291 | B151: Compl_Chk-V_MORTGAGE_RECORDS-transaction_date | C151: 1b4f01aa-e3f1-423a-bf14-404816796389 | D151: Compl_Chk-Mortgage_Records-transaction_date | E151: 4cbd9f9b-8a1c-43d3-805e-d5b5e9dae467 | F151: Completeness | G151: DED_Attribute_1071 | H151: transaction_date | I151: transaction_date,rec_status | J151: DED_Data_Table_083 | K151: VIRTUAL_MORTGAGE_RECORDS | L151: mortgage_records | M151: 2
A152: DQO-1292 | B152: Compl_Chk-V_MORTGAGE_RECORDS-transaction_type | C152: cbeb62ff-af94-4441-bf93-56aa32a36ca9 | D152: Compl_Chk-Mortgage_Records-transaction_type | E152: fba7e8a1-ff39-4ba3-869d-9b5af68a74ed | F152: Completeness | G152: DED_Attribute_1073 | H152: transaction_type | I152: transaction_type,rec_status | J152: DED_Data_Table_083 | K152: VIRTUAL_MORTGAGE_RECORDS | L152: mortgage_records | M152: 2
A153: DQO-2056 | B153: DataTyp_Chk-mortgage_rec-txn_dt | C153: c2b5733e-45e9-4850-97de-ed2549d9d408 | D153: DataTyp_Chk-Mortgage_Records-txn_dt | E153: 6436757a-5a9b-4cda-87a6-2dffd78b63f1 | F153: Conformity | G153: DED_Attribute_1071 | H153: transaction_date | I153: transaction_date,rec_status | J153: DED_Data_Table_083 | K153: VIRTUAL_MORTGAGE_RECORDS | L153: mortgage_records | M153: 2
A154: DQO-2057 | B154: Consec_Spc_Chk-mortgage_rec-txn_dt | C154: e33fdb16-bc61-4b6e-bfa5-a6f4dcc94b4f | D154: Consec_Spc_Chk-Mortgage_Records-txn_dt | E154: f7ce85ab-1690-402c-bcbd-9af0261bb2e8 | F154: Conformity | G154: DED_Attribute_1071 | H154: transaction_date | I154: transaction_date,rec_status | J154: DED_Data_Table_083 | K154: VIRTUAL_MORTGAGE_RECORDS | L154: mortgage_records | M154: 2
A155: DQO-2061 | B155: DataTyp_Chk-mortgage_rec-txn_type | C155: d77bb81c-b022-474c-a712-fc9ca03443b7 | D155: DataTyp_Chk-Mortgage_Records-txn_type | E155: e7d90f59-cd0f-4702-b0cc-0398de218aab | F155: Conformity | G155: DED_Attribute_1073 | H155: transaction_type | I155: transaction_type,rec_status | J155: DED_Data_Table_083 | K155: VIRTUAL_MORTGAGE_RECORDS | L155: mortgage_records | M155: 2
A156: DQO-2062 | B156: Consec_Spc_Chk-mortgage_rec-txn_type | C156: 1e3e3c4e-ee2e-4b95-8413-bfac64fbd23c | D156: Consec_Spc_Chk-Mortgage_Records-txn_type | E156: b47c309e-610f-4598-aa40-dc62e36e5d0c | F156: Conformity | G156: DED_Attribute_1073 | H156: transaction_type | I156: transaction_type,rec_status | J156: DED_Data_Table_083 | K156: VIRTUAL_MORTGAGE_RECORDS | L156: mortgage_records | M156: 2
A157: DQO-2337 | B157: Cons_Chk-VIRTUAL_MORTGAGE_RECORDS-transaction_type | C157: 8cfde21a-baca-4e66-aed0-729f519c8600 | D157: Consistency_Chk-Mortgage_Records-transaction_type | E157: 95bec2f1-be59-42ee-a53c-79b801174bca | F157: Consistency | G157: DED_Attribute_1073 | H157: transaction_type | I157: transaction_type,transaction_date,rec_status | J157: DED_Data_Table_083 | K157: VIRTUAL_MORTGAGE_RECORDS | L157: mortgage_records | M157: 2
A158: N/A | B158: N/A | C158: N?A | D158: Cons_Chk-VIRTUAL_MORTGAGE_RECORDS-transaction_type | E158: 0ff8c71d-73d8-4512-b0ef-3310fda83d7d | F158: Consistency | G158: N/A | H158: N/A | I158: transaction_type,transaction_date,rec_status | J158: DED_Data_Table_083 | K158: VIRTUAL_MORTGAGE_RECORDS | L158: mortgage_records | M158: 2
A159: DQO-2321 | B159: TransDep_Check-VIRTUAL_MORT-TRANSACTION_DATE | C159: 71e5b8c6-6d76-453e-aabe-e7bb1de1d8e2 | D159: TransDep_Check-Mortgage_Records-transaction_date | E159: 18843273-dc8c-4bdf-8a29-caa75e750e09 | F159: Consistency | G159: DED_Attribute_1071 | H159: transaction_date | I159: transaction_date,transaction_type,rec_status | J159: DED_Data_Table_083 | K159: VIRTUAL_MORTGAGE_RECORDS | L159: mortgage_records | M159: 2
...

Sheet S3
A1: DQO | B1: Rule_Title_B | C1: Purview_B | D1: Rule_Title_S | E1: Purview_S | F1: Dimension | G1: Attribute_ID | H1: Attribute_Name_From-Rule_Book | I1: Attribute_Name from file | J1: Asset_ID | K1: Asset_Name_B | L1: Asset_Name_S | M1: Sprint
A2: DQO-2816 | B2: Freshness_Check-br_vehicle_info | C2: 74354977-278f-414a-91c9-19cbd2dd4ed4 | D2: Freshness_Check-vehicle_info | E2: ebe3f8c9-42f7-44ab-a950-73f51acba554 | F2: Timeliness | G2: N/A | H2: NA - Table level rule | I2: 0 | J2: DED_Data_Table_234 | K2: br_vehicle_info | L2: vehicle_info | M2: 3
A3: DQO-2868 | B3: Uniqueness_Chk-br_vehicle_info | C3: 4fe6f2f0-048d-4058-8757-8ee0e37004db | D3: Uniqueness_Chk-vehicle_info | E3: e6c54235-c451-46b7-9879-4da37cbbbe5e | F3: Uniqueness | G3: N/A | H3: serv_prov_code, b1_per_id1, b1_per_id2, b1_per_id3, b1_per_type, b1_per_sub_type | I3: serv_prov_code,b1_per_id1,b1_per_id2,b1_per_id3,b1_per_type,b1_per_sub_type | J3: DED_Data_Table_234 | K3: br_vehicle_info | L3: vehicle_info | M3: 3
A4: DQO-3322 | B4: Comp_Check-br_vehicle_info-advertisement_type | C4: 66cb20b9-6585-4543-affc-e08d3da005a9 | D4: Comp_Check-vehicle_info-advertisement_type | E4: 042123b0-b029-4b15-a2b2-cb45e3c7cf39 | F4: Completeness | G4: DED_Attribute_3581 | H4: advertisement_type | I4: advertisement_type,rec_status | J4: DED_Data_Table_234 | K4: br_vehicle_info | L4: vehicle_info | M4: 3
A5: DQO-3323 | B5: Comp_Check-br_vehicle_info-plate_or_chassis_number | C5: 48fec99b-5d7a-4478-a9c5-82b6d404ae0d | D5: Comp_Check-vehicle_info-plate_or_chassis_number | E5: 55f853a9-b760-4ac8-8011-a0dfffa464f8 | F5: Completeness | G5: DED_Attribute_3582 | H5: plate_or_chassis_number | I5: plate_or_chassis_number,rec_status | J5: DED_Data_Table_234 | K5: br_vehicle_info | L5: vehicle_info | M5: 3
A6: DQO-3324 | B6: Completeness_Check-br_vehicle_info-plate_category | C6: f635f932-938a-4b23-983a-6b906b839906 | D6: Completeness_Check-vehicle_info-plate_category | E6: d0ed6e2a-9d4c-4e01-b8ed-567b00de28bc | F6: Completeness | G6: DED_Attribute_3584 | H6: plate_category | I6: plate_category,rec_status | J6: DED_Data_Table_234 | K6: br_vehicle_info | L6: vehicle_info | M6: 3
A7: DQO-3832 | B7: Consec_Spc_Chk-br_vehicle_info-advertisement_type | C7: 38566350-dc23-4c14-bfda-a0ae40236872 | D7: Consec_Chk-vehicle_info-advertisement_type | E7: 6c81ca7b-8272-48dc-9d3c-5c84e43b115c | F7: Conformity | G7: DED_Attribute_3581 | H7: advertisement_type | I7: advertisement_type,rec_status | J7: DED_Data_Table_234 | K7: br_vehicle_info | L7: vehicle_info | M7: 3
A8: DQO-3833 | B8: Consec_Chk-br_vehicle-plate_or_chassis_number | C8: de11a497-9e76-4dda-b450-8a3f751ebadf | D8: Consec_Chk-vehicle_info-plate_or_chassis_number | E8: 3781b14c-65f8-485b-83e9-fc130e0bfd27 | F8: Conformity | G8: DED_Attribute_3582 | H8: plate_or_chassis_number | I8: plate_or_chassis_number,rec_status | J8: DED_Data_Table_234 | K8: br_vehicle_info | L8: vehicle_info | M8: 3
A9: DQO-3834 | B9: Consec_Spc_Chk-br_vehicle_info-plate_category | C9: 73bceaf8-4afd-4ea0-9826-370e22ec3d85 | D9: Consec_Chk-vehicle_info-plate_category | E9: aa6c389a-11f2-4ade-9239-8632f62bbca7 | F9: Conformity | G9: DED_Attribute_3584 | H9: plate_category | I9: plate_category,rec_status | J9: DED_Data_Table_234 | K9: br_vehicle_info | L9: vehicle_info | M9: 3
A10: DQO-3850 | B10: Val_Chk-br_vehicle_info-advertisement_type | C10: cecbe143-89da-4ae8-96a8-fd2409cbb799 | D10: Val_Chk-vehicle_info-advertisement_type | E10: 8952cd38-2e5b-44ac-8533-17e0ad60c063 | F10: Conformity | G10: DED_Attribute_3581 | H10: advertisement_type | I10: advertisement_type,rec_status | J10: DED_Data_Table_234 | K10: br_vehicle_info | L10: vehicle_info | M10: 3
A11: DQO-4178 | B11: Val_Chk-br_vehicle_info-plate_or_chassis_number | C11: 11093150-ca17-4844-805a-e8bbdd234314 | D11: Val_Chk-vehicle_info-plate_or_chassis_number | E11: a84faf4a-9b09-4a0f-8a01-146d054033fc | F11: Conformity | G11: DED_Attribute_3582 | H11: plate_or_chassis_number | I11: plate_or_chassis_number,rec_status | J11: DED_Data_Table_234 | K11: br_vehicle_info | L11: vehicle_info | M11: 3
A12: DQO-2776 | B12: Freshness_Check-br_communication_information | C12: f2d6e45a-b245-4e6a-9ef6-843eb1cffe8b | D12: Freshness_Check-communication_information | E12: 1495efb5-61e2-49cb-9ba0-3f7715ee4066 | F12: Timeliness | G12: N/A | H12: NA - Table level rule | I12: 0 | J12: DED_Data_Table_187 | K12: br_communication_information | L12: communication_information | M12: 3
A13: DQO-2828 | B13: Uniqueness_Chk-br_communication_information | C13: f855ec72-9069-4702-a5d4-2066d0974b07 | D13: Uniqueness_Chk-communication_information | E13: 0b71cff7-3b7a-4a49-b8f9-c7f98ad4d3fa | F13: Uniqueness | G13: N/A | H13: serv_prov_code, b1_per_id1, b1_per_id2, b1_per_id3, b1_per_type, b1_per_sub_type | I13: serv_prov_code,b1_per_id1,b1_per_id2,b1_per_id3,b1_per_type,b1_per_sub_type | J13: DED_Data_Table_187 | K13: br_communication_information | L13: communication_information | M13: 3
A14: DQO-3055 | B14: Comp_Chk-br_com_informati-enterprise_mobile_number | C14: 75d38dc1-51d5-4a79-816a-bfe7155fb416 | D14: Comp_Chk-com_informati-enterprise_mobile_number | E14: 24ed94a7-78d3-4bdc-a1a7-9018219a90f1 | F14: Completeness | G14: DED_Attribute_2830 | H14: enterprise_mobile_number | I14: enterprise_mobile_number,rec_status | J14: DED_Data_Table_187 | K14: br_communication_information | L14: communication_information | M14: 3
A15: DQO-3056 | B15: Comp_Chk-br_communicatio_information-email_address | C15: 318b4e70-dcb5-4c4f-95e8-0dc05ed364f4 | D15: Comp_Chk-communicatio_information-email_address | E15: c6c8ec63-8b77-4d5c-853e-29a1725ebfeb | F15: Completeness | G15: DED_Attribute_2831 | H15: email_address | I15: email_address,rec_status | J15: DED_Data_Table_187 | K15: br_communication_information | L15: communication_information | M15: 3
A16: DQO-3057 | B16: Comp_Chk-br_com_info-authorized_sign_mobile_number | C16: 20e01c36-65c4-49c9-90fd-bbf3678165bd | D16: Comp_Chk-com_info-authorized_sign_mobile_number | E16: 05b6f9d8-7bad-4db5-89f1-eee94195ef46 | F16: Completeness | G16: DED_Attribute_2832 | H16: authorized_signatory_mobile_number | I16: authorized_signatory_mobile_number,rec_status | J16: DED_Data_Table_187 | K16: br_communication_information | L16: communication_information | M16: 3
A17: DQO-3529 | B17: Consec_Chk-br_comm_info-enterprise_mobile_number | C17: 14ee25f1-2597-43ef-a323-eb1d922b4f3a | D17: Consec_Chk-comm_info-enterprise_mobile_number | E17: 687dc888-1e42-4fc8-80ae-e514266f44fd | F17: Conformity | G17: DED_Attribute_2830 | H17: enterprise_mobile_number | I17: enterprise_mobile_number,rec_status | J17: DED_Data_Table_187 | K17: br_communication_information | L17: communication_information | M17: 3
A18: DQO-3530 | B18: Consec_Chk-br_comm_info-email_address | C18: 4e37718c-5b66-412d-aa46-b0545a6924ff | D18: Consec_Chk-communication_information-email_address | E18: 06dce948-fb71-4e21-8641-af7daf25c2a7 | F18: Conformity | G18: DED_Attribute_2831 | H18: email_address | I18: email_address,rec_status | J18: DED_Data_Table_187 | K18: br_communication_information | L18: communication_information | M18: 3
A19: DQO-3531 | B19: Consec_Chk-br_comm_info-auth_signatory_mobile_no | C19: cad119e5-2946-42b7-a87a-fdf89e4c9aa7 | D19: Consec_Chk-com_info-authorized_signatory_mob_nbr | E19: 3b6451ba-94f7-4f86-a416-2a6d7ca95e90 | F19: Conformity | G19: DED_Attribute_2832 | H19: authorized_signatory_mobile_number | I19: authorized_signatory_mobile_number,rec_status | J19: DED_Data_Table_187 | K19: br_communication_information | L19: communication_information | M19: 3
A20: DQO-3939 | B20: LTS_Chk-br_communication_information-email_address | C20: 3f9362f9-1435-40f9-910b-3eac266f8ad9 | D20: LTS_Chk-communication_information-email_address | E20: 2b9f4dc7-7321-4aa2-ac01-703e06f77ee9 | F20: Conformity | G20: DED_Attribute_2831 | H20: email_address | I20: email_address,rec_status | J20: DED_Data_Table_187 | K20: br_communication_information | L20: communication_information | M20: 3
A21: DQO-3953 | B21: Val_Chk-br_communication_info-enterprise_mob_numbr | C21: c5a0939c-e685-40bd-b078-78e8597e1e99 | D21: Val_Chk-communication_info-enterprise_mobile_numbr | E21: 6deae9f5-504d-4e84-bdb3-5c4659bb3b40 | F21: Conformity | G21: DED_Attribute_2830 | H21: enterprise_mobile_number | I21: enterprise_mobile_number,rec_status | J21: DED_Data_Table_187 | K21: br_communication_information | L21: communication_information | M21: 3
A22: DQO-2472 | B22: Validity_Check-br_COMM_INFO-Email_Address | C22: d1c84537-89a5-4dfd-a090-bf1021765ab6 | D22: Validity_Check-COMM_INFO-Email_Address | E22: dfbabc06-5f68-46cd-9502-de63c026d176 | F22: Conformity | G22: DED_Attribute_2831 | H22: email_address | I22: email_address,rec_status | J22: DED_Data_Table_187 | K22: br_communication_information | L22: communication_information | M22: 3
A23: DQO-2781 | B23: Freshness_Check-br_house_information | C23: 1d3b831d-1d1d-4d47-9cd7-43673c7ba95b | D23: Freshness_Check-house_information | E23: 8f3de390-a1ea-47cc-8c65-2477668618ef | F23: Timeliness | G23: N/A | H23: NA - Table level rule | I23: 0 | J23: DED_Data_Table_192 | K23: br_house_information | L23: house_information | M23: 3
A24: DQO-2833 | B24: Uniqueness_Chk-br_house_information | C24: 4857027d-0101-4d52-8d78-54627348fcf8 | D24: Uniqueness_Chk-house_information | E24: de6f9d57-4c98-4776-8ac6-bd68de042c05 | F24: Uniqueness | G24: N/A | H24: serv_prov_code, b1_per_id1, b1_per_id2, b1_per_id3, b1_per_type, b1_per_sub_type | I24: serv_prov_code,b1_per_id1,b1_per_id2,b1_per_id3,b1_per_type,b1_per_sub_type | J24: DED_Data_Table_192 | K24: br_house_information | L24: house_information | M24: 3
A25: DQO-3124 | B25: Comp_Chk-br_hou_inf-allow_insp__ab_fca_enter_home | C25: 84b04a93-6a61-45b3-8bfe-150977ba0239 | D25: Comp_Chk-hou_inf-allow_insp__ab_fca_enter_home | E25: dc5444a3-eec0-44c8-97e6-91eb210922ee | F25: Completeness | G25: DED_Attribute_2956 | H25: allow_the_inspectors_of_the_abu_dhabi_food_control_authority_to_enter_the_house_specified_above_and | I25: allow_the_inspectors_of_the_abu_dhabi_food_control_authority_to_enter_the_house_specified_above_and,rec_status | J25: DED_Data_Table_192 | K25: br_house_information | L25: house_information | M25: 3
A26: DQO-3125 | B26: Comp_Check-br_house_information-building_number | C26: 7ff0a420-d0c9-41c2-8928-047b7277128c | D26: Comp_Check-house_information-building_number | E26: 6b73f90e-4685-4016-8efe-da4d0712c689 | F26: Completeness | G26: DED_Attribute_2957 | H26: building_number | I26: building_number,rec_status | J26: DED_Data_Table_192 | K26: br_house_information | L26: house_information | M26: 3
A27: DQO-3126 | B27: Completeness_Check-br_house_information-mobile_no | C27: 7b193835-05e4-4953-a88c-239ffa8deee3 | D27: Completeness_Check-house_information-mobile_no | E27: 14163141-b0b3-4fd0-baf5-e8ef4ea8dfd0 | F27: Completeness | G27: DED_Attribute_2958 | H27: mobile_no | I27: mobile_no,rec_status | J27: DED_Data_Table_192 | K27: br_house_information | L27: house_information | M27: 3
A28: DQO-3127 | B28: Comp_Check-br_house_information-emirates_id_number | C28: f4c77479-cf3a-4a0b-84da-d44c3b8681df | D28: Comp_Check-house_information-emirates_id_number | E28: 0c54cd11-f5e8-40fa-9495-bbacf2c14385 | F28: Completeness | G28: DED_Attribute_2960 | H28: emirates_id_number | I28: emirates_id_number,rec_status | J28: DED_Data_Table_192 | K28: br_house_information | L28: house_information | M28: 3
A29: DQO-3128 | B29: Completeness_Check-br_house_information-owner_name | C29: 430c41cf-54dd-4d21-824d-534be122b093 | D29: Completeness_Check-house_information-owner_name | E29: cf3ae9c9-3fa0-4d82-96c7-75c613a888e3 | F29: Completeness | G29: DED_Attribute_2961 | H29: owner_name | I29: owner_name,rec_status | J29: DED_Data_Table_192 | K29: br_house_information | L29: house_information | M29: 3
A30: DQO-3129 | B30: Completeness_Check-br_house_information-district | C30: 7cfe423d-fee7-4c0b-a7b2-39fe459efb57 | D30: Completeness_Check-house_information-district | E30: fb1f6c5a-c315-4ae2-8951-eaa3e0bdbd13 | F30: Completeness | G30: DED_Attribute_2962 | H30: district | I30: district,rec_status | J30: DED_Data_Table_192 | K30: br_house_information | L30: house_information | M30: 3
A31: DQO-3600 | B31: Consec_Chk-br_house_info-allow_inspectors_house | C31: 9aca6464-a4a3-4cb7-8764-aff76363f90a | D31: Consec_Chk-house_info-allow_inspectors_enter_house | E31: 069c569b-4941-45be-83af-d006ebd44ce4 | F31: Conformity | G31: DED_Attribute_2956 | H31: allow_the_inspectors_of_the_abu_dhabi_food_control_authority_to_enter_the_house_specified_above_and | I31: allow_the_inspectors_of_the_abu_dhabi_food_control_authority_to_enter_the_house_specified_above_and,rec_status | J31: DED_Data_Table_192 | K31: br_house_information | L31: house_information | M31: 3
A32: DQO-3601 | B32: Consec_Chk-br_house_info-building_number | C32: 06ad5681-6e78-413c-bbfe-f5ce9466b7e3 | D32: Consec_Chk-house_information-building_number | E32: 2cc9bebd-fa43-4c4e-8beb-d7be39b1ef57 | F32: Conformity | G32: DED_Attribute_2957 | H32: building_number | I32: building_number,rec_status | J32: DED_Data_Table_192 | K32: br_house_information | L32: house_information | M32: 3
A33: DQO-3602 | B33: Consec_Spc_Chk-br_house_information-mobile_no | C33: 80197de1-c173-4412-8213-3ae85f4077df | D33: Consec_Chk-house_information-mobile_no | E33: ffb13abf-1dda-4c2b-88b2-47bb71a30387 | F33: Conformity | G33: DED_Attribute_2958 | H33: mobile_no | I33: mobile_no,rec_status | J33: DED_Data_Table_192 | K33: br_house_information | L33: house_information | M33: 3
A34: DQO-3603 | B34: Consec_Chk-br_house_info-emirates_id_number | C34: eb747fde-296b-42a7-b8c7-cc4deb604a33 | D34: Consec_Chk-house_information-emirates_id_number | E34: 41432962-a1f6-48f5-9bec-1da9e2acf564 | F34: Conformity | G34: DED_Attribute_2960 | H34: emirates_id_number | I34: emirates_id_number,rec_status | J34: DED_Data_Table_192 | K34: br_house_information | L34: house_information | M34: 3
A35: DQO-3604 | B35: Consec_Spc_Chk-br_house_information-owner_name | C35: 913ed33e-0991-4762-83d5-ea82750ae0db | D35: Consec_Chk-house_information-owner_name | E35: daa9817a-294c-462b-8ed1-cc2566960c7c | F35: Conformity | G35: DED_Attribute_2961 | H35: owner_name | I35: owner_name,rec_status | J35: DED_Data_Table_192 | K35: br_house_information | L35: house_information | M35: 3
... A43: DQO-2475 | B43: Validity_Check-br_HOUSE_INFO-Emirates_Id_No | C43: a12c1961-254e-4bb6-a6da-301d9e02b268 | D43: Validity_Check-HOUSE_INFO-Emirates_Id_No | E43: 504d103b-b46a-4b88-b1a1-6231f2155a73 | F43: Conformity | G43: DED_Attribute_2960 | H43: emirates_id_number | I43: emirates_id_number,rec_status | J43: DED_Data_Table_192 | K43: br_house_information | L43: house_information | M43: 3
A44: DQO-2782 | B44: Freshness_Check-br_hscode | C44: ce1b9af1-b1d3-4dec-9460-97365223bd84 | D44: Freshness_Check-hscode | E44: fe5a8895-0d87-4b81-9f93-46963dbb7256 | F44: Timeliness | G44: N/A | H44: NA - Table level rule | I44: 0 | J44: DED_Data_Table_193 | K44: br_hscode | L44: hscode | M44: 3
A45: DQO-3130 | B45: Comp_Check-br_hscode-hs_code_arabic_description | C45: 0a0b6541-8497-4e1f-8605-89db58f00d31 | D45: Comp_Check-hscode-hs_code_arabic_description | E45: 77133f77-e9e5-4952-9183-25c15a7df5eb | F45: Completeness | G45: DED_Attribute_2971 | H45: hs_code_arabic_description | I45: hs_code_arabic_description,rec_status | J45: DED_Data_Table_193 | K45: br_hscode | L45: hscode | M45: 3
A46: DQO-3131 | B46: Completeness_Check-br_hscode-hazard_item | C46: 53339466-7bb6-48da-aadf-5d1f19dc63e0 | D46: Completeness_Check-hscode-hazard_item | E46: 82db8d4f-b51a-4a12-a0bf-95c330496501 | F46: Completeness | G46: DED_Attribute_2972 | H46: hazard_item | I46: hazard_item,rec_status | J46: DED_Data_Table_193 | K46: br_hscode | L46: hscode | M46: 3
A47: DQO-3132 | B47: Completeness_Check-br_hscode-spare_part | C47: 8e7ca0ce-ffde-46b5-a3f5-26a6dc12e14e | D47: Completeness_Check-hscode-spare_part | E47: 0e36a6fe-4fd2-449e-9bd1-fac1291679f7 | F47: Completeness | G47: DED_Attribute_2973 | H47: spare_part | I47: spare_part,rec_status | J47: DED_Data_Table_193 | K47: br_hscode | L47: hscode | M47: 3
A48: DQO-3133 | B48: Completeness_Check-br_hscode-default_unit | C48: a73ce986-450a-4bea-8578-9e20b7f61ee2 | D48: Completeness_Check-hscode-default_unit | E48: 81555347-12f4-4cf4-9e18-50c6d9a523ee | F48: Completeness | G48: DED_Attribute_2974 | H48: default_unit | I48: default_unit,rec_status | J48: DED_Data_Table_193 | K48: br_hscode | L48: hscode | M48: 3
A49: DQO-3134 | B49: Completeness_Check-br_hscode-machine | C49: 59ce0121-e10c-48fc-a97f-9ada3be19054 | D49: Completeness_Check-hscode-machine | E49: 9a678168-ccd5-46a9-99ef-809a1deb3ff9 | F49: Completeness | G49: DED_Attribute_2975 | H49: machine | I49: machine,rec_status | J49: DED_Data_Table_193 | K49: br_hscode | L49: hscode | M49: 3
A50: DQO-3135 | B50: Comp_Check-br_hscode-hs_code_english_description | C50: 13835953-9ca7-4b6b-b4d6-3c0911bd3bc0 | D50: Comp_Check-hscode-hs_code_english_description | E50: 533d2a5a-217a-4e6b-b101-b99978e89b7e | F50: Completeness | G50: DED_Attribute_2976 | H50: hs_code_english_description | I50: hs_code_english_description,rec_status | J50: DED_Data_Table_193 | K50: br_hscode | L50: hscode | M50: 3
A51: DQO-3136 | B51: Completeness_Check-br_hscode-raw_material | C51: 2b3002a2-d39c-4382-9887-13c45036f67f | D51: Completeness_Check-hscode-raw_material | E51: a9b8491f-ede4-4e7f-bc16-e6f30418d583 | F51: Completeness | G51: DED_Attribute_2977 | H51: raw_material | I51: raw_material,rec_status | J51: DED_Data_Table_193 | K51: br_hscode | L51: hscode | M51: 3
A52: DQO-3137 | B52: Completeness_Check-br_hscode-hs-code | C52: e50c2866-b576-4dd6-90ac-29a01fc39f01 | D52: Completeness_Check-hscode-hs-code | E52: 77515665-f19c-481b-832e-35831a364dfc | F52: Completeness | G52: DED_Attribute_2978 | H52: hs-code | I52: hs-code,rec_status | J52: DED_Data_Table_193 | K52: br_hscode | L52: hscode | M52: 3
A53: DQO-2834 | B53: Uniqueness_Chk-br_hscode | C53: 440d36ea-8764-43c5-9602-5f478e5ba3ba | D53: Uniqueness_Chk-hscode | E53: d3320cd6-1018-4459-8f60-b58fdb980b3d | F53: Uniqueness | G53: N/A | H53: serv_prov_code, b1_per_id1, b1_per_id2, b1_per_id3, b1_per_type, b1_per_sub_type | I53: serv_prov_code,b1_per_id1,b1_per_id2,b1_per_id3,b1_per_type,b1_per_sub_type | J53: DED_Data_Table_193 | K53: br_hscode | L53: hscode | M53: 3
A54: DQO-3606 | B54: Consec_Chk-br_hscode-hs_code_arabic_description | C54: cd0fa653-858b-44a8-95b2-b5b6da779fce | D54: Consec_Chk-hscode-hs_code_arabic_description | E54: c5003a77-a0e8-4f96-b189-3bd58dab44c4 | F54: Conformity | G54: DED_Attribute_2971 | H54: hs_code_arabic_description | I54: hs_code_arabic_description,rec_status | J54: DED_Data_Table_193 | K54: br_hscode | L54: hscode | M54: 3
A55: DQO-3607 | B55: Consec_Spc_Chk-br_hscode-hazard_item | C55: b1f20e06-220f-4efd-a980-4c9c6278fa47 | D55: Consec_Chk-hscode-hazard_item | E55: e2052149-8a7e-4d13-9941-f7769b09efc9 | F55: Conformity | G55: DED_Attribute_2972 | H55: hazard_item | I55: hazard_item,rec_status | J55: DED_Data_Table_193 | K55: br_hscode | L55: hscode | M55: 3
A56: DQO-3608 | B56: Consec_Spc_Chk-br_hscode-spare_part | C56: 83d1220c-f9f4-4c8b-93dc-04544570c266 | D56: Consec_Chk-hscode-spare_part | E56: 7e725015-9bf9-40a8-99b5-cb70d3291f5d | F56: Conformity | G56: DED_Attribute_2973 | H56: spare_part | I56: spare_part,rec_status | J56: DED_Data_Table_193 | K56: br_hscode | L56: hscode | M56: 3
... A70: DQO-4248 | B70: Val_Chk-br_hscode-spare_part | C70: c1403253-1293-4657-ae9d-1d0721c914d2 | D70: Val_Chk-hscode-spare_part | E70: 53cdb550-bdab-46f9-ba74-175eca3da719 | F70: Conformity | G70: DED_Attribute_2973 | H70: spare_part | I70: spare_part,rec_status | J70: DED_Data_Table_193 | K70: br_hscode | L70: hscode | M70: 3
A71: DQO-2784 | B71: Freshness_Check-br_invest_in_building | C71: 4112050a-04d9-4c45-ae05-35daac454e50 | D71: Freshness_Check-invest_in_building | E71: d45ab5eb-66e0-4833-8b77-d30536c2f64b | F71: Timeliness | G71: N/A | H71: NA - Table level rule | I71: 0 | J71: DED_Data_Table_197 | K71: br_invest_in_building | L71: invest_in_building | M71: 3
A72: DQO-2836 | B72: Uniqueness_Chk-br_invest_in_building | C72: d6a52ca4-5ca1-48ef-80f7-dea64cfe1522 | D72: Uniqueness_Chk-invest_in_building | E72: 1e065258-b7d3-410e-ad95-bc8cd827ef4b | F72: Uniqueness | G72: N/A | H72: serv_prov_code, b1_per_id1, b1_per_id2, b1_per_id3, b1_per_type, b1_per_sub_type | I72: serv_prov_code,b1_per_id1,b1_per_id2,b1_per_id3,b1_per_type,b1_per_sub_type | J72: DED_Data_Table_197 | K72: br_invest_in_building | L72: invest_in_building | M72: 3
A73: DQO-3142 | B73: Comp_Chk-br_inve_in_building-investment_start_date | C73: fc5b0638-f79a-4b4f-b30c-bdd84d6fe969 | D73: Comp_Chk-inve_in_building-investment_start_date | E73: 7a5f3f58-ca89-4d3f-ace1-5eda7afe1f46 | F73: Completeness | G73: DED_Attribute_3031 | H73: investment_start_date | I73: investment_start_date,rec_status | J73: DED_Data_Table_197 | K73: br_invest_in_building | L73: invest_in_building | M73: 3
A74: DQO-3143 | B74: Comp_Chk-br_invest_in_building-investment_end_date | C74: 1e95ee4e-f38d-41d3-aae6-89c506a2b432 | D74: Comp_Chk-invest_in_building-investment_end_date | E74: 77e1008f-2a5a-4bf4-a6d3-1e0f1df397a1 | F74: Completeness | G74: DED_Attribute_3032 | H74: investment_end_date | I74: investment_end_date,rec_status | J74: DED_Data_Table_197 | K74: br_invest_in_building | L74: invest_in_building | M74: 3
A75: DQO-3144 | B75: Comp_Check-br_invest_in_building-first_name | C75: 981d3a90-ad73-4c9c-a8e2-273d1ed13a98 | D75: Comp_Check-invest_in_building-first_name | E75: 519fb419-54b5-44e4-b634-ffdeb3758f05 | F75: Completeness | G75: DED_Attribute_3033 | H75: first_name | I75: first_name,rec_status | J75: DED_Data_Table_197 | K75: br_invest_in_building | L75: invest_in_building | M75: 3
A76: DQO-3145 | B76: Completeness_Check-br_invest_in_building-last_name | C76: 29a093e4-d972-4fc1-8dcd-96063990bbba | D76: Completeness_Check-invest_in_building-last_name | E76: 44b5d426-46ce-47a5-b369-82d398c76f61 | F76: Completeness | G76: DED_Attribute_3034 | H76: last_name | I76: last_name,rec_status | J76: DED_Data_Table_197 | K76: br_invest_in_building | L76: invest_in_building | M76: 3
A77: DQO-3618 | B77: Consec_Chk-br_invest_bldg-investment_start_date | C77: 4773c700-19a6-4836-8514-7869166f1868 | D77: Consc_Chk-invest_in_building-investment_start_date | E77: 06d3423c-2b9e-434a-8dd4-62de67c10ce3 | F77: Conformity | G77: DED_Attribute_3031 | H77: investment_start_date | I77: investment_start_date,rec_status | J77: DED_Data_Table_197 | K77: br_invest_in_building | L77: invest_in_building | M77: 3
A78: DQO-3619 | B78: Consec_Chk-br_invest_bldg-investment_end_date | C78: 08cf6111-0183-4814-ae86-d4abbdfcb033 | D78: Consec_Chk-invest_in_building-investment_end_date | E78: 203c3b41-394e-4094-ab2a-1638132bee98 | F78: Conformity | G78: DED_Attribute_3032 | H78: investment_end_date | I78: investment_end_date,rec_status | J78: DED_Data_Table_197 | K78: br_invest_in_building | L78: invest_in_building | M78: 3
A79: DQO-3620 | B79: Consec_Spc_Chk-br_invest_in_building-first_name | C79: 6070a716-039c-4646-a52b-1a6f1306dba6 | D79: Consec_Chk-invest_in_building-first_name | E79: e25fcdbc-a9bd-4daf-8c33-9d299a47cd97 | F79: Conformity | G79: DED_Attribute_3033 | H79: first_name | I79: first_name,rec_status | J79: DED_Data_Table_197 | K79: br_invest_in_building | L79: invest_in_building | M79: 3
A80: DQO-3621 | B80: Consec_Spc_Chk-br_invest_in_building-last_name | C80: 75fddc81-4eef-420f-88b4-074c7fc73134 | D80: Consec_Chk-invest_in_building-last_name | E80: e2deab24-c3fd-4b88-812f-d6fe6fb13b4c | F80: Conformity | G80: DED_Attribute_3034 | H80: last_name | I80: last_name,rec_status | J80: DED_Data_Table_197 | K80: br_invest_in_building | L80: invest_in_building | M80: 3
A81: DQO-3971 | B81: Val_Chk-br_invest_in_building-first_name | C81: 0e87002c-1739-49ed-9770-bdf30664cdfc | D81: Val_Chk-invest_in_building-first_name | E81: 8b921833-7ce8-47b7-8cd5-abef8de2ba0d | F81: Conformity | G81: DED_Attribute_3033 | H81: first_name | I81: first_name,rec_status | J81: DED_Data_Table_197 | K81: br_invest_in_building | L81: invest_in_building | M81: 3
A82: DQO-3972 | B82: LTS_Chk-br_invest_in_building-first_name | C82: 21e5fa8b-c159-47b6-904c-48ec7523ba3b | D82: LTS_Chk-invest_in_building-first_name | E82: 78c42731-09fa-4da0-bf22-42f28b81d7f1 | F82: Conformity | G82: DED_Attribute_3033 | H82: first_name | I82: first_name,rec_status | J82: DED_Data_Table_197 | K82: br_invest_in_building | L82: invest_in_building | M82: 3
A83: DQO-4043 | B83: LTS_Chk-br_invest_in_building-last_name | C83: d59161cc-89aa-4353-87ec-f6b53e87665a | D83: LTS_Chk-invest_in_building-last_name | E83: a13762ba-b95d-4313-9dbb-d7d27c832b85 | F83: Conformity | G83: DED_Attribute_3034 | H83: last_name | I83: last_name,rec_status | J83: DED_Data_Table_197 | K83: br_invest_in_building | L83: invest_in_building | M83: 3
... A87: DQO-2527 | B87: Validity_Check-br_BLDG_INVEST-Invest_Start_Date | C87: a21cb888-bde8-4e69-ab6c-dc86135ecdad | D87: Validity_Check-BUILDING_INVEST-Invest_Start_Date | E87: 960728e0-25ff-482f-a75a-b6ed7665f8dd | F87: Conformity | G87: DED_Attribute_3031 | H87: investment_start_date | I87: investment_start_date,rec_status | J87: DED_Data_Table_197 | K87: br_invest_in_building | L87: invest_in_building | M87: 3
A88: DQO-2785 | B88: Freshness_Check-br_legal_form_detail | C88: 52472c3f-01c9-4874-a027-16a6cf80911f | D88: Freshness_Check-legal_form_detail | E88: f7ebb5f8-f210-4c67-bc56-2904843c4d73 | F88: Timeliness | G88: N/A | H88: NA - Table level rule | I88: 0 | J88: DED_Data_Table_198 | K88: br_legal_form_detail | L88: legal_form_detail | M88: 3
A89: DQO-2837 | B89: Uniqueness_Chk-br_legal_form_detail | C89: 3677f3ac-ad0b-4d99-9472-c4e36e25a8c3 | D89: Uniqueness_Chk-legal_form_detail | E89: af8533b5-e3a2-43ac-8db2-3baa6ab0c43b | F89: Uniqueness | G89: N/A | H89: serv_prov_code, b1_per_id1, b1_per_id2, b1_per_id3, b1_per_type, b1_per_sub_type | I89: serv_prov_code,b1_per_id1,b1_per_id2,b1_per_id3,b1_per_type,b1_per_sub_type | J89: DED_Data_Table_198 | K89: br_legal_form_detail | L89: legal_form_detail | M89: 3
A90: DQO-3146 | B90: Comp_Check-br_legal_form_detail-legal_form_arabic | C90: 7c9181e8-fb6c-429d-874e-4f393fe62578 | D90: Comp_Check-legal_form_detail-legal_form_arabic | E90: 7078b9de-21f6-48e4-96be-20dc3b6aa458 | F90: Completeness | G90: DED_Attribute_3043 | H90: legal_form_arabic | I90: legal_form_arabic,rec_status | J90: DED_Data_Table_198 | K90: br_legal_form_detail | L90: legal_form_detail | M90: 3
A91: DQO-3147 | B91: Comp_Check-br_legal_form_detail-capital_minimum | C91: 760aec61-a06b-469d-bda3-f0337facc156 | D91: Comp_Check-legal_form_detail-capital_minimum | E91: 6446f29d-158e-478a-9143-404997e9a250 | F91: Completeness | G91: DED_Attribute_3044 | H91: capital_minimum | I91: capital_minimum,rec_status | J91: DED_Data_Table_198 | K91: br_legal_form_detail | L91: legal_form_detail | M91: 3
A92: DQO-3148 | B92: Comp_Check-br_legal_form_detail-minimum_partners | C92: 97182588-1a62-4260-86fa-e86257a55856 | D92: Comp_Check-legal_form_detail-minimum_partners | E92: 6192ff8d-194c-41e6-9dfb-97e80fee125b | F92: Completeness | G92: DED_Attribute_3045 | H92: minimum_partners | I92: minimum_partners,rec_status | J92: DED_Data_Table_198 | K92: br_legal_form_detail | L92: legal_form_detail | M92: 3
A93: DQO-3149 | B93: Comp_Check-br_legal_form_detail-local_share | C93: 31acb705-d563-47a2-add1-3046b2644db6 | D93: Comp_Check-legal_form_detail-local_share | E93: ebe06111-4696-414f-a129-4b45f44f4725 | F93: Completeness | G93: DED_Attribute_3046 | H93: local_share | I93: local_share,rec_status | J93: DED_Data_Table_198 | K93: br_legal_form_detail | L93: legal_form_detail | M93: 3
A94: DQO-3150 | B94: Comp_Check-br_legal_form_detail-maximum_partners | C94: f4e64f54-9ac7-455b-bc7a-68ff5b393959 | D94: Comp_Check-legal_form_detail-maximum_partners | E94: bf309056-5a02-43d8-a27b-3ae881d6c6c0 | F94: Completeness | G94: DED_Attribute_3047 | H94: maximum_partners | I94: maximum_partners,rec_status | J94: DED_Data_Table_198 | K94: br_legal_form_detail | L94: legal_form_detail | M94: 3
A95: DQO-3151 | B95: Comp_Check-br_legal_form_detail-legal_form_english | C95: 1556b648-8a55-412f-9e9e-6a88d359184b | D95: Comp_Check-legal_form_detail-legal_form_english | E95: c90accd3-f9e6-4bc3-8d73-5f755c505460 | F95: Completeness | G95: DED_Attribute_3048 | H95: legal_form_english | I95: legal_form_english,rec_status | J95: DED_Data_Table_198 | K95: br_legal_form_detail | L95: legal_form_detail | M95: 3
A96: DQO-3152 | B96: Completeness_Check-br_legal_form_detail-fee | C96: a012c1de-68a0-4492-b698-d7d7ebbaf33e | D96: Completeness_Check-legal_form_detail-fee | E96: 193fa9dc-e410-4bc8-a7ed-23deff173839 | F96: Completeness | G96: DED_Attribute_3049 | H96: fee | I96: fee,rec_status | J96: DED_Data_Table_198 | K96: br_legal_form_detail | L96: legal_form_detail | M96: 3
A97: DQO-3622 | B97: Consec_Chk-br_legal_form-legal_form_arabic | C97: 9bc6e4c9-6a33-4d95-a94b-3b54b6b774b1 | D97: Consec_Chk-legal_form_detail-legal_form_arabic | E97: 4f225b1d-a7c8-4292-9a2a-694a646abb63 | F97: Conformity | G97: DED_Attribute_3043 | H97: legal_form_arabic | I97: legal_form_arabic,rec_status | J97: DED_Data_Table_198 | K97: br_legal_form_detail | L97: legal_form_detail | M97: 3
A98: DQO-3623 | B98: Consec_Chk-br_legal_form-capital_minimum | C98: eec12cfc-f0a4-414f-89c5-5215c0d442b7 | D98: Consec_Chk-legal_form_detail-capital_minimum | E98: 69ab1350-0a02-42b4-97e4-312dea326392 | F98: Conformity | G98: DED_Attribute_3044 | H98: capital_minimum | I98: capital_minimum,rec_status | J98: DED_Data_Table_198 | K98: br_legal_form_detail | L98: legal_form_detail | M98: 3
A99: DQO-3624 | B99: Consec_Chk-br_legal_form-minimum_partners | C99: c6411614-840f-4e12-acd4-ebd72a25cb52 | D99: Consec_Chk-legal_form_detail-minimum_partners | E99: 1c0ef33a-f5eb-449c-95e5-eea67903868a | F99: Conformity | G99: DED_Attribute_3045 | H99: minimum_partners | I99: minimum_partners,rec_status | J99: DED_Data_Table_198 | K99: br_legal_form_detail | L99: legal_form_detail | M99: 3
A100: DQO-3625 | B100: Consec_Spc_Chk-br_legal_form_detail-local_share | C100: b56075ac-7a8b-48da-b7e6-2a399250f4c1 | D100: Consec_Chk-legal_form_detail-local_share | E100: 5cd73f95-c693-4a39-87c1-f0834fa60af6 | F100: Conformity | G100: DED_Attribute_3046 | H100: local_share | I100: local_share,rec_status | J100: DED_Data_Table_198 | K100: br_legal_form_detail | L100: legal_form_detail | M100: 3
... A115: DQO-2561 | B115: Validity_Check-br_LEGAL_FORM_DTL-Minimum_Partners | C115: 2b86d7a7-da88-4b4d-a975-c9292d7b27c2 | D115: Validity_Check-LEGAL_FORM_DTL-Minimum_Partners | E115: 5c1cf613-be44-4ee4-a02c-f6baec519d0b | F115: Conformity | G115: DED_Attribute_3045 | H115: minimum_partners | I115: minimum_partners,rec_status | J115: DED_Data_Table_198 | K115: br_legal_form_detail | L115: legal_form_detail | M115: 3
A116: DQO-2783 | B116: Freshness_Check-br_innovator_info | C116: e401b440-a54c-4819-960e-81e3a2a0057d | D116: Freshness_Check-innovator_info | E116: 05c9a110-138a-49df-803f-0c2ce9fea950 | F116: Timeliness | G116: N/A | H116: NA - Table level rule | I116: 0 | J116: DED_Data_Table_196 | K116: br_innovator_info | L116: innovator_info | M116: 3
A117: DQO-3138 | B117: Comp_Check-br_innovator_info-study_specialization | C117: 17b4d0fd-a1a9-41da-b93b-d88a9517d115 | D117: Comp_Check-innovator_info-study_specialization | E117: 2e4b0fd6-0edf-48de-aa23-43b7c8bf86dc | F117: Completeness | G117: DED_Attribute_3019 | H117: study_specialization | I117: study_specialization,rec_status | J117: DED_Data_Table_196 | K117: br_innovator_info | L117: innovator_info | M117: 3
A118: DQO-3139 | B118: Completeness_Check-br_innovator_info-project_name | C118: 08c3bbc2-2f8f-4e22-8e77-9b0c6894c1f6 | D118: Completeness_Check-innovator_info-project_name | E118: d82e863b-f500-49b5-a125-3af07d74f5a7 | F118: Completeness | G118: DED_Attribute_3020 | H118: project_name | I118: project_name,rec_status | J118: DED_Data_Table_196 | K118: br_innovator_info | L118: innovator_info | M118: 3
A119: DQO-3140 | B119: Comp_Check-br_innovator_info-startup_location | C119: 76abbe71-5f56-4c59-9f4c-e5f5d1ddf089 | D119: Comp_Check-innovator_info-startup_location | E119: fc19b184-7911-470b-85ed-d35cefa1f326 | F119: Completeness | G119: DED_Attribute_3021 | H119: startup_location | I119: startup_location,rec_status | J119: DED_Data_Table_196 | K119: br_innovator_info | L119: innovator_info | M119: 3
A120: DQO-3141 | B120: Completeness_Check-br_innovator_info-startup_name | C120: 9198727f-42bf-4d46-9a7d-e9c6b1831cee | D120: Completeness_Check-innovator_info-startup_name | E120: 3c713d68-bbc0-472e-af7d-d127d49d4397 | F120: Completeness | G120: DED_Attribute_3022 | H120: startup_name | I120: startup_name,rec_status | J120: DED_Data_Table_196 | K120: br_innovator_info | L120: innovator_info | M120: 3
A121: DQO-2835 | B121: Uniqueness_Chk-br_innovator_info | C121: e8f87229-d0d5-4abe-bd42-fe838115e623 | D121: Uniqueness_Chk-innovator_info | E121: 0db70f14-59c9-4914-9643-8e3f795c0b3d | F121: Uniqueness | G121: N/A | H121: serv_prov_code, b1_per_id1, b1_per_id2, b1_per_id3, b1_per_type, b1_per_sub_type | I121: serv_prov_code,b1_per_id1,b1_per_id2,b1_per_id3,b1_per_type,b1_per_sub_type | J121: DED_Data_Table_196 | K121: br_innovator_info | L121: innovator_info | M121: 3
A122: DQO-3614 | B122: Consec_Chk-br_innov_info-study_specialization | C122: e53a02ea-21af-4138-a654-55f0afa10ff9 | D122: Consec_Chk-innovator_info-study_specialization | E122: 5d008797-c577-44af-8ae9-b113374b199f | F122: Conformity | G122: DED_Attribute_3019 | H122: study_specialization | I122: study_specialization,rec_status | J122: DED_Data_Table_196 | K122: br_innovator_info | L122: innovator_info | M122: 3
A123: DQO-3615 | B123: Consec_Spc_Chk-br_innovator_info-project_name | C123: 2e07cbd4-a05b-47e7-9483-459b63a45f46 | D123: Consec_Chk-innovator_info-project_name | E123: 37733b64-e059-4c5b-9af5-d91acdc2f2be | F123: Conformity | G123: DED_Attribute_3020 | H123: project_name | I123: project_name,rec_status | J123: DED_Data_Table_196 | K123: br_innovator_info | L123: innovator_info | M123: 3
A124: DQO-3616 | B124: Consec_Spc_Chk-br_innovator_info-startup_location | C124: 6e0519b4-c61c-4bb4-96c9-3a119bf20613 | D124: Consec_Chk-innovator_info-startup_location | E124: 56c799c3-40e4-421f-a646-715b5f4d2ddb | F124: Conformity | G124: DED_Attribute_3021 | H124: startup_location | I124: startup_location,rec_status | J124: DED_Data_Table_196 | K124: br_innovator_info | L124: innovator_info | M124: 3
A125: DQO-3617 | B125: Consec_Spc_Chk-br_innovator_info-startup_name | C125: c98964ea-c4bb-4945-ada1-f296eb57b9b0 | D125: Consec_Chk-innovator_info-startup_name | E125: 260c60f8-9ada-4e70-9054-d412d5a13d0b | F125: Conformity | G125: DED_Attribute_3022 | H125: startup_name | I125: startup_name,rec_status | J125: DED_Data_Table_196 | K125: br_innovator_info | L125: innovator_info | M125: 3
A126: DQO-4194 | B126: Val_Chk-br_innovator_info-project_name | C126: 0151b357-415f-43cc-b7c7-701c805f1eb4 | D126: Val_Chk-innovator_info-project_name | E126: cf76202c-c5c8-461f-807c-1da3e7be0abc | F126: Conformity | G126: DED_Attribute_3020 | H126: project_name | I126: project_name,rec_status,startup_name | J126: DED_Data_Table_196 | K126: br_innovator_info | L126: innovator_info | M126: 3
A127: DQO-4195 | B127: Len_Val_Chk-br_innovator_info-project_name | C127: e525d123-19ee-4bcb-a3d7-c9239d26031a | D127: Len_Val_Chk-innovator_info-project_name | E127: 6ddc023b-af2d-4da8-8aaf-c4db538e1278 | F127: Conformity | G127: DED_Attribute_3020 | H127: project_name | I127: project_name,rec_status | J127: DED_Data_Table_196 | K127: br_innovator_info | L127: innovator_info | M127: 3
A128: DQO-4196 | B128: LTS_Chk-br_innovator_info-project_name | C128: 44554468-50b4-452b-b430-83405d2a9b74 | D128: LTS_Chk-innovator_info-project_name | E128: 4cdd9e5e-8b68-469f-939c-b082069cdabf | F128: Conformity | G128: DED_Attribute_3020 | H128: project_name | I128: project_name,rec_status | J128: DED_Data_Table_196 | K128: br_innovator_info | L128: innovator_info | M128: 3
... A131: DQO-4255 | B131: LTS_Chk-br_innovator_info-study_specialization | C131: 09c00596-e107-4c23-b0f2-d0a108ef041d | D131: LTS_Chk-innovator_info-study_specialization | E131: f9f6beb7-4a88-4cca-9aaa-14331af8ea01 | F131: Conformity | G131: DED_Attribute_3019 | H131: study_specialization | I131: study_specialization,rec_status | J131: DED_Data_Table_196 | K131: br_innovator_info | L131: innovator_info | M131: 3
A132: DQO-2767 | B132: Freshness_Check-br_address | C132: d8cb2526-731e-46e8-86bb-e5218320fad4 | D132: Freshness_Check-address | E132: 2ead4e08-0d92-492e-ab3b-819cc46196f0 | F132: Timeliness | G132: N/A | H132: NA - Table level rule | I132: 0 | J132: DED_Data_Table_178 | K132: br_address | L132: address | M132: 3
A133: DQO-2819 | B133: Uniqueness_Chk-br_address | C133: a8f8be2b-9a07-4b1a-a184-d31fc89aadfd | D133: Uniqueness_Chk-address | E133: 791b70b2-1f95-43b8-8347-5d085811764e | F133: Uniqueness | G133: N/A | H133: serv_prov_code, b1_per_id1, b1_per_id2, b1_per_id3, b1_per_type, b1_per_sub_type | I133: serv_prov_code,b1_per_id1,b1_per_id2,b1_per_id3,b1_per_type,b1_per_sub_type | J133: DED_Data_Table_178 | K133: br_address | L133: address | M133: 3
A134: DQO-2919 | B134: Completeness_Check-br_address-land_area_in_sq_m | C134: 51c07db6-042d-49c9-a1c3-5645c71251e5 | D134: Completeness_Check-address-land_area_in_sq_m | E134: b37d898f-6424-4683-895e-ba2d72a52d7c | F134: Completeness | G134: DED_Attribute_2601 | H134: land_area_in_sq_m | I134: land_area_in_sq_m,rec_status | J134: DED_Data_Table_178 | K134: br_address | L134: address | M134: 3
A135: DQO-2920 | B135: Completeness_Check-br_address-sector | C135: e1498b72-b903-4243-8341-fdc7550a443d | D135: Completeness_Check-address-sector | E135: 9d63efbf-b28a-4f21-be7b-beb426819a43 | F135: Completeness | G135: DED_Attribute_2013 | H135: sector | I135: sector,rec_status | J135: DED_Data_Table_178 | K135: br_address | L135: address | M135: 3
A136: DQO-2921 | B136: Completeness_Check-br_address-land_location | C136: 8c8c4ace-8e68-461d-8aa0-8725f0b26fb4 | D136: Completeness_Check-address-land_location | E136: 6da05fd4-3e0c-4726-8391-9e21ee8f8eb7 | F136: Completeness | G136: DED_Attribute_2603 | H136: land_location | I136: land_location,rec_status | J136: DED_Data_Table_178 | K136: br_address | L136: address | M136: 3
A137: DQO-2922 | B137: Completeness_Check-br_address-tenant_name | C137: ab4d84f6-d8be-4f4f-a637-59ddb24497bd | D137: Completeness_Check-address-tenant_name | E137: 37794055-b514-437d-90e4-ae6bb131d609 | F137: Completeness | G137: DED_Attribute_2604 | H137: tenant_name | I137: tenant_name,rec_status | J137: DED_Data_Table_178 | K137: br_address | L137: address | M137: 3
A138: DQO-2923 | B138: Completeness_Check-br_address-zone | C138: 2b61bfbd-05e7-4b0d-9e4a-0014b76b4963 | D138: Completeness_Check-address-zone | E138: 9a178106-ee62-4e0c-9536-0dcc32035c4e | F138: Completeness | G138: DED_Attribute_2016 | H138: zone | I138: zone,rec_status | J138: DED_Data_Table_178 | K138: br_address | L138: address | M138: 3
A139: DQO-2924 | B139: Completeness_Check-br_address-city | C139: 04c5cb3c-255f-48f1-b726-f3f689cec2b8 | D139: Completeness_Check-address-city | E139: 5a8609f2-b554-4ccc-a794-e73d615d2a55 | F139: Completeness | G139: DED_Attribute_2010 | H139: city | I139: city,rec_status | J139: DED_Data_Table_178 | K139: br_address | L139: address | M139: 3
...

Sheet A
A1: Data Asset ID | B1: Data Asset Name (English, Silver) | C1: Sprint | D1: Domain | E1: Bronze Name
A2: DED_Data_Table_001 | B2: Financial_Audit_Trail | C2: Sprint 1 | D2: Financial Information | E2: ACCOUNTING_AUDIT_TRAIL
A3: DED_Data_Table_002 | B3: Status_Lookup | C3: Sprint 1 | D3: Economic Licenses | E3: APP_STATUS_GROUP
A4: DED_Data_Table_003 | B4: Status_Lookup_Language | C4: Sprint 1 | D4: Economic Licenses | E4: APP_STATUS_GROUP_I18N
A5: DED_Data_Table_004 | B5: Application_Master | C5: Sprint 1 | D5: Economic Licenses | E5: B1PERMIT
A6: DED_Data_Table_005 | B6: License_Expiration | C6: Sprint 1 | D6: Economic Licenses | E6: B1_EXPIRATION
A7: DED_Data_Table_006 | B7: Application_Address | C7: Sprint 1 | D7: Economic Licenses | E7: B3ADDRES
A8: DED_Data_Table_007 | B8: Application_District | C8: Sprint 1 | D8: Economic Licenses | E8: B3ADDRES_DISTRICT
A9: DED_Data_Table_008 | B9: Investor | C9: Sprint 1 | D9: Economic Licenses | E9: B3CONTACT
A10: DED_Data_Table_009 | B10: Company_Name | C10: Sprint 1 | D10: Economic Licenses | E10: B3CONTRA
A11: DED_Data_Table_010 | B11: Requirement_Condition | C11: Sprint 1 | D11: Economic Licenses | E11: B6CONDIT
A12: DED_Data_Table_011 | B12: Requirement_Condition_Dtl | C12: Sprint 1 | D12: Economic Licenses | E12: B6CONDIT_DETAIL
... A139: DED_Data_Table_236 | B139: rapo_attribute_i18n | C139: Sprint 2 | D139: Economic Licenses | E139: RAPO_ATTRIBUTE_I18N

Sheet Sheet1

Sheet T
A1: Data Attribute ID | B1: Data Attribute Name (English, Silver) | C1: Data Asset ID | D1: Data Asset Name (English, Silver)
A2: DED_Attribute_0001 | B2: SERV_PROV_CODE | C2: DED_Data_Table_001 | D2: Financial_Audit_Trail
A3: DED_Attribute_0002 | B3: B1_PER_ID1 | C3: DED_Data_Table_001 | D3: Financial_Audit_Trail
A4: DED_Attribute_0003 | B4: ACC_AUDIT_SEQ_NBR | C4: DED_Data_Table_001 | D4: Financial_Audit_Trail
A5: DED_Attribute_0004 | B5: B1_PER_ID2 | C5: DED_Data_Table_022 | D5: Financial_Audit_Trail
A6: DED_Attribute_0005 | B6: B1_PER_ID3 | C6: DED_Data_Table_001 | D6: Financial_Audit_Trail
A7: DED_Attribute_0006 | B7: INVOICE_NBR | C7: DED_Data_Table_001 | D7: Financial_Audit_Trail
A8: DED_Attribute_0007 | B8: RECEIPT_NBR | C8: DED_Data_Table_001 | D8: Financial_Audit_Trail
A9: DED_Attribute_0008 | B9: PAYMENT_SEQ_NBR | C9: DED_Data_Table_001 | D9: Financial_Audit_Trail
A10: DED_Attribute_0009 | B10: RECEIPT_AMOUNT | C10: DED_Data_Table_001 | D10: Financial_Audit_Trail
A11: DED_Attribute_0010 | B11: ACTION | C11: DED_Data_Table_001 | D11: Financial_Audit_Trail
A12: DED_Attribute_0011 | B12: FEEITEM_SEQ_NBR | C12: DED_Data_Table_001 | D12: Financial_Audit_Trail
... A4384: DED_Attribute_5684 | B4384: zip | C4384: DED_Data_Table_047 | D4384: license_professional

Sheet Sprint 1 Silver Dump
A1: name | B1: rule_id | C1: domain_id | D1: product_id | E1: asset_id | F1: dataset_name | G1: rule_expression_logic | H1: filter_Expression_logic | I1: null_Expression_logic | J1: column | K1: status | L1: dimension | M1: score | N1: type | O1: description | P1: typeProperties
A2: Completeness_Check-Application_Invoice-INVOICE_NBR | B2: d0745851-8329-4553-a2d9-4cfcf98b6cb2 | C2: 5718e0f6-886b-4e80-9980-37bac024cb4e | D2: 0ab78cb4-2cfa-409c-98c9-f784133fa8ff | E2: 93a78fa2-4157-4b13-b61c-06329e3c5377 | F2: application_invoice | J2: invoice_nbr | K2: Active | L2: Completeness | M2: 1 | N2: NotNull | O2: Checks that Application_Invoice-INVOICE_NBR is populated for every in-scope record and is not null, blank, or whitespace-only. Business meaning: Invoice number associated with the financial transaction recorded in the audit trail. | P2: {'column': {'type': 'Column', 'value': 'invoice_nbr'}}
A3: DataTypeValidity_Check- Appl_Inv-INVOICE_NBR | B3: 842f973e-0bb7-4e98-b887-21ac21339054 | C3: 5718e0f6-886b-4e80-9980-37bac024cb4e | D3: 0ab78cb4-2cfa-409c-98c9-f784133fa8ff | E3: 93a78fa2-4157-4b13-b61c-06329e3c5377 | F3: application_invoice | J3: invoice_nbr | K3: Active | L3: Consistency | M3: 1 | N3: TypeMatch | O3: Checks that Application_Invoice-INVOICE_NBR conforms to the expected source/Purview data type (NUMBER) so the value can be parsed and used consistently. Business meaning: Invoice number associated with the financial transaction recorded in the audit trail. | P3: {'column': {'type': 'Column', 'value': 'invoice_nbr'}}
A4: NumericValidity_Check-Appl_Inv-INVOICE_NBR | B4: eb731fa7-08c6-4d5d-a3d6-a66d17816269 | C4: 5718e0f6-886b-4e80-9980-37bac024cb4e | D4: 0ab78cb4-2cfa-409c-98c9-f784133fa8ff | E4: 93a78fa2-4157-4b13-b61c-06329e3c5377 | F4: application_invoice | G4: invoice_nbr >= 0 | H4: rec_status = 'A' AND invoice_nbr IS NOT NULL | J4: invoice_nbr,rec_status | K4: Active | L4: Conformity | M4: 1 | N4: CustomSQL | O4: Checks that non-null Application_Invoice-INVOICE_NBR values are positive whole-number identifiers, rejecting decimals, zero, negative, and non-numeric values. Business meaning: Invoice number associated with the financial transaction recorded in the audit trail. | P4: {'condition': 'invoice_nbr >= 0', 'columns': [{'value': 'invoice_nbr', 'type': 'Column'}, {'value': 'rec_status', 'type': 'Column'}], 'emptyCriteria': None, 'filterCriteria': "rec_status = 'A' AND invoice_nbr IS NOT NULL", 'ruleDialect': 'SparkSQL'}
A5: Completeness_Check-Appl_Inv-INVOICE_AMOUNT | B5: a5d78de9-918a-45f7-933a-8fc6ad551cf0 | C5: 5718e0f6-886b-4e80-9980-37bac024cb4e | D5: 0ab78cb4-2cfa-409c-98c9-f784133fa8ff | E5: 93a78fa2-4157-4b13-b61c-06329e3c5377 | F5: application_invoice | J5: invoice_amount | K5: Active | L5: Completeness | M5: 1 | N5: NotNull | O5: Checks that Application_Invoice-INVOICE_AMOUNT is populated for every in-scope record and is not null, blank, or whitespace-only. Business meaning: Amount of money associated with the financial item (fee, payment, refund, or adjustment) recorded for this transaction. | P5: {'column': {'type': 'Column', 'value': 'invoice_amount'}}
A6: DataTypeValidity_Check-Appl_Inv-INVOICE_AMOUNT | B6: 0a8f8f4d-9802-40f9-bb3a-a3de9d839fc4 | C6: 5718e0f6-886b-4e80-9980-37bac024cb4e | D6: 0ab78cb4-2cfa-409c-98c9-f784133fa8ff | E6: 93a78fa2-4157-4b13-b61c-06329e3c5377 | F6: application_invoice | J6: invoice_amount | K6: Active | L6: Consistency | M6: 1 | N6: TypeMatch | O6: Checks that Application_Invoice-INVOICE_AMOUNT conforms to the expected source/Purview data type (NUMBER) so the value can be parsed and used consistently. Business meaning: Amount of money associated with the financial item (fee, payment, refund, or adjustment) recorded for this transaction. | P6: {'column': {'type': 'Column', 'value': 'invoice_amount'}}
A7: RangeValidity_Check-Appl_Inv-INVOICE_AMOUNT | B7: 84be5831-a889-4861-bc7b-26192148d3f1 | C7: 5718e0f6-886b-4e80-9980-37bac024cb4e | D7: 0ab78cb4-2cfa-409c-98c9-f784133fa8ff | E7: 93a78fa2-4157-4b13-b61c-06329e3c5377 | F7: application_invoice | G7: invoice_amount >= 0 | J7: invoice_amount | K7: Disabled | L7: Conformity | M7: 0.8785779 | N7: CustomSQL | O7: Checks Application_Invoice.INVOICE_AMOUNT with the configured Purview Regex to enforce: >= 99.5% non-negative, with documented exceptions for voids, refunds, adjustments, and reversals.. Business meaning: Amount of money associated with the financial item (fee, payment, refund, or adjustment) recorded for this transaction. | P7: {'condition': ' invoice_amount >= 0', 'columns': [{'value': 'invoice_amount', 'type': 'Column'}], 'ruleDialect': 'SparkSQL'}
A8: Completeness_Check-Appl_Inv-INVOICE_DATE | B8: 9fc68d2e-cf36-4bed-bbb0-22fdeb181241 | C8: 5718e0f6-886b-4e80-9980-37bac024cb4e | D8: 0ab78cb4-2cfa-409c-98c9-f784133fa8ff | E8: 93a78fa2-4157-4b13-b61c-06329e3c5377 | F8: application_invoice | J8: invoice_date | K8: Active | L8: Completeness | M8: 1 | N8: NotNull | O8: Checks that Application_Invoice-INVOICE_DATE is populated for every in-scope record and is not null, blank, or whitespace-only. Business meaning: Business date associated with this record event (creation, update, status change, or processing), used for reporting and audit tracking. | P8: {'column': {'type': 'Column', 'value': 'invoice_date'}}
A9: DataTypeValidity_Check-Appl_Inv-INVOICE_DATE | B9: bec351be-650f-4fb7-b8e9-fb2e383bee44 | C9: 5718e0f6-886b-4e80-9980-37bac024cb4e | D9: 0ab78cb4-2cfa-409c-98c9-f784133fa8ff | E9: 93a78fa2-4157-4b13-b61c-06329e3c5377 | F9: application_invoice | J9: invoice_date | K9: Active | L9: Consistency | M9: 1 | N9: TypeMatch | O9: Checks that Application_Invoice-INVOICE_DATE conforms to the expected source/Purview data type (DATE) so the value can be parsed and used consistently. Business meaning: Business date associated with this record event (creation, update, status change, or processing), used for reporting and audit tracking. | P9: {'column': {'type': 'Column', 'value': 'invoice_date'}}
A10: DupRows_Check-Appl_Inv-SERV_PROV_CODE_INVOICE_NBR | B10: 8375ac64-aea6-4421-bcac-937afe68e528 | C10: 5718e0f6-886b-4e80-9980-37bac024cb4e | D10: 0ab78cb4-2cfa-409c-98c9-f784133fa8ff | E10: 93a78fa2-4157-4b13-b61c-06329e3c5377 | F10: application_invoice | J10: serv_prov_code,invoice_nbr | K10: Active | L10: Accuracy | M10: 1 | N10: Duplicate | O10: Checks that Application_Invoice has no duplicate active logical records for the approved business key (SERV_PROV_CODE, INVOICE_NBR). | P10: {'columns': [{'value': 'serv_prov_code', 'type': 'Column'}, {'value': 'invoice_nbr', 'type': 'Column'}]}
A11: Freshness_Check-SLA-Appl_Inv | B11: 3de58782-3397-4045-af8c-a98eb905dc8e | C11: 5718e0f6-886b-4e80-9980-37bac024cb4e | D11: 0ab78cb4-2cfa-409c-98c9-f784133fa8ff | E11: 93a78fa2-4157-4b13-b61c-06329e3c5377 | F11: application_invoice | G11: 172800000 | K11: Active | L11: Timeliness | M11: 1 | N11: Timeliness | O11: Checks that the Application_Invoice asset is refreshed within the approved operational SLA so its CDE values remain current for reporting and downstream consumption. | P11: {'timeDifference': 172800000}
A12: Concistency_Check-Appl_Inv-Invoice_Amt | B12: 666e2480-1776-431f-8061-635ec42fa7f6 | C12: 5718e0f6-886b-4e80-9980-37bac024cb4e | D12: 0ab78cb4-2cfa-409c-98c9-f784133fa8ff | E12: 93a78fa2-4157-4b13-b61c-06329e3c5377 | F12: application_invoice | G12: invoice_amount IS NOT NULL OR (invoice_date IS NOT NULL AND invoice_amount IS NOT NULL) | J12: invoice_amount,invoice_date | K12: Active | L12: Consistency | M12: 1 | N12: CustomSQL | O12: Checks that related fields in Application_Invoice satisfy the invoice amount/date consistency condition using a single-dataset Purview Custom row expression. Expected outcome: 100% of invoice amount records must have an invoice date. This prevents logically incomplete or inconsistent records without requiring cross-table joins. | P12: {'condition': 'invoice_amount IS NOT NULL OR (invoice_date IS NOT NULL AND invoice_amount IS NOT NULL)', 'filterCriteria': '', 'columns': [{'value': 'invoice_amount', 'type': 'Column'}, {'value': 'invoice_date', 'type': 'Column'}], 'ruleDialect': 'SparkSQL'}
A13: DateRangeVal_Chk-application_invoice-INVOICE_DAT | B13: 70e8036c-ab91-48ab-8307-32596c1966ae | C13: 5718e0f6-886b-4e80-9980-37bac024cb4e | D13: 0ab78cb4-2cfa-409c-98c9-f784133fa8ff | E13: 93a78fa2-4157-4b13-b61c-06329e3c5377 | F13: application_invoice | G13: !isNull({invoice_date}) && regexMatch(substring(toString({invoice_date}), 1, 10), '^[0-9]{4}-[0-9]{2}-[0-9]{2}$') && !isNull(toDate(substring(toString({invoice_date}), 1, 10), 'yyyy-MM-dd')) | H13: {rec_status} == 'A' && !isNull({invoice_date}) | J13: invoice_date,rec_status | K13: Active | L13: Conformity | M13: 1 | N13: CustomTruth | O13: This check ensures if the Invoice_Date follows the relevant date format | P13: {'condition': "!isNull({invoice_date})\n&& regexMatch(substring(toString({invoice_date}), 1, 10), '^[0-9]{4}-[0-9]{2}-[0-9]{2}$')\n&& !isNull(toDate(substring(toString({invoice_date}), 1, 10), 'yyyy-MM-dd'))", 'columns': [{'value': 'invoice_date', 'type': 'Column'}, {'value': 'rec_status', 'type': 'Column'}], 'emptyCriteria': None, 'filterCriteria': "{rec_status} == 'A' && !isNull({invoice_date})", 'ruleDialect': 'ADF'}
A14: Completeness_Check-workflow_language-RES_ID | B14: e96e8b44-dd07-41d5-8399-f8f025d6006f | C14: 212551b9-97e3-4ffc-9c4e-169f987349b2 | D14: cf23386e-459a-4327-88d5-4b456681e54e | E14: aa44b232-85dd-47d3-be0a-7f33f0327069 | F14: workflow_language | J14: res_id | K14: Active | L14: Completeness | M14: 1 | N14: NotNull | O14: Checks that Workflow_Language.RES_ID is populated for every in-scope record and is not null, blank, or whitespace-only. Business meaning: Identifier/code for res identifier used to uniquely reference the related entity in Accela and support joins, auditing, and reporting. Implement in Purview with the Empty/blank fields rule. | P14: {'column': {'type': 'Column', 'value': 'res_id'}}
A15: Datatype_Check-workflow_language.RES_ID | B15: 6883c8b0-4889-47d6-80e2-b338f454f91f | C15: 212551b9-97e3-4ffc-9c4e-169f987349b2 | D15: cf23386e-459a-4327-88d5-4b456681e54e | E15: aa44b232-85dd-47d3-be0a-7f33f0327069 | F15: workflow_language | J15: res_id | K15: Active | L15: Consistency | M15: 1 | N15: TypeMatch | O15: Checks that workflow_language.RES_ID conforms to the expected source/Purview data type (NUMBER) so the value can be parsed and used consistently. Business meaning: Identifier/code for res identifier used to uniquely reference the related entity in Accela and support joins, auditing, and reporting. Implement in Purview with the Data type match rule. | P15: {'column': {'type': 'Column', 'value': 'res_id'}}
A16: Completeness_Check-workflow_language.LANG_ID | B16: 1971990c-2500-4c52-8d9e-ce6ebfbc3eb8 | C16: 212551b9-97e3-4ffc-9c4e-169f987349b2 | D16: cf23386e-459a-4327-88d5-4b456681e54e | E16: aa44b232-85dd-47d3-be0a-7f33f0327069 | F16: workflow_language | J16: lang_id | K16: Active | L16: Completeness | M16: 1 | N16: NotNull | O16: Checks that workflow_language.LANG_ID is populated for every in-scope record and is not null, blank, or whitespace-only. Business meaning: Identifier/code for lang identifier used to uniquely reference the related entity in Accela and support joins, auditing, and reporting. Implement in Purview with the Empty/blank fields rule. | P16: {'column': {'type': 'Column', 'value': 'lang_id'}}
A17: Uniqueness-workflow_language-RES_ID | B17: 919e7ad0-9ece-4909-a806-c7a100a2280a | C17: 212551b9-97e3-4ffc-9c4e-169f987349b2 | D17: cf23386e-459a-4327-88d5-4b456681e54e | E17: aa44b232-85dd-47d3-be0a-7f33f0327069 | F17: workflow_language | J17: lang_id,res_id | K17: Active | L17: Accuracy | M17: 1 | N17: Duplicate | O17: Checks that workflow_languagehas no duplicate active logical records for the approved business key (RES_ID, LANG_ID). Implement as the single Purview Duplicate rows rule for the asset; any duplicates should be triaged and remediated at source. | P17: {'columns': [{'value': 'lang_id', 'type': 'Column'}, {'value': 'res_id', 'type': 'Column'}]}
A18: Timeliness-workflow_language-Rec_Status | B18: b4f7be75-4272-46ba-83f5-a22e88699963 | C18: 212551b9-97e3-4ffc-9c4e-169f987349b2 | D18: cf23386e-459a-4327-88d5-4b456681e54e | E18: aa44b232-85dd-47d3-be0a-7f33f0327069 | F18: workflow_language | G18: 172800000 | K18: Active | L18: Timeliness | M18: 1 | N18: Timeliness | O18: Checks that the workflow_language asset is refreshed within the approved operational SLA so its CDE values remain current for reporting and downstream consumption. Implement in Purview with the asset-level Freshness rule; the rule score is pass/fail. | P18: {'timeDifference': 172800000}
A19: Number_Format_Check-Workflow_Language-LANG_ID | B19: 25725e72-4b1c-46d2-a631-fa8492d9ab96 | C19: 212551b9-97e3-4ffc-9c4e-169f987349b2 | D19: cf23386e-459a-4327-88d5-4b456681e54e | E19: aa44b232-85dd-47d3-be0a-7f33f0327069 | F19: workflow_language | G19: regexMatch(lang_id ,'ar_AE') || regexMatch(lang_id,'en_US') | J19: lang_id | K19: Disabled | L19: Conformity | M19: -1 | N19: CustomSQL | O19: Checks that workflow_language.LANG_ID conforms to the expected source/Purview data type (VARCHAR2) so the value can be parsed and used consistently. Business meaning: Identifier/code for lang identifier used to uniquely reference the related entity in Accela and support joins, auditing, and reporting. | P19: {'condition': "regexMatch(lang_id ,'ar_AE') || regexMatch(lang_id,'en_US')", 'columns': [{'value': 'lang_id', 'type': 'Column'}], 'ruleDialect': 'SparkSQL'}
A20: Number_Format_Check-Workflow_Language-RES_ID | B20: c0df239b-75fa-48ca-96bf-5a0dca29df77 | C20: 212551b9-97e3-4ffc-9c4e-169f987349b2 | D20: cf23386e-459a-4327-88d5-4b456681e54e | E20: aa44b232-85dd-47d3-be0a-7f33f0327069 | F20: workflow_language | G20: res_id > 0 | H20: rec_status = 'A' AND res_id IS NOT NULL | J20: res_id,rec_status | K20: Active | L20: Conformity | M20: 1 | N20: CustomSQL | O20: Checks that non-null GPROCESS_I18N.RES_ID values are positive whole-number identifiers, rejecting, zero, negative. Business meaning: Identifier/code for res identifier used to uniquely reference the related entity in Accela and support joins, auditing, and reporting. Implement in Purview with the configured Custom SQL row expression. | P20: {'condition': 'res_id > 0', 'columns': [{'value': 'res_id', 'type': 'Column'}, {'value': 'rec_status', 'type': 'Column'}], 'emptyCriteria': None, 'filterCriteria': "rec_status = 'A' AND res_id IS NOT NULL", 'ruleDialect': 'SparkSQL'}
A21: Validity_Check-Workflow_Language-LANG_ID | B21: b0dc3d26-ad33-4bec-b11a-f27c4f794787 | C21: 212551b9-97e3-4ffc-9c4e-169f987349b2 | D21: cf23386e-459a-4327-88d5-4b456681e54e | E21: aa44b232-85dd-47d3-be0a-7f33f0327069 | F21: workflow_language | G21: regexMatch({lang_id} ,'ar_AE') || regexMatch({lang_id} ,'en_US') | J21: lang_id | K21: Disabled | L21: Conformity | M21: -1 | N21: Regex | O21: Checks that the language code matches an approved value, so the information remains valid and consistent. | P21: {'column': {'type': 'Column', 'value': 'lang_id'}, 'pattern': "regexMatch({lang_id} ,'ar_AE') || regexMatch({lang_id} ,'en_US')"}
A22: Validity_Chk-Workflow_Language-LANG_ID | B22: f585947a-4233-4248-8ae8-2b4e0d5701ea | C22: 212551b9-97e3-4ffc-9c4e-169f987349b2 | D22: cf23386e-459a-4327-88d5-4b456681e54e | E22: aa44b232-85dd-47d3-be0a-7f33f0327069 | F22: workflow_language | G22: regexMatch({lang_id} ,'ar_AE') || regexMatch({lang_id} ,'en_US') | H22: {rec_status} == 'A' && !isNull({lang_id}) | J22: lang_id,rec_status | K22: Active | L22: Conformity | M22: 1 | N22: CustomTruth | O22: Checks that the language code matches an approved value, so the information remains valid and consistent. | P22: {'condition': "regexMatch({lang_id} ,'ar_AE') || regexMatch({lang_id} ,'en_US')", 'columns': [{'value': 'lang_id', 'type': 'Column'}, {'value': 'rec_status', 'type': 'Column'}], 'emptyCriteria': None, 'filterCriteria': "{rec_status} == 'A' && !isNull({lang_id})", 'ruleDialect': 'ADF'}
A23: Completeness_Check-Workflow-SD_PRO_DES | B23: f05fbc78-ef28-464f-af69-17b91916987e | C23: 212551b9-97e3-4ffc-9c4e-169f987349b2 | D23: cf23386e-459a-4327-88d5-4b456681e54e | E23: 8ecca4fd-4b3c-42f0-9d95-2abd85107966 | F23: workflow | J23: sd_pro_des | K23: Active | L23: Completeness | M23: 1 | N23: NotNull | O23: Checks that Workflow-SD_PRO_DES is populated for every in-scope record and is not null, blank, or whitespace-only. Business meaning: Business data element 'sd pro des' captured in the ACCELAWorkflow dataset to support operational processing, compliance tracking, and reporting. | P23: {'column': {'type': 'Column', 'value': 'sd_pro_des'}}
A24: Completeness_Check-Workflow-G6_STAT_DD | B24: 91143fca-3a11-4d92-b11a-1b79ad81ad6c | C24: 212551b9-97e3-4ffc-9c4e-169f987349b2 | D24: cf23386e-459a-4327-88d5-4b456681e54e | E24: 8ecca4fd-4b3c-42f0-9d95-2abd85107966 | F24: workflow | J24: g6_stat_dd | K24: Disabled | L24: Completeness | M24: 0 | N24: NotNull | O24: Checks that Workflow-G6_STAT_DD is populated for every in-scope record and is not null, blank, or whitespace-only. Business meaning: Business data element 'g6 stat dd' captured in the ACCELAWorkflow dataset to support operational processing, compliance tracking, and reporting. | P24: {'column': {'type': 'Column', 'value': 'g6_stat_dd'}}
A25: String_Format_Check-Workflow-SD_PRO_DES | B25: e6670f96-8c3b-44bf-b69b-8d8441a6be40 | C25: 212551b9-97e3-4ffc-9c4e-169f987349b2 | D25: cf23386e-459a-4327-88d5-4b456681e54e | E25: 8ecca4fd-4b3c-42f0-9d95-2abd85107966 | F25: workflow | G25: !regexMatch({sd_pro_des}, '.*[؀-ۿ].*') | H25: {rec_status} == 'A' && !isNull({sd_pro_des}) | J25: sd_pro_des,rec_status | K25: Active | L25: Conformity | M25: 1 | N25: CustomTruth | O25: Checks that Workflow-SD_PRO_DES contains only English characters and not arabic or special characters | P25: {'condition': "!regexMatch({sd_pro_des}, '.*[\u0600-ۿ].*')", 'columns': [{'value': 'sd_pro_des', 'type': 'Column'}, {'value': 'rec_status', 'type': 'Column'}], 'emptyCriteria': None, 'filterCriteria': "{rec_status} == 'A' && !isNull({sd_pro_des})", 'ruleDialect': 'ADF'}
A26: Completeness_Check-Workflow-G6_ASGN_DD | B26: 39f5d2cd-49d6-4e23-8674-db97cc1f535d | C26: 212551b9-97e3-4ffc-9c4e-169f987349b2 | D26: cf23386e-459a-4327-88d5-4b456681e54e | E26: 8ecca4fd-4b3c-42f0-9d95-2abd85107966 | F26: workflow | J26: g6_asgn_dd | K26: Disabled | L26: Completeness | M26: 0.68019859 | N26: NotNull | O26: Checks that Workflow-G6_ASGN_DD is populated for every in-scope record and is not null, blank, or whitespace-only. Business meaning: Business data element 'g6 asgn dd' captured in the ACCELA Workflow dataset to support operational processing, compliance tracking, and reporting. | P26: {'column': {'type': 'Column', 'value': 'g6_asgn_dd'}}
A27: Uniqueness-Workflow-SERV_PROV_CODE, ID1,ID2,ID3 | B27: 30eccbd0-ab4d-4da6-8d8e-d703de52b52e | C27: 212551b9-97e3-4ffc-9c4e-169f987349b2 | D27: cf23386e-459a-4327-88d5-4b456681e54e | E27: 8ecca4fd-4b3c-42f0-9d95-2abd85107966 | F27: workflow | J27: b1_per_id1,b1_per_id2,b1_per_id3,relation_seq_id,sd_stp_num,serv_prov_code | K27: Active | L27: Accuracy | M27: 1 | N27: Duplicate | O27: Checks that Workflow has no duplicate active logical records for the approved business key (SERV_PROV_CODE, B1_PER_ID1, B1_PER_ID2, B1_PER_ID3, SD_STP_NUM, RELATION_SEQ_ID). Implement as the single Purview Duplicate rows rule for the asset; any duplicates should be triaged and remediated at source. | P27: {'columns': [{'value': 'b1_per_id1', 'type': 'Column'}, {'value': 'b1_per_id2', 'type': 'Column'}, {'value': 'b1_per_id3', 'type': 'Column'}, {'value': 'relation_seq_id', 'type': 'Column'}, {'value': 'sd_stp_num', 'type': 'Column'}, {'value': 'serv_prov_code', 'type': 'Column'}]}
A28: Timeliness-Workflow-REC_DATE | B28: 98342787-a3aa-4d1e-a7e3-53c36d1fa94c | C28: 212551b9-97e3-4ffc-9c4e-169f987349b2 | D28: cf23386e-459a-4327-88d5-4b456681e54e | E28: 8ecca4fd-4b3c-42f0-9d95-2abd85107966 | F28: workflow | G28: 172800000 | K28: Active | L28: Timeliness | M28: 1 | N28: Timeliness | O28: Checks that the Workflow asset is refreshed within the approved operational SLA so its CDE values remain current for reporting and downstream consumption. | P28: {'timeDifference': 172800000}
A29: Date_Format-Workflow-G6_STAT_DD | B29: 03281ba3-b387-4c81-a8fa-95d74625579f | C29: 212551b9-97e3-4ffc-9c4e-169f987349b2 | D29: cf23386e-459a-4327-88d5-4b456681e54e | E29: 8ecca4fd-4b3c-42f0-9d95-2abd85107966 | F29: workflow | G29: regexMatch(substring(toString({g6_stat_dd}), 1, 10), '^[0-9]{4}-[0-9]{2}-[0-9]{2}$') | H29: {rec_status} == 'A' && !isNull({g6_stat_dd}) | J29: g6_stat_dd,rec_status | K29: Active | L29: Conformity | M29: 1 | N29: CustomTruth | O29: Checks the Date Format for Workflow-G6_STAT_DD | P29: {'condition': "regexMatch(substring(toString({g6_stat_dd}), 1, 10), '^[0-9]{4}-[0-9]{2}-[0-9]{2}$')", 'columns': [{'value': 'g6_stat_dd', 'type': 'Column'}, {'value': 'rec_status', 'type': 'Column'}], 'emptyCriteria': None, 'filterCriteria': "{rec_status} == 'A' && !isNull({g6_stat_dd})", 'ruleDialect': 'ADF'}
A30: Date_Format-Workflow-G6_ASGN_DD | B30: 5d735399-2753-48d0-ba20-ec7b5f61066d | C30: 212551b9-97e3-4ffc-9c4e-169f987349b2 | D30: cf23386e-459a-4327-88d5-4b456681e54e | E30: 8ecca4fd-4b3c-42f0-9d95-2abd85107966 | F30: workflow | G30: regexMatch(substring(toString({g6_asgn_dd}), 1, 10), '^[0-9]{4}-[0-9]{2}-[0-9]{2}$') | H30: {rec_status} == 'A' && !isNull({g6_asgn_dd}) | J30: g6_asgn_dd,rec_status | K30: Active | L30: Conformity | M30: 1 | N30: CustomTruth | O30: Checks the Date Format for Workflow-G6_ASGN_DD | P30: {'condition': "regexMatch(substring(toString({g6_asgn_dd}), 1, 10), '^[0-9]{4}-[0-9]{2}-[0-9]{2}$')", 'columns': [{'value': 'g6_asgn_dd', 'type': 'Column'}, {'value': 'rec_status', 'type': 'Column'}], 'emptyCriteria': None, 'filterCriteria': "{rec_status} == 'A' && !isNull({g6_asgn_dd})", 'ruleDialect': 'ADF'}
A31: Completeness_Ck-Permit_Umbrella-QUANT_OF_UMBRELLAS | B31: b5b2e534-8e1e-4619-83cb-b88c11a18c92 | C31: 212551b9-97e3-4ffc-9c4e-169f987349b2 | D31: c57eb196-f492-4f17-bd84-b203f51b7431 | E31: a0bc0552-3d97-44e1-a6f7-f041f0d43ba7 | F31: permit_umbrella | J31: quantity_of_umbrellas | K31: Active | L31: Completeness | M31: 1 | N31: NotNull | O31: Validate that Permit_Umbrella.QUANTITIES_OF_UMBRELLAS is populated for records where the field is applicable. Source business description: Recorded umbrella type for the virtual-table entry. | P31: {'column': {'type': 'Column', 'value': 'quantity_of_umbrellas'}}
A32: DatTypMatch_Ck-Permit_Umbrella-QUANT_OF_UMBRELLAS | B32: 7f57727a-c000-442f-ad2e-fe17f21aa1bf | C32: 212551b9-97e3-4ffc-9c4e-169f987349b2 | D32: c57eb196-f492-4f17-bd84-b203f51b7431 | E32: a0bc0552-3d97-44e1-a6f7-f041f0d43ba7 | F32: permit_umbrella | J32: quantity_of_umbrellas | K32: Active | L32: Consistency | M32: 1 | N32: TypeMatch | O32: Validate that Permit_Umbrella.QUANTITIES_OF_UMBRELLAS is type number for records where the field is applicable. Source business description: Recorded umbrella type for the virtual-table entry. | P32: {'column': {'type': 'Column', 'value': 'quantity_of_umbrellas'}}
A33: NumVal_Check-Permit_Umbrella-QUANT_OF_UMBRELLAS | B33: 0a171573-74e2-445a-8a23-7f44a3d9f3e1 | C33: 212551b9-97e3-4ffc-9c4e-169f987349b2 | D33: c57eb196-f492-4f17-bd84-b203f51b7431 | E33: a0bc0552-3d97-44e1-a6f7-f041f0d43ba7 | F33: permit_umbrella | G33: quantity_of_umbrellas > 0 AND quantity_of_umbrellas = FLOOR( quantity_of_umbrellas) | H33: rec_status = 'A' AND quantity_of_umbrellas IS NOT NULL | J33: quantity_of_umbrellas,rec_status | K33: Active | L33: Conformity | M33: 1 | N33: CustomSQL | O33: Validate that Permit_Umbrella.QUANTITIES_OF_UMBRELLAS is valid number for records where the field is applicable. Source business description: Recorded umbrella type for the virtual-table entry. | P33: {'condition': 'quantity_of_umbrellas > 0 AND quantity_of_umbrellas = FLOOR( quantity_of_umbrellas)', 'columns': [{'value': 'quantity_of_umbrellas', 'type': 'Column'}, {'value': 'rec_status', 'type': 'Column'}], 'emptyCriteria': None, 'filterCriteria': "rec_status = 'A' AND quantity_of_umbrellas IS NOT NULL", 'ruleDialect': 'SparkSQL'}
A34: Timeliness_metadata_gap-PU-UMBRELLA_TYPE | B34: f1af842f-fde8-4ba6-b542-07b5b94f8d3b | C34: 212551b9-97e3-4ffc-9c4e-169f987349b2 | D34: c57eb196-f492-4f17-bd84-b203f51b7431 | E34: a0bc0552-3d97-44e1-a6f7-f041f0d43ba7 | F34: permit_umbrella | G34: 172800000 | K34: Active | L34: Timeliness | M34: 1 | N34: Timeliness | O34: This timeliness check is used to validate the data freshness of the Permit Umbrella table | P34: {'timeDifference': 172800000}
A35: Uniqueness_Check-Permit_Umbrella | B35: 5f6a172a-0471-4ab8-9ea5-571a86e85df5 | C35: 212551b9-97e3-4ffc-9c4e-169f987349b2 | D35: c57eb196-f492-4f17-bd84-b203f51b7431 | E35: a0bc0552-3d97-44e1-a6f7-f041f0d43ba7 | F35: permit_umbrella | J35: b1_per_id1,b1_per_id2,b1_per_id3,serv_prov_code,row_index | K35: Active | L35: Accuracy | M35: 1 | N35: Duplicate | O35: This check is used to identify the duplicate records in the table. The Unique key combination used is (serv_prov_code, b1_per_id1, b1_per_id2, b1_per_id3, row_index). | P35: {'columns': [{'value': 'b1_per_id1', 'type': 'Column'}, {'value': 'b1_per_id2', 'type': 'Column'}, {'value': 'b1_per_id3', 'type': 'Column'}, {'value': 'serv_prov_code', 'type': 'Column'}, {'value': 'row_index', 'type': 'Column'}]}
A36: String_check-Exemption_Change_Log-CHANGE_TYPE | B36: 5252f406-f0c2-4f7a-be7e-18f4cd8add74 | C36: 212551b9-97e3-4ffc-9c4e-169f987349b2 | D36: cf23386e-459a-4327-88d5-4b456681e54e | E36: 671af25e-da9a-49e8-bfde-912b302ff19e | F36: exemption_change_log | G36: ^[A-Za-z]+(?: [A-Za-z]+)*$ | J36: change_type | K36: Active | L36: Conformity | M36: 1 | N36: Regex | O36: Validate that populated values in Exemption_Change_Log. CHANGE_TYPE contain English printable characters only for string quality validation. | P36: {'column': {'type': 'Column', 'value': 'change_type'}, 'pattern': '^[A-Za-z]+(?: [A-Za-z]+)*$'}
A37: Completeness_check-Exemption_Change_Log-USER_NAME | B37: d7b003ba-a8bc-4aee-94e7-a62a2b2335cb | C37: 212551b9-97e3-4ffc-9c4e-169f987349b2 | D37: cf23386e-459a-4327-88d5-4b456681e54e | E37: 671af25e-da9a-49e8-bfde-912b302ff19e | F37: exemption_change_log | J37: user_name | K37: Active | L37: Completeness | M37: 1 | N37: NotNull | O37: Validate that Exemption_Change_Log.USER_NAME is populated for records where the field is applicable. Source business description: Recorded user name for the virtual-table entry. | P37: {'column': {'type': 'Column', 'value': 'user_name'}}
A38: String_check-Exemption_Change_Log-USER_NAME | B38: 3529144f-1712-4e48-a50e-9a96493ef812 | C38: 212551b9-97e3-4ffc-9c4e-169f987349b2 | D38: cf23386e-459a-4327-88d5-4b456681e54e | E38: 671af25e-da9a-49e8-bfde-912b302ff19e | F38: exemption_change_log | G38: ^[A-Za-z]+(?: [A-Za-z]+)*$ | J38: user_name | K38: Active | L38: Conformity | M38: 1 | N38: Regex | O38: Validate that populated values in Exemption_Change_Log. USER_NAME contain English/ASCII printable characters only for string quality validation. | P38: {'column': {'type': 'Column', 'value': 'user_name'}, 'pattern': '^[A-Za-z]+(?: [A-Za-z]+)*$'}
A39: Timeliness_Check-Exemption_Change_Log | B39: 8d8c2e4e-3d62-4309-bf09-89f39b3761fe | C39: 212551b9-97e3-4ffc-9c4e-169f987349b2 | D39: cf23386e-459a-4327-88d5-4b456681e54e | E39: 671af25e-da9a-49e8-bfde-912b302ff19e | F39: exemption_change_log | G39: 172800000 | K39: Active | L39: Timeliness | M39: 1 | N39: Timeliness | O39: This timeliness check is used to validate the data freshness of the Exemption Change Log table | P39: {'timeDifference': 172800000}
A40: Uniqueness_Check-Exemption_Change_Log | B40: 2c730e89-72d2-4e55-a078-fa34ad27614c | C40: 212551b9-97e3-4ffc-9c4e-169f987349b2 | D40: cf23386e-459a-4327-88d5-4b456681e54e | E40: 671af25e-da9a-49e8-bfde-912b302ff19e | F40: exemption_change_log | J40: b1_per_id1,b1_per_id2,b1_per_id3,serv_prov_code,row_index | K40: Active | L40: Accuracy | M40: 1 | N40: Duplicate | O40: This check is used to identify the duplicate records in the table. The Unique key combination used is (serv_prov_code, b1_per_id1, b1_per_id2, b1_per_id3, row_index) | P40: {'columns': [{'value': 'b1_per_id1', 'type': 'Column'}, {'value': 'b1_per_id2', 'type': 'Column'}, {'value': 'b1_per_id3', 'type': 'Column'}, {'value': 'serv_prov_code', 'type': 'Column'}, {'value': 'row_index', 'type': 'Column'}]}
A41: Completeness_Chk-Exemption_Change_Log-change_type | B41: cc832c8f-8d2b-4df7-9361-659e67ac6450 | C41: 212551b9-97e3-4ffc-9c4e-169f987349b2 | D41: cf23386e-459a-4327-88d5-4b456681e54e | E41: 671af25e-da9a-49e8-bfde-912b302ff19e | F41: exemption_change_log | J41: change_type | K41: Active | L41: Completeness | M41: 1 | N41: NotNull | O41: Checks that change_type in Exemption_Change_Log is populated for every in-scope record and is not null, blank, or whitespace-only. | P41: {'column': {'type': 'Column', 'value': 'change_type'}}
A42: Comp_Chk-applctn_Config_Language-R1_PER_GROUP | B42: 3d05cdc2-72aa-4489-a2cb-4c1b3880bf6c | C42: 212551b9-97e3-4ffc-9c4e-169f987349b2 | D42: cf23386e-459a-4327-88d5-4b456681e54e | E42: 67946da4-cda7-4f03-8771-3e3823d2c6e9 | F42: application_configuration_language | J42: r1_per_group | K42: Active | L42: Completeness | M42: 1 | N42: NotNull | O42: Checks that R1_PER_GROUP in application_Configuration_Language is populated for every in-scope record and is not null, blank, or whitespace-only. Business meaning: Per Group is required to support licensing operations, record identification, reporting, and downstream data integration. | P42: {'column': {'type': 'Column', 'value': 'r1_per_group'}}
A43: Comp_Chk-applctn_Config_Language-R1_PER_SUB_TYPE | B43: 7a4f724b-182c-40f6-b943-0d1e4dd93217 | C43: 212551b9-97e3-4ffc-9c4e-169f987349b2 | D43: cf23386e-459a-4327-88d5-4b456681e54e | E43: 67946da4-cda7-4f03-8771-3e3823d2c6e9 | F43: application_configuration_language | J43: r1_per_sub_type | K43: Active | L43: Completeness | M43: 0.96666667 | N43: NotNull | O43: Checks that R1_PER_SUB_TYPE in application_Configuration_Language is populated for every in-scope record and is not null, blank, or whitespace-only. Business meaning: Per Sub Type is required to support licensing operations, record identification, reporting, and downstream data integration. | P43: {'column': {'type': 'Column', 'value': 'r1_per_sub_type'}}
A44: Comp_Chk-applctn_Config_Language-R1_PER_CATEGORY | B44: 5e727671-7fe9-48d7-bdc0-ad0b67acdbc1 | C44: 212551b9-97e3-4ffc-9c4e-169f987349b2 | D44: cf23386e-459a-4327-88d5-4b456681e54e | E44: 67946da4-cda7-4f03-8771-3e3823d2c6e9 | F44: application_configuration_language | J44: r1_per_category | K44: Active | L44: Completeness | M44: 0.96666667 | N44: NotNull | O44: Checks that R1_PER_CATEGORY in application_Configuration_Language is populated for every in-scope record and is not null, blank, or whitespace-only. Business meaning: Per Category is required to support licensing operations, record identification, reporting, and downstream data integration. | P44: {'column': {'type': 'Column', 'value': 'r1_per_category'}}
A45: Freshness_Chk-application_Configuration_Language | B45: 2f9a4cb0-f015-4022-9d62-8f7eff28e64c | C45: 212551b9-97e3-4ffc-9c4e-169f987349b2 | D45: cf23386e-459a-4327-88d5-4b456681e54e | E45: 67946da4-cda7-4f03-8771-3e3823d2c6e9 | F45: application_configuration_language | G45: 172800000 | K45: Active | L45: Timeliness | M45: 1 | N45: Timeliness | O45: This timeliness check is used to validate the data freshness of the Application_Configuration_Language table | P45: {'timeDifference': 172800000}
A46: Dup_Rows_Check-application_Configuration_Language | B46: c247dcd9-ea7f-4268-8a96-101131c92353 | C46: 212551b9-97e3-4ffc-9c4e-169f987349b2 | D46: cf23386e-459a-4327-88d5-4b456681e54e | E46: 67946da4-cda7-4f03-8771-3e3823d2c6e9 | F46: application_configuration_language | J46: lang_id,res_id,serv_prov_code | K46: Active | L46: Accuracy | M46: 1 | N46: Duplicate | O46: This uniqueness check is used to validate the duplicate rows in the Application_Configuration_Language table for the columns - SERV_PROV_CODE, RES_ID, LANG_ID | P46: {'columns': [{'value': 'lang_id', 'type': 'Column'}, {'value': 'res_id', 'type': 'Column'}, {'value': 'serv_prov_code', 'type': 'Column'}]}
A47: Data_Val_Check-applctn_Config_Lang-R1_PER_GROUP | B47: 54910cb3-0981-45e6-9b25-f526e39acf35 | C47: 212551b9-97e3-4ffc-9c4e-169f987349b2 | D47: cf23386e-459a-4327-88d5-4b456681e54e | E47: 67946da4-cda7-4f03-8771-3e3823d2c6e9 | F47: application_configuration_language | J47: r1_per_group | K47: Active | L47: Consistency | M47: 1 | N47: TypeMatch | O47: Checks that R1_PER_GROUP in application_Configuration_Language conforms to the expected source/Purview data type so the value can be parsed and used consistently. | P47: {'column': {'type': 'Column', 'value': 'r1_per_group'}}
A48: Fmt_Val_Check-app_Config_Language-R1_PER_GROUP | B48: a1095ed0-1363-4102-86bd-721a6d5f9948 | C48: 212551b9-97e3-4ffc-9c4e-169f987349b2 | D48: cf23386e-459a-4327-88d5-4b456681e54e | E48: 67946da4-cda7-4f03-8771-3e3823d2c6e9 | F48: application_configuration_language | G48: ^[A-Za-z0-9\u0600-\u06FF '"\/&_*;:\-+@#^]+$ | J48: r1_per_group | K48: Active | L48: Conformity | M48: 1 | N48: Regex | O48: Checks that non-null R1_PER_GROUP in application_Configuration_Language values follow the English/Arabic letters, numbers, and spaces only with no special characters. Business meaning: Per Group should be stored in a standardized format to prevent malformed values from affecting search, matching, reporting, or integrations. | P48: {'column': {'type': 'Column', 'value': 'r1_per_group'}, 'pattern': '^[A-Za-z0-9\\u0600-\\u06FF \'"\\/&_*;:\\-+@#^]+$'}
A49: Data_Val_Check-applctn_Config_Lang-R1_PER_SUB_TYPE | B49: 19ce5988-52cf-4011-a567-2980763a898d | C49: 212551b9-97e3-4ffc-9c4e-169f987349b2 | D49: cf23386e-459a-4327-88d5-4b456681e54e | E49: 67946da4-cda7-4f03-8771-3e3823d2c6e9 | F49: application_configuration_language | J49: r1_per_sub_type | K49: Active | L49: Consistency | M49: 1 | N49: TypeMatch | O49: Checks that R1_PER_SUB_TYPE in application_Configuration_Language conforms to the expected source/Purview data type so the value can be parsed and used consistently. | P49: {'column': {'type': 'Column', 'value': 'r1_per_sub_type'}}
A50: Fmt_Val_Check-applctn_Config_Lang-R1_PER_SUB_TYPE | B50: bd8d6c30-0829-4ddb-b58f-e4766fad7297 | C50: 212551b9-97e3-4ffc-9c4e-169f987349b2 | D50: cf23386e-459a-4327-88d5-4b456681e54e | E50: 67946da4-cda7-4f03-8771-3e3823d2c6e9 | F50: application_configuration_language | G50: ^[A-Za-z0-9\u0600-\u06FF '"\/&_*;:\-+%@#^]+$ | J50: r1_per_sub_type | K50: Active | L50: Conformity | M50: 1 | N50: Regex | O50: Checks that non-null R1_PER_SUB_TYPE in application_Configuration_Language values follow the English/Arabic letters, numbers, and spaces only with no special characters. Business meaning: Per Sub Type should be stored in a standardized format to prevent malformed values from affecting search, matching, reporting, or integrations. | P50: {'column': {'type': 'Column', 'value': 'r1_per_sub_type'}, 'pattern': '^[A-Za-z0-9\\u0600-\\u06FF \'"\\/&_*;:\\-+%@#^]+$'}
A51: Data_Val_Check-applctn_Config_Lang-R1_PER_CATEGORY | B51: fbafcd16-5b61-4a5b-a307-67d7a174bbf5 | C51: 212551b9-97e3-4ffc-9c4e-169f987349b2 | D51: cf23386e-459a-4327-88d5-4b456681e54e | E51: 67946da4-cda7-4f03-8771-3e3823d2c6e9 | F51: application_configuration_language | J51: r1_per_category | K51: Active | L51: Consistency | M51: 1 | N51: TypeMatch | O51: Checks that R1_PER_CATEGORY in application_Configuration_Language conforms to the expected source/Purview data type so the value can be parsed and used consistently. | P51: {'column': {'type': 'Column', 'value': 'r1_per_category'}}
A52: Fmt_Val_Check-applctn_Config_Lang-R1_PER_CATEGORY | B52: 1ffdec3d-5e47-4e49-8fce-f8d2aef79dd7 | C52: 212551b9-97e3-4ffc-9c4e-169f987349b2 | D52: cf23386e-459a-4327-88d5-4b456681e54e | E52: 67946da4-cda7-4f03-8771-3e3823d2c6e9 | F52: application_configuration_language | G52: ^[A-Za-z0-9\u0600-\u06FF '"\/&_*;:\-+@#^]+$ | J52: r1_per_category | K52: Active | L52: Conformity | M52: 1 | N52: Regex | O52: Checks that non-null R1_PER_CATEGORY in application_Configuration_Language values follow the English/Arabic letters, numbers, and spaces only with no special characters. Business meaning: Per Category should be stored in a standardized format to prevent malformed values from affecting search, matching, reporting, or integrations. | P52: {'column': {'type': 'Column', 'value': 'r1_per_category'}, 'pattern': '^[A-Za-z0-9\\u0600-\\u06FF \'"\\/&_*;:\\-+@#^]+$'}
A53: Lead_Trail_Space_Chk-app_Config_Lang-R1_PER_GROUP | B53: a09b2248-c3b8-4aff-80b6-cd11abfdf0e9 | C53: 212551b9-97e3-4ffc-9c4e-169f987349b2 | D53: cf23386e-459a-4327-88d5-4b456681e54e | E53: 67946da4-cda7-4f03-8771-3e3823d2c6e9 | F53: application_configuration_language | G53: isNull(r1_per_group) OR r1_per_group = trim(r1_per_group) | H53: rec_status = 'A' AND r1_per_group IS NOT NULL | J53: r1_per_group,rec_status | K53: Active | L53: Conformity | M53: 1 | N53: CustomSQL | O53: Checks that application_Configuration_Language.R1_PER_GROUP does not contain leading or trailing spaces when represented as text. Business meaning: R1 Per Group should be stored without accidental whitespace at the start or end of the value so matching, filtering, reporting, and downstream integrations interpret the value consistently. | P53: {'condition': 'isNull(r1_per_group) OR r1_per_group = trim(r1_per_group)', 'columns': [{'value': 'r1_per_group', 'type': 'Column'}, {'value': 'rec_status', 'type': 'Column'}], 'emptyCriteria': None, 'filterCriteria': "rec_status = 'A' AND r1_per_group IS NOT NULL", 'ruleDialect': 'SparkSQL'}
A54: Cons_Space_Check-app_Config_Lang-R1_PER_GROUP | B54: 3b2c83e0-2fe0-4e7e-8caa-78686fae8c1d | C54: 212551b9-97e3-4ffc-9c4e-169f987349b2 | D54: cf23386e-459a-4327-88d5-4b456681e54e | E54: 67946da4-cda7-4f03-8771-3e3823d2c6e9 | F54: application_configuration_language | G54: isNull( r1_per_group ) OR r1_per_group RLIKE '^[^ ]*( [^ ]+)*$' | H54: rec_status = 'A' AND r1_per_group IS NOT NULL | J54: r1_per_group,rec_status | K54: Active | L54: Conformity | M54: 1 | N54: CustomSQL | O54: Checks that application_Configuration_Language.R1_PER_GROUP does not contain two or more consecutive spaces when represented as text. Business meaning: R1 Per Group should follow a clean spacing structure so searches, joins, duplicate checks, reports, and user-facing displays are not affected by inconsistent internal whitespace. | P54: {'condition': "isNull( r1_per_group ) OR r1_per_group RLIKE '^[^ ]*( [^ ]+)*$'", 'columns': [{'value': 'r1_per_group', 'type': 'Column'}, {'value': 'rec_status', 'type': 'Column'}], 'emptyCriteria': None, 'filterCriteria': "rec_status = 'A' AND r1_per_group IS NOT NULL", 'ruleDialect': 'SparkSQL'}
A55: Lead_Trail_Spc_Chk-app_Config_Lang-R1_PER_SUB_TYPE | B55: bbf6de88-e887-4d3a-aba8-a609e9601946 | C55: 212551b9-97e3-4ffc-9c4e-169f987349b2 | D55: cf23386e-459a-4327-88d5-4b456681e54e | E55: 67946da4-cda7-4f03-8771-3e3823d2c6e9 | F55: application_configuration_language | G55: isNull( r1_per_sub_type ) OR r1_per_sub_type = trim( r1_per_sub_type ) | H55: rec_status = 'A' AND r1_per_sub_type IS NOT NULL | J55: r1_per_sub_type,rec_status | K55: Active | L55: Conformity | M55: 1 | N55: CustomSQL | O55: Checks that application_Configuration_Language.R1_PER_SUB_TYPE does not contain leading or trailing spaces when represented as text. Business meaning: R1 Per Sub Type should be stored without accidental whitespace at the start or end of the value so matching, filtering, reporting, and downstream integrations interpret the value consistently. | P55: {'condition': 'isNull( r1_per_sub_type ) OR r1_per_sub_type = trim( r1_per_sub_type )', 'columns': [{'value': 'r1_per_sub_type', 'type': 'Column'}, {'value': 'rec_status', 'type': 'Column'}], 'emptyCriteria': None, 'filterCriteria': "rec_status = 'A' AND r1_per_sub_type IS NOT NULL", 'ruleDialect': 'SparkSQL'}
A56: Cons_Space_Check-app_Config_Lang-R1_PER_SUB_TYPE | B56: 43b15822-3be9-4477-974e-a93740dda3b9 | C56: 212551b9-97e3-4ffc-9c4e-169f987349b2 | D56: cf23386e-459a-4327-88d5-4b456681e54e | E56: 67946da4-cda7-4f03-8771-3e3823d2c6e9 | F56: application_configuration_language | G56: isNull( r1_per_sub_type ) OR r1_per_sub_type RLIKE '^[^ ]*( [^ ]+)*$' | H56: rec_status = 'A' AND r1_per_sub_type IS NOT NULL | J56: r1_per_sub_type,rec_status | K56: Active | L56: Conformity | M56: 1 | N56: CustomSQL | O56: Checks that application_Configuration_Language.R1_PER_SUB_TYPE does not contain two or more consecutive spaces when represented as text. Business meaning: R1 Per Sub Type should follow a clean spacing structure so searches, joins, duplicate checks, reports, and user-facing displays are not affected by inconsistent internal whitespace. | P56: {'condition': "isNull( r1_per_sub_type ) OR r1_per_sub_type RLIKE '^[^ ]*( [^ ]+)*$'", 'columns': [{'value': 'r1_per_sub_type', 'type': 'Column'}, {'value': 'rec_status', 'type': 'Column'}], 'emptyCriteria': None, 'filterCriteria': "rec_status = 'A' AND r1_per_sub_type IS NOT NULL", 'ruleDialect': 'SparkSQL'}
A57: Lead_Trail_Spc_Chk-app_Config_Lang-R1_PER_CATEGORY | B57: bb452ada-6218-4fa9-9ff5-7ab791887dfe | C57: 212551b9-97e3-4ffc-9c4e-169f987349b2 | D57: cf23386e-459a-4327-88d5-4b456681e54e | E57: 67946da4-cda7-4f03-8771-3e3823d2c6e9 | F57: application_configuration_language | G57: isNull( r1_per_category ) OR r1_per_category = trim( r1_per_category ) | H57: rec_status = 'A' AND r1_per_category IS NOT NULL | J57: r1_per_category,rec_status | K57: Active | L57: Conformity | M57: 1 | N57: CustomSQL | O57: Checks that application_Configuration_Language.R1_PER_CATEGORY does not contain leading or trailing spaces when represented as text. Business meaning: R1 Per Category should be stored without accidental whitespace at the start or end of the value so matching, filtering, reporting, and downstream integrations interpret the value consistently. | P57: {'condition': 'isNull( r1_per_category ) OR r1_per_category = trim( r1_per_category )', 'columns': [{'value': 'r1_per_category', 'type': 'Column'}, {'value': 'rec_status', 'type': 'Column'}], 'emptyCriteria': None, 'filterCriteria': "rec_status = 'A' AND r1_per_category IS NOT NULL", 'ruleDialect': 'SparkSQL'}
A58: Cons_Space_Check-app_Config_Lang-R1_PER_CATEGORY | B58: 7582f5d2-92dd-459e-8692-78d3185b4c0a | C58: 212551b9-97e3-4ffc-9c4e-169f987349b2 | D58: cf23386e-459a-4327-88d5-4b456681e54e | E58: 67946da4-cda7-4f03-8771-3e3823d2c6e9 | F58: application_configuration_language | G58: isNull( r1_per_category ) OR r1_per_category RLIKE '^[^ ]*( [^ ]+)*$' | H58: rec_status = 'A' AND r1_per_category IS NOT NULL | J58: r1_per_category,rec_status | K58: Active | L58: Conformity | M58: 1 | N58: CustomSQL | O58: Checks that application_Configuration_Language.R1_PER_CATEGORY does not contain two or more consecutive spaces when represented as text. Business meaning: R1 Per Category should follow a clean spacing structure so searches, joins, duplicate checks, reports, and user-facing displays are not affected by inconsistent internal whitespace. | P58: {'condition': "isNull( r1_per_category ) OR r1_per_category RLIKE '^[^ ]*( [^ ]+)*$'", 'columns': [{'value': 'r1_per_category', 'type': 'Column'}, {'value': 'rec_status', 'type': 'Column'}], 'emptyCriteria': None, 'filterCriteria': "rec_status = 'A' AND r1_per_category IS NOT NULL", 'ruleDialect': 'SparkSQL'}
A59: Accuracy_Chk-app_Config_Lang-R1_PER_SUB_TYPE | B59: 132d9364-fe6c-4450-8f8a-ca8d76c74f61 | C59: 212551b9-97e3-4ffc-9c4e-169f987349b2 | D59: cf23386e-459a-4327-88d5-4b456681e54e | E59: 67946da4-cda7-4f03-8771-3e3823d2c6e9 | F59: application_configuration_language | J59: r1_per_sub_type | K59: Disabled | L59: Accuracy | M59: 0 | N59: ReferenceCheck | O59: Ensures that the permit subtype in application matches the permit subtype in the base application configuration. Rule definition: Compares application_Configuration_Language.R1_PER_SUB_TYPE with application_configuration.R1_PER_SUB_TYPE for the same Silver business record. | P59: {'column': {'value': 'r1_per_sub_type', 'type': 'Column'}, 'referencedDatasetAlias': 'application_configuration', 'referencedDatasetColumn': {'value': 'r1_per_sub_type', 'type': 'Column'}}
A60: Freshness_Check-Permit_Balloons | B60: 4736159d-40de-420f-aa0b-18582ed9176f | C60: 212551b9-97e3-4ffc-9c4e-169f987349b2 | D60: c57eb196-f492-4f17-bd84-b203f51b7431 | E60: 2249387e-4e09-4ff4-96e0-5951b8227c0b | F60: permit_balloons | G60: 172800000 | K60: Active | L60: Timeliness | M60: 1 | N60: Timeliness | O60: This timeliness check is used to validate the data freshness of the Permit_Balloons table | P60: {'timeDifference': 172800000}
A61: Duplicate_Rows_Check-Permit_Balloons | B61: 8eeb6105-5b44-490b-bb4f-5616ad0df01b | C61: 212551b9-97e3-4ffc-9c4e-169f987349b2 | D61: c57eb196-f492-4f17-bd84-b203f51b7431 | E61: 2249387e-4e09-4ff4-96e0-5951b8227c0b | F61: permit_balloons | J61: b1_per_id1,b1_per_id2,b1_per_id3,serv_prov_code,show_dates,row_index | K61: Active | L61: Accuracy | M61: 1 | N61: Duplicate | O61: This uniqueness check is used to validate the duplicate rows in the Permit_Balloons table for the keys: serv_prov_code, b1_per_id1, b1_per_id2, b1_per_id3 and show_dates | P61: {'columns': [{'value': 'b1_per_id1', 'type': 'Column'}, {'value': 'b1_per_id2', 'type': 'Column'}, {'value': 'b1_per_id3', 'type': 'Column'}, {'value': 'serv_prov_code', 'type': 'Column'}, {'value': 'show_dates', 'type': 'Column'}, {'value': 'row_index', 'type': 'Column'}]}
A62: Completeness_Check-balloons-balloons_address | B62: 326df206-68a9-478b-8dc1-73f485bd6d58 | C62: 212551b9-97e3-4ffc-9c4e-169f987349b2 | D62: c57eb196-f492-4f17-bd84-b203f51b7431 | E62: 2249387e-4e09-4ff4-96e0-5951b8227c0b | F62: permit_balloons | J62: balloons_address | K62: Disabled | L62: Completeness | M62: 0 | N62: NotNull | O62: Validate Balloons Address is populated for in-scope records. | P62: {'column': {'type': 'Column', 'value': 'balloons_address'}}
A63: Data_Type_Check-Permit_Balloons-balloons_address | B63: a3b1c221-ef50-4a58-887f-1306b81c1083 | C63: 212551b9-97e3-4ffc-9c4e-169f987349b2 | D63: c57eb196-f492-4f17-bd84-b203f51b7431 | E63: 2249387e-4e09-4ff4-96e0-5951b8227c0b | F63: permit_balloons | J63: balloons_address | K63: Active | L63: Consistency | M63: 1 | N63: TypeMatch | O63: Validate Balloons Address matches the expected data type. | P63: {'column': {'type': 'Column', 'value': 'balloons_address'}}
A64: Comp_Check-Permit_Balloons-show_dates | B64: 0018d977-0acf-4cc9-9db0-80667c36d509 | C64: 212551b9-97e3-4ffc-9c4e-169f987349b2 | D64: c57eb196-f492-4f17-bd84-b203f51b7431 | E64: 2249387e-4e09-4ff4-96e0-5951b8227c0b | F64: permit_balloons | J64: show_dates | K64: Active | L64: Completeness | M64: 1 | N64: NotNull | O64: Validate Show Dates is populated for in-scope records. | P64: {'column': {'type': 'Column', 'value': 'show_dates'}}
A65: Data_Type_Check-Permit_Balloons-SHOW_DATES | B65: f6e7e557-c7c1-4a11-b2fa-9cc90f49dad6 | C65: 212551b9-97e3-4ffc-9c4e-169f987349b2 | D65: c57eb196-f492-4f17-bd84-b203f51b7431 | E65: 2249387e-4e09-4ff4-96e0-5951b8227c0b | F65: permit_balloons | J65: show_dates | K65: Active | L65: Consistency | M65: 1 | N65: TypeMatch | O65: Validate Show Dates matches the expected data type. | P65: {'column': {'type': 'Column', 'value': 'show_dates'}}
A66: Consec_Chk-Permit_Balloons-balloons_address | B66: ce4022b4-16b6-465e-85ca-4477c66c53ab | C66: 212551b9-97e3-4ffc-9c4e-169f987349b2 | D66: c57eb196-f492-4f17-bd84-b203f51b7431 | E66: 2249387e-4e09-4ff4-96e0-5951b8227c0b | F66: permit_balloons | G66: CAST(balloons_address AS STRING) RLIKE '.*[^ ].*' AND CAST(balloons_address AS STRING) NOT RLIKE '\\pCntrl' AND UPPER(CAST(balloons_address AS STRING)) NOT RLIKE '^[ ]*(NA|N/A|NIL|NONE|NULL|UNKNOWN|UNSPECIFIED|TEST|DUMMY|TBD|NOT APPLICABLE|-|--|\\.)[ ]*$' | H66: rec_status = 'A' AND balloons_address IS NOT NULL | J66: balloons_address,rec_status | K66: Active | L66: Conformity | M66: 1 | N66: CustomSQL | O66: Checks that Permit_Balloons.balloons_address does not contain two or more consecutive spaces when represented as text. Business meaning: Total Fee should follow a clean spacing structure so searches, joins, duplicate checks, reports, and user-facing displays are not affected by inconsistent internal whitespace. | P66: {'condition': "CAST(balloons_address AS STRING) RLIKE '.*[^ ].*' AND CAST(balloons_address AS STRING) NOT RLIKE '\\\\pCntrl' AND UPPER(CAST(balloons_address AS STRING)) NOT RLIKE '^[ ]*(NA|N/A|NIL|NONE|NULL|UNKNOWN|UNSPECIFIED|TEST|DUMMY|TBD|NOT APPLICABLE|-|--|\\\\.)[ ]*$'", 'columns': [{'value': 'balloons_address', 'type': 'Column'}, {'value': 'rec_status', 'type': 'Column'}], 'emptyCriteria': None, 'filterCriteria': "rec_status = 'A' AND balloons_address IS NOT NULL", 'ruleDialect': 'SparkSQL'}
A67: Freshness_Check-Permit_Air | B67: eceeb5a4-55c7-44d4-96bf-6fb50627febe | C67: 212551b9-97e3-4ffc-9c4e-169f987349b2 | D67: c57eb196-f492-4f17-bd84-b203f51b7431 | E67: 37b09b4b-8ca1-4692-b3a3-9eb4ede65d6a | F67: permit_air | G67: 172800000 | K67: Active | L67: Timeliness | M67: 1 | N67: Timeliness | O67: This timeliness check is used to validate the data freshness of the Permit_Air table | P67: {'timeDifference': 172800000}
A68: Duplicate_Rows_Check-Permit_Air | B68: 4df07bf0-04fa-49a2-b371-d58291e70b13 | C68: 212551b9-97e3-4ffc-9c4e-169f987349b2 | D68: c57eb196-f492-4f17-bd84-b203f51b7431 | E68: 37b09b4b-8ca1-4692-b3a3-9eb4ede65d6a | F68: permit_air | J68: b1_per_id1,b1_per_id2,b1_per_id3,serv_prov_code,row_index | K68: Active | L68: Accuracy | M68: 1 | N68: Duplicate | O68: This uniqueness check is used to validate the duplicate rows in the Permit_Air table for the keys: serv_prov_code, b1_per_id1, b1_per_id2, b1_per_id3 | P68: {'columns': [{'value': 'b1_per_id1', 'type': 'Column'}, {'value': 'b1_per_id2', 'type': 'Column'}, {'value': 'b1_per_id3', 'type': 'Column'}, {'value': 'serv_prov_code', 'type': 'Column'}, {'value': 'row_index', 'type': 'Column'}]}
A69: Comp_Check-Permit_Air-AIR_AD_TYPE | B69: 6fc625a6-d4a3-4533-bede-f2b0bd032bcc | C69: 212551b9-97e3-4ffc-9c4e-169f987349b2 | D69: c57eb196-f492-4f17-bd84-b203f51b7431 | E69: 37b09b4b-8ca1-4692-b3a3-9eb4ede65d6a | F69: permit_air | J69: air_ad_type | K69: Active | L69: Completeness | M69: 1 | N69: NotNull | O69: Validate Air Ad Type is populated for in-scope records. | P69: {'column': {'type': 'Column', 'value': 'air_ad_type'}}
A70: Data_Type_Check-Permit_Air-AIR_AD_TYPE | B70: 5830b54d-a1fb-4d28-8f9b-ef12e64d6823 | C70: 212551b9-97e3-4ffc-9c4e-169f987349b2 | D70: c57eb196-f492-4f17-bd84-b203f51b7431 | E70: 37b09b4b-8ca1-4692-b3a3-9eb4ede65d6a | F70: permit_air | J70: air_ad_type | K70: Active | L70: Consistency | M70: 1 | N70: TypeMatch | O70: Validate Air Ad Type matches the expected data type. | P70: {'column': {'type': 'Column', 'value': 'air_ad_type'}}
A71: Completeness_Check-Permit_Air-SHOW_DATES | B71: 4e6a52f3-24df-4c9b-9dfc-7e08278bdd90 | C71: 212551b9-97e3-4ffc-9c4e-169f987349b2 | D71: c57eb196-f492-4f17-bd84-b203f51b7431 | E71: 37b09b4b-8ca1-4692-b3a3-9eb4ede65d6a | F71: permit_air | J71: show_dates | K71: Active | L71: Completeness | M71: 1 | N71: NotNull | O71: Validate Show Dates is populated for in-scope records. | P71: {'column': {'type': 'Column', 'value': 'show_dates'}}
A72: Data_Type_Check-Permit_Air-SHOW_DATES | B72: 34ee9e87-3525-4a59-9171-1b10f6f5db6c | C72: 212551b9-97e3-4ffc-9c4e-169f987349b2 | D72: c57eb196-f492-4f17-bd84-b203f51b7431 | E72: 37b09b4b-8ca1-4692-b3a3-9eb4ede65d6a | F72: permit_air | J72: show_dates | K72: Active | L72: Consistency | M72: 1 | N72: TypeMatch | O72: Validate Show Dates matches the expected data type. | P72: {'column': {'type': 'Column', 'value': 'show_dates'}}
A73: Completeness_check-Inspector_Coordinates-DATETIME | B73: 60eebaf0-3fbc-4d07-bccc-b609fea27773 | C73: 32a86140-d73f-456d-bf8b-d9572e9c0770 | D73: c3b7130f-814c-4328-98dd-1df1e5769033 | E73: 48f9d755-27be-4ebe-91db-3e7368513b8b | F73: inspector_coordinates | J73: datetime | K73: Active | L73: Completeness | M73: 1 | N73: NotNull | O73: Validate that Inspector_Coordinates.DATETIME is populated for records where the field is applicable. Source business description: Date associated with date and time. | P73: {'column': {'type': 'Column', 'value': 'datetime'}}
A74: DataTypeValid_Check-Inspector_Coordinates-DATETIME | B74: 09abb4cf-4305-4b5e-9ac6-16a079482a1c | C74: 32a86140-d73f-456d-bf8b-d9572e9c0770 | D74: c3b7130f-814c-4328-98dd-1df1e5769033 | E74: 48f9d755-27be-4ebe-91db-3e7368513b8b | F74: inspector_coordinates | J74: datetime | K74: Active | L74: Consistency | M74: 1 | N74: TypeMatch | O74: Validate that populated values in Inspector_Coordinates.DATETIME can be interpreted as valid date/time values, based on the source metadata describing the attribute as date-related. | P74: {'column': {'type': 'Column', 'value': 'datetime'}}
A75: Timeliness_Check-Inspector_Coordinates | B75: 3a6d419b-9e38-4efe-b7c8-7f3a64175792 | C75: 32a86140-d73f-456d-bf8b-d9572e9c0770 | D75: c3b7130f-814c-4328-98dd-1df1e5769033 | E75: 48f9d755-27be-4ebe-91db-3e7368513b8b | F75: inspector_coordinates | G75: 172800000 | K75: Active | L75: Timeliness | M75: 1 | N75: Timeliness | O75: This timeliness check is used to validate the data freshness of the Inspector Coordinates table | P75: {'timeDifference': 172800000}
A76: Uniqueness_Check-Inspector_Coordinates | B76: b7124a1b-10e7-4a0d-b6a8-80f36eed657e | C76: 32a86140-d73f-456d-bf8b-d9572e9c0770 | D76: c3b7130f-814c-4328-98dd-1df1e5769033 | E76: 48f9d755-27be-4ebe-91db-3e7368513b8b | F76: inspector_coordinates | J76: b1_per_id1,b1_per_id2,b1_per_id3,serv_prov_code,row_index | K76: Active | L76: Accuracy | M76: 1 | N76: Duplicate | O76: This check is used to identify the duplicate records in the table. The Unique key combination used is (serv_prov_code, b1_per_id1, b1_per_id2, b1_per_id3) | P76: {'columns': [{'value': 'b1_per_id1', 'type': 'Column'}, {'value': 'b1_per_id2', 'type': 'Column'}, {'value': 'b1_per_id3', 'type': 'Column'}, {'value': 'serv_prov_code', 'type': 'Column'}, {'value': 'row_index', 'type': 'Column'}]}
A77: DateValid_Check-Inspector_Coordinates-DATETIME | B77: 9fc0a3e5-e36c-45bb-a249-b0f43802b9e9 | C77: 32a86140-d73f-456d-bf8b-d9572e9c0770 | D77: c3b7130f-814c-4328-98dd-1df1e5769033 | E77: 48f9d755-27be-4ebe-91db-3e7368513b8b | F77: inspector_coordinates | G77: ^[0-9]{2}/[0-9]{2}/[0-9]{4} [0-9]{2}:[0-9]{2}:[0-9]{2}$ | J77: datetime | K77: Active | L77: Conformity | M77: 1 | N77: Regex | O77: Validate that populated date/time values in Inspector_Coordinates.DATETIME are not blank strings after casting to text. | P77: {'column': {'type': 'Column', 'value': 'datetime'}, 'pattern': '^[0-9]{2}/[0-9]{2}/[0-9]{4} [0-9]{2}:[0-9]{2}:[0-9]{2}$'}
A78: Cus_Allow_Val_Chk-status_lookup-serv_prov_code | B78: fbebba0c-1dbe-4e32-9012-4397d0843136 | C78: 212551b9-97e3-4ffc-9c4e-169f987349b2 | D78: cf23386e-459a-4327-88d5-4b456681e54e | E78: d1f40986-7d6b-48e1-961d-37d258f16dc3 | F78: status_lookup | G78: serv_prov_code = "ADBC" | H78: rec_status = 'A' AND serv_prov_code IS NOT NULL | J78: serv_prov_code,rec_status | K78: Active | L78: Conformity | M78: 1 | N78: CustomSQL | O78: Custom rule to validate for the list of allowed values for serv_prov_code. Allowed Values = "ADBC" | P78: {'condition': 'serv_prov_code = "ADBC"', 'columns': [{'value': 'serv_prov_code', 'type': 'Column'}, {'value': 'rec_status', 'type': 'Column'}], 'emptyCriteria': None, 'filterCriteria': "rec_status = 'A' AND serv_prov_code IS NOT NULL", 'ruleDialect': 'SparkSQL'}
A79: Completeness_Check-status_lookup-serv-prov-code | B79: eaf38526-585f-4382-9e68-84a321f3d459 | C79: 212551b9-97e3-4ffc-9c4e-169f987349b2 | D79: cf23386e-459a-4327-88d5-4b456681e54e | E79: d1f40986-7d6b-48e1-961d-37d258f16dc3 | F79: status_lookup | J79: serv_prov_code | K79: Active | L79: Completeness | M79: 1 | N79: NotNull | O79: Checks that serv_prov_code is populated for every in-scope record and is not either of null, blank, or whitespace-only. | P79: {'column': {'type': 'Column', 'value': 'serv_prov_code'}}
A80: Completeness_Check-status-lookup-status | B80: 3f6e9cce-d832-4b48-84ec-fcd4e742e4f1 | C80: 212551b9-97e3-4ffc-9c4e-169f987349b2 | D80: cf23386e-459a-4327-88d5-4b456681e54e | E80: d1f40986-7d6b-48e1-961d-37d258f16dc3 | F80: status_lookup | J80: status | K80: Active | L80: Completeness | M80: 1 | N80: NotNull | O80: Checks if status is populated for every in-scope record and is not null, blank, or whitespace-only. Business meaning: Business data element 'status' captured in the status_lookup dataset to support operational processing, compliance tracking, and reporting. | P80: {'column': {'type': 'Column', 'value': 'status'}}
A81: Data_Validity_Check-status_lookup-status | B81: 78ab3718-da96-4bad-909b-aabc959ece70 | C81: 212551b9-97e3-4ffc-9c4e-169f987349b2 | D81: cf23386e-459a-4327-88d5-4b456681e54e | E81: d1f40986-7d6b-48e1-961d-37d258f16dc3 | F81: status_lookup | J81: status | K81: Active | L81: Consistency | M81: 1 | N81: TypeMatch | O81: Checks if status conforms to the expected source/Purview data type (VARCHAR2) so the value can be parsed and used consistently. | P81: {'column': {'type': 'Column', 'value': 'status'}}
A82: Duplicate_Rows_Check-status_lookup | B82: 96c10d6f-7f71-4852-993b-63bd08790dcb | C82: 212551b9-97e3-4ffc-9c4e-169f987349b2 | D82: cf23386e-459a-4327-88d5-4b456681e54e | E82: d1f40986-7d6b-48e1-961d-37d258f16dc3 | F82: status_lookup | J82: serv_prov_code,status,app_status_group_code | K82: Active | L82: Accuracy | M82: 1 | N82: Duplicate | O82: Checks that status_lookup has no duplicate active logical records for the approved business key (serv_prov_code, status, APP_STATUS_GROUP_CODE). | P82: {'columns': [{'value': 'serv_prov_code', 'type': 'Column'}, {'value': 'status', 'type': 'Column'}, {'value': 'app_status_group_code', 'type': 'Column'}]}
A83: String_Format_Check-status_lookup-status | B83: 384d3302-ef2e-4649-a880-5a68b29917ab | C83: 212551b9-97e3-4ffc-9c4e-169f987349b2 | D83: cf23386e-459a-4327-88d5-4b456681e54e | E83: d1f40986-7d6b-48e1-961d-37d258f16dc3 | F83: status_lookup | G83: ^[A-Za-z_-]+(?: [A-Za-z_-]+)*$ | J83: status | K83: Active | L83: Conformity | M83: 1 | N83: Regex | O83: Checks that non-null status values follow the approved code/identifier format and length, preventing malformed values from entering reporting or integrations. | P83: {'column': {'type': 'Column', 'value': 'status'}, 'pattern': '^[A-Za-z_-]+(?: [A-Za-z_-]+)*$'}
A84: Data_Val_Chk-status_lookup-serv_prov_code | B84: 2cfec829-7f5e-498b-a7f7-9e47677c6bc3 | C84: 212551b9-97e3-4ffc-9c4e-169f987349b2 | D84: cf23386e-459a-4327-88d5-4b456681e54e | E84: d1f40986-7d6b-48e1-961d-37d258f16dc3 | F84: status_lookup | J84: serv_prov_code | K84: Active | L84: Consistency | M84: 1 | N84: TypeMatch | O84: Checks that serv_prov_code conforms to the expected source/Purview data type (VARCHAR2) so the value can be parsed and used consistently. | P84: {'column': {'type': 'Column', 'value': 'serv_prov_code'}}
A85: Str_Check-status_lookup-serv_prov_code | B85: 4e826247-6f90-442b-afa7-d316a3e1d9f7 | C85: 212551b9-97e3-4ffc-9c4e-169f987349b2 | D85: cf23386e-459a-4327-88d5-4b456681e54e | E85: d1f40986-7d6b-48e1-961d-37d258f16dc3 | F85: status_lookup | G85: serv_prov_code = "ADBC" | H85: rec_status = 'A' AND serv_prov_code IS NOT NULL | J85: serv_prov_code,rec_status | K85: Active | L85: Conformity | M85: 1 | N85: CustomSQL | O85: Checks that non-null serv_prov_code values follow the approved code/identifier format and length, preventing malformed values from entering reporting or integrations. | P85: {'condition': 'serv_prov_code = "ADBC"', 'columns': [{'value': 'serv_prov_code', 'type': 'Column'}, {'value': 'rec_status', 'type': 'Column'}], 'emptyCriteria': None, 'filterCriteria': "rec_status = 'A' AND serv_prov_code IS NOT NULL", 'ruleDialect': 'SparkSQL'}
A86: Freshness_Check-status_lookup | B86: 4adf104c-e210-40eb-86d4-f11a61aae761 | C86: 212551b9-97e3-4ffc-9c4e-169f987349b2 | D86: cf23386e-459a-4327-88d5-4b456681e54e | E86: d1f40986-7d6b-48e1-961d-37d258f16dc3 | F86: status_lookup | G86: 172800000 | K86: Active | L86: Timeliness | M86: 1 | N86: Timeliness | O86: Checks that the status_lookup asset is refreshed within the approved operational SLA so its CDE values remain current for reporting and downstream consumption. | P86: {'timeDifference': 172800000}
A87: Completeness_Chk-Stat_Lookup-APP_STATUS_GROUP_CODE | B87: 698bb391-591a-417a-ab72-5338c7c265cd | C87: 212551b9-97e3-4ffc-9c4e-169f987349b2 | D87: cf23386e-459a-4327-88d5-4b456681e54e | E87: d1f40986-7d6b-48e1-961d-37d258f16dc3 | F87: status_lookup | J87: app_status_group_code | K87: Active | L87: Completeness | M87: 1 | N87: NotNull | O87: Checks that the application status group is provided for every status record, so the information is complete. | P87: {'column': {'type': 'Column', 'value': 'app_status_group_code'}}
A88: Validity_Chk-Status_Lookup-APP_STATUS_GROUP_CODE | B88: a2b86782-b81d-4eb6-bc6a-8fbb931b79a9 | C88: 212551b9-97e3-4ffc-9c4e-169f987349b2 | D88: cf23386e-459a-4327-88d5-4b456681e54e | E88: d1f40986-7d6b-48e1-961d-37d258f16dc3 | F88: status_lookup | G88: ^[A-Za-z_.\- ]+$ | J88: app_status_group_code | K88: Active | L88: Conformity | M88: 1 | N88: Regex | O88: Checks that the application status group matches an approved value, so the information remains valid and consistent. | P88: {'column': {'type': 'Column', 'value': 'app_status_group_code'}, 'pattern': '^[A-Za-z_.\\- ]+$'}
A89: Accuracy_Check-Status_Lookup-STATUS | B89: fcde947a-4b1b-4804-9a23-4f03e6a16904 | C89: 212551b9-97e3-4ffc-9c4e-169f987349b2 | D89: cf23386e-459a-4327-88d5-4b456681e54e | E89: d1f40986-7d6b-48e1-961d-37d258f16dc3 | F89: status_lookup | J89: status | K89: Disabled | L89: Accuracy | M89: 0.5945946 | N89: ReferenceCheck | O89: Compares Status_Lookup.STATUS with Status_Lookup_Language.STATUS for the same business record. | P89: {'column': {'value': 'status', 'type': 'Column'}, 'referencedDatasetAlias': 'status_lookup_language', 'referencedDatasetColumn': {'value': 'status', 'type': 'Column'}}
A90: Completeness_Check-Status_Lookup_Language-lang_id | B90: 99fd2a81-44ef-4a01-9cfd-d092c0227ba7 | C90: 212551b9-97e3-4ffc-9c4e-169f987349b2 | D90: cf23386e-459a-4327-88d5-4b456681e54e | E90: bd94add1-6597-4f2d-b575-4a8fcb5d972e | F90: status_lookup_language | J90: lang_id | K90: Active | L90: Completeness | M90: 1 | N90: NotNull | O90: Checks that lang_id in Status_Lookup_Language is populated for every in-scope record and is not null, blank, or whitespace-only. | P90: {'column': {'type': 'Column', 'value': 'lang_id'}}
A91: Completeness_Check-Status_Lookup_Language-RES_ID | B91: a1bf6c71-f317-4159-a4fe-75d86f072de7 | C91: 212551b9-97e3-4ffc-9c4e-169f987349b2 | D91: cf23386e-459a-4327-88d5-4b456681e54e | E91: bd94add1-6597-4f2d-b575-4a8fcb5d972e | F91: status_lookup_language | J91: res_id | K91: Active | L91: Completeness | M91: 1 | N91: NotNull | O91: Checks that RES_ID in Status_Lookup_Language is populated for every in-scope record and is not null, blank, or whitespace-only. | P91: {'column': {'type': 'Column', 'value': 'res_id'}}
A92: Data_Validity_Check-Status_Lookup_Language-RES_ID | B92: 426305da-c4e0-4e37-93a2-66971640d212 | C92: 212551b9-97e3-4ffc-9c4e-169f987349b2 | D92: cf23386e-459a-4327-88d5-4b456681e54e | E92: bd94add1-6597-4f2d-b575-4a8fcb5d972e | F92: status_lookup_language | J92: res_id | K92: Active | L92: Consistency | M92: 1 | N92: TypeMatch | O92: Checks that RES_ID in Status_Lookup_Language conforms to the expected source/Purview data type (NUMBER) so the value can be parsed and used consistently. | P92: {'column': {'type': 'Column', 'value': 'res_id'}}
A93: Num_Val_Check-Status_Lookup_Language-RES_ID | B93: ba6b58e3-4c09-4b68-bd92-ae3fc2591b96 | C93: 212551b9-97e3-4ffc-9c4e-169f987349b2 | D93: cf23386e-459a-4327-88d5-4b456681e54e | E93: bd94add1-6597-4f2d-b575-4a8fcb5d972e | F93: status_lookup_language | G93: res_id >= 0 | H93: rec_status = 'A' AND res_id IS NOT NULL | J93: res_id,rec_status | K93: Active | L93: Conformity | M93: 1 | N93: CustomSQL | O93: Checks that non-null RES_ID values in Status_Lookup_Language are positive whole-number identifiers, rejecting decimals, zero, negative, and non-numeric values. | P93: {'condition': 'res_id >= 0', 'columns': [{'value': 'res_id', 'type': 'Column'}, {'value': 'rec_status', 'type': 'Column'}], 'emptyCriteria': None, 'filterCriteria': "rec_status = 'A' AND res_id IS NOT NULL", 'ruleDialect': 'SparkSQL'}
A94: String_Format_Check-Status_Lookup_Language-LAN_ID | B94: 4defcb72-fc6f-4234-89e8-23135413d0bf | C94: 212551b9-97e3-4ffc-9c4e-169f987349b2 | D94: cf23386e-459a-4327-88d5-4b456681e54e | E94: bd94add1-6597-4f2d-b575-4a8fcb5d972e | F94: status_lookup_language | G94: regexMatch({lang_id} ,'ar_AE') || regexMatch({lang_id} ,'en_US') | H94: {rec_status} == 'A' && !isNull({lang_id}) | J94: lang_id,rec_status | K94: Active | L94: Conformity | M94: 1 | N94: CustomTruth | O94: Checks that non-null LANG_ID values IN Status_Lookup_Language follow the approved language-code format and do not contain invalid characters. | P94: {'condition': "regexMatch({lang_id} ,'ar_AE') || regexMatch({lang_id} ,'en_US')", 'columns': [{'value': 'lang_id', 'type': 'Column'}, {'value': 'rec_status', 'type': 'Column'}], 'emptyCriteria': None, 'filterCriteria': "{rec_status} == 'A' && !isNull({lang_id})", 'ruleDialect': 'ADF'}
A95: Completeness_Check-Status_Lookup_Language-STATUS | B95: f2b601fa-6e66-419f-91ca-42480e542666 | C95: 212551b9-97e3-4ffc-9c4e-169f987349b2 | D95: cf23386e-459a-4327-88d5-4b456681e54e | E95: bd94add1-6597-4f2d-b575-4a8fcb5d972e | F95: status_lookup_language | J95: status | K95: Active | L95: Completeness | M95: 1 | N95: NotNull | O95: Checks that STATUS in Status_Lookup_Language is populated for every in-scope record and is not null, blank, or whitespace-only. | P95: {'column': {'type': 'Column', 'value': 'status'}}
A96: Data_Validity_Check-Status_Lookup_Language-STATUS | B96: 6c594b21-d671-4f87-bc46-ff353ec56657 | C96: 212551b9-97e3-4ffc-9c4e-169f987349b2 | D96: cf23386e-459a-4327-88d5-4b456681e54e | E96: bd94add1-6597-4f2d-b575-4a8fcb5d972e | F96: status_lookup_language | J96: status | K96: Active | L96: Consistency | M96: 1 | N96: TypeMatch | O96: Checks that STATUS in Status_Lookup_Language conforms to the expected source/Purview data type (VARCHAR2) so the value can be parsed and used consistently. | P96: {'column': {'type': 'Column', 'value': 'status'}}
A97: String_Format_Check-Status_Lookup_Language-STATUS | B97: 41f2960d-3440-4926-ad1d-1d7d1999587a | C97: 212551b9-97e3-4ffc-9c4e-169f987349b2 | D97: cf23386e-459a-4327-88d5-4b456681e54e | E97: bd94add1-6597-4f2d-b575-4a8fcb5d972e | F97: status_lookup_language | G97: regexMatch(lower({status}), `^[a-z_-]+( [a-z_-]+)*$`) || regexMatch({status}, `^[؀-ۿ_-]+( [؀-ۿ_-]+)*$`) | H97: {rec_status} == 'A' && !isNull({status}) | J97: status,rec_status | K97: Active | L97: Conformity | M97: 1 | N97: CustomTruth | O97: Checks that non-null STATUS values in Status_Lookup_Language follow the approved code/identifier format and length, preventing malformed values from entering reporting or integrations. | P97: {'condition': 'regexMatch(lower({status}), `^[a-z_-]+( [a-z_-]+)*$`) || regexMatch({status}, `^[\u0600-ۿ_-]+( [\u0600-ۿ_-]+)*$`)', 'filterCriteria': "{rec_status} == 'A' && !isNull({status})", 'emptyCriteria': None, 'columns': [{'value': 'status', 'type': 'Column'}, {'value': 'rec_status', 'type': 'Column'}], 'ruleDialect': 'ADF'}
A98: Ref_Lookup_Check-Status_Lookup_Language-STATUS | B98: f401766d-272c-46a6-bc4a-c9c5299b6576 | C98: 212551b9-97e3-4ffc-9c4e-169f987349b2 | D98: cf23386e-459a-4327-88d5-4b456681e54e | E98: bd94add1-6597-4f2d-b575-4a8fcb5d972e | F98: status_lookup_language | J98: status | K98: Disabled | L98: Accuracy | M98: 0.49206349 | N98: ReferenceCheck | O98: Checks if non-null STATUS values in Status_Lookup_Language exist in the approved reference or master data asset before the value is trusted by downstream consumers. Refer to APP_STATUS_GROUP Table. | P98: {'column': {'value': 'status', 'type': 'Column'}, 'referencedDatasetAlias': 'status_lookup', 'referencedDatasetColumn': {'value': 'status', 'type': 'Column'}}
A99: Duplicate_Check-Status_Lookup_Language | B99: 67aeb19c-c1c7-40da-abc2-2e4ab53c7fac | C99: 212551b9-97e3-4ffc-9c4e-169f987349b2 | D99: cf23386e-459a-4327-88d5-4b456681e54e | E99: bd94add1-6597-4f2d-b575-4a8fcb5d972e | F99: status_lookup_language | J99: res_id,lang_id | K99: Active | L99: Accuracy | M99: 1 | N99: Duplicate | O99: Checks that Status_Lookup_Language has no duplicate active logical records for the approved business key (RES_ID, LANG_ID). | P99: {'columns': [{'value': 'res_id', 'type': 'Column'}, {'value': 'lang_id', 'type': 'Column'}]}
A100: Freshness_Check-Status_Lookup_Language | B100: 466ab382-6ae3-4f8d-aa1e-06cad783f66c | C100: 212551b9-97e3-4ffc-9c4e-169f987349b2 | D100: cf23386e-459a-4327-88d5-4b456681e54e | E100: bd94add1-6597-4f2d-b575-4a8fcb5d972e | F100: status_lookup_language | G100: 172800000 | K100: Active | L100: Timeliness | M100: 1 | N100: Timeliness | O100: Checks that the Status_Lookup_Language asset is refreshed within the approved operational SLA so its CDE values remain current for reporting and downstream consumption. | P100: {'timeDifference': 172800000}
...
